Workbook
Name Scenario: '01_CONTROL'!$D$12
Name Hold_Y: '01_CONTROL'!$D$14
Name Hold_Col: '01_CONTROL'!$G$14
Name Entry_Multiple: '01_CONTROL'!$D$16
Name Exit_Method: '01_CONTROL'!$D$17
Name Exit_Multiple: '01_CONTROL'!$D$18
Name Exit_Equity_Target: '01_CONTROL'!$D$19
Name Debt_Structure: '01_CONTROL'!$D$20
Name IR_Mode: '01_CONTROL'!$D$21
Name Bench_Rate: '01_CONTROL'!$D$22
Name Tax_Rate: '01_CONTROL'!$D$26
Name Exit_Fee_Pct: '01_CONTROL'!$D$35
Name Coven_NetLev_Max: '01_CONTROL'!$D$71
Name Coven_IntCov_Min: '01_CONTROL'!$D$72
Name Min_Liq_Target: '01_CONTROL'!$D$73
Name Purchase_Price: '01_CONTROL'!$D$15
Name FX_Mode: '01_CONTROL'!$D$23
Name FX_Rate: '01_CONTROL'!$D$24
Name Lev_Target: '01_CONTROL'!$D$48
Name Revolver_Limit: '01_CONTROL'!$G$49
Name Cash_Sweep: '01_CONTROL'!$G$54
Name Mgmt_Rollover_Pct: '01_CONTROL'!$G$55
Name WC_Adjust: '01_CONTROL'!$G$56
Name TRAINING_MODE: 01_CONTROL!$G$12

Sheet 00_DASHBOARD
B2: CHECKS: | C2: =HYPERLINK("#'90_CHECKS'!B6",'90_CHECKS'!$C$22)
B3: LBO Dashboard (Sponsor IC)
B4: CatalystOne (Sweden) | HR platform | Training case | Reporting currency: DKK
B5: Key outputs update automatically from 01_CONTROL toggles.
B7: Key deal outputs
B9: Entry EV (DKKm) | C9: ='05_SOURCES_AND_USES'!$D$33 | E9: Entry multiple (x) | F9: =Entry_Multiple | H9: Leverage (Net debt / EBITDA, x) | I9: ='10_COVENANTS_AND_CREDIT_METRICS'!$D$34
H10: Learning cues (click)
B11: ENTRY EV (DKKm) | C11: ='05_SOURCES_AND_USES'!$D$16 | E11: EXIT MULTIPLE (x) | F11: =Exit_Multiple | H11: ENTRY EV | I11: Valuation starting point, drives equity check. | J11: =HYPERLINK("#'82_LBO_LEARN_INTERPRETATION'!B11","Learn")
B12: ENTRY MULTIPLE (x) | C12: =Entry_Multiple | E12: SPONSOR IRR | F12: ='09_RETURNS'!$D$20 | H12: ENTRY MULTIPLE | I12: Paying up needs a clear thesis or leverage/FCF. | J12: =HYPERLINK("#'82_LBO_LEARN_INTERPRETATION'!B12","Learn")
B13: TOTAL DEBT (DKKm) | C13: ='05_SOURCES_AND_USES'!$D$37 | E13: SPONSOR MOIC | F13: ='09_RETURNS'!$D$21 | H13: TOTAL DEBT | I13: Leverage boosts IRR but tightens covenants. | J13: =HYPERLINK("#'82_LBO_LEARN_INTERPRETATION'!B13","Learn")
B14: TOTAL EQUITY (DKKm) | C14: ='05_SOURCES_AND_USES'!$D$40 | E14: PEAK NET LEVERAGE (x) | F14: ='10_COVENANTS_AND_CREDIT_METRICS'!$D$34 | H14: TOTAL EQUITY | I14: Equity check is denominator for returns. | J14: =HYPERLINK("#'82_LBO_LEARN_INTERPRETATION'!B14","Learn")
B15: ENTRY LEVERAGE (x) | C15: ='05_SOURCES_AND_USES'!$D$37/'05_SOURCES_AND_USES'!$D$14 | E15: MIN LIQUIDITY (DKKm) | F15: ='10_COVENANTS_AND_CREDIT_METRICS'!$D$35 | H15: ENTRY LEVERAGE | I15: Risk-return; watch peak leverage and liquidity. | J15: =HYPERLINK("#'82_LBO_LEARN_INTERPRETATION'!B15","Learn")
E16: MIN COVENANT HEADROOM (x) | F16: ='10_COVENANTS_AND_CREDIT_METRICS'!$D$36 | H16: EXIT MULTIPLE | I16: Largest driver, defend range and stress downside. | J16: =HYPERLINK("#'82_LBO_LEARN_INTERPRETATION'!B16","Learn")
E17: CHECKS STATUS | F17: ='90_CHECKS'!$C$2 | H17: SPONSOR IRR | I17: Timing-sensitive headline, reconcile to MOIC. | J17: =HYPERLINK("#'82_LBO_LEARN_INTERPRETATION'!B17","Learn")
B18: Min covenant headroom (x) | C18: ='10_COVENANTS_AND_CREDIT_METRICS'!$D$36 | H18: SPONSOR MOIC | I18: Value creation multiple, pair with hold period. | J18: =HYPERLINK("#'82_LBO_LEARN_INTERPRETATION'!B18","Learn")
H19: PEAK NET LEVERAGE | I19: Stress point for credit risk and flexibility. | J19: =HYPERLINK("#'82_LBO_LEARN_INTERPRETATION'!B19","Learn")
H20: MIN LIQUIDITY | I20: First line of defense, watch revolver usage. | J20: =HYPERLINK("#'82_LBO_LEARN_INTERPRETATION'!B20","Learn")
H21: MIN COV HEADROOM | I21: Breach risk, identify what breaks first. | J21: =HYPERLINK("#'82_LBO_LEARN_INTERPRETATION'!B21","Learn")
B22: Checks status | H22: CHECKS STATUS | I22: Must be PASS before interpreting outputs. | J22: =HYPERLINK("#'82_LBO_LEARN_INTERPRETATION'!B22","Learn")
B24: Overall | C24: ='90_CHECKS'!$C$22 | D24: See 90_Checks for details
B26: Charts
B28: Year | C28: Total debt | D28: Net leverage
B29: 1 | C29: =INDEX('06_DEBT_SCHEDULES'!$F$67:$L$67,1,1) | D29: =INDEX('10_COVENANTS_AND_CREDIT_METRICS'!$F$19:$L$19,1,1)
B30: 2 | C30: =INDEX('06_DEBT_SCHEDULES'!$F$67:$L$67,1,2) | D30: =INDEX('10_COVENANTS_AND_CREDIT_METRICS'!$F$19:$L$19,1,2)
B31: 3 | C31: =INDEX('06_DEBT_SCHEDULES'!$F$67:$L$67,1,3) | D31: =INDEX('10_COVENANTS_AND_CREDIT_METRICS'!$F$19:$L$19,1,3)
B32: 4 | C32: =INDEX('06_DEBT_SCHEDULES'!$F$67:$L$67,1,4) | D32: =INDEX('10_COVENANTS_AND_CREDIT_METRICS'!$F$19:$L$19,1,4)
B33: 5 | C33: =INDEX('06_DEBT_SCHEDULES'!$F$67:$L$67,1,5) | D33: =INDEX('10_COVENANTS_AND_CREDIT_METRICS'!$F$19:$L$19,1,5)
B34: 6 | C34: =INDEX('06_DEBT_SCHEDULES'!$F$67:$L$67,1,6) | D34: =INDEX('10_COVENANTS_AND_CREDIT_METRICS'!$F$19:$L$19,1,6)
B35: 7 | C35: =INDEX('06_DEBT_SCHEDULES'!$F$67:$L$67,1,7) | D35: =INDEX('10_COVENANTS_AND_CREDIT_METRICS'!$F$19:$L$19,1,7)
B37: IRR heatmap (Exit multiple vs Entry multiple)
B39: (Links to 11_SENSITIVITIES)
C41: ='11_SENSITIVITIES'!D23 | D41: ='11_SENSITIVITIES'!E23 | E41: ='11_SENSITIVITIES'!F23 | F41: ='11_SENSITIVITIES'!G23 | G41: ='11_SENSITIVITIES'!H23 | H41: ='11_SENSITIVITIES'!I23
B42: ='11_SENSITIVITIES'!C24 | C42: ='11_SENSITIVITIES'!D24 | D42: ='11_SENSITIVITIES'!E24 | E42: ='11_SENSITIVITIES'!F24 | F42: ='11_SENSITIVITIES'!G24 | G42: ='11_SENSITIVITIES'!H24 | H42: ='11_SENSITIVITIES'!I24
B43: ='11_SENSITIVITIES'!C25 | C43: ='11_SENSITIVITIES'!D25 | D43: ='11_SENSITIVITIES'!E25 | E43: ='11_SENSITIVITIES'!F25 | F43: ='11_SENSITIVITIES'!G25 | G43: ='11_SENSITIVITIES'!H25 | H43: ='11_SENSITIVITIES'!I25
B44: ='11_SENSITIVITIES'!C26 | C44: ='11_SENSITIVITIES'!D26 | D44: ='11_SENSITIVITIES'!E26 | E44: ='11_SENSITIVITIES'!F26 | F44: ='11_SENSITIVITIES'!G26 | G44: ='11_SENSITIVITIES'!H26 | H44: ='11_SENSITIVITIES'!I26
B45: ='11_SENSITIVITIES'!C27 | C45: ='11_SENSITIVITIES'!D27 | D45: ='11_SENSITIVITIES'!E27 | E45: ='11_SENSITIVITIES'!F27 | F45: ='11_SENSITIVITIES'!G27 | G45: ='11_SENSITIVITIES'!H27 | H45: ='11_SENSITIVITIES'!I27
B46: ='11_SENSITIVITIES'!C28 | C46: ='11_SENSITIVITIES'!D28 | D46: ='11_SENSITIVITIES'!E28 | E46: ='11_SENSITIVITIES'!F28 | F46: ='11_SENSITIVITIES'!G28 | G46: ='11_SENSITIVITIES'!H28 | H46: ='11_SENSITIVITIES'!I28
B47: ='11_SENSITIVITIES'!C29 | C47: ='11_SENSITIVITIES'!D29 | D47: ='11_SENSITIVITIES'!E29 | E47: ='11_SENSITIVITIES'!F29 | F47: ='11_SENSITIVITIES'!G29 | G47: ='11_SENSITIVITIES'!H29 | H47: ='11_SENSITIVITIES'!I29
B49: What this means (interpretation)
B51: • IRR and MOIC are sensitive to exit multiple and growth. Review 11_SENSITIVITIES heatmaps.
B52: • Deleveraging is driven primarily by unlevered FCF (EBITDA minus tax, NWC, capex).
B53: • Downside: stress revenue growth and margin (01_CONTROL scenario) and check liquidity + covenants.
B54: • Sanity: entry multiple vs market comps; confirm debt terms and sweep assumptions.
B55: • If checks show FAIL, do not use outputs. Fix 90_Checks first.

Sheet 01_CONTROL
B1: LBO Model Builder (Training Simulation)
B2: CHECKS: | C2: =HYPERLINK("#'90_CHECKS'!B6",'90_CHECKS'!$C$22)
B3: Checks: | C3: =HYPERLINK("#'90_CHECKS'!B2","Go to 90_CHECKS")
B4: Units: | C4: DKKm
B5: Version: | C5: v0.1
B6: Date: | C6: 46069
B10: MODEL CONTROLS AND GLOBAL ASSUMPTIONS
B12: Scenario | D12: Base | F12: TRAINING_MODE (ON/OFF) | G12: OFF
B13: Scenario index (1=Base,2=Upside,3=Downside) | D13: =MATCH(D12,{"Base","Upside","Downside"},0)
B14: Hold period (years) | D14: 5 | G14: =Hold_Y+1
B15: Hold col index (LTM=1, Year1=2...) | D15: =1+D14
B16: Entry EV multiple (x LTM EBITDA) - primary driver | D16: 12
B17: Exit method | D17: Exit Multiple
B18: Exit EV multiple (x EBITDA) | D18: 13
B19: Exit equity value target (DKKm, used if Exit method = Equity Value) | D19: 0
B20: Debt structure | D20: Standard
B21: Interest rate mode | D21: Floating
B22: Benchmark rate (e.g., CIBOR 3M) | D22: 0.03
B23: FX enabled? | D23: Off
B24: Target currency | D24: SEK
B25: FX rate (DKK per target currency unit) | D25: 0.65
B26: Corporate tax rate | D26: 0.22
B27: Margin ramp (years) | D27: 2
B28: TARGET LTM INPUTS (SINGLE-ENTRY)
B30: LTM Revenue (DKKm) | D30: 450
B31: LTM EBITDA margin | D31: 0.28
B32: LTM EBITDA (DKKm) | D32: =D30*D31
B33: Opening cash at close (DKKm) | D33: 0
B34: Existing net debt refinanced (DKKm, + means debt) | D34: 0
B35: Exit fees (% EV) | D35: 0.01
B36: SCENARIO ASSUMPTIONS (EDIT BLUE, ACTIVE DRIVES MODEL)
B38: Assumption | C38: Unit | D38: Base | E38: Upside | F38: Downside | G38: Active
B39: Revenue growth (annual) | C39: % | D39: 0.1 | E39: 0.12 | F39: 0.06 | G39: =CHOOSE($D$13, D39, E39, F39)
B40: EBITDA margin (steady state) | C40: % | D40: 0.29 | E40: 0.31 | F40: 0.26 | G40: =CHOOSE($D$13, D40, E40, F40)
B41: Capex (% revenue) | C41: % | D41: 0.03 | E41: 0.035 | F41: 0.025 | G41: =CHOOSE($D$13, D41, E41, F41)
B42: D&A (% revenue) | C42: % | D42: 0.02 | E42: 0.02 | F42: 0.02 | G42: =CHOOSE($D$13, D42, E42, F42)
B43: NWC method | C43: text | D43: PctRev | E43: DSO | F43: PctRev | G43: =CHOOSE($D$13, D43, E43, F43)
B44: NWC (% revenue) | C44: % | D44: 0.05 | E44: 0.04 | F44: 0.06 | G44: =CHOOSE($D$13, D44, E44, F44)
B45: DSO (days) | C45: days | D45: 60 | E45: 55 | F45: 70 | G45: =CHOOSE($D$13, D45, E45, F45)
B46: DPO (days) | C46: days | D46: 45 | E46: 50 | F46: 40 | G46: =CHOOSE($D$13, D46, E46, F46)
B47: DIO (days) | C47: days | D47: 0 | E47: 0 | F47: 0 | G47: =CHOOSE($D$13, D47, E47, F47)
B48: Total leverage at entry (x LTM EBITDA) | C48: x | D48: 4.5 | E48: 5 | F48: 4 | G48: =CHOOSE($D$13, D48, E48, F48)
B49: Revolver size (DKKm) | C49: DKKm | D49: 75 | E49: 90 | F49: 60 | G49: =CHOOSE($D$13, D49, E49, F49)
B50: TLA leverage (x EBITDA) | C50: x | D50: 2 | E50: 2 | F50: 2 | G50: =CHOOSE($D$13, D50, E50, F50)
B51: TLB leverage (x EBITDA) | C51: x | D51: 2 | E51: 2.5 | F51: 1.5 | G51: =CHOOSE($D$13, D51, E51, F51)
B52: SSN leverage (x EBITDA) | C52: x | D52: 0.5 | E52: 0.5 | F52: 0.5 | G52: =CHOOSE($D$13, D52, E52, F52)
B53: Mezz/PIK leverage (x EBITDA) | C53: x | D53: 0 | E53: 0 | F53: 0 | G53: =CHOOSE($D$13, D53, E53, F53)
B54: Cash sweep (% of excess cash) | C54: % | D54: 1 | E54: 1 | F54: 1 | G54: =CHOOSE($D$13, D54, E54, F54)
B55: Mgmt rollover (% of equity) | C55: % | D55: 0.1 | E55: 0.1 | F55: 0.1 | G55: =CHOOSE($D$13, D55, E55, F55)
... B57: Financing fees (% new debt) | C57: % | D57: 0.02 | E57: 0.02 | F57: 0.02 | G57: =CHOOSE($D$13, D57, E57, F57)
B60: DEBT TERMS (EDIT BLUE, USED ACROSS SCHEDULES)
B62: Tranche | C62: Amort % p.a. | D62: Spread | E62: Floor | F62: Fixed rate | G62: Seniority (1=first sweep)
B63: Revolver | C63: 0 | D63: 0.035 | E63: 0 | F63: 0.06 | G63: 1
B64: Term Loan A | C64: 0.1 | D64: 0.04 | E64: 0 | F64: 0.065 | G64: 2
B65: Term Loan B | C65: 0.05 | D65: 0.045 | E65: 0 | F65: 0.07 | G65: 3
B66: SSN | C66: 0 | D66: 0.055 | E66: 0 | F66: 0.08 | G66: 4
B67: Mezz/PIK | C67: 0 | D67: 0.09 | E67: 0 | F67: 0.11 | G67: 5
B69: COVENANT ASSUMPTIONS (ILLUSTRATIVE, EDIT BLUE)
B71: Net leverage covenant (max, x) | D71: 6
B72: Interest coverage covenant (min, x) | D72: 2
B73: Minimum liquidity target (DKKm) | D73: 25

Sheet 02_INPUTS_TARGET_HISTORICALS
B1: LBO Model Builder (Training Simulation)
B2: CHECKS: | C2: =HYPERLINK("#'90_CHECKS'!B6",'90_CHECKS'!$C$22)
B3: Checks: | C3: =HYPERLINK("#'90_CHECKS'!B2","Go to 90_CHECKS")
B4: Units: | C4: DKKm
B5: Version: | C5: v0.1
B6: Date: | C6: 46069
B7: Period end | E7: 46022 | F7: 46387 | G7: 46752 | H7: 47118 | I7: 47483 | J7: 47848 | K7: 48213 | L7: 48579
B8: Period | E8: LTM | F8: 2026E | G8: 2027E | H8: 2028E | I8: 2029E | J8: 2030E | K8: 2031E | L8: 2032E
B9: Year # | E9: 0 | F9: 1 | G9: 2 | H9: 3 | I9: 4 | J9: 5 | K9: 6 | L9: 7

Sheet 03_DRIVERS_AND_FORECAST
B1: LBO Model Builder (Training Simulation)
B2: CHECKS: | C2: =HYPERLINK("#'90_CHECKS'!B6",'90_CHECKS'!$C$22)
B3: Checks: | C3: =HYPERLINK("#'90_CHECKS'!B2","Go to 90_CHECKS")
B4: Units: | C4: DKKm
B5: Version: | C5: v0.1
B6: Date: | C6: 46069
B7: Period end | E7: 46022 | F7: 46387 | G7: 46752 | H7: 47118 | I7: 47483 | J7: 47848 | K7: 48213 | L7: 48579
B8: Period | E8: LTM | F8: 2026E | G8: 2027E | H8: 2028E | I8: 2029E | J8: 2030E | K8: 2031E | L8: 2032E
B9: Year # | E9: 0 | F9: 1 | G9: 2 | H9: 3 | I9: 4 | J9: 5 | K9: 6 | L9: 7
B10: OPERATING DRIVERS (SCENARIO-DRIVEN)
B12: Revenue (DKKm) | C12: DKKm | E12: ='01_CONTROL'!$D$30 | F12: =E12*(1+F13) | G12: =F12*(1+G13) | H12: =G12*(1+H13) | I12: =H12*(1+I13) | J12: =I12*(1+J13) | K12: =J12*(1+K13) | L12: =K12*(1+L13)
B13: Revenue growth (active) | C13: % | F13: ='01_CONTROL'!$G$39 | G13: ='01_CONTROL'!$G$39 | H13: ='01_CONTROL'!$G$39 | I13: ='01_CONTROL'!$G$39 | J13: ='01_CONTROL'!$G$39 | K13: ='01_CONTROL'!$G$39 | L13: ='01_CONTROL'!$G$39
B15: EBITDA margin (active ramp) | C15: % | E15: ='01_CONTROL'!$D$31 | F15: ='01_CONTROL'!$D$31 + MIN(1,F9/'01_CONTROL'!$D$27)*('01_CONTROL'!$G$40-'01_CONTROL'!$D$31) | G15: ='01_CONTROL'!$D$31 + MIN(1,G9/'01_CONTROL'!$D$27)*('01_CONTROL'!$G$40-'01_CONTROL'!$D$31) | H15: ='01_CONTROL'!$D$31 + MIN(1,H9/'01_CONTROL'!$D$27)*('01_CONTROL'!$G$40-'01_CONTROL'!$D$31) | I15: ='01_CONTROL'!$D$31 + MIN(1,I9/'01_CONTROL'!$D$27)*('01_CONTROL'!$G$40-'01_CONTROL'!$D$31) | J15: ='01_CONTROL'!$D$31 + MIN(1,J9/'01_CONTROL'!$D$27)*('01_CONTROL'!$G$40-'01_CONTROL'!$D$31) | K15: ='01_CONTROL'!$D$31 + MIN(1,K9/'01_CONTROL'!$D$27)*('01_CONTROL'!$G$40-'01_CONTROL'!$D$31) | L15: ='01_CONTROL'!$D$31 + MIN(1,L9/'01_CONTROL'!$D$27)*('01_CONTROL'!$G$40-'01_CONTROL'!$D$31)
B16: EBITDA (DKKm) | C16: DKKm | E16: =E12*E15 | F16: =F12*F15 | G16: =G12*G15 | H16: =H12*H15 | I16: =I12*I15 | J16: =J12*J15 | K16: =K12*K15 | L16: =L12*L15
B18: Capex (% revenue) | C18: % | F18: ='01_CONTROL'!$G$41 | G18: ='01_CONTROL'!$G$41 | H18: ='01_CONTROL'!$G$41 | I18: ='01_CONTROL'!$G$41 | J18: ='01_CONTROL'!$G$41 | K18: ='01_CONTROL'!$G$41 | L18: ='01_CONTROL'!$G$41
B19: D&A (% revenue) | C19: % | F19: ='01_CONTROL'!$G$42 | G19: ='01_CONTROL'!$G$42 | H19: ='01_CONTROL'!$G$42 | I19: ='01_CONTROL'!$G$42 | J19: ='01_CONTROL'!$G$42 | K19: ='01_CONTROL'!$G$42 | L19: ='01_CONTROL'!$G$42
B21: NWC method (active) | C21: text | E21: ='01_CONTROL'!$G$43
B22: NWC (% revenue) if PctRev | C22: % | F22: ='01_CONTROL'!$G$44
B23: DSO / DPO / DIO (days) if DSO | C23: days | F23: ='01_CONTROL'!$G$45 | G23: ='01_CONTROL'!$G$46 | H23: ='01_CONTROL'!$G$47

Sheet 04_OPERATING_MODEL
B1: LBO Model Builder (Training Simulation)
B2: CHECKS: | C2: =HYPERLINK("#'90_CHECKS'!B6",'90_CHECKS'!$C$22)
B3: Checks: | C3: =HYPERLINK("#'90_CHECKS'!B2","Go to 90_CHECKS")
B4: Units: | C4: DKKm
B5: Version: | C5: v0.1
B6: Date: | C6: 46069
B7: Period end | E7: 46022 | F7: 46387 | G7: 46752 | H7: 47118 | I7: 47483 | J7: 47848 | K7: 48213 | L7: 48579
B8: Period | E8: LTM | F8: 2026E | G8: 2027E | H8: 2028E | I8: 2029E | J8: 2030E | K8: 2031E | L8: 2032E
B9: Year # | E9: 0 | F9: 1 | G9: 2 | H9: 3 | I9: 4 | J9: 5 | K9: 6 | L9: 7
B10: OPERATING MODEL (3-STATEMENT-LITE)
B12: INCOME STATEMENT (DKKM)
B14: Revenue | C14: DKKm | E14: ='03_DRIVERS_AND_FORECAST'!E12 | F14: ='03_DRIVERS_AND_FORECAST'!F12 | G14: ='03_DRIVERS_AND_FORECAST'!G12 | H14: ='03_DRIVERS_AND_FORECAST'!H12 | I14: ='03_DRIVERS_AND_FORECAST'!I12 | J14: ='03_DRIVERS_AND_FORECAST'!J12 | K14: ='03_DRIVERS_AND_FORECAST'!K12 | L14: ='03_DRIVERS_AND_FORECAST'!L12
B15: EBITDA | C15: DKKm | E15: ='03_DRIVERS_AND_FORECAST'!E16 | F15: ='03_DRIVERS_AND_FORECAST'!F16 | G15: ='03_DRIVERS_AND_FORECAST'!G16 | H15: ='03_DRIVERS_AND_FORECAST'!H16 | I15: ='03_DRIVERS_AND_FORECAST'!I16 | J15: ='03_DRIVERS_AND_FORECAST'!J16 | K15: ='03_DRIVERS_AND_FORECAST'!K16 | L15: ='03_DRIVERS_AND_FORECAST'!L16
B16: EBITDA margin | C16: % | E16: =IF(E14=0,0,E15/E14) | F16: =IF(F14=0,0,F15/F14) | G16: =IF(G14=0,0,G15/G14) | H16: =IF(H14=0,0,H15/H14) | I16: =IF(I14=0,0,I15/I14) | J16: =IF(J14=0,0,J15/J14) | K16: =IF(K14=0,0,K15/K14) | L16: =IF(L14=0,0,L15/L14)
B17: D&A | C17: DKKm | E17: =E14*'03_DRIVERS_AND_FORECAST'!E19 | F17: =F14*'03_DRIVERS_AND_FORECAST'!F19 | G17: =G14*'03_DRIVERS_AND_FORECAST'!G19 | H17: =H14*'03_DRIVERS_AND_FORECAST'!H19 | I17: =I14*'03_DRIVERS_AND_FORECAST'!I19 | J17: =J14*'03_DRIVERS_AND_FORECAST'!J19 | K17: =K14*'03_DRIVERS_AND_FORECAST'!K19 | L17: =L14*'03_DRIVERS_AND_FORECAST'!L19
B18: EBIT | C18: DKKm | E18: =E15-E17 | F18: =F15-F17 | G18: =G15-G17 | H18: =H15-H17 | I18: =I15-I17 | J18: =J15-J17 | K18: =K15-K17 | L18: =L15-L17
B19: Unlevered cash taxes | C19: DKKm | E19: =MAX(0,E18)*'01_CONTROL'!$D$26 | F19: =MAX(0,F18)*'01_CONTROL'!$D$26 | G19: =MAX(0,G18)*'01_CONTROL'!$D$26 | H19: =MAX(0,H18)*'01_CONTROL'!$D$26 | I19: =MAX(0,I18)*'01_CONTROL'!$D$26 | J19: =MAX(0,J18)*'01_CONTROL'!$D$26 | K19: =MAX(0,K18)*'01_CONTROL'!$D$26 | L19: =MAX(0,L18)*'01_CONTROL'!$D$26
B20: NOPAT | C20: DKKm | E20: =E18-E19 | F20: =F18-F19 | G20: =G18-G19 | H20: =H18-H19 | I20: =I18-I19 | J20: =J18-J19 | K20: =K18-K19 | L20: =L18-L19
B22: WORKING CAPITAL (DKKM)
B24: NWC method flag (1=PctRev,0=DSO) | C24: flag | E24: =IF('03_DRIVERS_AND_FORECAST'!$E$21="PctRev",1,0) | F24: =IF('03_DRIVERS_AND_FORECAST'!$E$21="PctRev",1,0) | G24: =IF('03_DRIVERS_AND_FORECAST'!$E$21="PctRev",1,0) | H24: =IF('03_DRIVERS_AND_FORECAST'!$E$21="PctRev",1,0) | I24: =IF('03_DRIVERS_AND_FORECAST'!$E$21="PctRev",1,0) | J24: =IF('03_DRIVERS_AND_FORECAST'!$E$21="PctRev",1,0) | K24: =IF('03_DRIVERS_AND_FORECAST'!$E$21="PctRev",1,0) | L24: =IF('03_DRIVERS_AND_FORECAST'!$E$21="PctRev",1,0)
B25: NWC (PctRev method) | C25: DKKm | E25: =E14*'03_DRIVERS_AND_FORECAST'!$F$22 | F25: =F14*'03_DRIVERS_AND_FORECAST'!$F$22 | G25: =G14*'03_DRIVERS_AND_FORECAST'!$F$22 | H25: =H14*'03_DRIVERS_AND_FORECAST'!$F$22 | I25: =I14*'03_DRIVERS_AND_FORECAST'!$F$22 | J25: =J14*'03_DRIVERS_AND_FORECAST'!$F$22 | K25: =K14*'03_DRIVERS_AND_FORECAST'!$F$22 | L25: =L14*'03_DRIVERS_AND_FORECAST'!$F$22
B27: Accounts receivable (DSO method) | C27: DKKm | E27: =E14/365*'03_DRIVERS_AND_FORECAST'!$F$23 | F27: =F14/365*'03_DRIVERS_AND_FORECAST'!$F$23 | G27: =G14/365*'03_DRIVERS_AND_FORECAST'!$F$23 | H27: =H14/365*'03_DRIVERS_AND_FORECAST'!$F$23 | I27: =I14/365*'03_DRIVERS_AND_FORECAST'!$F$23 | J27: =J14/365*'03_DRIVERS_AND_FORECAST'!$F$23 | K27: =K14/365*'03_DRIVERS_AND_FORECAST'!$F$23 | L27: =L14/365*'03_DRIVERS_AND_FORECAST'!$F$23
B28: Accounts payable (DPO method) | C28: DKKm | E28: =(E14-E15)/365*'03_DRIVERS_AND_FORECAST'!$G$23 | F28: =(F14-F15)/365*'03_DRIVERS_AND_FORECAST'!$G$23 | G28: =(G14-G15)/365*'03_DRIVERS_AND_FORECAST'!$G$23 | H28: =(H14-H15)/365*'03_DRIVERS_AND_FORECAST'!$G$23 | I28: =(I14-I15)/365*'03_DRIVERS_AND_FORECAST'!$G$23 | J28: =(J14-J15)/365*'03_DRIVERS_AND_FORECAST'!$G$23 | K28: =(K14-K15)/365*'03_DRIVERS_AND_FORECAST'!$G$23 | L28: =(L14-L15)/365*'03_DRIVERS_AND_FORECAST'!$G$23
B29: Net working capital (DSO method) | C29: DKKm | E29: =E27-E28 | F29: =F27-F28 | G29: =G27-G28 | H29: =H27-H28 | I29: =I27-I28 | J29: =J27-J28 | K29: =K27-K28 | L29: =L27-L28
B31: Selected NWC | C31: DKKm | E31: =IF(E24=1,E25,E29) | F31: =IF(F24=1,F25,F29) | G31: =IF(G24=1,G25,G29) | H31: =IF(H24=1,H25,H29) | I31: =IF(I24=1,I25,I29) | J31: =IF(J24=1,J25,J29) | K31: =IF(K24=1,K25,K29) | L31: =IF(L24=1,L25,L29)
B32: Change in NWC | C32: DKKm | E32: 0 | F32: =F31-E31 | G32: =G31-F31 | H32: =H31-G31 | I32: =I31-H31 | J32: =J31-I31 | K32: =K31-J31 | L32: =L31-K31
B34: UNLEVERED FREE CASH FLOW (DKKM)
B36: Capex | C36: DKKm | E36: 0 | F36: =-F14*'03_DRIVERS_AND_FORECAST'!F18 | G36: =-G14*'03_DRIVERS_AND_FORECAST'!G18 | H36: =-H14*'03_DRIVERS_AND_FORECAST'!H18 | I36: =-I14*'03_DRIVERS_AND_FORECAST'!I18 | J36: =-J14*'03_DRIVERS_AND_FORECAST'!J18 | K36: =-K14*'03_DRIVERS_AND_FORECAST'!K18 | L36: =-L14*'03_DRIVERS_AND_FORECAST'!L18
B37: Unlevered FCF | C37: DKKm | E37: 0 | F37: =F20+F17+F36-F32 | G37: =G20+G17+G36-G32 | H37: =H20+H17+H36-H32 | I37: =I20+I17+I36-I32 | J37: =J20+J17+J36-J32 | K37: =K20+K17+K36-K32 | L37: =L20+L17+L36-L32

Sheet 05_SOURCES_AND_USES
B1: LBO Model Builder (Training Simulation)
B2: CHECKS: | C2: =HYPERLINK("#'90_CHECKS'!B6",'90_CHECKS'!$C$22)
B3: Checks: | C3: =HYPERLINK("#'90_CHECKS'!B2","Go to 90_CHECKS")
B4: Units: | C4: DKKm
B5: Version: | C5: v0.1
B6: Date: | C6: 46069
B10: SOURCES & USES (ENTRY)
B12: ENTRY VALUATION
B14: LTM EBITDA (DKKm) | D14: ='01_CONTROL'!$D$32
B15: Entry EV multiple (x) | D15: ='01_CONTROL'!$D$16
B16: Entry Enterprise Value (EV) (DKKm) | D16: =D14*D15
B17: Existing net debt refinanced (DKKm) | D17: ='01_CONTROL'!$D$34
B18: Equity purchase price (to seller) (DKKm) | D18: =D16-D17
B20: USES
B22: Equity purchase price | D22: =D18
B23: Refinance existing net debt | D23: =D17
B24: Advisory fees | D24: =D16*'01_CONTROL'!$G$56
B25: Financing fees | D25: =D37*'01_CONTROL'!$G$57
B26: Working capital adjustment | D26: 0
B28: Total uses | D28: =SUM(D22:D26)
B30: SOURCES
B32: Debt structure flag (1=Standard,0=Simple) | D32: =IF('01_CONTROL'!$D$20="Standard",1,0)
B33: Term Loan A | D33: =D32*'01_CONTROL'!$G$50*D14
B34: Term Loan B | D34: =IF(D32=1,'01_CONTROL'!$G$51*D14, '01_CONTROL'!$G$48*D14)
B35: Senior Secured Notes | D35: =D32*'01_CONTROL'!$G$52*D14
B36: Mezz / PIK | D36: =D32*'01_CONTROL'!$G$53*D14
B37: Total new term debt (ex revolver) | D37: =SUM(D33:D36)
B38: Sponsor equity (plug) | D38: =D40-D39
B39: Mgmt rollover equity | D39: =D40*'01_CONTROL'!$G$55
B40: Total equity | D40: =D28-D37
B41: Total sources | D41: =D37+D40
B43: CHECKS
B44: Sources - Uses check | C44: DKKm | D44: =D37+D40-D28
B45: Sources - Uses (must be 0) | D45: =D41-D28

Sheet 06_DEBT_SCHEDULES
B1: LBO Model Builder (Training Simulation)
B2: CHECKS: | C2: =HYPERLINK("#'90_CHECKS'!B6",'90_CHECKS'!$C$22)
B3: Checks: | C3: =HYPERLINK("#'90_CHECKS'!B2","Go to 90_CHECKS")
B4: Units: | C4: DKKm
B5: Version: | C5: v0.1
B6: Date: | C6: 46069
B7: Period end | E7: 46022 | F7: 46387 | G7: 46752 | H7: 47118 | I7: 47483 | J7: 47848 | K7: 48213 | L7: 48579
B8: Period | E8: LTM | F8: 2026E | G8: 2027E | H8: 2028E | I8: 2029E | J8: 2030E | K8: 2031E | L8: 2032E
B9: Year # | E9: 0 | F9: 1 | G9: 2 | H9: 3 | I9: 4 | J9: 5 | K9: 6 | L9: 7
B10: DEBT SCHEDULES (ALL TRANCHES)
B12: INPUTS
B14: Revolver limit (DKKm) | C14: DKKm | E14: ='01_CONTROL'!$G$49
B15: TLA opening balance at close (DKKm) | C15: DKKm | E15: ='05_SOURCES_AND_USES'!$D$33
B16: TLB opening balance at close (DKKm) | C16: DKKm | E16: ='05_SOURCES_AND_USES'!$D$34
B17: SSN opening balance at close (DKKm) | C17: DKKm | E17: ='05_SOURCES_AND_USES'!$D$35
B18: Mezz/PIK opening balance at close (DKKm) | C18: DKKm | E18: ='05_SOURCES_AND_USES'!$D$36
B20: REVOLVER (DRAW/REPAY)
B22: Opening balance | C22: DKKm | E22: 0 | F22: =E25 | G22: =F25 | H22: =G25 | I22: =H25 | J22: =I25 | K22: =J25 | L22: =K25
B23: Draws | C23: DKKm | E23: 0 | F23: ='07_CASH_FLOW_WATERFALL'!F30 | G23: ='07_CASH_FLOW_WATERFALL'!G30 | H23: ='07_CASH_FLOW_WATERFALL'!H30 | I23: ='07_CASH_FLOW_WATERFALL'!I30 | J23: ='07_CASH_FLOW_WATERFALL'!J30 | K23: ='07_CASH_FLOW_WATERFALL'!K30 | L23: ='07_CASH_FLOW_WATERFALL'!L30
B24: Repayments | C24: DKKm | E24: 0 | F24: ='07_CASH_FLOW_WATERFALL'!F31 | G24: ='07_CASH_FLOW_WATERFALL'!G31 | H24: ='07_CASH_FLOW_WATERFALL'!H31 | I24: ='07_CASH_FLOW_WATERFALL'!I31 | J24: ='07_CASH_FLOW_WATERFALL'!J31 | K24: ='07_CASH_FLOW_WATERFALL'!K31 | L24: ='07_CASH_FLOW_WATERFALL'!L31
B25: Ending balance | C25: DKKm | E25: =E22+E23-E24 | F25: =F22+F23-F24 | G25: =G22+G23-G24 | H25: =H22+H23-H24 | I25: =I22+I23-I24 | J25: =J22+J23-J24 | K25: =K22+K23-K24 | L25: =L22+L23-L24
B26: All-in rate | C26: % | F26: =IF(IR_Mode="Fixed",'01_CONTROL'!$F$63,MAX(Bench_Rate+'01_CONTROL'!$D$63,'01_CONTROL'!$E$63)) | G26: =IF(IR_Mode="Fixed",'01_CONTROL'!$F$63,MAX(Bench_Rate+'01_CONTROL'!$D$63,'01_CONTROL'!$E$63)) | H26: =IF(IR_Mode="Fixed",'01_CONTROL'!$F$63,MAX(Bench_Rate+'01_CONTROL'!$D$63,'01_CONTROL'!$E$63)) | I26: =IF(IR_Mode="Fixed",'01_CONTROL'!$F$63,MAX(Bench_Rate+'01_CONTROL'!$D$63,'01_CONTROL'!$E$63)) | J26: =IF(IR_Mode="Fixed",'01_CONTROL'!$F$63,MAX(Bench_Rate+'01_CONTROL'!$D$63,'01_CONTROL'!$E$63)) | K26: =IF(IR_Mode="Fixed",'01_CONTROL'!$F$63,MAX(Bench_Rate+'01_CONTROL'!$D$63,'01_CONTROL'!$E$63)) | L26: =IF(IR_Mode="Fixed",'01_CONTROL'!$F$63,MAX(Bench_Rate+'01_CONTROL'!$D$63,'01_CONTROL'!$E$63))
B27: Cash interest | C27: DKKm | E27: 0 | F27: =F22*F26 | G27: =G22*G26 | H27: =H22*H26 | I27: =I22*I26 | J27: =J22*J26 | K27: =K22*K26 | L27: =L22*L26
B29: TERM LOAN A
B31: Opening balance | C31: DKKm | E31: ='06_DEBT_SCHEDULES'!$E$15 | F31: =E34 | G31: =F34 | H31: =G34 | I31: =H34 | J31: =I34 | K31: =J34 | L31: =K34
B32: Mandatory amortization | C32: DKKm | E32: 0 | F32: =MIN(F31,'01_CONTROL'!$C$64*F31) | G32: =MIN(G31,'01_CONTROL'!$C$64*G31) | H32: =MIN(H31,'01_CONTROL'!$C$64*H31) | I32: =MIN(I31,'01_CONTROL'!$C$64*I31) | J32: =MIN(J31,'01_CONTROL'!$C$64*J31) | K32: =MIN(K31,'01_CONTROL'!$C$64*K31) | L32: =MIN(L31,'01_CONTROL'!$C$64*L31)
B33: Optional sweep | C33: DKKm | E33: 0 | F33: ='07_CASH_FLOW_WATERFALL'!F33 | G33: ='07_CASH_FLOW_WATERFALL'!G33 | H33: ='07_CASH_FLOW_WATERFALL'!H33 | I33: ='07_CASH_FLOW_WATERFALL'!I33 | J33: ='07_CASH_FLOW_WATERFALL'!J33 | K33: ='07_CASH_FLOW_WATERFALL'!K33 | L33: ='07_CASH_FLOW_WATERFALL'!L33
B34: Ending balance | C34: DKKm | E34: =E31-E32-E33 | F34: =F31-F32-F33 | G34: =G31-G32-G33 | H34: =H31-H32-H33 | I34: =I31-I32-I33 | J34: =J31-J32-J33 | K34: =K31-K32-K33 | L34: =L31-L32-L33
B35: All-in rate | C35: % | F35: =IF(IR_Mode="Fixed",'01_CONTROL'!$F$64,MAX(Bench_Rate+'01_CONTROL'!$D$64,'01_CONTROL'!$E$64)) | G35: =IF(IR_Mode="Fixed",'01_CONTROL'!$F$64,MAX(Bench_Rate+'01_CONTROL'!$D$64,'01_CONTROL'!$E$64)) | H35: =IF(IR_Mode="Fixed",'01_CONTROL'!$F$64,MAX(Bench_Rate+'01_CONTROL'!$D$64,'01_CONTROL'!$E$64)) | I35: =IF(IR_Mode="Fixed",'01_CONTROL'!$F$64,MAX(Bench_Rate+'01_CONTROL'!$D$64,'01_CONTROL'!$E$64)) | J35: =IF(IR_Mode="Fixed",'01_CONTROL'!$F$64,MAX(Bench_Rate+'01_CONTROL'!$D$64,'01_CONTROL'!$E$64)) | K35: =IF(IR_Mode="Fixed",'01_CONTROL'!$F$64,MAX(Bench_Rate+'01_CONTROL'!$D$64,'01_CONTROL'!$E$64)) | L35: =IF(IR_Mode="Fixed",'01_CONTROL'!$F$64,MAX(Bench_Rate+'01_CONTROL'!$D$64,'01_CONTROL'!$E$64))
B36: Cash interest | C36: DKKm | E36: 0 | F36: =F31*F35 | G36: =G31*G35 | H36: =H31*H35 | I36: =I31*I35 | J36: =J31*J35 | K36: =K31*K35 | L36: =L31*L35
B38: TERM LOAN B
B40: Opening balance | C40: DKKm | E40: ='06_DEBT_SCHEDULES'!$E$16 | F40: =E43 | G40: =F43 | H40: =G43 | I40: =H43 | J40: =I43 | K40: =J43 | L40: =K43
B41: Mandatory amortization | C41: DKKm | E41: 0 | F41: =MIN(F40,'01_CONTROL'!$C$65*F40) | G41: =MIN(G40,'01_CONTROL'!$C$65*G40) | H41: =MIN(H40,'01_CONTROL'!$C$65*H40) | I41: =MIN(I40,'01_CONTROL'!$C$65*I40) | J41: =MIN(J40,'01_CONTROL'!$C$65*J40) | K41: =MIN(K40,'01_CONTROL'!$C$65*K40) | L41: =MIN(L40,'01_CONTROL'!$C$65*L40)
B42: Optional sweep | C42: DKKm | E42: 0 | F42: ='07_CASH_FLOW_WATERFALL'!F34 | G42: ='07_CASH_FLOW_WATERFALL'!G34 | H42: ='07_CASH_FLOW_WATERFALL'!H34 | I42: ='07_CASH_FLOW_WATERFALL'!I34 | J42: ='07_CASH_FLOW_WATERFALL'!J34 | K42: ='07_CASH_FLOW_WATERFALL'!K34 | L42: ='07_CASH_FLOW_WATERFALL'!L34
B43: Ending balance | C43: DKKm | E43: =E40-E41-E42 | F43: =F40-F41-F42 | G43: =G40-G41-G42 | H43: =H40-H41-H42 | I43: =I40-I41-I42 | J43: =J40-J41-J42 | K43: =K40-K41-K42 | L43: =L40-L41-L42
B44: All-in rate | C44: % | F44: =IF(IR_Mode="Fixed",'01_CONTROL'!$F$65,MAX(Bench_Rate+'01_CONTROL'!$D$65,'01_CONTROL'!$E$65)) | G44: =IF(IR_Mode="Fixed",'01_CONTROL'!$F$65,MAX(Bench_Rate+'01_CONTROL'!$D$65,'01_CONTROL'!$E$65)) | H44: =IF(IR_Mode="Fixed",'01_CONTROL'!$F$65,MAX(Bench_Rate+'01_CONTROL'!$D$65,'01_CONTROL'!$E$65)) | I44: =IF(IR_Mode="Fixed",'01_CONTROL'!$F$65,MAX(Bench_Rate+'01_CONTROL'!$D$65,'01_CONTROL'!$E$65)) | J44: =IF(IR_Mode="Fixed",'01_CONTROL'!$F$65,MAX(Bench_Rate+'01_CONTROL'!$D$65,'01_CONTROL'!$E$65)) | K44: =IF(IR_Mode="Fixed",'01_CONTROL'!$F$65,MAX(Bench_Rate+'01_CONTROL'!$D$65,'01_CONTROL'!$E$65)) | L44: =IF(IR_Mode="Fixed",'01_CONTROL'!$F$65,MAX(Bench_Rate+'01_CONTROL'!$D$65,'01_CONTROL'!$E$65))
B45: Cash interest | C45: DKKm | E45: 0 | F45: =F40*F44 | G45: =G40*G44 | H45: =H40*H44 | I45: =I40*I44 | J45: =J40*J44 | K45: =K40*K44 | L45: =L40*L44
B47: SENIOR SECURED NOTES
B49: Opening balance | C49: DKKm | E49: ='06_DEBT_SCHEDULES'!$E$17 | F49: =E52 | G49: =F52 | H49: =G52 | I49: =H52 | J49: =I52 | K49: =J52 | L49: =K52
B50: Mandatory amortization | C50: DKKm | E50: 0 | F50: =MIN(F49,'01_CONTROL'!$C$66*F49) | G50: =MIN(G49,'01_CONTROL'!$C$66*G49) | H50: =MIN(H49,'01_CONTROL'!$C$66*H49) | I50: =MIN(I49,'01_CONTROL'!$C$66*I49) | J50: =MIN(J49,'01_CONTROL'!$C$66*J49) | K50: =MIN(K49,'01_CONTROL'!$C$66*K49) | L50: =MIN(L49,'01_CONTROL'!$C$66*L49)
B51: Optional sweep | C51: DKKm | E51: 0 | F51: ='07_CASH_FLOW_WATERFALL'!F35 | G51: ='07_CASH_FLOW_WATERFALL'!G35 | H51: ='07_CASH_FLOW_WATERFALL'!H35 | I51: ='07_CASH_FLOW_WATERFALL'!I35 | J51: ='07_CASH_FLOW_WATERFALL'!J35 | K51: ='07_CASH_FLOW_WATERFALL'!K35 | L51: ='07_CASH_FLOW_WATERFALL'!L35
B52: Ending balance | C52: DKKm | E52: =E49-E50-E51 | F52: =F49-F50-F51 | G52: =G49-G50-G51 | H52: =H49-H50-H51 | I52: =I49-I50-I51 | J52: =J49-J50-J51 | K52: =K49-K50-K51 | L52: =L49-L50-L51
B53: All-in rate | C53: % | F53: =IF(IR_Mode="Fixed",'01_CONTROL'!$F$66,MAX(Bench_Rate+'01_CONTROL'!$D$66,'01_CONTROL'!$E$66)) | G53: =IF(IR_Mode="Fixed",'01_CONTROL'!$F$66,MAX(Bench_Rate+'01_CONTROL'!$D$66,'01_CONTROL'!$E$66)) | H53: =IF(IR_Mode="Fixed",'01_CONTROL'!$F$66,MAX(Bench_Rate+'01_CONTROL'!$D$66,'01_CONTROL'!$E$66)) | I53: =IF(IR_Mode="Fixed",'01_CONTROL'!$F$66,MAX(Bench_Rate+'01_CONTROL'!$D$66,'01_CONTROL'!$E$66)) | J53: =IF(IR_Mode="Fixed",'01_CONTROL'!$F$66,MAX(Bench_Rate+'01_CONTROL'!$D$66,'01_CONTROL'!$E$66)) | K53: =IF(IR_Mode="Fixed",'01_CONTROL'!$F$66,MAX(Bench_Rate+'01_CONTROL'!$D$66,'01_CONTROL'!$E$66)) | L53: =IF(IR_Mode="Fixed",'01_CONTROL'!$F$66,MAX(Bench_Rate+'01_CONTROL'!$D$66,'01_CONTROL'!$E$66))
B54: Cash interest | C54: DKKm | E54: 0 | F54: =F49*F53 | G54: =G49*G53 | H54: =H49*H53 | I54: =I49*I53 | J54: =J49*J53 | K54: =K49*K53 | L54: =L49*L53
B56: MEZZANINE / PIK
B58: Opening balance | C58: DKKm | E58: ='06_DEBT_SCHEDULES'!$E$18 | F58: =E61 | G58: =F61 | H58: =G61 | I58: =H61 | J58: =I61 | K58: =J61 | L58: =K61
B59: Mandatory amortization | C59: DKKm | E59: 0 | F59: =MIN(F58,'01_CONTROL'!$C$67*F58) | G59: =MIN(G58,'01_CONTROL'!$C$67*G58) | H59: =MIN(H58,'01_CONTROL'!$C$67*H58) | I59: =MIN(I58,'01_CONTROL'!$C$67*I58) | J59: =MIN(J58,'01_CONTROL'!$C$67*J58) | K59: =MIN(K58,'01_CONTROL'!$C$67*K58) | L59: =MIN(L58,'01_CONTROL'!$C$67*L58)
B60: Optional sweep | C60: DKKm | E60: 0 | F60: ='07_CASH_FLOW_WATERFALL'!F36 | G60: ='07_CASH_FLOW_WATERFALL'!G36 | H60: ='07_CASH_FLOW_WATERFALL'!H36 | I60: ='07_CASH_FLOW_WATERFALL'!I36 | J60: ='07_CASH_FLOW_WATERFALL'!J36 | K60: ='07_CASH_FLOW_WATERFALL'!K36 | L60: ='07_CASH_FLOW_WATERFALL'!L36
B61: Ending balance | C61: DKKm | E61: =E58-E59-E60 | F61: =F58-F59-F60 | G61: =G58-G59-G60 | H61: =H58-H59-H60 | I61: =I58-I59-I60 | J61: =J58-J59-J60 | K61: =K58-K59-K60 | L61: =L58-L59-L60
B62: All-in rate | C62: % | F62: =IF(IR_Mode="Fixed",'01_CONTROL'!$F$67,MAX(Bench_Rate+'01_CONTROL'!$D$67,'01_CONTROL'!$E$67)) | G62: =IF(IR_Mode="Fixed",'01_CONTROL'!$F$67,MAX(Bench_Rate+'01_CONTROL'!$D$67,'01_CONTROL'!$E$67)) | H62: =IF(IR_Mode="Fixed",'01_CONTROL'!$F$67,MAX(Bench_Rate+'01_CONTROL'!$D$67,'01_CONTROL'!$E$67)) | I62: =IF(IR_Mode="Fixed",'01_CONTROL'!$F$67,MAX(Bench_Rate+'01_CONTROL'!$D$67,'01_CONTROL'!$E$67)) | J62: =IF(IR_Mode="Fixed",'01_CONTROL'!$F$67,MAX(Bench_Rate+'01_CONTROL'!$D$67,'01_CONTROL'!$E$67)) | K62: =IF(IR_Mode="Fixed",'01_CONTROL'!$F$67,MAX(Bench_Rate+'01_CONTROL'!$D$67,'01_CONTROL'!$E$67)) | L62: =IF(IR_Mode="Fixed",'01_CONTROL'!$F$67,MAX(Bench_Rate+'01_CONTROL'!$D$67,'01_CONTROL'!$E$67))
B63: Cash interest | C63: DKKm | E63: 0 | F63: =F58*F62 | G63: =G58*G62 | H63: =H58*H62 | I63: =I58*I62 | J63: =J58*J62 | K63: =K58*K62 | L63: =L58*L62
B65: DEBT TOTALS
B67: Total debt (ending) | C67: DKKm | E67: =SUM(E25,E34,E43,E52,E61) | F67: =SUM(F25,F34,F43,F52,F61) | G67: =SUM(G25,G34,G43,G52,G61) | H67: =SUM(H25,H34,H43,H52,H61) | I67: =SUM(I25,I34,I43,I52,I61) | J67: =SUM(J25,J34,J43,J52,J61) | K67: =SUM(K25,K34,K43,K52,K61) | L67: =SUM(L25,L34,L43,L52,L61)

Sheet 07_CASH_FLOW_WATERFALL
B1: LBO Model Builder (Training Simulation)
B2: CHECKS: | C2: =HYPERLINK("#'90_CHECKS'!B6",'90_CHECKS'!$C$22)
B3: Checks: | C3: =HYPERLINK("#'90_CHECKS'!B2","Go to 90_CHECKS")
B4: Units: | C4: DKKm
B5: Version: | C5: v0.1
B6: Date: | C6: 46069
B7: Period end | E7: 46022 | F7: 46387 | G7: 46752 | H7: 47118 | I7: 47483 | J7: 47848 | K7: 48213 | L7: 48579
B8: Period | E8: LTM | F8: 2026E | G8: 2027E | H8: 2028E | I8: 2029E | J8: 2030E | K8: 2031E | L8: 2032E
B9: Year # | E9: 0 | F9: 1 | G9: 2 | H9: 3 | I9: 4 | J9: 5 | K9: 6 | L9: 7
B10: CASH FLOW WATERFALL (NON-CIRCULAR)
B12: CASH AVAILABLE FOR DEBT SERVICE (DKKM)
B14: EBITDA | C14: DKKm | E14: ='04_OPERATING_MODEL'!E15 | F14: ='04_OPERATING_MODEL'!F15 | G14: ='04_OPERATING_MODEL'!G15 | H14: ='04_OPERATING_MODEL'!H15 | I14: ='04_OPERATING_MODEL'!I15 | J14: ='04_OPERATING_MODEL'!J15 | K14: ='04_OPERATING_MODEL'!K15 | L14: ='04_OPERATING_MODEL'!L15
B15: Cash taxes (levered) | C15: DKKm | E15: =-MAX(0,'04_OPERATING_MODEL'!E18-E28)*'01_CONTROL'!$D$26 | F15: =-MAX(0,'04_OPERATING_MODEL'!F18-F28)*'01_CONTROL'!$D$26 | G15: =-MAX(0,'04_OPERATING_MODEL'!G18-G28)*'01_CONTROL'!$D$26 | H15: =-MAX(0,'04_OPERATING_MODEL'!H18-H28)*'01_CONTROL'!$D$26 | I15: =-MAX(0,'04_OPERATING_MODEL'!I18-I28)*'01_CONTROL'!$D$26 | J15: =-MAX(0,'04_OPERATING_MODEL'!J18-J28)*'01_CONTROL'!$D$26 | K15: =-MAX(0,'04_OPERATING_MODEL'!K18-K28)*'01_CONTROL'!$D$26 | L15: =-MAX(0,'04_OPERATING_MODEL'!L18-L28)*'01_CONTROL'!$D$26
B16: Change in NWC (cash effect) | C16: DKKm | E16: =-'04_OPERATING_MODEL'!E32 | F16: =-'04_OPERATING_MODEL'!F32 | G16: =-'04_OPERATING_MODEL'!G32 | H16: =-'04_OPERATING_MODEL'!H32 | I16: =-'04_OPERATING_MODEL'!I32 | J16: =-'04_OPERATING_MODEL'!J32 | K16: =-'04_OPERATING_MODEL'!K32 | L16: =-'04_OPERATING_MODEL'!L32
B17: Capex (cash effect) | C17: DKKm | E17: ='04_OPERATING_MODEL'!E36 | F17: ='04_OPERATING_MODEL'!F36 | G17: ='04_OPERATING_MODEL'!G36 | H17: ='04_OPERATING_MODEL'!H36 | I17: ='04_OPERATING_MODEL'!I36 | J17: ='04_OPERATING_MODEL'!J36 | K17: ='04_OPERATING_MODEL'!K36 | L17: ='04_OPERATING_MODEL'!L36
B18: Other (cash) | C18: DKKm | E18: 0 | F18: 0 | G18: 0 | H18: 0 | I18: 0 | J18: 0 | K18: 0 | L18: 0
B19: Cash before debt service | C19: DKKm | E19: =SUM(E14:E18) | F19: =SUM(F14:F18) | G19: =SUM(G14:G18) | H19: =SUM(H14:H18) | I19: =SUM(I14:I18) | J19: =SUM(J14:J18) | K19: =SUM(K14:K18) | L19: =SUM(L14:L18)
B20: Cash interest (total) | C20: DKKm | E20: =-('06_DEBT_SCHEDULES'!E27+'06_DEBT_SCHEDULES'!E36+'06_DEBT_SCHEDULES'!E45+'06_DEBT_SCHEDULES'!E54+'06_DEBT_SCHEDULES'!E63) | F20: =-('06_DEBT_SCHEDULES'!F27+'06_DEBT_SCHEDULES'!F36+'06_DEBT_SCHEDULES'!F45+'06_DEBT_SCHEDULES'!F54+'06_DEBT_SCHEDULES'!F63) | G20: =-('06_DEBT_SCHEDULES'!G27+'06_DEBT_SCHEDULES'!G36+'06_DEBT_SCHEDULES'!G45+'06_DEBT_SCHEDULES'!G54+'06_DEBT_SCHEDULES'!G63) | H20: =-('06_DEBT_SCHEDULES'!H27+'06_DEBT_SCHEDULES'!H36+'06_DEBT_SCHEDULES'!H45+'06_DEBT_SCHEDULES'!H54+'06_DEBT_SCHEDULES'!H63) | I20: =-('06_DEBT_SCHEDULES'!I27+'06_DEBT_SCHEDULES'!I36+'06_DEBT_SCHEDULES'!I45+'06_DEBT_SCHEDULES'!I54+'06_DEBT_SCHEDULES'!I63) | J20: =-('06_DEBT_SCHEDULES'!J27+'06_DEBT_SCHEDULES'!J36+'06_DEBT_SCHEDULES'!J45+'06_DEBT_SCHEDULES'!J54+'06_DEBT_SCHEDULES'!J63) | K20: =-('06_DEBT_SCHEDULES'!K27+'06_DEBT_SCHEDULES'!K36+'06_DEBT_SCHEDULES'!K45+'06_DEBT_SCHEDULES'!K54+'06_DEBT_SCHEDULES'!K63) | L20: =-('06_DEBT_SCHEDULES'!L27+'06_DEBT_SCHEDULES'!L36+'06_DEBT_SCHEDULES'!L45+'06_DEBT_SCHEDULES'!L54+'06_DEBT_SCHEDULES'!L63)
B21: Cash after interest | C21: DKKm | E21: =E19+E20 | F21: =F19+F20 | G21: =G19+G20 | H21: =H19+H20 | I21: =I19+I20 | J21: =J19+J20 | K21: =K19+K20 | L21: =L19+L20
B22: Mandatory amort (total) | C22: DKKm | E22: =-('06_DEBT_SCHEDULES'!E32+'06_DEBT_SCHEDULES'!E41+'06_DEBT_SCHEDULES'!E50+'06_DEBT_SCHEDULES'!E59) | F22: =-('06_DEBT_SCHEDULES'!F32+'06_DEBT_SCHEDULES'!F41+'06_DEBT_SCHEDULES'!F50+'06_DEBT_SCHEDULES'!F59) | G22: =-('06_DEBT_SCHEDULES'!G32+'06_DEBT_SCHEDULES'!G41+'06_DEBT_SCHEDULES'!G50+'06_DEBT_SCHEDULES'!G59) | H22: =-('06_DEBT_SCHEDULES'!H32+'06_DEBT_SCHEDULES'!H41+'06_DEBT_SCHEDULES'!H50+'06_DEBT_SCHEDULES'!H59) | I22: =-('06_DEBT_SCHEDULES'!I32+'06_DEBT_SCHEDULES'!I41+'06_DEBT_SCHEDULES'!I50+'06_DEBT_SCHEDULES'!I59) | J22: =-('06_DEBT_SCHEDULES'!J32+'06_DEBT_SCHEDULES'!J41+'06_DEBT_SCHEDULES'!J50+'06_DEBT_SCHEDULES'!J59) | K22: =-('06_DEBT_SCHEDULES'!K32+'06_DEBT_SCHEDULES'!K41+'06_DEBT_SCHEDULES'!K50+'06_DEBT_SCHEDULES'!K59) | L22: =-('06_DEBT_SCHEDULES'!L32+'06_DEBT_SCHEDULES'!L41+'06_DEBT_SCHEDULES'!L50+'06_DEBT_SCHEDULES'!L59)
B23: Cash after mandatory amort | C23: DKKm | E23: =E21+E22 | F23: =F21+F22 | G23: =G21+G22 | H23: =H21+H22 | I23: =I21+I22 | J23: =J21+J22 | K23: =K21+K22 | L23: =L21+L22
B24: Sweep % (active) | C24: % | E24: ='01_CONTROL'!$G$54 | F24: ='01_CONTROL'!$G$54 | G24: ='01_CONTROL'!$G$54 | H24: ='01_CONTROL'!$G$54 | I24: ='01_CONTROL'!$G$54 | J24: ='01_CONTROL'!$G$54 | K24: ='01_CONTROL'!$G$54 | L24: ='01_CONTROL'!$G$54
B25: Cash available for optional sweep | C25: DKKm | E25: =MAX(0,E23)*E24 | F25: =MAX(0,F23)*F24 | G25: =MAX(0,G23)*G24 | H25: =MAX(0,H23)*H24 | I25: =MAX(0,I23)*I24 | J25: =MAX(0,J23)*J24 | K25: =MAX(0,K23)*K24 | L25: =MAX(0,L23)*L24
B26: Retained cash (non-swept) | C26: DKKm | E26: =MAX(0,E23)-E25 | F26: =MAX(0,F23)-F25 | G26: =MAX(0,G23)-G25 | H26: =MAX(0,H23)-H25 | I26: =MAX(0,I23)-I25 | J26: =MAX(0,J23)-J25 | K26: =MAX(0,K23)-K25 | L26: =MAX(0,L23)-L25
B27: Cash deficit (requires revolver draw) | C27: DKKm | E27: =-MIN(0,E23) | F27: =-MIN(0,F23) | G27: =-MIN(0,G23) | H27: =-MIN(0,H23) | I27: =-MIN(0,I23) | J27: =-MIN(0,J23) | K27: =-MIN(0,K23) | L27: =-MIN(0,L23)
B28: Interest sum helper (positive) | C28: DKKm | E28: 0 | F28: =('06_DEBT_SCHEDULES'!F27+'06_DEBT_SCHEDULES'!F36+'06_DEBT_SCHEDULES'!F45+'06_DEBT_SCHEDULES'!F54+'06_DEBT_SCHEDULES'!F63) | G28: =('06_DEBT_SCHEDULES'!G27+'06_DEBT_SCHEDULES'!G36+'06_DEBT_SCHEDULES'!G45+'06_DEBT_SCHEDULES'!G54+'06_DEBT_SCHEDULES'!G63) | H28: =('06_DEBT_SCHEDULES'!H27+'06_DEBT_SCHEDULES'!H36+'06_DEBT_SCHEDULES'!H45+'06_DEBT_SCHEDULES'!H54+'06_DEBT_SCHEDULES'!H63) | I28: =('06_DEBT_SCHEDULES'!I27+'06_DEBT_SCHEDULES'!I36+'06_DEBT_SCHEDULES'!I45+'06_DEBT_SCHEDULES'!I54+'06_DEBT_SCHEDULES'!I63) | J28: =('06_DEBT_SCHEDULES'!J27+'06_DEBT_SCHEDULES'!J36+'06_DEBT_SCHEDULES'!J45+'06_DEBT_SCHEDULES'!J54+'06_DEBT_SCHEDULES'!J63) | K28: =('06_DEBT_SCHEDULES'!K27+'06_DEBT_SCHEDULES'!K36+'06_DEBT_SCHEDULES'!K45+'06_DEBT_SCHEDULES'!K54+'06_DEBT_SCHEDULES'!K63) | L28: =('06_DEBT_SCHEDULES'!L27+'06_DEBT_SCHEDULES'!L36+'06_DEBT_SCHEDULES'!L45+'06_DEBT_SCHEDULES'!L54+'06_DEBT_SCHEDULES'!L63)
B29: ALLOCATION: REVOLVER THEN SWEEP ORDER
B30: Revolver draw | C30: DKKm | E30: 0 | F30: =MIN('06_DEBT_SCHEDULES'!$E$14-'06_DEBT_SCHEDULES'!F22, F27) | G30: =MIN('06_DEBT_SCHEDULES'!$E$14-'06_DEBT_SCHEDULES'!G22, G27) | H30: =MIN('06_DEBT_SCHEDULES'!$E$14-'06_DEBT_SCHEDULES'!H22, H27) | I30: =MIN('06_DEBT_SCHEDULES'!$E$14-'06_DEBT_SCHEDULES'!I22, I27) | J30: =MIN('06_DEBT_SCHEDULES'!$E$14-'06_DEBT_SCHEDULES'!J22, J27) | K30: =MIN('06_DEBT_SCHEDULES'!$E$14-'06_DEBT_SCHEDULES'!K22, K27) | L30: =MIN('06_DEBT_SCHEDULES'!$E$14-'06_DEBT_SCHEDULES'!L22, L27)
B31: Revolver repay | C31: DKKm | E31: 0 | F31: =MIN('06_DEBT_SCHEDULES'!F22, F25) | G31: =MIN('06_DEBT_SCHEDULES'!G22, G25) | H31: =MIN('06_DEBT_SCHEDULES'!H22, H25) | I31: =MIN('06_DEBT_SCHEDULES'!I22, I25) | J31: =MIN('06_DEBT_SCHEDULES'!J22, J25) | K31: =MIN('06_DEBT_SCHEDULES'!K22, K25) | L31: =MIN('06_DEBT_SCHEDULES'!L22, L25)
B32: Remaining sweep after revolver | C32: DKKm | E32: 0 | F32: =MAX(0,F25-F31) | G32: =MAX(0,G25-G31) | H32: =MAX(0,H25-H31) | I32: =MAX(0,I25-I31) | J32: =MAX(0,J25-J31) | K32: =MAX(0,K25-K31) | L32: =MAX(0,L25-L31)
B33: Sweep to Term Loan B | C33: DKKm | E33: 0 | F33: =MIN(F32, MAX(0,'06_DEBT_SCHEDULES'!F40-'06_DEBT_SCHEDULES'!F41)) | G33: =MIN(G32, MAX(0,'06_DEBT_SCHEDULES'!G40-'06_DEBT_SCHEDULES'!G41)) | H33: =MIN(H32, MAX(0,'06_DEBT_SCHEDULES'!H40-'06_DEBT_SCHEDULES'!H41)) | I33: =MIN(I32, MAX(0,'06_DEBT_SCHEDULES'!I40-'06_DEBT_SCHEDULES'!I41)) | J33: =MIN(J32, MAX(0,'06_DEBT_SCHEDULES'!J40-'06_DEBT_SCHEDULES'!J41)) | K33: =MIN(K32, MAX(0,'06_DEBT_SCHEDULES'!K40-'06_DEBT_SCHEDULES'!K41)) | L33: =MIN(L32, MAX(0,'06_DEBT_SCHEDULES'!L40-'06_DEBT_SCHEDULES'!L41))
B34: Sweep to Term Loan A | C34: DKKm | E34: 0 | F34: =MIN(MAX(0,F32-F33), MAX(0,'06_DEBT_SCHEDULES'!F31-'06_DEBT_SCHEDULES'!F32)) | G34: =MIN(MAX(0,G32-G33), MAX(0,'06_DEBT_SCHEDULES'!G31-'06_DEBT_SCHEDULES'!G32)) | H34: =MIN(MAX(0,H32-H33), MAX(0,'06_DEBT_SCHEDULES'!H31-'06_DEBT_SCHEDULES'!H32)) | I34: =MIN(MAX(0,I32-I33), MAX(0,'06_DEBT_SCHEDULES'!I31-'06_DEBT_SCHEDULES'!I32)) | J34: =MIN(MAX(0,J32-J33), MAX(0,'06_DEBT_SCHEDULES'!J31-'06_DEBT_SCHEDULES'!J32)) | K34: =MIN(MAX(0,K32-K33), MAX(0,'06_DEBT_SCHEDULES'!K31-'06_DEBT_SCHEDULES'!K32)) | L34: =MIN(MAX(0,L32-L33), MAX(0,'06_DEBT_SCHEDULES'!L31-'06_DEBT_SCHEDULES'!L32))
B35: Sweep to SSN | C35: DKKm | E35: 0 | F35: =MIN(MAX(0,F32-F33-F34), MAX(0,'06_DEBT_SCHEDULES'!F49-'06_DEBT_SCHEDULES'!F50)) | G35: =MIN(MAX(0,G32-G33-G34), MAX(0,'06_DEBT_SCHEDULES'!G49-'06_DEBT_SCHEDULES'!G50)) | H35: =MIN(MAX(0,H32-H33-H34), MAX(0,'06_DEBT_SCHEDULES'!H49-'06_DEBT_SCHEDULES'!H50)) | I35: =MIN(MAX(0,I32-I33-I34), MAX(0,'06_DEBT_SCHEDULES'!I49-'06_DEBT_SCHEDULES'!I50)) | J35: =MIN(MAX(0,J32-J33-J34), MAX(0,'06_DEBT_SCHEDULES'!J49-'06_DEBT_SCHEDULES'!J50)) | K35: =MIN(MAX(0,K32-K33-K34), MAX(0,'06_DEBT_SCHEDULES'!K49-'06_DEBT_SCHEDULES'!K50)) | L35: =MIN(MAX(0,L32-L33-L34), MAX(0,'06_DEBT_SCHEDULES'!L49-'06_DEBT_SCHEDULES'!L50))
B36: Sweep to Mezz/PIK | C36: DKKm | E36: 0 | F36: =MIN(MAX(0,F32-F33-F34-F35), MAX(0,'06_DEBT_SCHEDULES'!F58-'06_DEBT_SCHEDULES'!F59)) | G36: =MIN(MAX(0,G32-G33-G34-G35), MAX(0,'06_DEBT_SCHEDULES'!G58-'06_DEBT_SCHEDULES'!G59)) | H36: =MIN(MAX(0,H32-H33-H34-H35), MAX(0,'06_DEBT_SCHEDULES'!H58-'06_DEBT_SCHEDULES'!H59)) | I36: =MIN(MAX(0,I32-I33-I34-I35), MAX(0,'06_DEBT_SCHEDULES'!I58-'06_DEBT_SCHEDULES'!I59)) | J36: =MIN(MAX(0,J32-J33-J34-J35), MAX(0,'06_DEBT_SCHEDULES'!J58-'06_DEBT_SCHEDULES'!J59)) | K36: =MIN(MAX(0,K32-K33-K34-K35), MAX(0,'06_DEBT_SCHEDULES'!K58-'06_DEBT_SCHEDULES'!K59)) | L36: =MIN(MAX(0,L32-L33-L34-L35), MAX(0,'06_DEBT_SCHEDULES'!L58-'06_DEBT_SCHEDULES'!L59))
B38: CASH BALANCE
B40: Residual sweep (not allocated) | C40: DKKm | E40: 0 | F40: =MAX(0,F32-F33-F34-F35-F36) | G40: =MAX(0,G32-G33-G34-G35-G36) | H40: =MAX(0,H32-H33-H34-H35-H36) | I40: =MAX(0,I32-I33-I34-I35-I36) | J40: =MAX(0,J32-J33-J34-J35-J36) | K40: =MAX(0,K32-K33-K34-K35-K36) | L40: =MAX(0,L32-L33-L34-L35-L36)
B41: Ending cash balance | C41: DKKm | E41: ='01_CONTROL'!$D$33 | F41: =IF(F27>0,0,F26+F40) | G41: =IF(G27>0,0,G26+G40) | H41: =IF(H27>0,0,H26+H40) | I41: =IF(I27>0,0,I26+I40) | J41: =IF(J27>0,0,J26+J40) | K41: =IF(K27>0,0,K26+K40) | L41: =IF(L27>0,0,L26+L40)
B42: Cash bridge check (should be 0) | C42: DKKm | E42: 0 | F42: =F23 - (F26+F31+F33+F34+F35+F36+F40) + F30 | G42: =G23 - (G26+G31+G33+G34+G35+G36+G40) + G30 | H42: =H23 - (H26+H31+H33+H34+H35+H36+H40) + H30 | I42: =I23 - (I26+I31+I33+I34+I35+I36+I40) + I30 | J42: =J23 - (J26+J31+J33+J34+J35+J36+J40) + J30 | K42: =K23 - (K26+K31+K33+K34+K35+K36+K40) + K30 | L42: =L23 - (L26+L31+L33+L34+L35+L36+L40) + L30

Sheet 08_EXIT_AND_EQUITY_BRIDGE
B1: LBO Model Builder (Training Simulation)
B2: CHECKS: | C2: =HYPERLINK("#'90_CHECKS'!B6",'90_CHECKS'!$C$22)
B3: Checks: | C3: =HYPERLINK("#'90_CHECKS'!B2","Go to 90_CHECKS")
B4: Units: | C4: DKKm
B5: Version: | C5: v0.1
B6: Date: | C6: 46069
B10: EXIT AND EQUITY BRIDGE
B12: EXIT ASSUMPTIONS AND EV
B14: Exit year (hold period, years) | D14: ='01_CONTROL'!$D$14
B15: Exit EBITDA (DKKm) | D15: =INDEX('04_OPERATING_MODEL'!$E$15:$L$15,1,Hold_Col)
B16: Exit method | D16: ='01_CONTROL'!$D$17
B17: Exit multiple (x) | D17: ='01_CONTROL'!$D$18
B18: Exit equity value target (DKKm) | D18: ='01_CONTROL'!$D$19
B19: Exit fees (% EV) | D19: ='01_CONTROL'!$D$35
B21: EV TO EQUITY BRIDGE (DKKM)
B23: Exit EV (DKKm) | D23: =IF(Exit_Method="Exit Multiple", D15*Exit_Multiple, (Exit_Equity_Target + D24 - D25)/(1-D19))
B24: Less: net debt at exit | D24: =INDEX('06_DEBT_SCHEDULES'!$E$67:$L$67,1,Hold_Col)
B25: Plus: cash at exit | D25: =INDEX('07_CASH_FLOW_WATERFALL'!$E$41:$L$41,1,Hold_Col)
B26: Less: exit fees | D26: =D23*D19
B27: Exit equity proceeds | D27: =D23-D24+D25-D26
B29: EQUITY PROCEEDS SPLIT (DKKM)
B31: Sponsor equity invested | D31: ='05_SOURCES_AND_USES'!$D$38
B32: Mgmt equity invested | D32: ='05_SOURCES_AND_USES'!$D$39
B33: Total equity invested | D33: ='05_SOURCES_AND_USES'!$D$40
B34: Sponsor ownership (%) | D34: =IF(D33=0,0,D31/D33)
B35: Sponsor proceeds at exit | D35: =D27*D34
B36: Mgmt proceeds at exit | D36: =D27-D35

Sheet 09_RETURNS
B1: LBO Model Builder (Training Simulation)
B2: CHECKS: | C2: =HYPERLINK("#'90_CHECKS'!B6",'90_CHECKS'!$C$22)
B3: Checks: | C3: =HYPERLINK("#'90_CHECKS'!B2","Go to 90_CHECKS")
B4: Units: | C4: DKKm
B5: Version: | C5: v0.1
B6: Date: | C6: 46069
E9: ='04_OPERATING_MODEL'!E9 | F9: ='04_OPERATING_MODEL'!F9 | G9: ='04_OPERATING_MODEL'!G9 | H9: ='04_OPERATING_MODEL'!H9 | I9: ='04_OPERATING_MODEL'!I9 | J9: ='04_OPERATING_MODEL'!J9 | K9: ='04_OPERATING_MODEL'!K9 | L9: ='04_OPERATING_MODEL'!L9
B10: RETURNS
B12: EQUITY CASH FLOWS (DKKM)
B14: Sponsor equity CF | C14: DKKm | E14: =-'05_SOURCES_AND_USES'!$D$38 | F14: =IF(F9=Hold_Y,'08_EXIT_AND_EQUITY_BRIDGE'!$D$35,0) | G14: =IF(G9=Hold_Y,'08_EXIT_AND_EQUITY_BRIDGE'!$D$35,0) | H14: =IF(H9=Hold_Y,'08_EXIT_AND_EQUITY_BRIDGE'!$D$35,0) | I14: =IF(I9=Hold_Y,'08_EXIT_AND_EQUITY_BRIDGE'!$D$35,0) | J14: =IF(J9=Hold_Y,'08_EXIT_AND_EQUITY_BRIDGE'!$D$35,0) | K14: =IF(K9=Hold_Y,'08_EXIT_AND_EQUITY_BRIDGE'!$D$35,0) | L14: =IF(L9=Hold_Y,'08_EXIT_AND_EQUITY_BRIDGE'!$D$35,0)
B15: Mgmt equity CF | C15: DKKm | E15: =-'05_SOURCES_AND_USES'!$D$39 | F15: =IF(F9=Hold_Y,'08_EXIT_AND_EQUITY_BRIDGE'!$D$36,0) | G15: =IF(G9=Hold_Y,'08_EXIT_AND_EQUITY_BRIDGE'!$D$36,0) | H15: =IF(H9=Hold_Y,'08_EXIT_AND_EQUITY_BRIDGE'!$D$36,0) | I15: =IF(I9=Hold_Y,'08_EXIT_AND_EQUITY_BRIDGE'!$D$36,0) | J15: =IF(J9=Hold_Y,'08_EXIT_AND_EQUITY_BRIDGE'!$D$36,0) | K15: =IF(K9=Hold_Y,'08_EXIT_AND_EQUITY_BRIDGE'!$D$36,0) | L15: =IF(L9=Hold_Y,'08_EXIT_AND_EQUITY_BRIDGE'!$D$36,0)
B16: Total equity CF | C16: DKKm | E16: =E14+E15 | F16: =F14+F15 | G16: =G14+G15 | H16: =H14+H15 | I16: =I14+I15 | J16: =J14+J15 | K16: =K14+K15 | L16: =L14+L15
B18: KEY METRICS
B20: Sponsor IRR | D20: =IRR(OFFSET($E$14,0,0,1,Hold_Col))
B21: Sponsor MOIC | D21: =IF('05_SOURCES_AND_USES'!$D$38=0,0,'08_EXIT_AND_EQUITY_BRIDGE'!$D$35/'05_SOURCES_AND_USES'!$D$38)
B22: Mgmt IRR | D22: =IRR(OFFSET($E$15,0,0,1,Hold_Col))
B23: Total equity IRR | D23: =IRR(OFFSET($E$16,0,0,1,Hold_Col))
B24: Total equity MOIC | D24: =IF('05_SOURCES_AND_USES'!$D$40=0,0,'08_EXIT_AND_EQUITY_BRIDGE'!$D$27/'05_SOURCES_AND_USES'!$D$40)
B25: Deleveraging (Net debt entry -> exit) | D25: ='05_SOURCES_AND_USES'!$D$37 - '08_EXIT_AND_EQUITY_BRIDGE'!$D$24

Sheet 10_COVENANTS_AND_CREDIT_METRICS
B1: LBO Model Builder (Training Simulation)
B2: CHECKS: | C2: =HYPERLINK("#'90_CHECKS'!B6",'90_CHECKS'!$C$22)
B3: Checks: | C3: =HYPERLINK("#'90_CHECKS'!B2","Go to 90_CHECKS")
B4: Units: | C4: DKKm
B5: Version: | C5: v0.1
B6: Date: | C6: 46069
B7: Period end | E7: 46022 | F7: 46387 | G7: 46752 | H7: 47118 | I7: 47483 | J7: 47848 | K7: 48213 | L7: 48579
B8: Period | E8: LTM | F8: 2026E | G8: 2027E | H8: 2028E | I8: 2029E | J8: 2030E | K8: 2031E | L8: 2032E
B9: Year # | E9: 0 | F9: 1 | G9: 2 | H9: 3 | I9: 4 | J9: 5 | K9: 6 | L9: 7
B10: COVENANTS AND CREDIT METRICS
B12: CREDIT METRICS (DKKM / X)
B14: EBITDA | C14: DKKm | E14: ='04_OPERATING_MODEL'!E15 | F14: ='04_OPERATING_MODEL'!F15 | G14: ='04_OPERATING_MODEL'!G15 | H14: ='04_OPERATING_MODEL'!H15 | I14: ='04_OPERATING_MODEL'!I15 | J14: ='04_OPERATING_MODEL'!J15 | K14: ='04_OPERATING_MODEL'!K15 | L14: ='04_OPERATING_MODEL'!L15
B15: Total debt (ending) | C15: DKKm | E15: ='06_DEBT_SCHEDULES'!E67 | F15: ='06_DEBT_SCHEDULES'!F67 | G15: ='06_DEBT_SCHEDULES'!G67 | H15: ='06_DEBT_SCHEDULES'!H67 | I15: ='06_DEBT_SCHEDULES'!I67 | J15: ='06_DEBT_SCHEDULES'!J67 | K15: ='06_DEBT_SCHEDULES'!K67 | L15: ='06_DEBT_SCHEDULES'!L67
B16: Cash (ending) | C16: DKKm | E16: ='07_CASH_FLOW_WATERFALL'!E41 | F16: ='07_CASH_FLOW_WATERFALL'!F41 | G16: ='07_CASH_FLOW_WATERFALL'!G41 | H16: ='07_CASH_FLOW_WATERFALL'!H41 | I16: ='07_CASH_FLOW_WATERFALL'!I41 | J16: ='07_CASH_FLOW_WATERFALL'!J41 | K16: ='07_CASH_FLOW_WATERFALL'!K41 | L16: ='07_CASH_FLOW_WATERFALL'!L41
B17: Net debt | C17: DKKm | E17: =E15-E16 | F17: =F15-F16 | G17: =G15-G16 | H17: =H15-H16 | I17: =I15-I16 | J17: =J15-J16 | K17: =K15-K16 | L17: =L15-L16
B18: Gross leverage (x) | C18: x | E18: =IF(E14=0,0,E15/E14) | F18: =IF(F14=0,0,F15/F14) | G18: =IF(G14=0,0,G15/G14) | H18: =IF(H14=0,0,H15/H14) | I18: =IF(I14=0,0,I15/I14) | J18: =IF(J14=0,0,J15/J14) | K18: =IF(K14=0,0,K15/K14) | L18: =IF(L14=0,0,L15/L14)
B19: Net leverage (x) | C19: x | E19: =IF(E14=0,0,E17/E14) | F19: =IF(F14=0,0,F17/F14) | G19: =IF(G14=0,0,G17/G14) | H19: =IF(H14=0,0,H17/H14) | I19: =IF(I14=0,0,I17/I14) | J19: =IF(J14=0,0,J17/J14) | K19: =IF(K14=0,0,K17/K14) | L19: =IF(L14=0,0,L17/L14)
B20: Cash interest (positive) | C20: DKKm | E20: ='07_CASH_FLOW_WATERFALL'!E28 | F20: ='07_CASH_FLOW_WATERFALL'!F28 | G20: ='07_CASH_FLOW_WATERFALL'!G28 | H20: ='07_CASH_FLOW_WATERFALL'!H28 | I20: ='07_CASH_FLOW_WATERFALL'!I28 | J20: ='07_CASH_FLOW_WATERFALL'!J28 | K20: ='07_CASH_FLOW_WATERFALL'!K28 | L20: ='07_CASH_FLOW_WATERFALL'!L28
B21: Interest coverage (x) | C21: x | E21: =IF(E20=0,0,E14/E20) | F21: =IF(F20=0,0,F14/F20) | G21: =IF(G20=0,0,G14/G20) | H21: =IF(H20=0,0,H14/H20) | I21: =IF(I20=0,0,I14/I20) | J21: =IF(J20=0,0,J14/J20) | K21: =IF(K20=0,0,K14/K20) | L21: =IF(L20=0,0,L14/L20)
B22: Undrawn revolver | C22: DKKm | E22: ='06_DEBT_SCHEDULES'!$E$14-'06_DEBT_SCHEDULES'!E25 | F22: ='06_DEBT_SCHEDULES'!$F$14-'06_DEBT_SCHEDULES'!F25 | G22: ='06_DEBT_SCHEDULES'!$G$14-'06_DEBT_SCHEDULES'!G25 | H22: ='06_DEBT_SCHEDULES'!$H$14-'06_DEBT_SCHEDULES'!H25 | I22: ='06_DEBT_SCHEDULES'!$I$14-'06_DEBT_SCHEDULES'!I25 | J22: ='06_DEBT_SCHEDULES'!$J$14-'06_DEBT_SCHEDULES'!J25 | K22: ='06_DEBT_SCHEDULES'!$K$14-'06_DEBT_SCHEDULES'!K25 | L22: ='06_DEBT_SCHEDULES'!$L$14-'06_DEBT_SCHEDULES'!L25
B23: Liquidity (cash + undrawn) | C23: DKKm | E23: =E16+E22 | F23: =F16+F22 | G23: =G16+G22 | H23: =H16+H22 | I23: =I16+I22 | J23: =J16+J22 | K23: =K16+K22 | L23: =L16+L22
B25: COVENANT HEADROOM
B27: Net leverage headroom (max - actual) | C27: x | E27: =Coven_NetLev_Max-E19 | F27: =Coven_NetLev_Max-F19 | G27: =Coven_NetLev_Max-G19 | H27: =Coven_NetLev_Max-H19 | I27: =Coven_NetLev_Max-I19 | J27: =Coven_NetLev_Max-J19 | K27: =Coven_NetLev_Max-K19 | L27: =Coven_NetLev_Max-L19
B28: Interest coverage headroom (actual - min) | C28: x | E28: =E21-Coven_IntCov_Min | F28: =F21-Coven_IntCov_Min | G28: =G21-Coven_IntCov_Min | H28: =H21-Coven_IntCov_Min | I28: =I21-Coven_IntCov_Min | J28: =J21-Coven_IntCov_Min | K28: =K21-Coven_IntCov_Min | L28: =L21-Coven_IntCov_Min
B29: Liquidity headroom (actual - target) | C29: DKKm | E29: =E23-Min_Liq_Target | F29: =F23-Min_Liq_Target | G29: =G23-Min_Liq_Target | H29: =H23-Min_Liq_Target | I29: =I23-Min_Liq_Target | J29: =J23-Min_Liq_Target | K29: =K23-Min_Liq_Target | L29: =L23-Min_Liq_Target
B32: SUMMARY (FOR DASHBOARD TILES)
B34: Peak net leverage (x) | D34: =MAX($F$19:$L$19)
B35: Min liquidity (DKKm) | D35: =MIN($F$23:$L$23)
B36: Min covenant headroom (net lev, x) | D36: =MIN($F$27:$L$27)
B37: Min covenant headroom (int cov, x) | D37: =MIN($F$28:$L$28)

Sheet 11_SENSITIVITIES
B2: CHECKS: | C2: =HYPERLINK("#'90_CHECKS'!B6",'90_CHECKS'!$C$22)
B4: Sensitivities (data tables)
B6: Data tables compute in Excel. Set Calculation to Automatic.
B8: IRR heatmap: Exit multiple vs Revenue growth (proxy for EBITDA CAGR)
C12: ='09_RETURNS'!$D$20 | D12: -0.02 | E12: 0 | F12: 0.02 | G12: 0.04 | H12: 0.06 | I12: 0.08 | J12: 0.1
C13: 7
C14: 8
C15: 9 | K15: SENSITIVITY HELPERS (links to core model)
C16: 10 | K16: LTM EBITDA (DKKm) | L16: ='01_CONTROL'!$D$32
C17: 11 | K17: Leverage target (x) | L17: ='01_CONTROL'!$D$48
K18: Total new debt (DKKm) | L18: =$L$16*$L$17
K19: Debt at exit (DKKm) | L19: =INDEX('06_DEBT_SCHEDULES'!$E$67:$L$67,1,Hold_Col)
K20: Cash at exit (DKKm) | L20: =INDEX('07_CASH_FLOW_WATERFALL'!$E$41:$L$41,1,Hold_Col)
K21: Exit EBITDA (DKKm) | L21: =INDEX('04_OPERATING_MODEL'!$E$15:$L$15,1,Hold_Col)
K22: Exit fees (% EV) | L22: ='01_CONTROL'!$D$35
D23: 9 | E23: 10 | F23: 11 | G23: 12 | H23: 13 | I23: 14 | K23: Advisory fee (% EV) | L23: ='01_CONTROL'!$D$56
C24: 7 | D24: =IFERROR(IF(((D$23*$L$16)*(1+$L$23)+$L$18*$L$24-$L$18)<=0,NA(),((($C24*$L$21)-$L$19+$L$20-($C24*$L$21)*$L$22)/((D$23*$L$16)*(1+$L$23)+$L$18*$L$24-$L$18))^(1/Hold_Y)-1),NA()) | E24: =IFERROR(IF(((E$23*$L$16)*(1+$L$23)+$L$18*$L$24-$L$18)<=0,NA(),((($C24*$L$21)-$L$19+$L$20-($C24*$L$21)*$L$22)/((E$23*$L$16)*(1+$L$23)+$L$18*$L$24-$L$18))^(1/Hold_Y)-1),NA()) | F24: =IFERROR(IF(((F$23*$L$16)*(1+$L$23)+$L$18*$L$24-$L$18)<=0,NA(),((($C24*$L$21)-$L$19+$L$20-($C24*$L$21)*$L$22)/((F$23*$L$16)*(1+$L$23)+$L$18*$L$24-$L$18))^(1/Hold_Y)-1),NA()) | G24: =IFERROR(IF(((G$23*$L$16)*(1+$L$23)+$L$18*$L$24-$L$18)<=0,NA(),((($C24*$L$21)-$L$19+$L$20-($C24*$L$21)*$L$22)/((G$23*$L$16)*(1+$L$23)+$L$18*$L$24-$L$18))^(1/Hold_Y)-1),NA()) | H24: =IFERROR(IF(((H$23*$L$16)*(1+$L$23)+$L$18*$L$24-$L$18)<=0,NA(),((($C24*$L$21)-$L$19+$L$20-($C24*$L$21)*$L$22)/((H$23*$L$16)*(1+$L$23)+$L$18*$L$24-$L$18))^(1/Hold_Y)-1),NA()) | I24: =IFERROR(IF(((I$23*$L$16)*(1+$L$23)+$L$18*$L$24-$L$18)<=0,NA(),((($C24*$L$21)-$L$19+$L$20-($C24*$L$21)*$L$22)/((I$23*$L$16)*(1+$L$23)+$L$18*$L$24-$L$18))^(1/Hold_Y)-1),NA()) | K24: Financing fee (% debt) | L24: ='01_CONTROL'!$D$57
C25: 8 | D25: =IFERROR(IF(((D$23*$L$16)*(1+$L$23)+$L$18*$L$24-$L$18)<=0,NA(),((($C25*$L$21)-$L$19+$L$20-($C25*$L$21)*$L$22)/((D$23*$L$16)*(1+$L$23)+$L$18*$L$24-$L$18))^(1/Hold_Y)-1),NA()) | E25: =IFERROR(IF(((E$23*$L$16)*(1+$L$23)+$L$18*$L$24-$L$18)<=0,NA(),((($C25*$L$21)-$L$19+$L$20-($C25*$L$21)*$L$22)/((E$23*$L$16)*(1+$L$23)+$L$18*$L$24-$L$18))^(1/Hold_Y)-1),NA()) | F25: =IFERROR(IF(((F$23*$L$16)*(1+$L$23)+$L$18*$L$24-$L$18)<=0,NA(),((($C25*$L$21)-$L$19+$L$20-($C25*$L$21)*$L$22)/((F$23*$L$16)*(1+$L$23)+$L$18*$L$24-$L$18))^(1/Hold_Y)-1),NA()) | G25: =IFERROR(IF(((G$23*$L$16)*(1+$L$23)+$L$18*$L$24-$L$18)<=0,NA(),((($C25*$L$21)-$L$19+$L$20-($C25*$L$21)*$L$22)/((G$23*$L$16)*(1+$L$23)+$L$18*$L$24-$L$18))^(1/Hold_Y)-1),NA()) | H25: =IFERROR(IF(((H$23*$L$16)*(1+$L$23)+$L$18*$L$24-$L$18)<=0,NA(),((($C25*$L$21)-$L$19+$L$20-($C25*$L$21)*$L$22)/((H$23*$L$16)*(1+$L$23)+$L$18*$L$24-$L$18))^(1/Hold_Y)-1),NA()) | I25: =IFERROR(IF(((I$23*$L$16)*(1+$L$23)+$L$18*$L$24-$L$18)<=0,NA(),((($C25*$L$21)-$L$19+$L$20-($C25*$L$21)*$L$22)/((I$23*$L$16)*(1+$L$23)+$L$18*$L$24-$L$18))^(1/Hold_Y)-1),NA()) | K25: Mgmt rollover (% equity) | L25: ='01_CONTROL'!$D$55
C26: 9 | D26: =IFERROR(IF(((D$23*$L$16)*(1+$L$23)+$L$18*$L$24-$L$18)<=0,NA(),((($C26*$L$21)-$L$19+$L$20-($C26*$L$21)*$L$22)/((D$23*$L$16)*(1+$L$23)+$L$18*$L$24-$L$18))^(1/Hold_Y)-1),NA()) | E26: =IFERROR(IF(((E$23*$L$16)*(1+$L$23)+$L$18*$L$24-$L$18)<=0,NA(),((($C26*$L$21)-$L$19+$L$20-($C26*$L$21)*$L$22)/((E$23*$L$16)*(1+$L$23)+$L$18*$L$24-$L$18))^(1/Hold_Y)-1),NA()) | F26: =IFERROR(IF(((F$23*$L$16)*(1+$L$23)+$L$18*$L$24-$L$18)<=0,NA(),((($C26*$L$21)-$L$19+$L$20-($C26*$L$21)*$L$22)/((F$23*$L$16)*(1+$L$23)+$L$18*$L$24-$L$18))^(1/Hold_Y)-1),NA()) | G26: =IFERROR(IF(((G$23*$L$16)*(1+$L$23)+$L$18*$L$24-$L$18)<=0,NA(),((($C26*$L$21)-$L$19+$L$20-($C26*$L$21)*$L$22)/((G$23*$L$16)*(1+$L$23)+$L$18*$L$24-$L$18))^(1/Hold_Y)-1),NA()) | H26: =IFERROR(IF(((H$23*$L$16)*(1+$L$23)+$L$18*$L$24-$L$18)<=0,NA(),((($C26*$L$21)-$L$19+$L$20-($C26*$L$21)*$L$22)/((H$23*$L$16)*(1+$L$23)+$L$18*$L$24-$L$18))^(1/Hold_Y)-1),NA()) | I26: =IFERROR(IF(((I$23*$L$16)*(1+$L$23)+$L$18*$L$24-$L$18)<=0,NA(),((($C26*$L$21)-$L$19+$L$20-($C26*$L$21)*$L$22)/((I$23*$L$16)*(1+$L$23)+$L$18*$L$24-$L$18))^(1/Hold_Y)-1),NA()) | K26: Cumulative unlevered FCF (Y1..Hold) | L26: =SUM('04_OPERATING_MODEL'!$F$37:INDEX('04_OPERATING_MODEL'!$F$37:$L$37,1,Hold_Y))
C27: 10 | D27: =IFERROR(IF(((D$23*$L$16)*(1+$L$23)+$L$18*$L$24-$L$18)<=0,NA(),((($C27*$L$21)-$L$19+$L$20-($C27*$L$21)*$L$22)/((D$23*$L$16)*(1+$L$23)+$L$18*$L$24-$L$18))^(1/Hold_Y)-1),NA()) | E27: =IFERROR(IF(((E$23*$L$16)*(1+$L$23)+$L$18*$L$24-$L$18)<=0,NA(),((($C27*$L$21)-$L$19+$L$20-($C27*$L$21)*$L$22)/((E$23*$L$16)*(1+$L$23)+$L$18*$L$24-$L$18))^(1/Hold_Y)-1),NA()) | F27: =IFERROR(IF(((F$23*$L$16)*(1+$L$23)+$L$18*$L$24-$L$18)<=0,NA(),((($C27*$L$21)-$L$19+$L$20-($C27*$L$21)*$L$22)/((F$23*$L$16)*(1+$L$23)+$L$18*$L$24-$L$18))^(1/Hold_Y)-1),NA()) | G27: =IFERROR(IF(((G$23*$L$16)*(1+$L$23)+$L$18*$L$24-$L$18)<=0,NA(),((($C27*$L$21)-$L$19+$L$20-($C27*$L$21)*$L$22)/((G$23*$L$16)*(1+$L$23)+$L$18*$L$24-$L$18))^(1/Hold_Y)-1),NA()) | H27: =IFERROR(IF(((H$23*$L$16)*(1+$L$23)+$L$18*$L$24-$L$18)<=0,NA(),((($C27*$L$21)-$L$19+$L$20-($C27*$L$21)*$L$22)/((H$23*$L$16)*(1+$L$23)+$L$18*$L$24-$L$18))^(1/Hold_Y)-1),NA()) | I27: =IFERROR(IF(((I$23*$L$16)*(1+$L$23)+$L$18*$L$24-$L$18)<=0,NA(),((($C27*$L$21)-$L$19+$L$20-($C27*$L$21)*$L$22)/((I$23*$L$16)*(1+$L$23)+$L$18*$L$24-$L$18))^(1/Hold_Y)-1),NA()) | K27: TLB spread (proxy) | L27: ='01_CONTROL'!$D$65
C28: 11 | D28: =IFERROR(IF(((D$23*$L$16)*(1+$L$23)+$L$18*$L$24-$L$18)<=0,NA(),((($C28*$L$21)-$L$19+$L$20-($C28*$L$21)*$L$22)/((D$23*$L$16)*(1+$L$23)+$L$18*$L$24-$L$18))^(1/Hold_Y)-1),NA()) | E28: =IFERROR(IF(((E$23*$L$16)*(1+$L$23)+$L$18*$L$24-$L$18)<=0,NA(),((($C28*$L$21)-$L$19+$L$20-($C28*$L$21)*$L$22)/((E$23*$L$16)*(1+$L$23)+$L$18*$L$24-$L$18))^(1/Hold_Y)-1),NA()) | F28: =IFERROR(IF(((F$23*$L$16)*(1+$L$23)+$L$18*$L$24-$L$18)<=0,NA(),((($C28*$L$21)-$L$19+$L$20-($C28*$L$21)*$L$22)/((F$23*$L$16)*(1+$L$23)+$L$18*$L$24-$L$18))^(1/Hold_Y)-1),NA()) | G28: =IFERROR(IF(((G$23*$L$16)*(1+$L$23)+$L$18*$L$24-$L$18)<=0,NA(),((($C28*$L$21)-$L$19+$L$20-($C28*$L$21)*$L$22)/((G$23*$L$16)*(1+$L$23)+$L$18*$L$24-$L$18))^(1/Hold_Y)-1),NA()) | H28: =IFERROR(IF(((H$23*$L$16)*(1+$L$23)+$L$18*$L$24-$L$18)<=0,NA(),((($C28*$L$21)-$L$19+$L$20-($C28*$L$21)*$L$22)/((H$23*$L$16)*(1+$L$23)+$L$18*$L$24-$L$18))^(1/Hold_Y)-1),NA()) | I28: =IFERROR(IF(((I$23*$L$16)*(1+$L$23)+$L$18*$L$24-$L$18)<=0,NA(),((($C28*$L$21)-$L$19+$L$20-($C28*$L$21)*$L$22)/((I$23*$L$16)*(1+$L$23)+$L$18*$L$24-$L$18))^(1/Hold_Y)-1),NA()) | K28: Base entry EV (DKKm) | L28: ='05_SOURCES_AND_USES'!$D$16
C29: 12 | D29: =IFERROR(IF(((D$23*$L$16)*(1+$L$23)+$L$18*$L$24-$L$18)<=0,NA(),((($C29*$L$21)-$L$19+$L$20-($C29*$L$21)*$L$22)/((D$23*$L$16)*(1+$L$23)+$L$18*$L$24-$L$18))^(1/Hold_Y)-1),NA()) | E29: =IFERROR(IF(((E$23*$L$16)*(1+$L$23)+$L$18*$L$24-$L$18)<=0,NA(),((($C29*$L$21)-$L$19+$L$20-($C29*$L$21)*$L$22)/((E$23*$L$16)*(1+$L$23)+$L$18*$L$24-$L$18))^(1/Hold_Y)-1),NA()) | F29: =IFERROR(IF(((F$23*$L$16)*(1+$L$23)+$L$18*$L$24-$L$18)<=0,NA(),((($C29*$L$21)-$L$19+$L$20-($C29*$L$21)*$L$22)/((F$23*$L$16)*(1+$L$23)+$L$18*$L$24-$L$18))^(1/Hold_Y)-1),NA()) | G29: =IFERROR(IF(((G$23*$L$16)*(1+$L$23)+$L$18*$L$24-$L$18)<=0,NA(),((($C29*$L$21)-$L$19+$L$20-($C29*$L$21)*$L$22)/((G$23*$L$16)*(1+$L$23)+$L$18*$L$24-$L$18))^(1/Hold_Y)-1),NA()) | H29: =IFERROR(IF(((H$23*$L$16)*(1+$L$23)+$L$18*$L$24-$L$18)<=0,NA(),((($C29*$L$21)-$L$19+$L$20-($C29*$L$21)*$L$22)/((H$23*$L$16)*(1+$L$23)+$L$18*$L$24-$L$18))^(1/Hold_Y)-1),NA()) | I29: =IFERROR(IF(((I$23*$L$16)*(1+$L$23)+$L$18*$L$24-$L$18)<=0,NA(),((($C29*$L$21)-$L$19+$L$20-($C29*$L$21)*$L$22)/((I$23*$L$16)*(1+$L$23)+$L$18*$L$24-$L$18))^(1/Hold_Y)-1),NA()) | K29: Base entry uses excl. financing fee (DKKm) | L29: =$L$28*(1+$L$23)+'05_SOURCES_AND_USES'!$D$19
K30: Base exit EV (DKKm) | L30: =Exit_Multiple*$L$21
B33: IRR: EXIT MULTIPLE vs EBITDA CAGR (approx, debt & cash at exit held constant)
B35: Varies leverage target and benchmark rate | D35: -0.02 | E35: 0 | F35: 0.02 | G35: 0.04 | H35: 0.06 | I35: 0.08
C36: 7 | D36: =IFERROR(IF(='05_SOURCES_AND_USES'!$D$40<=0,NA(),((($C36*($L$16*(1+D$35)^Hold_Y))-$L$19+$L$20-($C36*($L$16*(1+D$35)^Hold_Y))*$L$22)/='05_SOURCES_AND_USES'!$D$40)^(1/Hold_Y)-1),NA()) | E36: =IFERROR(IF(='05_SOURCES_AND_USES'!$D$40<=0,NA(),((($C36*($L$16*(1+E$35)^Hold_Y))-$L$19+$L$20-($C36*($L$16*(1+E$35)^Hold_Y))*$L$22)/='05_SOURCES_AND_USES'!$D$40)^(1/Hold_Y)-1),NA()) | F36: =IFERROR(IF(='05_SOURCES_AND_USES'!$D$40<=0,NA(),((($C36*($L$16*(1+F$35)^Hold_Y))-$L$19+$L$20-($C36*($L$16*(1+F$35)^Hold_Y))*$L$22)/='05_SOURCES_AND_USES'!$D$40)^(1/Hold_Y)-1),NA()) | G36: =IFERROR(IF(='05_SOURCES_AND_USES'!$D$40<=0,NA(),((($C36*($L$16*(1+G$35)^Hold_Y))-$L$19+$L$20-($C36*($L$16*(1+G$35)^Hold_Y))*$L$22)/='05_SOURCES_AND_USES'!$D$40)^(1/Hold_Y)-1),NA()) | H36: =IFERROR(IF(='05_SOURCES_AND_USES'!$D$40<=0,NA(),((($C36*($L$16*(1+H$35)^Hold_Y))-$L$19+$L$20-($C36*($L$16*(1+H$35)^Hold_Y))*$L$22)/='05_SOURCES_AND_USES'!$D$40)^(1/Hold_Y)-1),NA()) | I36: =IFERROR(IF(='05_SOURCES_AND_USES'!$D$40<=0,NA(),((($C36*($L$16*(1+I$35)^Hold_Y))-$L$19+$L$20-($C36*($L$16*(1+I$35)^Hold_Y))*$L$22)/='05_SOURCES_AND_USES'!$D$40)^(1/Hold_Y)-1),NA())
B37: Leverage (x) | C37: 8 | D37: =IFERROR(IF(='05_SOURCES_AND_USES'!$D$40<=0,NA(),((($C37*($L$16*(1+D$35)^Hold_Y))-$L$19+$L$20-($C37*($L$16*(1+D$35)^Hold_Y))*$L$22)/='05_SOURCES_AND_USES'!$D$40)^(1/Hold_Y)-1),NA()) | E37: =IFERROR(IF(='05_SOURCES_AND_USES'!$D$40<=0,NA(),((($C37*($L$16*(1+E$35)^Hold_Y))-$L$19+$L$20-($C37*($L$16*(1+E$35)^Hold_Y))*$L$22)/='05_SOURCES_AND_USES'!$D$40)^(1/Hold_Y)-1),NA()) | F37: =IFERROR(IF(='05_SOURCES_AND_USES'!$D$40<=0,NA(),((($C37*($L$16*(1+F$35)^Hold_Y))-$L$19+$L$20-($C37*($L$16*(1+F$35)^Hold_Y))*$L$22)/='05_SOURCES_AND_USES'!$D$40)^(1/Hold_Y)-1),NA()) | G37: =IFERROR(IF(='05_SOURCES_AND_USES'!$D$40<=0,NA(),((($C37*($L$16*(1+G$35)^Hold_Y))-$L$19+$L$20-($C37*($L$16*(1+G$35)^Hold_Y))*$L$22)/='05_SOURCES_AND_USES'!$D$40)^(1/Hold_Y)-1),NA()) | H37: =IFERROR(IF(='05_SOURCES_AND_USES'!$D$40<=0,NA(),((($C37*($L$16*(1+H$35)^Hold_Y))-$L$19+$L$20-($C37*($L$16*(1+H$35)^Hold_Y))*$L$22)/='05_SOURCES_AND_USES'!$D$40)^(1/Hold_Y)-1),NA()) | I37: =IFERROR(IF(='05_SOURCES_AND_USES'!$D$40<=0,NA(),((($C37*($L$16*(1+I$35)^Hold_Y))-$L$19+$L$20-($C37*($L$16*(1+I$35)^Hold_Y))*$L$22)/='05_SOURCES_AND_USES'!$D$40)^(1/Hold_Y)-1),NA())
B38: 3.5 | C38: 9 | D38: =IFERROR(IF(='05_SOURCES_AND_USES'!$D$40<=0,NA(),((($C38*($L$16*(1+D$35)^Hold_Y))-$L$19+$L$20-($C38*($L$16*(1+D$35)^Hold_Y))*$L$22)/='05_SOURCES_AND_USES'!$D$40)^(1/Hold_Y)-1),NA()) | E38: =IFERROR(IF(='05_SOURCES_AND_USES'!$D$40<=0,NA(),((($C38*($L$16*(1+E$35)^Hold_Y))-$L$19+$L$20-($C38*($L$16*(1+E$35)^Hold_Y))*$L$22)/='05_SOURCES_AND_USES'!$D$40)^(1/Hold_Y)-1),NA()) | F38: =IFERROR(IF(='05_SOURCES_AND_USES'!$D$40<=0,NA(),((($C38*($L$16*(1+F$35)^Hold_Y))-$L$19+$L$20-($C38*($L$16*(1+F$35)^Hold_Y))*$L$22)/='05_SOURCES_AND_USES'!$D$40)^(1/Hold_Y)-1),NA()) | G38: =IFERROR(IF(='05_SOURCES_AND_USES'!$D$40<=0,NA(),((($C38*($L$16*(1+G$35)^Hold_Y))-$L$19+$L$20-($C38*($L$16*(1+G$35)^Hold_Y))*$L$22)/='05_SOURCES_AND_USES'!$D$40)^(1/Hold_Y)-1),NA()) | H38: =IFERROR(IF(='05_SOURCES_AND_USES'!$D$40<=0,NA(),((($C38*($L$16*(1+H$35)^Hold_Y))-$L$19+$L$20-($C38*($L$16*(1+H$35)^Hold_Y))*$L$22)/='05_SOURCES_AND_USES'!$D$40)^(1/Hold_Y)-1),NA()) | I38: =IFERROR(IF(='05_SOURCES_AND_USES'!$D$40<=0,NA(),((($C38*($L$16*(1+I$35)^Hold_Y))-$L$19+$L$20-($C38*($L$16*(1+I$35)^Hold_Y))*$L$22)/='05_SOURCES_AND_USES'!$D$40)^(1/Hold_Y)-1),NA())
B39: 4 | C39: 10 | D39: =IFERROR(IF(='05_SOURCES_AND_USES'!$D$40<=0,NA(),((($C39*($L$16*(1+D$35)^Hold_Y))-$L$19+$L$20-($C39*($L$16*(1+D$35)^Hold_Y))*$L$22)/='05_SOURCES_AND_USES'!$D$40)^(1/Hold_Y)-1),NA()) | E39: =IFERROR(IF(='05_SOURCES_AND_USES'!$D$40<=0,NA(),((($C39*($L$16*(1+E$35)^Hold_Y))-$L$19+$L$20-($C39*($L$16*(1+E$35)^Hold_Y))*$L$22)/='05_SOURCES_AND_USES'!$D$40)^(1/Hold_Y)-1),NA()) | F39: =IFERROR(IF(='05_SOURCES_AND_USES'!$D$40<=0,NA(),((($C39*($L$16*(1+F$35)^Hold_Y))-$L$19+$L$20-($C39*($L$16*(1+F$35)^Hold_Y))*$L$22)/='05_SOURCES_AND_USES'!$D$40)^(1/Hold_Y)-1),NA()) | G39: =IFERROR(IF(='05_SOURCES_AND_USES'!$D$40<=0,NA(),((($C39*($L$16*(1+G$35)^Hold_Y))-$L$19+$L$20-($C39*($L$16*(1+G$35)^Hold_Y))*$L$22)/='05_SOURCES_AND_USES'!$D$40)^(1/Hold_Y)-1),NA()) | H39: =IFERROR(IF(='05_SOURCES_AND_USES'!$D$40<=0,NA(),((($C39*($L$16*(1+H$35)^Hold_Y))-$L$19+$L$20-($C39*($L$16*(1+H$35)^Hold_Y))*$L$22)/='05_SOURCES_AND_USES'!$D$40)^(1/Hold_Y)-1),NA()) | I39: =IFERROR(IF(='05_SOURCES_AND_USES'!$D$40<=0,NA(),((($C39*($L$16*(1+I$35)^Hold_Y))-$L$19+$L$20-($C39*($L$16*(1+I$35)^Hold_Y))*$L$22)/='05_SOURCES_AND_USES'!$D$40)^(1/Hold_Y)-1),NA())
B40: 4.5 | C40: 11 | D40: =IFERROR(IF(='05_SOURCES_AND_USES'!$D$40<=0,NA(),((($C40*($L$16*(1+D$35)^Hold_Y))-$L$19+$L$20-($C40*($L$16*(1+D$35)^Hold_Y))*$L$22)/='05_SOURCES_AND_USES'!$D$40)^(1/Hold_Y)-1),NA()) | E40: =IFERROR(IF(='05_SOURCES_AND_USES'!$D$40<=0,NA(),((($C40*($L$16*(1+E$35)^Hold_Y))-$L$19+$L$20-($C40*($L$16*(1+E$35)^Hold_Y))*$L$22)/='05_SOURCES_AND_USES'!$D$40)^(1/Hold_Y)-1),NA()) | F40: =IFERROR(IF(='05_SOURCES_AND_USES'!$D$40<=0,NA(),((($C40*($L$16*(1+F$35)^Hold_Y))-$L$19+$L$20-($C40*($L$16*(1+F$35)^Hold_Y))*$L$22)/='05_SOURCES_AND_USES'!$D$40)^(1/Hold_Y)-1),NA()) | G40: =IFERROR(IF(='05_SOURCES_AND_USES'!$D$40<=0,NA(),((($C40*($L$16*(1+G$35)^Hold_Y))-$L$19+$L$20-($C40*($L$16*(1+G$35)^Hold_Y))*$L$22)/='05_SOURCES_AND_USES'!$D$40)^(1/Hold_Y)-1),NA()) | H40: =IFERROR(IF(='05_SOURCES_AND_USES'!$D$40<=0,NA(),((($C40*($L$16*(1+H$35)^Hold_Y))-$L$19+$L$20-($C40*($L$16*(1+H$35)^Hold_Y))*$L$22)/='05_SOURCES_AND_USES'!$D$40)^(1/Hold_Y)-1),NA()) | I40: =IFERROR(IF(='05_SOURCES_AND_USES'!$D$40<=0,NA(),((($C40*($L$16*(1+I$35)^Hold_Y))-$L$19+$L$20-($C40*($L$16*(1+I$35)^Hold_Y))*$L$22)/='05_SOURCES_AND_USES'!$D$40)^(1/Hold_Y)-1),NA())
B41: 5 | C41: 12 | D41: =IFERROR(IF(='05_SOURCES_AND_USES'!$D$40<=0,NA(),((($C41*($L$16*(1+D$35)^Hold_Y))-$L$19+$L$20-($C41*($L$16*(1+D$35)^Hold_Y))*$L$22)/='05_SOURCES_AND_USES'!$D$40)^(1/Hold_Y)-1),NA()) | E41: =IFERROR(IF(='05_SOURCES_AND_USES'!$D$40<=0,NA(),((($C41*($L$16*(1+E$35)^Hold_Y))-$L$19+$L$20-($C41*($L$16*(1+E$35)^Hold_Y))*$L$22)/='05_SOURCES_AND_USES'!$D$40)^(1/Hold_Y)-1),NA()) | F41: =IFERROR(IF(='05_SOURCES_AND_USES'!$D$40<=0,NA(),((($C41*($L$16*(1+F$35)^Hold_Y))-$L$19+$L$20-($C41*($L$16*(1+F$35)^Hold_Y))*$L$22)/='05_SOURCES_AND_USES'!$D$40)^(1/Hold_Y)-1),NA()) | G41: =IFERROR(IF(='05_SOURCES_AND_USES'!$D$40<=0,NA(),((($C41*($L$16*(1+G$35)^Hold_Y))-$L$19+$L$20-($C41*($L$16*(1+G$35)^Hold_Y))*$L$22)/='05_SOURCES_AND_USES'!$D$40)^(1/Hold_Y)-1),NA()) | H41: =IFERROR(IF(='05_SOURCES_AND_USES'!$D$40<=0,NA(),((($C41*($L$16*(1+H$35)^Hold_Y))-$L$19+$L$20-($C41*($L$16*(1+H$35)^Hold_Y))*$L$22)/='05_SOURCES_AND_USES'!$D$40)^(1/Hold_Y)-1),NA()) | I41: =IFERROR(IF(='05_SOURCES_AND_USES'!$D$40<=0,NA(),((($C41*($L$16*(1+I$35)^Hold_Y))-$L$19+$L$20-($C41*($L$16*(1+I$35)^Hold_Y))*$L$22)/='05_SOURCES_AND_USES'!$D$40)^(1/Hold_Y)-1),NA())
B42: 5.5 | C42: 0.06
B43: 6 | C43: 0.07
B44: IRR: ENTRY LEVERAGE (x) vs BENCHMARK RATE (approx, cash sweep from unlevered FCF)
D46: 0.02 | E46: 0.03 | F46: 0.04 | G46: 0.05 | H46: 0.06
C47: 3 | D47: =IFERROR(IF((($L$29+($C47*$L$16)*$L$24)-($C47*$L$16))<=0,NA(),(($L$30-MAX(0,($C47*$L$16)-$L$26+(($C47*$L$16)*(D$46+$L$27)*Hold_Y))-$L$30*$L$22)/(($L$29+($C47*$L$16)*$L$24)-($C47*$L$16)))^(1/Hold_Y)-1),NA()) | E47: =IFERROR(IF((($L$29+($C47*$L$16)*$L$24)-($C47*$L$16))<=0,NA(),(($L$30-MAX(0,($C47*$L$16)-$L$26+(($C47*$L$16)*(E$46+$L$27)*Hold_Y))-$L$30*$L$22)/(($L$29+($C47*$L$16)*$L$24)-($C47*$L$16)))^(1/Hold_Y)-1),NA()) | F47: =IFERROR(IF((($L$29+($C47*$L$16)*$L$24)-($C47*$L$16))<=0,NA(),(($L$30-MAX(0,($C47*$L$16)-$L$26+(($C47*$L$16)*(F$46+$L$27)*Hold_Y))-$L$30*$L$22)/(($L$29+($C47*$L$16)*$L$24)-($C47*$L$16)))^(1/Hold_Y)-1),NA()) | G47: =IFERROR(IF((($L$29+($C47*$L$16)*$L$24)-($C47*$L$16))<=0,NA(),(($L$30-MAX(0,($C47*$L$16)-$L$26+(($C47*$L$16)*(G$46+$L$27)*Hold_Y))-$L$30*$L$22)/(($L$29+($C47*$L$16)*$L$24)-($C47*$L$16)))^(1/Hold_Y)-1),NA()) | H47: =IFERROR(IF((($L$29+($C47*$L$16)*$L$24)-($C47*$L$16))<=0,NA(),(($L$30-MAX(0,($C47*$L$16)-$L$26+(($C47*$L$16)*(H$46+$L$27)*Hold_Y))-$L$30*$L$22)/(($L$29+($C47*$L$16)*$L$24)-($C47*$L$16)))^(1/Hold_Y)-1),NA())
C48: 3.5 | D48: =IFERROR(IF((($L$29+($C48*$L$16)*$L$24)-($C48*$L$16))<=0,NA(),(($L$30-MAX(0,($C48*$L$16)-$L$26+(($C48*$L$16)*(D$46+$L$27)*Hold_Y))-$L$30*$L$22)/(($L$29+($C48*$L$16)*$L$24)-($C48*$L$16)))^(1/Hold_Y)-1),NA()) | E48: =IFERROR(IF((($L$29+($C48*$L$16)*$L$24)-($C48*$L$16))<=0,NA(),(($L$30-MAX(0,($C48*$L$16)-$L$26+(($C48*$L$16)*(E$46+$L$27)*Hold_Y))-$L$30*$L$22)/(($L$29+($C48*$L$16)*$L$24)-($C48*$L$16)))^(1/Hold_Y)-1),NA()) | F48: =IFERROR(IF((($L$29+($C48*$L$16)*$L$24)-($C48*$L$16))<=0,NA(),(($L$30-MAX(0,($C48*$L$16)-$L$26+(($C48*$L$16)*(F$46+$L$27)*Hold_Y))-$L$30*$L$22)/(($L$29+($C48*$L$16)*$L$24)-($C48*$L$16)))^(1/Hold_Y)-1),NA()) | G48: =IFERROR(IF((($L$29+($C48*$L$16)*$L$24)-($C48*$L$16))<=0,NA(),(($L$30-MAX(0,($C48*$L$16)-$L$26+(($C48*$L$16)*(G$46+$L$27)*Hold_Y))-$L$30*$L$22)/(($L$29+($C48*$L$16)*$L$24)-($C48*$L$16)))^(1/Hold_Y)-1),NA()) | H48: =IFERROR(IF((($L$29+($C48*$L$16)*$L$24)-($C48*$L$16))<=0,NA(),(($L$30-MAX(0,($C48*$L$16)-$L$26+(($C48*$L$16)*(H$46+$L$27)*Hold_Y))-$L$30*$L$22)/(($L$29+($C48*$L$16)*$L$24)-($C48*$L$16)))^(1/Hold_Y)-1),NA())
C49: 4 | D49: =IFERROR(IF((($L$29+($C49*$L$16)*$L$24)-($C49*$L$16))<=0,NA(),(($L$30-MAX(0,($C49*$L$16)-$L$26+(($C49*$L$16)*(D$46+$L$27)*Hold_Y))-$L$30*$L$22)/(($L$29+($C49*$L$16)*$L$24)-($C49*$L$16)))^(1/Hold_Y)-1),NA()) | E49: =IFERROR(IF((($L$29+($C49*$L$16)*$L$24)-($C49*$L$16))<=0,NA(),(($L$30-MAX(0,($C49*$L$16)-$L$26+(($C49*$L$16)*(E$46+$L$27)*Hold_Y))-$L$30*$L$22)/(($L$29+($C49*$L$16)*$L$24)-($C49*$L$16)))^(1/Hold_Y)-1),NA()) | F49: =IFERROR(IF((($L$29+($C49*$L$16)*$L$24)-($C49*$L$16))<=0,NA(),(($L$30-MAX(0,($C49*$L$16)-$L$26+(($C49*$L$16)*(F$46+$L$27)*Hold_Y))-$L$30*$L$22)/(($L$29+($C49*$L$16)*$L$24)-($C49*$L$16)))^(1/Hold_Y)-1),NA()) | G49: =IFERROR(IF((($L$29+($C49*$L$16)*$L$24)-($C49*$L$16))<=0,NA(),(($L$30-MAX(0,($C49*$L$16)-$L$26+(($C49*$L$16)*(G$46+$L$27)*Hold_Y))-$L$30*$L$22)/(($L$29+($C49*$L$16)*$L$24)-($C49*$L$16)))^(1/Hold_Y)-1),NA()) | H49: =IFERROR(IF((($L$29+($C49*$L$16)*$L$24)-($C49*$L$16))<=0,NA(),(($L$30-MAX(0,($C49*$L$16)-$L$26+(($C49*$L$16)*(H$46+$L$27)*Hold_Y))-$L$30*$L$22)/(($L$29+($C49*$L$16)*$L$24)-($C49*$L$16)))^(1/Hold_Y)-1),NA())
C50: 4.5 | D50: =IFERROR(IF((($L$29+($C50*$L$16)*$L$24)-($C50*$L$16))<=0,NA(),(($L$30-MAX(0,($C50*$L$16)-$L$26+(($C50*$L$16)*(D$46+$L$27)*Hold_Y))-$L$30*$L$22)/(($L$29+($C50*$L$16)*$L$24)-($C50*$L$16)))^(1/Hold_Y)-1),NA()) | E50: =IFERROR(IF((($L$29+($C50*$L$16)*$L$24)-($C50*$L$16))<=0,NA(),(($L$30-MAX(0,($C50*$L$16)-$L$26+(($C50*$L$16)*(E$46+$L$27)*Hold_Y))-$L$30*$L$22)/(($L$29+($C50*$L$16)*$L$24)-($C50*$L$16)))^(1/Hold_Y)-1),NA()) | F50: =IFERROR(IF((($L$29+($C50*$L$16)*$L$24)-($C50*$L$16))<=0,NA(),(($L$30-MAX(0,($C50*$L$16)-$L$26+(($C50*$L$16)*(F$46+$L$27)*Hold_Y))-$L$30*$L$22)/(($L$29+($C50*$L$16)*$L$24)-($C50*$L$16)))^(1/Hold_Y)-1),NA()) | G50: =IFERROR(IF((($L$29+($C50*$L$16)*$L$24)-($C50*$L$16))<=0,NA(),(($L$30-MAX(0,($C50*$L$16)-$L$26+(($C50*$L$16)*(G$46+$L$27)*Hold_Y))-$L$30*$L$22)/(($L$29+($C50*$L$16)*$L$24)-($C50*$L$16)))^(1/Hold_Y)-1),NA()) | H50: =IFERROR(IF((($L$29+($C50*$L$16)*$L$24)-($C50*$L$16))<=0,NA(),(($L$30-MAX(0,($C50*$L$16)-$L$26+(($C50*$L$16)*(H$46+$L$27)*Hold_Y))-$L$30*$L$22)/(($L$29+($C50*$L$16)*$L$24)-($C50*$L$16)))^(1/Hold_Y)-1),NA())
C51: 5 | D51: =IFERROR(IF((($L$29+($C51*$L$16)*$L$24)-($C51*$L$16))<=0,NA(),(($L$30-MAX(0,($C51*$L$16)-$L$26+(($C51*$L$16)*(D$46+$L$27)*Hold_Y))-$L$30*$L$22)/(($L$29+($C51*$L$16)*$L$24)-($C51*$L$16)))^(1/Hold_Y)-1),NA()) | E51: =IFERROR(IF((($L$29+($C51*$L$16)*$L$24)-($C51*$L$16))<=0,NA(),(($L$30-MAX(0,($C51*$L$16)-$L$26+(($C51*$L$16)*(E$46+$L$27)*Hold_Y))-$L$30*$L$22)/(($L$29+($C51*$L$16)*$L$24)-($C51*$L$16)))^(1/Hold_Y)-1),NA()) | F51: =IFERROR(IF((($L$29+($C51*$L$16)*$L$24)-($C51*$L$16))<=0,NA(),(($L$30-MAX(0,($C51*$L$16)-$L$26+(($C51*$L$16)*(F$46+$L$27)*Hold_Y))-$L$30*$L$22)/(($L$29+($C51*$L$16)*$L$24)-($C51*$L$16)))^(1/Hold_Y)-1),NA()) | G51: =IFERROR(IF((($L$29+($C51*$L$16)*$L$24)-($C51*$L$16))<=0,NA(),(($L$30-MAX(0,($C51*$L$16)-$L$26+(($C51*$L$16)*(G$46+$L$27)*Hold_Y))-$L$30*$L$22)/(($L$29+($C51*$L$16)*$L$24)-($C51*$L$16)))^(1/Hold_Y)-1),NA()) | H51: =IFERROR(IF((($L$29+($C51*$L$16)*$L$24)-($C51*$L$16))<=0,NA(),(($L$30-MAX(0,($C51*$L$16)-$L$26+(($C51*$L$16)*(H$46+$L$27)*Hold_Y))-$L$30*$L$22)/(($L$29+($C51*$L$16)*$L$24)-($C51*$L$16)))^(1/Hold_Y)-1),NA())
C52: 5.5 | D52: =IFERROR(IF((($L$29+($C52*$L$16)*$L$24)-($C52*$L$16))<=0,NA(),(($L$30-MAX(0,($C52*$L$16)-$L$26+(($C52*$L$16)*(D$46+$L$27)*Hold_Y))-$L$30*$L$22)/(($L$29+($C52*$L$16)*$L$24)-($C52*$L$16)))^(1/Hold_Y)-1),NA()) | E52: =IFERROR(IF((($L$29+($C52*$L$16)*$L$24)-($C52*$L$16))<=0,NA(),(($L$30-MAX(0,($C52*$L$16)-$L$26+(($C52*$L$16)*(E$46+$L$27)*Hold_Y))-$L$30*$L$22)/(($L$29+($C52*$L$16)*$L$24)-($C52*$L$16)))^(1/Hold_Y)-1),NA()) | F52: =IFERROR(IF((($L$29+($C52*$L$16)*$L$24)-($C52*$L$16))<=0,NA(),(($L$30-MAX(0,($C52*$L$16)-$L$26+(($C52*$L$16)*(F$46+$L$27)*Hold_Y))-$L$30*$L$22)/(($L$29+($C52*$L$16)*$L$24)-($C52*$L$16)))^(1/Hold_Y)-1),NA()) | G52: =IFERROR(IF((($L$29+($C52*$L$16)*$L$24)-($C52*$L$16))<=0,NA(),(($L$30-MAX(0,($C52*$L$16)-$L$26+(($C52*$L$16)*(G$46+$L$27)*Hold_Y))-$L$30*$L$22)/(($L$29+($C52*$L$16)*$L$24)-($C52*$L$16)))^(1/Hold_Y)-1),NA()) | H52: =IFERROR(IF((($L$29+($C52*$L$16)*$L$24)-($C52*$L$16))<=0,NA(),(($L$30-MAX(0,($C52*$L$16)-$L$26+(($C52*$L$16)*(H$46+$L$27)*Hold_Y))-$L$30*$L$22)/(($L$29+($C52*$L$16)*$L$24)-($C52*$L$16)))^(1/Hold_Y)-1),NA())
C53: 6 | D53: =IFERROR(IF((($L$29+($C53*$L$16)*$L$24)-($C53*$L$16))<=0,NA(),(($L$30-MAX(0,($C53*$L$16)-$L$26+(($C53*$L$16)*(D$46+$L$27)*Hold_Y))-$L$30*$L$22)/(($L$29+($C53*$L$16)*$L$24)-($C53*$L$16)))^(1/Hold_Y)-1),NA()) | E53: =IFERROR(IF((($L$29+($C53*$L$16)*$L$24)-($C53*$L$16))<=0,NA(),(($L$30-MAX(0,($C53*$L$16)-$L$26+(($C53*$L$16)*(E$46+$L$27)*Hold_Y))-$L$30*$L$22)/(($L$29+($C53*$L$16)*$L$24)-($C53*$L$16)))^(1/Hold_Y)-1),NA()) | F53: =IFERROR(IF((($L$29+($C53*$L$16)*$L$24)-($C53*$L$16))<=0,NA(),(($L$30-MAX(0,($C53*$L$16)-$L$26+(($C53*$L$16)*(F$46+$L$27)*Hold_Y))-$L$30*$L$22)/(($L$29+($C53*$L$16)*$L$24)-($C53*$L$16)))^(1/Hold_Y)-1),NA()) | G53: =IFERROR(IF((($L$29+($C53*$L$16)*$L$24)-($C53*$L$16))<=0,NA(),(($L$30-MAX(0,($C53*$L$16)-$L$26+(($C53*$L$16)*(G$46+$L$27)*Hold_Y))-$L$30*$L$22)/(($L$29+($C53*$L$16)*$L$24)-($C53*$L$16)))^(1/Hold_Y)-1),NA()) | H53: =IFERROR(IF((($L$29+($C53*$L$16)*$L$24)-($C53*$L$16))<=0,NA(),(($L$30-MAX(0,($C53*$L$16)-$L$26+(($C53*$L$16)*(H$46+$L$27)*Hold_Y))-$L$30*$L$22)/(($L$29+($C53*$L$16)*$L$24)-($C53*$L$16)))^(1/Hold_Y)-1),NA())

Sheet 80_LBO_LEARN_MAP
B2: CHECKS: | C2: =HYPERLINK("#'90_CHECKS'!B6",'90_CHECKS'!$C$22) | D2: =HYPERLINK("#'80_LBO_LEARN_MAP'!B8","LEARN MAP") | E2: =HYPERLINK("#'00_DASHBOARD'!B3","DASHBOARD")
B6: 80_LBO_LEARN_MAP | Explainability map (Top 30 KPIs)
B8: Purpose: One page map from KPIs to model cells, with drivers, pitfalls, sanity checks, and IC-ready scripts.
B10: KPI | C10: Where (click) | D10: Definition | E10: Primary drivers (specific cells/lines) | F10: Directional intuition | G10: Common pitfalls | H10: Sanity checks | I10: If asked in IC, say this
B11: Sponsor IRR | C11: =HYPERLINK("#'00_DASHBOARD'!F12","00_DASHBOARD!F12") | D11: Annualized equity return to sponsor based on equity cash flows (close to exit). | E11: Calc: 09_RETURNS!D20. Key inputs: Entry_Multiple (01_CONTROL!D16), Exit_Multiple (01_CONTROL!D18), Hold_Y (01_CONTROL!D14), Lev_Target (01_CONTROL!D48), Rev growth (01_CONTROL!F39:H39), EBITDA margin (01_CONTROL!F40:H40), Bench rate (01_CONTROL!D22). | F11: Higher exit equity proceeds and shorter hold increase IRR. Higher equity check reduces IRR, all else equal. | G11: Wrong sign convention in equity CFs; IRR range off by one year; mixing total equity vs sponsor equity. | H11: IRR should move up with higher exit multiple; if MOIC up but IRR down, check hold period; confirm exit cash flow is only in exit year. | I11: Base case IRR is driven mainly by (i) entry vs exit multiple, (ii) EBITDA growth, and (iii) deleveraging. Under our debt terms, most variance comes from exit and operating performance.
B12: Sponsor MOIC | C12: =HYPERLINK("#'00_DASHBOARD'!F13","00_DASHBOARD!F13") | D12: Multiple of money on sponsor equity (exit proceeds divided by equity invested). | E12: Calc: 09_RETURNS!D21. Key lines: Sponsor equity (05_SOURCES_AND_USES!D38), Sponsor proceeds (08_EXIT_AND_EQUITY_BRIDGE!D35). | F12: MOIC increases with higher exit equity value and lower equity check at entry. | G12: Using total equity instead of sponsor equity; including fees twice; comparing MOIC across different hold periods without IRR context. | H12: MOIC >=1.0x in base case; MOIC should increase with exit multiple; sponsor proceeds should tie to EV-to-equity bridge. | I12: MOIC is simply exit equity proceeds over the entry equity check. It is less sensitive to timing than IRR, so we pair it with hold period.
B13: Sponsor equity cash flow schedule | C13: =HYPERLINK("#'09_RETURNS'!E14","09_RETURNS!E14") | D13: Sponsor cash flows by year, negative at close, positive at exit (no interim distributions in this base template). | E13: Rows: 09_RETURNS!E14:L14. Inputs: Sponsor equity (05_SOURCES_AND_USES!D38) and Sponsor exit proceeds (08_EXIT_AND_EQUITY_BRIDGE!D35) with timing from Hold_Y. | F13: Earlier inflows improve IRR. Bigger initial outflow lowers IRR unless exit scales. | G13: Placing exit proceeds in wrong column; leaving stray interim cash flows; mixing sponsor vs total equity. | H13: Exactly one negative at close and one positive at exit in this template; sum of equity CFs should equal proceeds minus invested. | I13: Equity cash flows are clean: one check at close, one distribution at exit. That makes MOIC and IRR easy to reconcile to entry equity and exit proceeds.
B14: Entry EV | C14: =HYPERLINK("#'00_DASHBOARD'!C11","00_DASHBOARD!C11") | D14: Enterprise value paid at entry (EV) based on LTM EBITDA times entry multiple. | E14: Calc: 05_SOURCES_AND_USES!D16. Inputs: LTM EBITDA (01_CONTROL!D32) and Entry multiple (01_CONTROL!D16). | F14: Higher entry EV increases equity required if leverage is held constant, lowering returns. | G14: Confusing EV with equity purchase price; forgetting existing net debt refinance; inconsistent units (DKKm). | H14: Entry EV equals LTM EBITDA times multiple; sources and uses should still tie after any change. | I14: Entry EV is the headline valuation. Given fixed leverage, higher EV mechanically increases the equity check and lowers returns unless growth or exit offsets.
B15: Entry multiple | C15: =HYPERLINK("#'00_DASHBOARD'!C12","00_DASHBOARD!C12") | D15: EV divided by LTM EBITDA at entry. Primary valuation driver in this model. | E15: 01_CONTROL!D16 and LTM EBITDA (01_CONTROL!D32). | F15: Higher entry multiple reduces equity returns unless matched by stronger growth, higher exit multiple, or more deleveraging. | G15: Using wrong EBITDA definition (LTM vs run rate); mismatching currency; mixing pre IFRS16 vs post IFRS16 EBITDA. | H15: Check that EV and multiple move consistently; compare to exit multiple sensitivity. | I15: Entry multiple is the biggest lever on equity check. If we pay up, we need a clear thesis on growth, margins, or multiple durability.
B16: Equity check (total equity at close) | C16: =HYPERLINK("#'00_DASHBOARD'!C14","00_DASHBOARD!C14") | D16: Total equity required to fund Sources and Uses after debt sources. Includes sponsor plus management rollover if any. | E16: Calc: 05_SOURCES_AND_USES!D40. Inputs: EV (D16), fees (01_CONTROL!D56:D57), leverage (01_CONTROL!D48), mgmt rollover % (01_CONTROL!G55). | F16: Higher fees or lower leverage increases equity check. Larger equity check lowers IRR all else equal. | G16: Double counting financing fees; letting equity be a plug without checking leverage; wrong sign for WC adjustment. | H16: Sources minus uses equals zero; sponsor plus mgmt equals total equity. | I16: Equity check is what the sponsor wires. In IC we link it directly to valuation, leverage, and fees.
B17: Debt / Equity split | C17: =HYPERLINK("#'05_SOURCES_AND_USES'!D37","05_SOURCES_AND_USES!D37") | D17: Funding mix at close: total new debt vs total equity. | E17: Debt total (05!D37) driven by leverage target (01_CONTROL!D48) and debt structure toggle (01_CONTROL!D20). | F17: More debt can boost IRR via lower equity check but raises risk via interest, covenants, and refinance sensitivity. | G17: Ignoring revolver constraints; using gross leverage when covenants are net; assuming sweep always works in downside. | H17: Debt plus equity equals total uses; leverage metrics reconcile to debt totals. | I17: We are choosing a risk return point: more leverage improves equity efficiency but reduces downside protection and increases covenant pressure.
B18: Entry leverage (Debt / EBITDA) | C18: =HYPERLINK("#'00_DASHBOARD'!C15","00_DASHBOARD!C15") | D18: Total new debt at close divided by LTM EBITDA. | E18: Debt total (05!D37) and LTM EBITDA (01_CONTROL!D32). | F18: Higher leverage reduces equity check and can lift IRR, but increases cash interest and covenant risk. | G18: Using EBITDA with add backs not available to lenders; mixing net and gross leverage. | H18: Compare to covenant definitions in 10_COVENANTS; check interest coverage stays reasonable. | I18: Leverage is the core underwriting decision. We evaluate it alongside free cash flow, downside stress, and covenant headroom.
B19: Total debt by tranche (close) | C19: =HYPERLINK("#'06_DEBT_SCHEDULES'!E15","06_DEBT_SCHEDULES!E15") | D19: Initial drawn balances for each tranche at close (revolver, TLA, TLB, SSN, Mezz depending on toggle). | E19: Sources & Uses debt allocation logic (05_SOURCES_AND_USES debt lines) and Debt_Structure toggle (01_CONTROL!D20). | F19: More senior debt is cheaper but may have tighter covenants; junior/PIK increases cost but may add flexibility. | G19: Mismatch between S&U and debt schedule opening balances; forgetting fees or draw timing. | H19: Debt schedule opening balances match sources and uses debt amounts; each tranche roll forward ties each period. | I19: We look at the tranche mix because it drives cash interest, amortization burden, and covenant package.
B20: Debt paydown path (total) | C20: =HYPERLINK("#'06_DEBT_SCHEDULES'!F67","06_DEBT_SCHEDULES!F67") | D20: Total debt outstanding by year after mandatory amortization and optional sweeps. | E20: Cash available (07_CASH_FLOW_WATERFALL!F23), sweep % (01_CONTROL!G54), mandatory amort inputs (01_CONTROL rows 63-67), interest rates. | F20: Higher FCF conversion and lower interest accelerate deleveraging. | G20: Circularity between interest and sweep; sweep exceeding available cash; negative debt balances. | H20: Ending debt never negative; cash bridge check equals zero; total debt declines with positive free cash flow. | I20: Deleveraging is the main downside protection in software LBOs. We show the path and what drives the speed.
B21: Debt paydown per tranche (priority) | C21: =HYPERLINK("#'07_CASH_FLOW_WATERFALL'!F33","07_CASH_FLOW_WATERFALL!F33") | D21: Optional sweep amounts allocated by tranche priority (Term B, Term A, SSN, Mezz). | E21: Sweep pool (07!F25) and tranche capacity (06 ending vs mandatory). | F21: Sweeps first reduce higher priority debt, improving covenants and reducing interest. | G21: Sweep order inconsistent with credit agreement; sweeping revolver incorrectly; paying beyond outstanding. | H21: Sum of tranche sweeps equals total sweep pool minus revolver repay; tranche sweep capped at available balance. | I21: We follow contractual priority. In IC we articulate which debt gets taken out first and why that matters for risk.
B22: Revolver draw/repay | C22: =HYPERLINK("#'07_CASH_FLOW_WATERFALL'!F30","07_CASH_FLOW_WATERFALL!F30") | D22: Revolver draws when cash is insufficient and repays when surplus exists, within the revolver limit. | E22: Cash deficit (07!F27), revolver limit (01_CONTROL!D49 / named Revolver_Limit) and ending revolver balance (06 rows 22-25). | F22: Revolver is liquidity backstop; frequent draws signal tight cash generation. | G22: Allowing negative revolver or exceeding limit; forgetting minimum cash assumptions; double counting interest. | H22: Revolver ending between 0 and limit; liquidity never negative unless explicitly allowed; checks in 90_CHECKS pass. | I22: We treat the revolver as the first liquidity valve. If we need it in base case, the deal is likely too tight.
B23: Cash interest (total) | C23: =HYPERLINK("#'07_CASH_FLOW_WATERFALL'!F20","07_CASH_FLOW_WATERFALL!F20") | D23: Total cash interest paid across all tranches each year. | E23: Debt balances (06) and all-in rates (06 rows 26,35,44,53,62), benchmark rate (01_CONTROL!D22) and spreads. | F23: Higher debt or higher rates reduce cash available for paydown, slowing deleveraging and reducing returns. | G23: Using ending balance instead of average; mixing fixed vs floating modes; ignoring floors. | H23: Interest rises with debt and rates; interest coverage remains sensible; no negative interest values. | I23: Interest is the biggest cash drain. We stress benchmark rates and confirm we still delever without covenant pressure.
B24: Blended cost of debt | C24: =HYPERLINK("#'06_DEBT_SCHEDULES'!F65","06_DEBT_SCHEDULES!F65") | D24: Weighted average cash interest rate across outstanding tranches. | E24: All-in rates per tranche and weights by outstanding balance. | F24: More junior debt or higher floating rates increase blended cost and reduce FCF conversion. | G24: Weighting by initial debt instead of current; forgetting revolver pricing; mixing fixed and floating in weighting. | H24: Blended rate sits between senior and mezz rates; moves with benchmark in floating mode. | I24: Blended cost is what matters for cash generation. It informs our rate shock sensitivity and debt capacity.
B25: Cash sweep pool | C25: =HYPERLINK("#'07_CASH_FLOW_WATERFALL'!F25","07_CASH_FLOW_WATERFALL!F25") | D25: Cash available for optional repayment after interest and mandatory amortization, scaled by sweep percentage. | E25: Cash after mandatory amort (07!F23) and Sweep % (01_CONTROL!G54). | F25: Higher sweep % accelerates paydown but reduces retained cash, which can reduce liquidity buffers. | G25: Sweeping cash needed for minimum liquidity; assuming 100% sweep in downside; mismatching with credit agreement. | H25: Ending cash and liquidity remain positive; sweep does not exceed cash surplus. | I25: We balance sweep aggressiveness against liquidity. A higher sweep speeds deleveraging but can increase operating risk.
B26: Unlevered FCF | C26: =HYPERLINK("#'04_OPERATING_MODEL'!F37","04_OPERATING_MODEL!F37") | D26: Operating cash generation before financing: NOPAT + D&A - capex - change in NWC. | E26: NOPAT (04!F20), D&A (04!F17), capex (04!F36), ΔNWC (04!F32), tax rate (01_CONTROL!D26). | F26: Better margins, lower capex, and improved working capital increase FCF and deleveraging speed. | G26: Double counting D&A; wrong sign on ΔNWC; using EBITDA instead of EBIT for tax base. | H26: FCF tracks EBITDA with reasonable conversion; capex and ΔNWC signs are consistent (investment uses cash). | I26: Deleveraging comes from unlevered free cash flow. We focus on FCF conversion rather than EBITDA alone.
B27: Cash before debt service | C27: =HYPERLINK("#'07_CASH_FLOW_WATERFALL'!F19","07_CASH_FLOW_WATERFALL!F19") | D27: Cash generation after tax, capex, working capital but before interest and debt repayments. | E27: EBITDA (07!F14), cash taxes (07!F15), ΔNWC (07!F16), capex (07!F17). | F27: Higher EBITDA and better conversion increase this pool, supporting debt paydown and resilience. | G27: Sign errors on capex or ΔNWC; taxes computed on wrong base; mixing levered and unlevered tax. | H27: Reconciles directionally to unlevered FCF; negative in downside should prompt liquidity review. | I27: This line is the core cash engine. It tells us whether the business can self fund deleveraging.
B28: Cash after interest | C28: =HYPERLINK("#'07_CASH_FLOW_WATERFALL'!F21","07_CASH_FLOW_WATERFALL!F21") | D28: Cash remaining after paying cash interest. | E28: Cash before debt service (07!F19) and total interest (07!F20). | F28: Interest rate shocks compress this line and slow paydown. | G28: Interest line incomplete or double counted; interest timing mismatch; using PIK as cash. | H28: Cash after interest declines when rates rise; compare to interest coverage metric. | I28: This is where rate risk shows up first. We test whether the model still delevers with a realistic rate shock.
B29: Exit EV | C29: =HYPERLINK("#'08_EXIT_AND_EQUITY_BRIDGE'!D23","08_EXIT_AND_EQUITY_BRIDGE!D23") | D29: Enterprise value at exit, driven by exit EBITDA and exit multiple (or equity target method). | E29: Exit EBITDA (08!D15), Exit multiple (01_CONTROL!D18) or Exit equity target (01_CONTROL!D19), Exit method toggle (01_CONTROL!D17). | F29: Higher exit multiple or higher exit EBITDA increases EV and returns. | G29: Exit year mismatch; using wrong EBITDA definition; mixing exit multiple method with equity target without consistent bridge. | H29: Exit EV equals exit EBITDA times exit multiple in multiple mode; reconcile to sensitivity tables. | I29: Exit EV is the biggest valuation driver. We defend it with comp ranges and business quality, and stress a conservative downside.
B30: Exit equity proceeds (total) | C30: =HYPERLINK("#'08_EXIT_AND_EQUITY_BRIDGE'!D27","08_EXIT_AND_EQUITY_BRIDGE!D27") | D30: Equity value at exit after subtracting net debt and fees, plus cash. | E30: Exit EV (08!D23), debt at exit (06 row 67 indexed), cash at exit (07 row 41 indexed), exit fees % (01_CONTROL!D35). | F30: Lower net debt at exit and higher cash increase equity value, improving returns. | G30: Wrong sign on debt or cash; double counting fees; using gross debt instead of net. | H30: EV to equity bridge ties: Equity = EV - debt + cash - fees; sponsor + mgmt proceeds sum to total equity proceeds. | I30: We translate enterprise value into equity proceeds via the bridge. Deleveraging is what converts EV into equity value.
B31: Net debt at exit | C31: =HYPERLINK("#'08_EXIT_AND_EQUITY_BRIDGE'!D24","08_EXIT_AND_EQUITY_BRIDGE!D24") | D31: Debt outstanding at exit (gross debt in this bridge line), paired with cash line to get net debt. | E31: Total debt at exit from debt schedules and cash at exit from waterfall. | F31: More paydown reduces net debt and increases equity proceeds. | G31: Mixing cash and revolver; using ending cash balance incorrectly; timing mismatch. | H31: Check that debt at exit matches debt schedule; cash at exit matches waterfall ending cash. | I31: Net debt at exit is the levered value creation component. It is where cash generation translates into equity uplift.
B32: Peak net leverage | C32: =HYPERLINK("#'00_DASHBOARD'!F14","00_DASHBOARD!F14") | D32: Maximum net leverage over the forecast period. | E32: Net leverage series (10_COVENANTS!F19:L19) and cash path, debt path. | F32: Higher peak leverage increases risk and can constrain operational flexibility. | G32: Using gross instead of net; not aligning EBITDA definition; ignoring one off EBITDA adjustments. | H32: Peak should usually be near entry unless EBITDA drops or cash burn; validate with debt and EBITDA path. | I32: Peak leverage is the stress point. We focus on whether the company can operate through that peak without covenant or liquidity issues.
B33: Minimum liquidity | C33: =HYPERLINK("#'00_DASHBOARD'!F15","00_DASHBOARD!F15") | D33: Lowest liquidity (cash plus undrawn revolver) during the hold period. | E33: Liquidity series (10_COVENANTS!F23:L23) driven by cash and undrawn revolver. | F33: Lower liquidity means higher refinancing and operating risk. | G33: Not including undrawn revolver; allowing negative cash; ignoring seasonal working capital needs. | H33: Min liquidity should be positive in base case; revolver not exceeded; no negative cash unless allowed. | I33: Liquidity is our first line of defense. We monitor the minimum point and make sure buffers are credible.
B34: Interest coverage | C34: =HYPERLINK("#'10_COVENANTS_AND_CREDIT_METRICS'!F21","10_COVENANTS_AND_CREDIT_METRICS!F21") | D34: EBITDA divided by cash interest, a proxy for debt service capacity. | E34: EBITDA (10_COVENANTS!F14) and cash interest (10_COVENANTS!F20). | F34: Higher coverage means more headroom to service debt, reduces default risk. | G34: Using EBIT instead of EBITDA; including PIK as cash interest; wrong interest sign. | H34: Coverage should fall when rates rise; cross check against cash after interest line. | I34: Coverage is the quickest test of rate sensitivity. If coverage gets tight, we have limited flexibility.
B35: Covenant headroom (net leverage) | C35: =HYPERLINK("#'10_COVENANTS_AND_CREDIT_METRICS'!F27","10_COVENANTS_AND_CREDIT_METRICS!F27") | D35: Covenant maximum net leverage minus actual net leverage. Negative means breach. | E35: Actual net leverage and covenant max input (01_CONTROL named Coven_NetLev_Max). | F35: More headroom means safer. Lower EBITDA or higher debt reduces headroom. | G35: Mismatch covenant definition; using gross leverage; ignoring add backs. | H35: Min headroom on dashboard should match series min; breach corresponds to red flag in checks. | I35: We focus on minimum headroom, not average. That tells us how close we get to default under base and downside.
B36: Cash bridge check | C36: =HYPERLINK("#'07_CASH_FLOW_WATERFALL'!F42","07_CASH_FLOW_WATERFALL!F42") | D36: Internal control ensuring cash is fully explained by sources and uses of cash in the waterfall. | E36: All waterfall components including revolver draw/repay and sweep allocations. | F36: Should be zero. Non zero indicates a plug or logic break. | G36: Missing a cash item; wrong sign; circular link; sweep not tying. | H36: Must be zero across all years; 90_CHECKS should flag if not. | I36: We trust outputs only if controls pass. This bridge ensures there is no unexplained cash plug.
B37: Sources = Uses check | C37: =HYPERLINK("#'90_CHECKS'!D7","90_CHECKS!D7") | D37: Control that total sources equal total uses at close (must be zero). | E37: 05_SOURCES_AND_USES totals and tie out line (05!D44). | F37: Must be zero always. Any non zero means transaction funding is inconsistent. | G37: Forgetting fees; sign errors; missing management rollover; mismatched debt opening balances. | H37: Zero tolerance; if broken, do not rely on returns outputs. | I37: We only discuss returns once sources and uses ties exactly, otherwise the equity check is wrong.
B38: Value creation bridge (EV drivers) | C38: =HYPERLINK("#'86_LBO_SPECIAL_MODULE'!B10","86_LBO_SPECIAL_MODULE!B10") | D38: Decomposes equity value change into EBITDA growth, multiple change, and deleveraging (and dividends if any). | E38: Entry EV (05!D16), entry multiple (01_CONTROL!D16), exit EBITDA (08!D15), exit multiple (01_CONTROL!D18), net debt entry and exit. | F38: In software LBOs, value creation is typically growth plus deleveraging; multiple expansion is upside but not core thesis. | G38: Attributing debt paydown twice; mixing EV and equity; using inconsistent EBITDA definition. | H38: Sum of components reconciles to change in EV and change in equity; deleveraging component equals change in net debt. | I38: Returns come from three levers: grow EBITDA, exit at a supportive multiple, and pay down debt through cash flow. We underwrite the first and third as controllable.
B39: Exit EBITDA | C39: =HYPERLINK("#'08_EXIT_AND_EQUITY_BRIDGE'!D15","08_EXIT_AND_EQUITY_BRIDGE!D15") | D39: Exit-year EBITDA used for exit valuation. | E39: Drivers: operating forecast (03 drivers) and margin assumptions. | F39: Higher growth/margin raises exit EBITDA. | G39: Pitfalls: wrong exit year, one-offs. | H39: Sanity: tie to operating model exit year. | I39: Exit EBITDA is the performance anchor for exit value, we stress it under downside.
B40: Exit multiple | C40: =HYPERLINK("#'00_DASHBOARD'!F11","00_DASHBOARD!F11") | D40: Exit EV multiple applied to exit EBITDA (or overridden by equity target method). | E40: Drivers: 01_CONTROL!D18 and Exit_Method toggle. | F40: Higher exit multiple increases EV. | G40: Pitfalls: aggressive exit; mismatch with comps. | H40: Sanity: compare to entry multiple and peer range. | I40: We use a defensible multiple range and show sensitivity.

Sheet 81_LBO_LEARN_FORMULAS
B2: CHECKS: | C2: =HYPERLINK("#'90_CHECKS'!B6",'90_CHECKS'!$C$22) | D2: =HYPERLINK("#'80_LBO_LEARN_MAP'!B8","LEARN MAP") | E2: =HYPERLINK("#'00_DASHBOARD'!B3","DASHBOARD")
B6: 81_LBO_LEARN_FORMULAS | Formula walkthrough (35 critical formulas)
B8: Purpose: This is the 'why it works' layer. Each formula is shown as text (robust across Excel versions) and links back to the model cell.
B10: # | C10: Formula topic | D10: Model cell (click) | E10: Formula (text) | F10: Plain-language explanation | G10: Why it matters | H10: Typical mistake | I10: Mini example
B11: 1 | C11: Entry EV (LTM EBITDA * Entry multiple) | D11: =HYPERLINK("#'05_SOURCES_AND_USES'!D16","05_SOURCES_AND_USES!D16") | E11: '=D14*D15 | F11: Calculates enterprise value paid at entry from LTM EBITDA and entry multiple. | G11: Anchors valuation and the equity check. Every return metric depends on this starting point. | H11: Using wrong EBITDA (run-rate vs LTM) or mixing units (DKK vs DKKm). | I11: If LTM EBITDA=300 and multiple=12.0x, EV=3,600 DKKm.
B12: 2 | C12: Total Uses (sum of all uses) | D12: =HYPERLINK("#'05_SOURCES_AND_USES'!D28","05_SOURCES_AND_USES!D28") | E12: '=SUM(D22:D26) | F12: Sums equity purchase and transaction costs to get total cash requirement at close. | G12: Must tie exactly to sources. If wrong, equity check is wrong and returns are wrong. | H12: Missing a fee line or wrong sign on WC adjustment. | I12: If Uses lines are 3,600 + 50 + 20, total uses=3,670.
B13: 3 | C13: Total Debt (sum of debt sources) | D13: =HYPERLINK("#'05_SOURCES_AND_USES'!D37","05_SOURCES_AND_USES!D37") | E13: '=SUM(D33:D36) | F13: Adds up all new debt tranches raised at close. | G13: Determines leverage, interest burden, and equity check (since equity plugs the gap). | H13: Forgetting a tranche or including revolver availability as drawn debt. | I13: If TLA=600 and TLB=750, total debt=1,350.
B14: 4 | C14: Total Equity (uses minus debt) | D14: =HYPERLINK("#'05_SOURCES_AND_USES'!D40","05_SOURCES_AND_USES!D40") | E14: '=D28-D37 | F14: Calculates total equity needed after debt sources. | G14: This is the equity check the deal requires, and is the denominator for MOIC. | H14: Referencing the wrong debt total or leaving equity as a hardcoded plug. | I14: If uses=3,670 and debt=1,350, equity=2,320.
B15: 5 | C15: Sponsor equity (total equity minus mgmt rollover) | D15: =HYPERLINK("#'05_SOURCES_AND_USES'!D38","05_SOURCES_AND_USES!D38") | E15: '=D40-D39 | F15: Splits total equity into sponsor and management portions using the rollover percent. | G15: Returns to sponsor depend on sponsor equity and sponsor proceeds at exit. | H15: Mgmt rollover applied to EV instead of equity, or % entered as whole number (10 vs 10%). | I15: If equity=2,320 and mgmt=10%, sponsor equity=2,088.
B16: 6 | C16: Financing fees (% of new debt) | D16: =HYPERLINK("#'05_SOURCES_AND_USES'!D25","05_SOURCES_AND_USES!D25") | E16: '=D37*'01_CONTROL'!$G$57 | F16: Computes financing fees as a % of new debt raised. | G16: Fees reduce equity returns and must be included for realistic underwriting. | H16: Applying fee to EV instead of debt, or double counting at exit. | I16: If debt=1,350 and fee=1.0%, fee=13.5.
B17: 7 | C17: Sources-Uses check (must be 0) | D17: =HYPERLINK("#'05_SOURCES_AND_USES'!D44","05_SOURCES_AND_USES!D44") | E17: '=D37+D40-D28 | F17: Calculates Sources minus Uses to ensure the close funding ties out. | G17: This is a hard gate for model credibility before discussing IRR/MOIC. | H17: Leaving the check blank or pointing to wrong totals. | I17: If sources=3,670 and uses=3,670, check=0.
B18: 8 | C18: Revenue forecast (prior year * (1+growth)) | D18: =HYPERLINK("#'03_DRIVERS_AND_FORECAST'!F12","03_DRIVERS_AND_FORECAST!F12") | E18: '=E12*(1+F13) | F18: Projects revenue from prior year revenue and active growth rate. | G18: Revenue drives EBITDA, cash flow, and covenant metrics in a software LBO. | H18: Growth applied to wrong base year or mixing % as whole numbers. | I18: If revenue=1,200 and growth=6%, next year=1,272.
B19: 9 | C19: EBITDA margin ramp (active) | D19: =HYPERLINK("#'03_DRIVERS_AND_FORECAST'!F15","03_DRIVERS_AND_FORECAST!F15") | E19: '='01_CONTROL'!$D$31 + MIN(1,F9/'01_CONTROL'!$D$27)*('01_CONTROL'!$G$40-'01_CONTROL'!$D$31) | F19: Builds an EBITDA margin path that ramps from current margin to target margin over time. | G19: Margin is a key lever on FCF conversion and deleveraging speed. | H19: Ramping the wrong direction or using % points vs %. | I19: If start margin=25% and target=27%, ramp adds 2% pts over ramp years.
B20: 10 | C20: EBITDA = Revenue * EBITDA margin | D20: =HYPERLINK("#'03_DRIVERS_AND_FORECAST'!F16","03_DRIVERS_AND_FORECAST!F16") | E20: '=F12*F15 | F20: Calculates EBITDA from revenue and EBITDA margin. | G20: EBITDA is the core driver for valuation, leverage, and covenants. | H20: Using gross margin instead of EBITDA margin; hardcoding EBITDA. | I20: If revenue=1,272 and margin=27%, EBITDA=343.4.
B21: 11 | C21: Unlevered FCF (NOPAT + D&A - capex - ΔNWC) | D21: =HYPERLINK("#'04_OPERATING_MODEL'!F37","04_OPERATING_MODEL!F37") | E21: '=F20+F17+F36-F32 | F21: Computes free cash flow available before financing by combining NOPAT, non-cash D&A, capex, and working capital. | G21: This is what pays down debt and creates downside protection. | H21: Wrong sign on ΔNWC or capex; taxing EBITDA instead of EBIT/NOPAT. | I21: NOPAT 150 + D&A 20 - capex 30 - ΔNWC 10 = 130.
B22: 12 | C22: Cash taxes (levered, cash) | D22: =HYPERLINK("#'07_CASH_FLOW_WATERFALL'!F15","07_CASH_FLOW_WATERFALL!F15") | E22: '=-MAX(0,'04_OPERATING_MODEL'!F18-F28)*'01_CONTROL'!$D$26 | F22: Calculates cash taxes paid in the waterfall based on taxable income proxy and tax rate. | G22: Taxes reduce cash available for debt service and impact deleveraging. | H22: Using EBIT vs EBT incorrectly; forgetting to cap at zero when losses. | I22: If taxable base=200 and tax=22%, cash tax=44.
B23: 13 | C23: Cash before debt service | D23: =HYPERLINK("#'07_CASH_FLOW_WATERFALL'!F19","07_CASH_FLOW_WATERFALL!F19") | E23: '=SUM(F14:F18) | F23: Sums EBITDA and cash conversion items to get cash generated before interest and debt repayment. | G23: This line is the cash engine that funds interest, amortization, and sweep. | H23: Double counting capex or ΔNWC; wrong sign convention. | I23: EBITDA 340 - tax 40 - ΔNWC 10 - capex 30 = 260.
B24: 14 | C24: Total cash interest (sum across tranches) | D24: =HYPERLINK("#'07_CASH_FLOW_WATERFALL'!F20","07_CASH_FLOW_WATERFALL!F20") | E24: '=-('06_DEBT_SCHEDULES'!F27+'06_DEBT_SCHEDULES'!F36+'06_DEBT_SCHEDULES'!F45+'06_DEBT_SCHEDULES'!F54+'06_DEBT_SCHEDULES'!F63) | F24: Aggregates cash interest from all debt tranches into one waterfall line. | G24: Interest is often the largest financing cash outflow and a key sensitivity. | H24: Missing a tranche; treating PIK as cash interest; sign errors. | I24: If TLA interest 30 and TLB interest 45, total=75.
B25: 15 | C25: Cash after interest | D25: =HYPERLINK("#'07_CASH_FLOW_WATERFALL'!F21","07_CASH_FLOW_WATERFALL!F21") | E25: '=F19+F20 | F25: Adds the interest line to cash before debt service to get cash remaining after interest. | G25: Determines how much cash is left to amortize debt and sweep. | H25: Interest sign wrong (should be negative in waterfall). | I25: 260 cash before + (-75) interest = 185.
B26: 16 | C26: Mandatory amort (total) | D26: =HYPERLINK("#'07_CASH_FLOW_WATERFALL'!F22","07_CASH_FLOW_WATERFALL!F22") | E26: '=-('06_DEBT_SCHEDULES'!F32+'06_DEBT_SCHEDULES'!F41+'06_DEBT_SCHEDULES'!F50+'06_DEBT_SCHEDULES'!F59) | F26: Aggregates mandatory amortization across tranches. | G26: Mandatory paydown is contractual and affects deleveraging and liquidity. | H26: Forgetting a tranche or using % of revenue instead of % of debt. | I26: If TLA 20 and TLB 10, mandatory total=30.
B27: 17 | C27: Sweep pool = MAX(0, cash after mandatory) * sweep% | D27: =HYPERLINK("#'07_CASH_FLOW_WATERFALL'!F25","07_CASH_FLOW_WATERFALL!F25") | E27: '=MAX(0,F23)*F24 | F27: Calculates optional sweep cash based on surplus cash and sweep percentage. | G27: Optional sweep is the controllable lever that accelerates deleveraging. | H27: Sweeping when cash is negative; ignoring liquidity target. | I27: If surplus=155 and sweep%=50%, sweep pool=77.5.
B28: 18 | C28: Revolver draw (if deficit) | D28: =HYPERLINK("#'07_CASH_FLOW_WATERFALL'!F30","07_CASH_FLOW_WATERFALL!F30") | E28: '=MIN('06_DEBT_SCHEDULES'!$E$14-'06_DEBT_SCHEDULES'!F22, F27) | F28: Draws revolver up to available capacity when there is a cash deficit. | G28: Ensures liquidity is modeled realistically without negative cash plugs. | H28: Allowing draw beyond revolver limit; not linking to deficit. | I28: If deficit=40 and capacity=100, draw=40.
B29: 19 | C29: Revolver repay (if surplus) | D29: =HYPERLINK("#'07_CASH_FLOW_WATERFALL'!F31","07_CASH_FLOW_WATERFALL!F31") | E29: '=MIN('06_DEBT_SCHEDULES'!F22, F25) | F29: Repays revolver first using available sweep cash, capped by revolver balance. | G29: Standard cash management logic and reduces interest cost. | H29: Repaying more than outstanding; repaying while deficit exists. | I29: If rev balance=30 and sweep pool=80, repay=30.
B30: 20 | C30: Sweep allocation to Term Loan B (priority) | D30: =HYPERLINK("#'07_CASH_FLOW_WATERFALL'!F33","07_CASH_FLOW_WATERFALL!F33") | E30: '=MIN(F32, MAX(0,'06_DEBT_SCHEDULES'!F40-'06_DEBT_SCHEDULES'!F41)) | F30: Allocates optional sweep to Term Loan B first, capped by available balance after mandatory amort. | G30: Implements credit agreement priority and drives tranche-level deleveraging. | H30: Wrong priority order; not capping by remaining balance. | I30: If sweep remaining=50 and TLB remaining=40, pay 40 to TLB.
B31: 21 | C31: Revolver ending balance roll-forward | D31: =HYPERLINK("#'06_DEBT_SCHEDULES'!F25","06_DEBT_SCHEDULES!F25") | E31: '=F22+F23-F24 | F31: Updates revolver ending balance: opening + draws - repayments. | G31: Ensures revolver mechanics tie and interest is calculated on correct balances. | H31: Sign errors or links to wrong waterfall lines. | I31: If opening 0 + draw 40 - repay 30, ending 10.
B32: 22 | C32: Floating all-in rate with floor | D32: =HYPERLINK("#'06_DEBT_SCHEDULES'!F35","06_DEBT_SCHEDULES!F35") | E32: '=IF(IR_Mode="Fixed",'01_CONTROL'!$F$64,MAX(Bench_Rate+'01_CONTROL'!$D$64,'01_CONTROL'!$E$64)) | F32: Sets all-in floating rate as MAX(benchmark+spread, floor) unless fixed mode is selected. | G32: Captures rate sensitivity and protects from unrealistic low-rate cases. | H32: Forgetting floor, or applying spread twice. | I32: If benchmark 3% + spread 4% =7%, floor 5%, rate=7%.
B33: 23 | C33: Debt mandatory amortization (cap at balance) | D33: =HYPERLINK("#'06_DEBT_SCHEDULES'!F32","06_DEBT_SCHEDULES!F32") | E33: '=MIN(F31,'01_CONTROL'!$C$64*F31) | F33: Computes scheduled amortization as min(balance, amort% * balance). | G33: Prevents over-amortization and supports clean roll-forward ties. | H33: Amort based on original balance instead of current; forgetting MIN cap. | I33: If balance=100 and amort%=5%, amort=5.
B34: 24 | C34: Optional sweep link from waterfall | D34: =HYPERLINK("#'06_DEBT_SCHEDULES'!F33","06_DEBT_SCHEDULES!F33") | E34: '='07_CASH_FLOW_WATERFALL'!F33 | F34: Pulls optional sweep for the tranche from the waterfall allocation line. | G34: Keeps cash waterfall as the single source of truth for optional repayments. | H34: Duplicating sweep logic in both sheets leading to mismatches. | I34: If waterfall assigns 40 to TLA, tranche optional sweep=40.
B35: 25 | C35: Exit EV (multiple method) | D35: =HYPERLINK("#'08_EXIT_AND_EQUITY_BRIDGE'!D23","08_EXIT_AND_EQUITY_BRIDGE!D23") | E35: '=IF(Exit_Method="Exit Multiple", D15*Exit_Multiple, (Exit_Equity_Target + D24 - D25)/(1-D19)) | F35: Calculates exit EV from exit EBITDA and exit multiple when exit method is 'Exit Multiple'. | G35: Exit valuation is the largest driver of returns, so logic must be clear and auditable. | H35: Exit year mismatch; using entry EBITDA; wrong multiple reference. | I35: Exit EBITDA 450 and multiple 11.0x gives EV=4,950.
B36: 26 | C36: EV-to-Equity bridge | D36: =HYPERLINK("#'08_EXIT_AND_EQUITY_BRIDGE'!D27","08_EXIT_AND_EQUITY_BRIDGE!D27") | E36: '=D23-D24+D25-D26 | F36: Converts exit EV to equity proceeds: EV - debt + cash - fees. | G36: This is the translation from business value to equity value and return. | H36: Wrong sign on cash or debt; fees applied to equity not EV. | I36: EV 4,950 - debt 1,000 + cash 100 - fees 50 = 4,000.
B37: 27 | C37: Sponsor proceeds (split by ownership) | D37: =HYPERLINK("#'08_EXIT_AND_EQUITY_BRIDGE'!D35","08_EXIT_AND_EQUITY_BRIDGE!D35") | E37: '=D27*D34 | F37: Allocates total exit equity proceeds to sponsor based on sponsor ownership of equity. | G37: Determines sponsor MOIC and sponsor IRR. | H37: Ownership computed from wrong equity amounts; not tying sponsor+mgmt to total. | I37: If equity proceeds 4,000 and sponsor owns 90%, sponsor gets 3,600.
B38: 28 | C38: Sponsor MOIC | D38: =HYPERLINK("#'09_RETURNS'!D21","09_RETURNS!D21") | E38: '=IF('05_SOURCES_AND_USES'!$D$38=0,0,'08_EXIT_AND_EQUITY_BRIDGE'!$D$35/'05_SOURCES_AND_USES'!$D$38) | F38: Computes MOIC as sponsor exit proceeds divided by sponsor equity invested. | G38: Quickly checks if returns are plausible and ties directly to cash flows. | H38: Using total equity instead of sponsor equity; mismatched proceeds cell. | I38: Proceeds 3,600 / equity 2,088 = 1.72x.
B39: 29 | C39: Sponsor IRR (range correctness) | D39: =HYPERLINK("#'09_RETURNS'!D20","09_RETURNS!D20") | E39: '=IRR(OFFSET($E$14,0,0,1,Hold_Col)) | F39: Calculates IRR on the sponsor equity cash flow row, using Hold_Col to include only years 0..exit. | G39: IRR is IC headline, so the range and timing must be correct. | H39: Off-by-one in hold column; missing exit cash flow; negative sign mistakes. | I39: Cash flows: -2,088 in Year0 and +3,600 in Year5 implies ~11.5% IRR.
B40: 30 | C40: Net leverage | D40: =HYPERLINK("#'10_COVENANTS_AND_CREDIT_METRICS'!F19","10_COVENANTS_AND_CREDIT_METRICS!F19") | E40: '=IF(F14=0,0,F17/F14) | F40: Calculates net leverage as net debt divided by EBITDA for each year. | G40: Used for covenants, credit risk, and downside protection assessment. | H40: Using gross debt or wrong cash definition; EBITDA definition mismatch. | I40: Net debt 1,200 / EBITDA 400 = 3.0x.
B41: 31 | C41: Interest coverage | D41: =HYPERLINK("#'10_COVENANTS_AND_CREDIT_METRICS'!F21","10_COVENANTS_AND_CREDIT_METRICS!F21") | E41: '=IF(F20=0,0,F14/F20) | F41: Calculates EBITDA divided by cash interest. | G41: Key lender metric and fast sanity check for rate sensitivity. | H41: Interest sign wrong; including PIK; using EBIT not EBITDA. | I41: EBITDA 400 / interest 80 = 5.0x.
B42: 32 | C42: Net leverage covenant headroom | D42: =HYPERLINK("#'10_COVENANTS_AND_CREDIT_METRICS'!F27","10_COVENANTS_AND_CREDIT_METRICS!F27") | E42: '=Coven_NetLev_Max-F19 | F42: Compares actual net leverage to covenant maximum to compute headroom. | G42: Directly answers 'how close are we to a breach'. | H42: Covenant max hardcoded in the calc; using gross leverage by mistake. | I42: If max 5.0x and actual 4.2x, headroom 0.8x.
B43: 33 | C43: Peak net leverage (summary tile) | D43: =HYPERLINK("#'10_COVENANTS_AND_CREDIT_METRICS'!D34","10_COVENANTS_AND_CREDIT_METRICS!D34") | E43: '=MAX($F$19:$L$19) | F43: Takes the maximum of the net leverage series over the period. | G43: Highlights the stress point and drives dashboard risk summary. | H43: Range not covering full period; including blank columns. | I43: If series peaks at 4.5x, peak leverage is 4.5x.
B44: 34 | C44: Cash bridge check (should be 0) | D44: =HYPERLINK("#'07_CASH_FLOW_WATERFALL'!F42","07_CASH_FLOW_WATERFALL!F42") | E44: '=F23 - (F26+F31+F33+F34+F35+F36+F40) + F30 | F44: Checks that cash after mandatory amort equals uses of cash (sweep, revolver, ending cash). | G44: Prevents hidden cash plugs and circularity issues. | H44: Missing a term in the bridge; wrong sign on draw/repay. | I44: If cash after mandatory is 155 and uses sum to 155, check=0.
B45: 35 | C45: Sensitivity IRR cell (Exit vs Entry multiple) | D45: =HYPERLINK("#'11_SENSITIVITIES'!D24","11_SENSITIVITIES!D24") | E45: '=IFERROR(IF(((D$23*$L$16)*(1+$L$23)+$L$18*$L$24-$L$18)<=0,NA(),((($C24*$L$21)-$L$19+$L$20-($C24*$L$21)*$L$22)/((D$23*$L$16)*(1+$L$23)+$L$18*$L$24-$L$18))^(1/Hold_Y)-1),NA()) | F45: Computes an IRR approximation for a given entry and exit multiple pair, holding debt and cash paths constant. | G45: Lets you see how valuation assumptions dominate returns in IC discussion. | H45: Mixing up entry vs exit multiple references; forgetting fees; dividing by wrong equity. | I45: Entry 12x, exit 11x on growing EBITDA should produce lower IRR than exit 12x.

Sheet 82_LBO_LEARN_INTERPRETATION
B2: CHECKS: | C2: =HYPERLINK("#'90_CHECKS'!B6",'90_CHECKS'!$C$22) | D2: =HYPERLINK("#'80_LBO_LEARN_MAP'!B8","LEARN MAP") | E2: =HYPERLINK("#'00_DASHBOARD'!B3","DASHBOARD")
B6: 82_LBO_LEARN_INTERPRETATION | Dashboard interpretation + IC scripts
B8: Use this tab to speak in IC-style: what the tile means, what it signals, and the next question.
B10: Dashboard tile | C10: Where (click) | D10: How to interpret (1-2 lines) | E10: What it signals | F10: What could mislead | G10: Follow-up question
B11: ENTRY EV (DKKm) | C11: =HYPERLINK("#'00_DASHBOARD'!C11","00_DASHBOARD!C11") | D11: Enterprise value paid at entry. It is the starting point for equity required. | E11: High EV vs EBITDA implies paying up. With fixed leverage it increases equity check and lowers returns. | F11: EV can be inflated if EBITDA includes one-offs or add-backs. Ensure LTM definition matches lender and comps. | G11: Is entry multiple supported by comps and growth durability?
B12: ENTRY MULTIPLE (x) | C12: =HYPERLINK("#'00_DASHBOARD'!C12","00_DASHBOARD!C12") | D12: EV divided by LTM EBITDA. Primary valuation assumption. | E12: Higher entry multiple means you need stronger growth, margin expansion, or deleveraging to hit returns. | F12: Multiple comparisons can mislead if peers have different growth, churn, or IFRS16 treatment. | G12: What is the comp range and what quality premium is justified?
B13: TOTAL DEBT (DKKm) | C13: =HYPERLINK("#'00_DASHBOARD'!C13","00_DASHBOARD!C13") | D13: Total funded debt at close across tranches. | E13: More debt increases equity efficiency but raises interest burden and covenant risk. | F13: If revolver is shown as drawn when it is just availability, debt and leverage will look worse than reality. | G13: How much is fixed vs floating and what is the amort profile?
B14: TOTAL EQUITY (DKKm) | C14: =HYPERLINK("#'00_DASHBOARD'!C14","00_DASHBOARD!C14") | D14: Total equity check required at close (sponsor plus management). | E14: Bigger equity check reduces IRR unless exit equity scales proportionally. | F14: Equity can be understated if fees or WC adjustments are missing. | G14: Do Sources and Uses tie and are fees fully captured?
B15: ENTRY LEVERAGE (x) | C15: =HYPERLINK("#'00_DASHBOARD'!C15","00_DASHBOARD!C15") | D15: Debt divided by LTM EBITDA at entry. | E15: This is the core risk-return choice. Higher leverage tightens liquidity and covenant headroom. | F15: Leverage can be overstated if EBITDA is conservatively defined or understated if add-backs are aggressive. | G15: What is net leverage and covenant leverage definition?
B16: EXIT MULTIPLE (x) | C16: =HYPERLINK("#'00_DASHBOARD'!F11","00_DASHBOARD!F11") | D16: Exit valuation multiple applied to exit EBITDA in the base method. | E16: Exit assumptions dominate returns. A conservative exit multiple protects downside. | F16: Exit multiples can be biased upward by bull markets. Use a range and show sensitivity. | G16: What is the defensible exit multiple range and why?
B17: SPONSOR IRR | C17: =HYPERLINK("#'00_DASHBOARD'!F12","00_DASHBOARD!F12") | D17: Annualized return to the sponsor over the hold period. | E17: High IRR typically reflects strong value growth and or fast deleveraging or short hold. | F17: IRR is timing sensitive. Check hold period, exit timing, and whether there are interim distributions. | G17: What is MOIC and what drives the IRR to that level?
B18: SPONSOR MOIC | C18: =HYPERLINK("#'00_DASHBOARD'!F13","00_DASHBOARD!F13") | D18: Multiple of money: exit sponsor proceeds over sponsor equity invested. | E18: MOIC captures value creation without timing effects and ties directly to entry and exit equity. | F18: MOIC can look fine even if hold is long. Always pair with IRR. | G18: How does MOIC change across exit multiple and growth sensitivity?
B19: PEAK NET LEVERAGE (x) | C19: =HYPERLINK("#'00_DASHBOARD'!F14","00_DASHBOARD!F14") | D19: Maximum net leverage across the forecast period. | E19: Peak indicates the stress point for covenants and liquidity. | F19: If cash definition differs, peak net leverage may be misread. Confirm net debt definition. | G19: At what year does peak occur and what drives it (EBITDA vs debt)?
B20: MIN LIQUIDITY (DKKm) | C20: =HYPERLINK("#'00_DASHBOARD'!F15","00_DASHBOARD!F15") | D20: Lowest cash plus undrawn revolver during the hold. | E20: Low liquidity raises operating risk and covenant default risk even if leverage looks ok. | F20: Liquidity ignores seasonal WC unless modeled. Check WC assumptions in downside. | G20: What is the minimum cash buffer policy and revolver availability?
B21: MIN COVENANT HEADROOM (x) | C21: =HYPERLINK("#'00_DASHBOARD'!F16","00_DASHBOARD!F16") | D21: Worst headroom vs covenant level, negative implies breach. | E21: This is the lender risk test under base and downside. | F21: Headroom can be misstated if covenant definition differs from model definition. | G21: Which covenant trips first and under what scenario?
B22: CHECKS STATUS | C22: =HYPERLINK("#'00_DASHBOARD'!F17","00_DASHBOARD!F17") | D22: Model control summary. Must be PASS before relying on results. | E22: FAIL signals a broken tie-out or logic issue, stop and fix before interpreting outputs. | F22: A PASS does not guarantee realism, only mechanical consistency. | G22: Which check failed and what is the root cause line?
B25: IC-ready scripts (12 common LBO questions)
B27: Topic | C27: Script (2-3 sentences)
B28: Valuation defensibility | C28: Entry multiple is justified by recurring revenue, strong retention, and peer comp range. We show sensitivities because small multiple changes dominate IRR, so we underwrite to a conservative exit.
B29: Leverage comfort | C29: Leverage is set so cash interest and covenants stay robust under downside. We focus on peak net leverage, minimum liquidity, and headroom, not just entry leverage.
B30: Downside protection | C30: The downside case stresses growth and margin while keeping costs realistic. We track what breaks first across leverage, coverage, and liquidity, then show levers that are executable.
B31: Deleveraging drivers | C31: Deleveraging is driven by unlevered free cash flow conversion, not accounting EBITDA alone. The biggest swing factors are margin path, working capital, and capex discipline.
B32: Interest rate sensitivity | C32: Floating exposure hits cash after interest first. We test a +200 bps shock and show whether the model still pays down debt and stays inside covenants.
B33: Covenant headroom | C33: We use net leverage and interest coverage and show the minimum headroom year. If headroom is tight, we identify realistic fixes like lower leverage, tighter capex, or better WC conversion.
B34: Exit assumptions | C34: Exit multiple is anchored to comps and we frame a range. We avoid underwriting to multiple expansion, and instead show base returns driven by EBITDA growth and deleveraging.
B35: Working capital risks | C35: Working capital swings can create liquidity stress even in SaaS, especially if billing terms change. We stress ΔNWC and show impact on revolver usage and covenant headroom.
B36: Capex underinvestment risk | C36: Capex below sustainable levels can inflate FCF but harm product competitiveness. We keep capex aligned with D&A and business needs and stress capex creep in downside.
B37: Value creation sources | C37: We decompose returns into EBITDA growth, multiple change, and deleveraging. The controllable levers are operating performance and cash conversion, so we focus there.
B38: Sponsor control levers | C38: Levers include pricing and upsell, cost discipline, working capital management, and debt terms such as sweep and amort. We show which levers move IRR most efficiently.
B39: Sanity checks | C39: Before any IC narrative, we confirm Sources equals Uses, debt roll-forwards tie, cash bridge checks to zero, and exit bridge ties. If checks fail, outputs are not decision-ready.

Sheet 83_LBO_LEARN_SCENARIOS
B2: CHECKS: | C2: =HYPERLINK("#'90_CHECKS'!B6",'90_CHECKS'!$C$22) | D2: =HYPERLINK("#'80_LBO_LEARN_MAP'!B8","LEARN MAP") | E2: =HYPERLINK("#'00_DASHBOARD'!B3","DASHBOARD")
B6: 83_LBO_LEARN_SCENARIOS | Scenario narratives (Base vs Upside vs Downside)
B8: How to use: (1) Review scenario assumptions pulled from 01_CONTROL. (2) To populate scenario outputs, set 01_CONTROL!D12 to each scenario and copy the dashboard tiles into the blue capture cells below. This keeps the learning layer additive (no model changes).
B10: Scenario assumptions (pulled from 01_CONTROL)
B12: Assumption | C12: Base | D12: Upside | E12: Downside | F12: Aggressiveness (Base) | G12: Aggressiveness (Upside) | H12: Aggressiveness (Downside) | I12: Notes (what to watch)
B13: Revenue growth (annual) | C13: ='01_CONTROL'!D39 | D13: ='01_CONTROL'!E39 | E13: ='01_CONTROL'!F39 | F13: =IF(C13<=0.06,"Conservative",IF(C13<=0.1,"Neutral","Aggressive")) | G13: =IF(D13<=0.06,"Conservative",IF(D13<=0.1,"Neutral","Aggressive")) | H13: =IF(E13<=0.06,"Conservative",IF(E13<=0.1,"Neutral","Aggressive")) | I13: Higher is more aggressive. Check customer churn and pricing power.
B14: EBITDA margin (steady state) | C14: ='01_CONTROL'!D40 | D14: ='01_CONTROL'!E40 | E14: ='01_CONTROL'!F40 | F14: =IF(C14<=0.26,"Conservative",IF(C14<=0.29,"Neutral","Aggressive")) | G14: =IF(D14<=0.26,"Conservative",IF(D14<=0.29,"Neutral","Aggressive")) | H14: =IF(E14<=0.26,"Conservative",IF(E14<=0.29,"Neutral","Aggressive")) | I14: Higher is more aggressive. Confirm cost plan and implementation realism.
B15: Capex (% revenue) | C15: ='01_CONTROL'!D41 | D15: ='01_CONTROL'!E41 | E15: ='01_CONTROL'!F41 | F15: =IF(C15<=0.02,"Aggressive",IF(C15<=0.03,"Neutral","Conservative")) | G15: =IF(D15<=0.02,"Aggressive",IF(D15<=0.03,"Neutral","Conservative")) | H15: =IF(E15<=0.02,"Aggressive",IF(E15<=0.03,"Neutral","Conservative")) | I15: Lower capex is more aggressive. Watch underinvestment risk.
B16: Working capital (NWC % revenue) | C16: ='01_CONTROL'!D44 | D16: ='01_CONTROL'!E44 | E16: ='01_CONTROL'!F44 | F16: =IF(C16<=0.04,"Aggressive",IF(C16<=0.05,"Neutral","Conservative")) | G16: =IF(D16<=0.04,"Aggressive",IF(D16<=0.05,"Neutral","Conservative")) | H16: =IF(E16<=0.04,"Aggressive",IF(E16<=0.05,"Neutral","Conservative")) | I16: Lower NWC % is more aggressive. Validate billing terms.
B17: Benchmark rate (floating) | C17: ='01_CONTROL'!D22 | D17: ='01_CONTROL'!D22 | E17: ='01_CONTROL'!D22 | F17: =IF(C17>=0.05,"Conservative",IF(C17>=0.03,"Neutral","Aggressive")) | G17: =IF(D17>=0.05,"Conservative",IF(D17>=0.03,"Neutral","Aggressive")) | H17: =IF(E17>=0.05,"Conservative",IF(E17>=0.03,"Neutral","Aggressive")) | I17: Higher rates are more conservative for returns; stress +200 bps separately.
B18: Entry multiple (x) | C18: ='01_CONTROL'!D16 | D18: ='01_CONTROL'!D16 | E18: ='01_CONTROL'!D16 | F18: =IF(C18>=13,"Aggressive",IF(C18>=11,"Neutral","Conservative")) | G18: =IF(D18>=13,"Aggressive",IF(D18>=11,"Neutral","Conservative")) | H18: =IF(E18>=13,"Aggressive",IF(E18>=11,"Neutral","Conservative")) | I18: Higher entry multiple is more aggressive (harder to earn).
B19: Exit multiple (x) | C19: ='01_CONTROL'!D18 | D19: ='01_CONTROL'!D18 | E19: ='01_CONTROL'!D18 | F19: =IF(C19>=13,"Aggressive",IF(C19>=11,"Neutral","Conservative")) | G19: =IF(D19>=13,"Aggressive",IF(D19>=11,"Neutral","Conservative")) | H19: =IF(E19>=13,"Aggressive",IF(E19>=11,"Neutral","Conservative")) | I19: Higher exit multiple is more aggressive. Use a defensible range.
B22: Scenario outputs (paste values after toggling Scenario in 01_CONTROL)
B24: Output KPI | C24: Base (paste) | D24: Upside (paste) | E24: Downside (paste) | F24: Upside - Base | G24: Downside - Base
B25: Sponsor IRR | F25: =IF(OR(C25="",D25=""),"",D25-C25) | G25: =IF(OR(C25="",E25=""),"",E25-C25)
B26: Sponsor MOIC | F26: =IF(OR(C26="",D26=""),"",D26-C26) | G26: =IF(OR(C26="",E26=""),"",E26-C26)
B27: Peak net leverage (x) | F27: =IF(OR(C27="",D27=""),"",D27-C27) | G27: =IF(OR(C27="",E27=""),"",E27-C27)
B28: Min covenant headroom (net lev, x) | F28: =IF(OR(C28="",D28=""),"",D28-C28) | G28: =IF(OR(C28="",E28=""),"",E28-C28)
B29: Min liquidity (DKKm) | F29: =IF(OR(C29="",D29=""),"",D29-C29) | G29: =IF(OR(C29="",E29=""),"",E29-C29)
B32: Narrative (tie back to model cells)
B34: What must be true for Upside: | C34: Upside assumes higher growth (01_CONTROL!E39) and higher steady-state margin (01_CONTROL!E40). For IC, anchor this in retention, pricing power, and a credible cost plan with execution milestones.
B35: What breaks first in Downside: | C35: Downside compresses growth and margin (01_CONTROL!F39:F40) and worsens WC (01_CONTROL!F44). Watch liquidity (10_COVENANTS!Min liquidity) and covenant headroom first, then deleveraging speed.
B36: Which 3 assumptions drive ~80% of variance: | C36: Exit multiple (01_CONTROL!D18), revenue growth (01_CONTROL scenario growth), and margin path (01_CONTROL scenario margin). These dominate EV and FCF, which then drive equity proceeds and IRR.

Sheet 84_LBO_LEARN_DRILLS
B2: CHECKS: | C2: =HYPERLINK("#'90_CHECKS'!B6",'90_CHECKS'!$C$22) | D2: =HYPERLINK("#'80_LBO_LEARN_MAP'!B8","LEARN MAP") | E2: =HYPERLINK("#'00_DASHBOARD'!B3","DASHBOARD")
B6: 84_LBO_LEARN_DRILLS | Exercises + scoring (hands-on)
B8: Rule: Change ONLY allowed input cells. Do not hardcode outputs. Use 90_CHECKS and dashboard to verify mechanics are intact.
B10: Daily drill mode
B12: Mode (blue): | C12: Rotate
B13: Today drill #: | C13: =IF($C$12="Random",RANDBETWEEN(1,12),MOD(TODAY(),12)+1)
B14: Attempts (blue):
B15: Passes (blue):
B16: Date (auto): | C16: =TODAY()
B18: Baseline snapshot (paste values as values into blue cells before starting)
B20: Metric | C20: Baseline (paste) | D20: Current (live) | E20: Delta
B21: Sponsor IRR | D21: ='00_DASHBOARD'!F12 | E21: =IF(OR(C21="",D21=""),"",D21-C21)
B22: Sponsor MOIC | D22: ='00_DASHBOARD'!F13 | E22: =IF(OR(C22="",D22=""),"",D22-C22)
B23: Exit multiple | D23: ='00_DASHBOARD'!F11 | E23: =IF(OR(C23="",D23=""),"",D23-C23)
B24: Entry multiple | D24: ='00_DASHBOARD'!C12 | E24: =IF(OR(C24="",D24=""),"",D24-C24)
B25: Peak net leverage | D25: ='00_DASHBOARD'!F14 | E25: =IF(OR(C25="",D25=""),"",D25-C25)
B26: Min liquidity (DKKm) | D26: ='00_DASHBOARD'!F15 | E26: =IF(OR(C26="",D26=""),"",D26-C26)
B27: Min covenant headroom (x) | D27: ='00_DASHBOARD'!F16 | E27: =IF(OR(C27="",D27=""),"",D27-C27)
B28: Benchmark rate | D28: ='01_CONTROL'!D22 | E28: =IF(OR(C28="",D28=""),"",D28-C28)
B29: Leverage target | D29: ='01_CONTROL'!D48 | E29: =IF(OR(C29="",D29=""),"",D29-C29)
B30: Debt structure | D30: ='01_CONTROL'!D20 | E30: =IF(OR(C30="",D30=""),"",IF(C30=D30,"OK","CHANGED"))
B31: Scenario | D31: ='01_CONTROL'!D12 | E31: =IF(OR(C31="",D31=""),"",IF(C31=D31,"OK","CHANGED"))
B32: Active revenue growth | D32: ='01_CONTROL'!G39 | E32: =IF(OR(C32="",D32=""),"",D32-C32)
B33: Net leverage in Year 3 (x) | D33: ='10_COVENANTS_AND_CREDIT_METRICS'!H19 | E33: =IF(OR(C33="",D33=""),"",D33-C33)
B35: Target IRR for Drill 5 (blue): | C35: 0.2
B36: Drill 8: Breach observed (TRUE/FALSE, blue): | C36: FALSE
B37: Drill 8: Fix applied (TRUE/FALSE, blue): | C37: FALSE
B38: Drill 10: IRR at low exit multiple (paste, blue):
B39: Drill 10: IRR at high exit multiple (paste, blue):
B40: Drill 12 bullets (fill C40:C45, blue):
B48: 12 drills (PASS/FAIL is live vs baseline snapshot)
B50: # | C50: Objective | D50: Allowed inputs (specific cells) | E50: Forbidden inputs | F50: PASS/FAIL (live) | G50: Why this works (driver logic)
B51: 1 | C51: Increase IRR by +3pp without changing exit multiple | D51: 01_CONTROL scenario inputs: growth (row 39), margin (row 40), capex (row 41), NWC (row 44). Optional: sweep % (G54). | E51: Do NOT change exit multiple (01_CONTROL!D18), entry multiple (01_CONTROL!D16), leverage target (01_CONTROL!D48). | F51: =IF(AND($D$21>=$C$21+0.03,$D$23=$C$23,$D$24=$C$24,$D$29=$C$29),"PASS","FAIL") | G51: Operating improvements raise FCF and debt paydown, increasing equity proceeds with the same exit valuation multiple.
B52: 2 | C52: Increase MOIC by +0.3x without changing entry multiple | D52: Allowed: operating drivers, leverage target, debt structure, exit multiple (if you want). | E52: Entry multiple must not change. | F52: =IF(AND($D$22>=$C$22+0.30,$D$24=$C$24),"PASS","FAIL") | G52: MOIC is exit equity divided by entry equity. Holding entry multiple forces value creation elsewhere.
B53: 3 | C53: Reduce peak leverage by 0.5x while keeping IRR within -1pp | D53: Allowed: leverage target, sweep %, operating drivers. | E53: Entry and exit multiple must not change. | F53: =IF(AND($D$25<=$C$25-0.5,$D$21>=$C$21-0.01,$D$24=$C$24,$D$23=$C$23),"PASS","FAIL") | G53: Lower starting debt and/or faster paydown reduces peak leverage. Keeping IRR near baseline trains trade-off thinking.
B54: 4 | C54: Offset +200 bps interest rate shock while keeping MOIC flat (±0.02x) | D54: Set benchmark rate (01_CONTROL!D22) = baseline + 2.00%. Allowed: leverage, sweep %, operating drivers. | E54: Do not change entry multiple. | F54: =IF(AND($D$28>=$C$28+0.02,ABS($D$22-$C$22)<=0.02,$D$24=$C$24),"PASS","FAIL") | G54: Higher rates reduce cash after interest. You offset by lowering leverage or improving FCF conversion.
B55: 5 | C55: Hit a target IRR by changing debt structure (and explain trade-offs) | D55: Debt structure (01_CONTROL!D20), leverage target (D48), tranche spreads/amort (rows 63-67). | E55: Prefer no change to exit multiple for a credit-driven result. | F55: =IF(AND($D$21>=$C$35,$D$30<>$C$30),"PASS","FAIL") | G55: Structure changes pricing and amort burden. This shifts cash interest and paydown speed, affecting equity proceeds.
B56: 6 | C56: Improve returns via operating levers only (no leverage change) | D56: Change only operating assumptions (growth/margin/capex/NWC) using scenario table inputs. | E56: No change to leverage target, entry multiple, exit multiple. | F56: =IF(AND($D$21>=$C$21+0.02,$D$29=$C$29,$D$24=$C$24,$D$23=$C$23),"PASS","FAIL") | G56: Pure operational improvement increases unlevered FCF and deleveraging without relying on financial engineering.
B57: 7 | C57: Build a credible downside that still avoids covenant breach | D57: Set Scenario to Downside and adjust downside assumptions only (01_CONTROL!F39:F44). | E57: Do not 'fix' by raising exit multiple. | F57: =IF(AND($D$31="Downside",$D$27>=0,$D$26>=0),"PASS","FAIL") | G57: Downside should be realistic and still show survival if leverage is appropriate.
B58: 8 | C58: Force a covenant breach then fix it using two levers | D58: Step 1: create breach (lower margin, higher rates). Step 2: fix using two realistic levers (lower leverage, better WC, capex discipline). | E58: Do not hardcode outputs or change model formulas. | F58: =IF(AND($C$36=TRUE,$C$37=TRUE,$D$27>=0),"PASS","FAIL") | G58: Trains diagnose-and-fix workflow: identify what breaks first and apply credible levers.
B59: 9 | C59: Improve deleveraging speed without changing revenue growth | D59: Keep active revenue growth unchanged. Improve FCF conversion (margin/capex/WC/sweep) to reduce Year 3 net leverage by 0.5x. | E59: Do not change revenue growth, entry multiple, exit multiple. | F59: =IF(AND($D$33<=$C$33-0.5,$D$32=$C$32),"PASS","FAIL") | G59: With growth fixed, deleveraging comes from better conversion and cash discipline.
B60: 10 | C60: Quantify exit multiple dominance and defend a range | D60: Use sensitivity pack and record IRR at two exit multiples. | E60: Do not change operating assumptions while testing. | F60: =IF(AND($C$38<>"",$C$39<>"",ABS($C$39-$C$38)>=0.05),"PASS","FAIL") | G60: Shows how much return is driven by multiple. IC expects a defended range with quantified impact.
B61: 11 | C61: Definition mismatch drill (NWC method) and checks | D61: Switch NWC method (01_CONTROL!D43/E43/F43) and validate checks remain PASS and logic holds. | E61: No hardcodes; do not bypass checks. | F61: ='90_CHECKS'!$C$22 | G61: This trains definition awareness and reliance on checks for model integrity.
B62: 12 | C62: Value creation bridge in 6 bullets (speed drill) | D62: Use 86_LBO_SPECIAL_MODULE return decomposition and fill bullets. | E62: No model input changes required. | F62: =IF(COUNTA($C$40:$C$45)=6,"PASS","FAIL") | G62: Trains IC storytelling: EBITDA growth, multiple, deleveraging, plus risks and sensitivities.

Sheet 85_LBO_LEARN_MISTAKES
B2: CHECKS: | C2: =HYPERLINK("#'90_CHECKS'!B6",'90_CHECKS'!$C$22) | D2: =HYPERLINK("#'80_LBO_LEARN_MAP'!B8","LEARN MAP") | E2: =HYPERLINK("#'00_DASHBOARD'!B3","DASHBOARD")
B6: 85_LBO_LEARN_MISTAKES | Mistake library (25) + training mode (simulated)
B8: Purpose: Common mistakes that break LBO models, grouped by category. Training mode is simulated to avoid altering core outputs.
B10: Mistake library (25 common issues)
B12: Category | C12: Mistake | D12: What you see | E12: Root cause | F12: Quick fix | G12: Where to validate (cell/check)
B13: Mechanics | C13: Sign convention flipped on capex or ΔNWC | D13: FCF increases when capex increases | E13: Wrong sign in cash flow lines | F13: Check capex and ΔNWC signs in 04/07; investment uses cash | G13: 07_CASH_FLOW_WATERFALL!F17 and 04_OPERATING_MODEL!F32/F36
B14: Mechanics | C14: Sources and Uses does not tie | D14: Equity check wrong; returns nonsense | E14: Missing fee or incorrect total | F14: Fix S&U totals and confirm tie line equals 0 | G14: 05_SOURCES_AND_USES!D44 and 90_CHECKS Sources=Uses
B15: Mechanics | C15: Hold period off-by-one | D15: Exit cash flow in wrong year | E15: Hold_Col misaligned to Hold_Y | F15: Verify Hold_Col = Hold_Y+1 and exit indexes | G15: 01_CONTROL!G14 and 09_RETURNS!D20
B16: Mechanics | C16: Hardcoded number inside formula area | D16: Hidden assumption | E16: Manual overwrite of calc cell | F16: Move to blue input and reference | G16: Scan for blue fonts and use 90_CHECKS trace discipline
B17: Operating model | C17: Revenue growth applied to wrong base year | D17: Growth not compounding correctly | E17: Wrong reference in revenue forecast | F17: Check 03 revenue forecast uses prior-year revenue | G17: 03_DRIVERS_AND_FORECAST!F12
B18: Operating model | C18: Margin ramp mis-specified | D18: Margins jump unrealistically | E18: Ramp logic or years wrong | F18: Check margin ramp years and target margin | G18: 03_DRIVERS_AND_FORECAST!F15 and 01_CONTROL!D27
B19: Operating model | C19: ΔNWC sign error | D19: WC investment increases cash | E19: Sign reversed | F19: Ensure ΔNWC is a cash outflow when WC increases | G19: 04_OPERATING_MODEL!F32 and 07_WATERFALL!F16
B20: Operating model | C20: Capex unrealistic vs D&A | D20: FCF inflated | E20: Capex % too low | F20: Stress capex and sanity vs D&A | G20: 01_CONTROL row 41 and 04_OPERATING_MODEL capex/D&A lines
B21: Debt schedules | C21: Debt roll-forward doesn't tie | D21: Ending balances jump/negative | E21: Missing draw/repay or sweep line | F21: Check open+draws-mandatory-optional=close | G21: 06_DEBT_SCHEDULES tranche blocks
B22: Debt schedules | C22: Revolver breaches limit | D22: Liquidity misleading | E22: Draw not capped by limit | F22: Cap draw and repay appropriately | G22: 07_WATERFALL!F30 and 90_CHECKS revolver check
B23: Debt schedules | C23: Sweep order wrong | D23: Wrong tranche delevers first | E23: Allocation logic wrong | F23: Match credit agreement priority | G23: 07_WATERFALL!F33:F36
... B37: Mechanics | C37: Zeros not displayed consistently | D37: Cluttered output tables | E37: No consistent zero format | F37: Use '-' for zeros in outputs where appropriate | G37: Formatting review on outputs
B40: Optional TRAINING_MODE (simulated issues list + answer key)
B42: TRAINING_MODE status (01_CONTROL!G12): | C42: =TRAINING_MODE
B44: If TRAINING_MODE = ON: use this simulated list (do not break core model). Identify which check would catch it and where.
B46: Simulated issue | C46: What it looks like | D46: Answer key (what check should catch it)
B47: Hardcode in calc cell | C47: EBITDA overwritten as a number | D47: Should be caught by review: blue font policy violated; reconcile to 03_DRIVERS and 04_OPERATING.
B48: Debt roll-forward mismatch | C48: Optional sweep not linked | D48: Should show debt roll-forward / cash bridge mismatch and FAIL in checks.
B49: Sweep exceeds cash | C49: Sweep allocation not capped | D49: Cash bridge check becomes non-zero (07!F42) and 90_CHECKS should flag.
B50: Exit bridge sign error | C50: Cash subtracted instead of added | D50: Exit equity proceeds no longer equals EV-to-equity bridge; tie-out fails.
B51: Broken link placeholder | C51: Key tile #REF! | D51: Dashboard trace fails; checks should show FAIL.

Sheet 86_LBO_SPECIAL_MODULE
B2: CHECKS: | C2: =HYPERLINK("#'90_CHECKS'!B6",'90_CHECKS'!$C$22) | D2: =HYPERLINK("#'80_LBO_LEARN_MAP'!B8","LEARN MAP") | E2: =HYPERLINK("#'00_DASHBOARD'!B3","DASHBOARD")
B6: 86_LBO_SPECIAL_MODULE | Return decomposition + waterfall explainer + covenant lab
B8: This tab contains three LBO-specific mini-modules used in IC prep: (1) value creation attribution, (2) debt waterfall explainer, (3) downside protection and covenant lab.
B10: 1) Return decomposition bridge (Value creation attribution)
B12: Driver | C12: Value (DKKm) | D12: Link / source
B13: Entry EBITDA (LTM) | C13: ='01_CONTROL'!$D$32 | D13: =HYPERLINK("#'01_CONTROL'!D32","01_CONTROL!D32")
B14: Exit EBITDA (selected exit year) | C14: ='08_EXIT_AND_EQUITY_BRIDGE'!$D$15 | D14: =HYPERLINK("#'08_EXIT_AND_EQUITY_BRIDGE'!D15","08_EXIT_AND_EQUITY_BRIDGE!D15")
B15: Entry multiple (x) | C15: ='01_CONTROL'!$D$16 | D15: =HYPERLINK("#'01_CONTROL'!D16","01_CONTROL!D16")
B16: Exit multiple (x) | C16: ='01_CONTROL'!$D$18 | D16: =HYPERLINK("#'01_CONTROL'!D18","01_CONTROL!D18")
B17: Entry EV | C17: ='05_SOURCES_AND_USES'!$D$16 | D17: =HYPERLINK("#'05_SOURCES_AND_USES'!D16","05_SOURCES_AND_USES!D16")
B18: Exit EV | C18: ='08_EXIT_AND_EQUITY_BRIDGE'!$D$23 | D18: =HYPERLINK("#'08_EXIT_AND_EQUITY_BRIDGE'!D23","08_EXIT_AND_EQUITY_BRIDGE!D23")
B19: Entry net debt (debt - cash at close) | C19: ='05_SOURCES_AND_USES'!$D$37-'07_CASH_FLOW_WATERFALL'!$E$41 | D19: Debt: =HYPERLINK("#'05_SOURCES_AND_USES'!D37","05_SOURCES_AND_USES!D37") | Cash: =HYPERLINK("#'07_CASH_FLOW_WATERFALL'!E41","07_CASH_FLOW_WATERFALL!E41")
B20: Exit net debt (debt - cash at exit) | C20: ='08_EXIT_AND_EQUITY_BRIDGE'!$D$24-'08_EXIT_AND_EQUITY_BRIDGE'!$D$25 | D20: =HYPERLINK("#'08_EXIT_AND_EQUITY_BRIDGE'!D24","08_EXIT_AND_EQUITY_BRIDGE!D24") / =HYPERLINK("#'08_EXIT_AND_EQUITY_BRIDGE'!D25","08_EXIT_AND_EQUITY_BRIDGE!D25")
B21: Total equity invested | C21: ='05_SOURCES_AND_USES'!$D$40 | D21: =HYPERLINK("#'05_SOURCES_AND_USES'!D40","05_SOURCES_AND_USES!D40")
B22: Total equity proceeds (exit) | C22: ='08_EXIT_AND_EQUITY_BRIDGE'!$D$27 | D22: =HYPERLINK("#'08_EXIT_AND_EQUITY_BRIDGE'!D27","08_EXIT_AND_EQUITY_BRIDGE!D27")
B24: Attribution (EV bridge + deleveraging to equity)
B26: Component | C26: Formula | D26: Value (DKKm) | E26: IC script
B27: EBITDA growth (at entry multiple) | C27: =(Exit EBITDA - Entry EBITDA) * Entry multiple | D27: =($C$14-$C$13)*$C$15 | E27: At constant multiple, growth in EBITDA creates EV uplift. We underwrite this via retention, ARR expansion, and cost actions.
B28: Multiple change (at exit EBITDA) | C28: =Exit EBITDA * (Exit multiple - Entry multiple) | D28: =$C$14*($C$16-$C$15) | E28: Multiple expansion is upside, not the base thesis. We show sensitivity and anchor to comp ranges.
B29: Deleveraging (net debt reduction to equity) | C29: =Entry net debt - Exit net debt | D29: =$C$19-$C$20 | E29: Cash flow pays down net debt, converting EV into equity value. This is the controllable downside-protection lever.
B30: Dividends / distributions | C30: =0 in this template | D30: =0 | E30: No interim distributions modeled here. If dividends are added, they increase IRR and cash yield.
B31: Check: Total equity value created | C31: =(Total proceeds - Total invested) | D31: =$C$22-$C$21 | E31: This is the total equity uplift. Components above should reconcile directionally to this change (EV effects + deleveraging).
B34: 2) Debt waterfall explainer (step-by-step)
B36: Select year (1=Year1, etc) (blue): | C36: 1
B38: Step | C38: Pulled from model | D38: Value (DKKm) | E38: Why it matters / pitfall
B39: EBITDA | C39: 07_CASH_FLOW_WATERFALL!Row 14 | D39: =INDEX('07_CASH_FLOW_WATERFALL'!$E$14:$L$14,1,$C$36+1) | E39: Start of cash engine. Ensure EBITDA definition matches covenants and valuation.
B40: Less: cash taxes | C40: 07_CASH_FLOW_WATERFALL!Row 15 | D40: =INDEX('07_CASH_FLOW_WATERFALL'!$E$15:$L$15,1,$C$36+1) | E40: Taxes reduce cash. Pitfall: taxing EBITDA instead of EBIT/EBT logic.
B41: Less: ΔNWC | C41: 07_CASH_FLOW_WATERFALL!Row 16 | D41: =INDEX('07_CASH_FLOW_WATERFALL'!$E$16:$L$16,1,$C$36+1) | E41: WC investment consumes cash. Pitfall: sign errors or unrealistic WC assumptions.
B42: Less: capex | C42: 07_CASH_FLOW_WATERFALL!Row 17 | D42: =INDEX('07_CASH_FLOW_WATERFALL'!$E$17:$L$17,1,$C$36+1) | E42: Capex is real cash. Pitfall: underestimating maintenance capex for software platform.
B43: =Cash before debt service | C43: 07_CASH_FLOW_WATERFALL!Row 19 | D43: =INDEX('07_CASH_FLOW_WATERFALL'!$E$19:$L$19,1,$C$36+1) | E43: This is the cash pool to service debt.
B44: Less: cash interest | C44: 07_CASH_FLOW_WATERFALL!Row 20 | D44: =INDEX('07_CASH_FLOW_WATERFALL'!$E$20:$L$20,1,$C$36+1) | E44: Rate shocks hit here first. Validate interest lines include all tranches.
B45: =Cash after interest | C45: 07_CASH_FLOW_WATERFALL!Row 21 | D45: =INDEX('07_CASH_FLOW_WATERFALL'!$E$21:$L$21,1,$C$36+1) | E45: If negative, expect revolver draw or liquidity stress.
B46: Less: mandatory amort | C46: 07_CASH_FLOW_WATERFALL!Row 22 | D46: =INDEX('07_CASH_FLOW_WATERFALL'!$E$22:$L$22,1,$C$36+1) | E46: Contractual paydown. Pitfall: amort exceeding balance.
B47: =Cash after mandatory | C47: 07_CASH_FLOW_WATERFALL!Row 23 | D47: =INDEX('07_CASH_FLOW_WATERFALL'!$E$23:$L$23,1,$C$36+1) | E47: This feeds optional sweep and revolver logic.
B48: Optional sweep pool | C48: 07_CASH_FLOW_WATERFALL!Row 25 | D48: =INDEX('07_CASH_FLOW_WATERFALL'!$E$25:$L$25,1,$C$36+1) | E48: Cash to repay term debt (post sweep%). Pitfall: sweeping below liquidity target.
B49: Revolver draw | C49: 07_CASH_FLOW_WATERFALL!Row 30 | D49: =INDEX('07_CASH_FLOW_WATERFALL'!$E$30:$L$30,1,$C$36+1) | E49: Draw only if deficit and within limit.
B50: Revolver repay | C50: 07_CASH_FLOW_WATERFALL!Row 31 | D50: =INDEX('07_CASH_FLOW_WATERFALL'!$E$31:$L$31,1,$C$36+1) | E50: Repay revolver first when surplus exists.
B51: Ending cash | C51: 07_CASH_FLOW_WATERFALL!Row 41 | D51: =INDEX('07_CASH_FLOW_WATERFALL'!$E$41:$L$41,1,$C$36+1) | E51: Ending cash must be explained. Validate cash bridge check is 0.
B52: Cash bridge check | C52: 07_CASH_FLOW_WATERFALL!Row 42 | D52: =INDEX('07_CASH_FLOW_WATERFALL'!$E$42:$L$42,1,$C$36+1) | E52: Must be 0. If not, stop and fix logic before interpreting outputs.
B55: 3) Downside protection & covenant lab
B57: What breaks first? (live): | C57: =IF('10_COVENANTS_AND_CREDIT_METRICS'!$D$35<0,"Liquidity",IF('10_COVENANTS_AND_CREDIT_METRICS'!$D$36<0,"Net leverage covenant",IF('10_COVENANTS_AND_CREDIT_METRICS'!$D$37<0,"Interest coverage covenant","None in current scenario")) )
B59: Metric | C59: Min / peak (live) | D59: Source | E59: How to fix (realistic levers)
B60: Peak net leverage (x) | C60: ='10_COVENANTS_AND_CREDIT_METRICS'!$D$34 | D60: =HYPERLINK("#'10_COVENANTS_AND_CREDIT_METRICS'!D34","10_COVENANTS_AND_CREDIT_METRICS!D34") | E60: Lower leverage target, increase sweep %, improve margin, reduce capex, improve WC conversion.
B61: Min liquidity (DKKm) | C61: ='10_COVENANTS_AND_CREDIT_METRICS'!$D$35 | D61: =HYPERLINK("#'10_COVENANTS_AND_CREDIT_METRICS'!D35","10_COVENANTS_AND_CREDIT_METRICS!D35") | E61: Lower leverage, reduce sweep %, add revolver capacity, improve WC, delay capex (if realistic).
B62: Min net leverage headroom (x) | C62: ='10_COVENANTS_AND_CREDIT_METRICS'!$D$36 | D62: =HYPERLINK("#'10_COVENANTS_AND_CREDIT_METRICS'!D36","10_COVENANTS_AND_CREDIT_METRICS!D36") | E62: Delever faster via FCF, reduce debt at close, improve EBITDA via pricing/cost actions.
B63: Min interest coverage headroom (x) | C63: ='10_COVENANTS_AND_CREDIT_METRICS'!$D$37 | D63: =HYPERLINK("#'10_COVENANTS_AND_CREDIT_METRICS'!D37","10_COVENANTS_AND_CREDIT_METRICS!D37") | E63: Hedge rates, reduce floating exposure, reduce leverage, improve EBITDA conversion.

Sheet 90_CHECKS
B2: CHECKS: | C2: =HYPERLINK("#'90_CHECKS'!B6",'90_CHECKS'!$C$22)
B4: Checks hub (must be GREEN before sending)
B6: Check | C6: Status | D6: Value
B7: Sources = Uses tie | C7: =IFERROR(IF(ABS('05_SOURCES_AND_USES'!$D$44)<0.001,"PASS","FAIL"),"FAIL") | D7: ='05_SOURCES_AND_USES'!$D$44
B8: Cash roll-forward (no plug) | C8: =IFERROR(IF($D$8<0.001,"PASS","FAIL"),"FAIL") | D8: =MAX(ABS('07_CASH_FLOW_WATERFALL'!$E$42),ABS('07_CASH_FLOW_WATERFALL'!$F$42),ABS('07_CASH_FLOW_WATERFALL'!$G$42),ABS('07_CASH_FLOW_WATERFALL'!$H$42),ABS('07_CASH_FLOW_WATERFALL'!$I$42),ABS('07_CASH_FLOW_WATERFALL'!$J$42),ABS('07_CASH_FLOW_WATERFALL'!$K$42),ABS('07_CASH_FLOW_WATERFALL'!$L$42))
B9: Revolver >= 0 and <= limit | C9: =IFERROR(IF(AND(MIN('06_DEBT_SCHEDULES'!$E$25:$L$25)>=-0.001,MAX('06_DEBT_SCHEDULES'!$E$25:$L$25)<=Revolver_Limit+0.001),"PASS","FAIL"),"FAIL") | D9: =MAX('06_DEBT_SCHEDULES'!$E$25:$L$25)
B10: Debt balances non-negative | C10: =IFERROR(IF(AND(MIN('06_DEBT_SCHEDULES'!$E$35:$L$35)>=-0.001,MIN('06_DEBT_SCHEDULES'!$E$45:$L$45)>=-0.001,MIN('06_DEBT_SCHEDULES'!$E$55:$L$55)>=-0.001,MIN('06_DEBT_SCHEDULES'!$E$65:$L$65)>=-0.001),"PASS","FAIL"),"FAIL") | D10: =MIN('06_DEBT_SCHEDULES'!$E$67:$L$67)
B11: Exit equity split ties | C11: =IFERROR(IF(ABS($D$11)<0.001,"PASS","FAIL"),"FAIL") | D11: ='08_EXIT_AND_EQUITY_BRIDGE'!$D$27-('08_EXIT_AND_EQUITY_BRIDGE'!$D$35+'08_EXIT_AND_EQUITY_BRIDGE'!$D$36)
B12: No negative cash | C12: =IFERROR(IF(MIN('07_CASH_FLOW_WATERFALL'!$E$41:$L$41)>=-0.001,"PASS","FAIL"),"FAIL") | D12: =MIN('07_CASH_FLOW_WATERFALL'!$E$41:$L$41)
B13: Dashboard tiles linked | C13: =IFERROR(IF(AND(ISNUMBER('00_DASHBOARD'!$C$11),ISNUMBER('00_DASHBOARD'!$F$12),ISNUMBER('00_DASHBOARD'!$F$13)),"PASS","FAIL"),"FAIL") | D13: ='00_DASHBOARD'!$D$16
B20: Overall
B22: Overall status | C22: =IF(COUNTIF($C$7:$C$13,"FAIL")=0,"PASS","FAIL")

Sheet 99_APPENDIX_DATA
B1: LBO Model Builder (Training Simulation)
B2: CHANGE LOG | C2: =HYPERLINK("#'90_CHECKS'!B6",'90_CHECKS'!$C$22)
B3: Date | C3: Author | D3: Change
B4: 2026-02-16 | C4: Model update | D4: Added learning layer tabs 80-86 (map, formulas, interpretation, scenarios, drills, mistakes, special module).
B5: 2026-02-16 | C5: Model fix | D5: Added missing Sources-Uses tie line in 05_SOURCES_AND_USES!D44 to support 90_CHECKS Sources=Uses check (no output impact).
B6: 2026-02-16 | C6: Control add | D6: Added TRAINING_MODE toggle (01_CONTROL!G12) default OFF (no output impact).
