Workbook

Sheet 00_DASHBOARD
B1: Dashboard | C1: Control | D1: Issuer | E1: Offer | F1: Checks
B2: ECM Transaction Dashboard | H2: CHECKS: | I2: ='90_CHECKS'!$E$4 | J2: Failed: | K2: ='90_CHECKS'!$E$5
B6: KEY OUTPUTS (DIRECT LINKS ONLY) | L6: Learn cue | M6: Go to learn
E7: LOW | F7: BASE | G7: HIGH
B8: Offer type | E8: ='01_CONTROL'!$E$8 | F8: ='01_CONTROL'!$E$8 | G8: ='01_CONTROL'!$E$8 | L8: Selected method drives speed/fairness/certainty. | M8: Learn
L9: Anchor for discount, TERP, and optics. Check basis/date. | M9: Learn
B10: Issue price | C10: DKK/sh | E10: ='04_OFFER_SETUP'!E8 | F10: ='04_OFFER_SETUP'!F8 | G10: ='04_OFFER_SETUP'!G8 | L10: Offer price: lower Ps improves take-up but worsens dilution. | M10: Learn
L11: Discount is meaningless without basis (P0 definition). | M11: Learn
B12: Discount | C12: % | E12: ='04_OFFER_SETUP'!E9 | F12: ='04_OFFER_SETUP'!F9 | G12: ='04_OFFER_SETUP'!G9
B14: New shares issued | C14: m sh | E14: ='06_CAP_TABLE_OWNERSHIP'!E12 | F14: ='06_CAP_TABLE_OWNERSHIP'!F12 | G14: ='06_CAP_TABLE_OWNERSHIP'!G12
B16: Gross proceeds (total) | C16: DKKm | E16: ='07_PROCEEDS_AND_FEES'!E10 | F16: ='07_PROCEEDS_AND_FEES'!F10 | G16: ='07_PROCEEDS_AND_FEES'!G10 | L16: Headline size. Separate primary vs secondary in proceeds. | M16: Learn
L17: Fees should reduce net proceeds (watch sign conventions). | M17: Learn
B18: Net proceeds (issuer) | C18: DKKm | E18: ='07_PROCEEDS_AND_FEES'!E16 | F18: ='07_PROCEEDS_AND_FEES'!F16 | G18: ='07_PROCEEDS_AND_FEES'!G16 | L18: This is what the issuer actually gets (cash bridge input). | M18: Learn
L19: Share-count driver. Links to dilution and float mechanics. | M19: Learn
B20: Dilution | C20: % | E20: ='06_CAP_TABLE_OWNERSHIP'!E14 | F20: ='06_CAP_TABLE_OWNERSHIP'!F14 | G20: ='06_CAP_TABLE_OWNERSHIP'!G14 | L20: Mechanical dilution. Always show who is diluted. | M20: Learn
B22: Free float % post (base) | C22: % | E22: ='06_CAP_TABLE_OWNERSHIP'!$E$34 | F22: ='06_CAP_TABLE_OWNERSHIP'!$F$34 | G22: ='06_CAP_TABLE_OWNERSHIP'!$G$34 | L22: Float matters for liquidity/index. Confirm holder tagging. | M22: Learn
B24: Net debt post (base) | C24: DKKm | E24: ='08_PRO_FORMA_BS_LEVERAGE'!$E$27 | F24: ='08_PRO_FORMA_BS_LEVERAGE'!$F$27 | G24: ='08_PRO_FORMA_BS_LEVERAGE'!$G$27
L25: Net debt depends on proceeds split and definition. | M25: Learn
B26: ND/EBITDA post (base) | C26: x | E26: ='08_PRO_FORMA_BS_LEVERAGE'!$E$34 | F26: ='08_PRO_FORMA_BS_LEVERAGE'!$F$34 | G26: ='08_PRO_FORMA_BS_LEVERAGE'!$G$34 | L26: Leverage story: check EBITDA basis and currency. | M26: Learn
B30: CHECKS STATUS | L30: Hard gate: do not present outputs unless 90_CHECKS = PASS. | M30: Learn
B31: Overall | E31: ='90_CHECKS'!$E$4
B32: Failed checks | C32: # | E32: ='90_CHECKS'!$E$5
B35: CHARTS (BASE)
B36: Metric | C36: Value
B37: Free float % pre | C37: ='06_CAP_TABLE_OWNERSHIP'!$E$33
B38: Free float % post | C38: ='06_CAP_TABLE_OWNERSHIP'!$E$34
B40: Waterfall | C40: DKKm
B41: Primary Gross | C41: ='07_PROCEEDS_AND_FEES'!$F$8
B42: Fees | C42: =-'07_PROCEEDS_AND_FEES'!$F$15
B43: Net to issuer | C43: ='07_PROCEEDS_AND_FEES'!$F$16

Sheet 01_CONTROL
B1: Dashboard | C1: Control | D1: Issuer | E1: Offer | F1: Checks
B2: ECM Model Control Panel | H2: CHECKS: | I2: ='90_CHECKS'!$E$4 | J2: Failed: | K2: ='90_CHECKS'!$E$5
B6: MASTER TOGGLES (SINGLE SOURCE OF TRUTH)
B8: Offer type | E8: RIGHTS ISSUE
B10: Reference price type | E10: LAST CLOSE
B11: Price input mode | E11: DISCOUNT
B13: Raise mode | E13: TARGET_GROSS
B14: Primary vs secondary | E14: PRIMARY_ONLY
B16: Underwriting (RI) | E16: FULLY_UNDERWRITTEN
B18: Take up scenario (RI) | E18: 80% | H18: Map
D19: Take up rate (numeric) | E19: =INDEX($I$19:$I$21,MATCH(E18,$H$19:$H$21,0)) | H19: 60% | I19: 0.6
B20: Rump extra discount (RI) | C20: % | E20: 0 | H20: 80% | I20: 0.8
B21: Backstop enabled (RI) | E21: NO | H21: 100% | I21: 1
B22: Backstop fee % (RI) | C22: % | E22: 0
B26: SCENARIO INPUTS (LOW / BASE / HIGH)
E27: LOW | F27: BASE | G27: HIGH
B28: Discount % | C28: % | E28: 0.1 | F28: 0.08 | G28: 0.05
B29: Direct issue price | C29: DKK/sh | E29: 0 | F29: 0 | G29: 0
B30: Target gross (primary) | C30: DKKm | E30: 500 | F30: 700 | G30: 900
B31: Target net (primary) | C31: DKKm | E31: 0 | F31: 0 | G31: 0
B32: Shares issued (primary) | C32: m sh | E32: 0 | F32: 0 | G32: 0
B33: Secondary shares sold | C33: m sh | E33: 0 | F33: 0 | G33: 0
B37: FEES (APPLY TO PRIMARY GROSS)
B38: Underwriting fee % | C38: % | E38: 0.03
B39: Advisory fee % | C39: % | E39: 0.01
B40: Other costs (fixed) | C40: DKKm | E40: 5
B44: USE OF PROCEEDS (MUST SUM TO 100%)
B45: Debt paydown % | C45: % | E45: 0.6
B46: Cash retained % | C46: % | E46: 0.3
B47: Growth investment % | C47: % | E47: 0.1
B48: Sum | C48: % | E48: =E45+E46+E47 | F48: =IF(ABS(E48-1)<0.0001,"OK","FIX")

Sheet 02_ISSUER_INPUTS
B1: Dashboard | C1: Control | D1: Issuer | E1: Offer | F1: Checks
B2: Issuer Inputs | H2: CHECKS: | I2: ='90_CHECKS'!$E$4 | J2: Failed: | K2: ='90_CHECKS'!$E$5
B6: SHARE STRUCTURE
B7: Current shares outstanding | C7: m sh | E7: 100
B8: Dilutive instruments (optional) | C8: m sh | E8: 0
B9: Fully diluted shares (optional) | C9: m sh | E9: =E7+E8
B13: SHAREHOLDER TABLE (INPUTS)
B14: Holder | C14: Bucket | D14: Pre % | E14: Participation adj (RI) | F14: Allocation % (PP/ABB) | G14: Pre shares (m)
B15: Holder 1 | C15: MAJOR | D15: 0.2 | E15: 1 | F15: 0.2 | G15: =$E$7*D15
B16: Holder 2 | C16: MAJOR | D16: 0.15 | E16: 1 | F16: 0.15 | G16: =$E$7*D16
B17: Holder 3 | C17: MAJOR | D17: 0.1 | E17: 0.8 | F17: 0.1 | G17: =$E$7*D17
B18: Holder 4 | C18: MAJOR | D18: 0.05 | E18: 0.5 | F18: 0.05 | G18: =$E$7*D18
B19: Holder 5 | C19: MAJOR | D19: 0.03 | E19: 0 | F19: 0.03 | G19: =$E$7*D19
B20: Free float | C20: FREE_FLOAT | D20: 0.47 | E20: 0.6 | F20: 0.47 | G20: =$E$7*D20
B21: New investors (post) | C21: NEW | D21: 0 | E21: 0 | F21: 0 | G21: =$E$7*D21
B22: Other (balancing) | C22: OTHER | D22: 0 | E22: 0 | F22: 0 | G22: =$E$7*D22
B23: TOTAL | D23: =SUM(D15:D22) | G23: =SUM(G15:G22)
B26: BALANCE SHEET SNAPSHOT
B27: Cash | C27: DKKm | E27: 200
B28: Gross debt | C28: DKKm | E28: 600
B29: Net debt | C29: DKKm | E29: =E28-E27
B32: LEVERAGE INPUT
B33: EBITDA | C33: DKKm | E33: 250
B34: Net debt / EBITDA | C34: x | E34: =IFERROR(E29/E33,0)

Sheet 03_MARKET_DATA
B1: Dashboard | C1: Control | D1: Issuer | E1: Offer | F1: Checks
B2: Market Data | H2: CHECKS: | I2: ='90_CHECKS'!$E$4 | J2: Failed: | K2: ='90_CHECKS'!$E$5
B6: REFERENCE PRICE
B7: Reference price (P0) | C7: DKK/sh | E7: 100
B8: Reference price type | E8: ='01_CONTROL'!$E$10
B10: Market cap pre | C10: DKKm | E10: ='02_ISSUER_INPUTS'!$E$7*E7
B14: OPTIONAL TRADING METRICS
B15: Volatility proxy (optional) | C15: % | E15: 0.3

Sheet 04_OFFER_SETUP
B1: Dashboard | C1: Control | D1: Issuer | E1: Offer | F1: Checks
B2: Offer Setup | H2: CHECKS: | I2: ='90_CHECKS'!$E$4 | J2: Failed: | K2: ='90_CHECKS'!$E$5
B6: CORE INPUTS AND PRICING
E7: LOW | F7: BASE | G7: HIGH
B8: Issue price (Ps) | C8: DKK/sh | E8: =IF('01_CONTROL'!$E$11="DISCOUNT",'03_MARKET_DATA'!$E$7*(1-'01_CONTROL'!E$28),'01_CONTROL'!E$29) | F8: =IF('01_CONTROL'!$E$11="DISCOUNT",'03_MARKET_DATA'!$E$7*(1-'01_CONTROL'!F$28),'01_CONTROL'!F$29) | G8: =IF('01_CONTROL'!$E$11="DISCOUNT",'03_MARKET_DATA'!$E$7*(1-'01_CONTROL'!G$28),'01_CONTROL'!G$29)
B9: Discount | C9: % | E9: =IFERROR(1-E$8/'03_MARKET_DATA'!$E$7,0) | F9: =IFERROR(1-F$8/'03_MARKET_DATA'!$E$7,0) | G9: =IFERROR(1-G$8/'03_MARKET_DATA'!$E$7,0)
B13: OFFER SIZING (PRIMARY AND SECONDARY)
B14: Raise mode | E14: ='01_CONTROL'!$E$13
B15: Primary new shares | C15: m sh | E15: =IF('01_CONTROL'!$E$13="TARGET_GROSS",'01_CONTROL'!E$30/E$8,IF('01_CONTROL'!$E$13="TARGET_NET",('01_CONTROL'!E$31 + '01_CONTROL'!$E$40)/(1-('01_CONTROL'!$E$38+'01_CONTROL'!$E$39))/E$8,'01_CONTROL'!E$32)) | F15: =IF('01_CONTROL'!$E$13="TARGET_GROSS",'01_CONTROL'!F$30/F$8,IF('01_CONTROL'!$E$13="TARGET_NET",('01_CONTROL'!F$31 + '01_CONTROL'!$E$40)/(1-('01_CONTROL'!$E$38+'01_CONTROL'!$E$39))/F$8,'01_CONTROL'!F$32)) | G15: =IF('01_CONTROL'!$E$13="TARGET_GROSS",'01_CONTROL'!G$30/G$8,IF('01_CONTROL'!$E$13="TARGET_NET",('01_CONTROL'!G$31 + '01_CONTROL'!$E$40)/(1-('01_CONTROL'!$E$38+'01_CONTROL'!$E$39))/G$8,'01_CONTROL'!G$32))
B16: Secondary shares sold | C16: m sh | E16: ='01_CONTROL'!E$33 | F16: ='01_CONTROL'!F$33 | G16: ='01_CONTROL'!G$33
B17: Total shares sold | C17: m sh | E17: =E$15+E$16 | F17: =F$15+F$16 | G17: =G$15+G$16
B19: Gross proceeds (primary) | C19: DKKm | E19: =E$15*E$8 | F19: =F$15*F$8 | G19: =G$15*G$8
B20: Gross proceeds (secondary) | C20: DKKm | E20: =E$16*E$8 | F20: =F$16*F$8 | G20: =G$16*G$8
B21: Gross proceeds (total) | C21: DKKm | E21: =E$19+E$20 | F21: =F$19+F$20 | G21: =G$19+G$20

Sheet 05_RIGHTS_TERP_ENTITLE
B1: Dashboard | C1: Control | D1: Issuer | E1: Offer | F1: Checks
B2: Rights Issue: TERP and Entitlement | H2: CHECKS: | I2: ='90_CHECKS'!$E$4 | J2: Failed: | K2: ='90_CHECKS'!$E$5
B6: TERP MECHANICS
E7: LOW | F7: BASE | G7: HIGH
B8: Pre shares (N) | C8: m sh | E8: ='02_ISSUER_INPUTS'!$E$7 | F8: ='02_ISSUER_INPUTS'!$E$7 | G8: ='02_ISSUER_INPUTS'!$E$7
B9: New shares marketed (M) | C9: m sh | E9: ='04_OFFER_SETUP'!E$15 | F9: ='04_OFFER_SETUP'!F$15 | G9: ='04_OFFER_SETUP'!G$15
B10: Reference price (P0) | C10: DKK/sh | E10: ='03_MARKET_DATA'!$E$7 | F10: ='03_MARKET_DATA'!$E$7 | G10: ='03_MARKET_DATA'!$E$7
B11: Issue price (Ps) | C11: DKK/sh | E11: ='04_OFFER_SETUP'!E$8 | F11: ='04_OFFER_SETUP'!F$8 | G11: ='04_OFFER_SETUP'!G$8
B12: TERP | C12: DKK/sh | E12: =IFERROR((E$8*E$10+E$9*E$11)/(E$8+E$9),0) | F12: =IFERROR((F$8*F$10+F$9*F$11)/(F$8+F$9),0) | G12: =IFERROR((G$8*G$10+G$9*G$11)/(G$8+G$9),0)
B13: Value of right (P0 - TERP) | C13: DKK/sh | E13: =E$10-E$12 | F13: =F$10-F$12 | G13: =G$10-G$12
B17: TAKE UP AND RUMP
B18: Underwriting | E18: ='01_CONTROL'!$E$16
B19: Take up rate | C19: % | E19: ='01_CONTROL'!$E$19
B21: Subscribed shares (M * take up) | C21: m sh | E21: =E$9*$E$19 | F21: =F$9*$E$19 | G21: =G$9*$E$19
B22: Rump shares | C22: m sh | E22: =E$9-E$21 | F22: =F$9-F$21 | G22: =G$9-G$21
B23: Issued shares | C23: m sh | E23: =IF($E$18="BEST_EFFORTS",E$21,E$9) | F23: =IF($E$18="BEST_EFFORTS",F$21,F$9) | G23: =IF($E$18="BEST_EFFORTS",G$21,G$9)

Sheet 06_CAP_TABLE_OWNERSHIP
B1: Dashboard | C1: Control | D1: Issuer | E1: Offer | F1: Checks
B2: Cap Table and Ownership | H2: CHECKS: | I2: ='90_CHECKS'!$E$4 | J2: Failed: | K2: ='90_CHECKS'!$E$5
B6: SHARE COUNT BRIDGE
E7: LOW | F7: BASE | G7: HIGH
B8: Offer type | E8: ='01_CONTROL'!$E$8 | F8: =E8 | G8: =E8
B9: Pre shares | C9: m sh | E9: ='02_ISSUER_INPUTS'!$E$7 | F9: ='02_ISSUER_INPUTS'!$E$7 | G9: ='02_ISSUER_INPUTS'!$E$7
B10: New shares marketed (primary) | C10: m sh | E10: ='04_OFFER_SETUP'!E$15 | F10: ='04_OFFER_SETUP'!F$15 | G10: ='04_OFFER_SETUP'!G$15
B11: Take up rate (RI) | C11: % | E11: ='01_CONTROL'!$E$19 | F11: =E11 | G11: =E11
B12: New shares issued | C12: m sh | E12: =IF($E$8="RIGHTS ISSUE",IF('01_CONTROL'!$E$16="BEST_EFFORTS",E$10*$E$11,E$10),E$10) | F12: =IF($E$8="RIGHTS ISSUE",IF('01_CONTROL'!$E$16="BEST_EFFORTS",F$10*$E$11,F$10),F$10) | G12: =IF($E$8="RIGHTS ISSUE",IF('01_CONTROL'!$E$16="BEST_EFFORTS",G$10*$E$11,G$10),G$10)
B13: Post shares | C13: m sh | E13: =E$9+E$12 | F13: =F$9+F$12 | G13: =G$9+G$12
B14: Dilution to non participating | C14: % | E14: =IFERROR(1-(E$9/E$13),0) | F14: =IFERROR(1-(F$9/F$13),0) | G14: =IFERROR(1-(G$9/G$13),0)
B18: OWNERSHIP TABLE (BASE)
B19: Holder | C19: Bucket | D19: Pre % | E19: Pre shares (m) | F19: New shares (m) | G19: Post shares (m) | H19: Post % | I19: Delta %
B20: ='02_ISSUER_INPUTS'!B15 | C20: ='02_ISSUER_INPUTS'!C15 | D20: ='02_ISSUER_INPUTS'!D15 | E20: ='02_ISSUER_INPUTS'!G15 | F20: =IF($E$8="RIGHTS ISSUE",IF($B20="New investors (post)",0,IFERROR($E20*($F$10/$F$9)*$E$11*'02_ISSUER_INPUTS'!E15,0)),IFERROR($F$12*'02_ISSUER_INPUTS'!F15,0)) | G20: =$E20+F20 | H20: =IFERROR(G20/$F$13,0) | I20: =H20-D20
B21: ='02_ISSUER_INPUTS'!B16 | C21: ='02_ISSUER_INPUTS'!C16 | D21: ='02_ISSUER_INPUTS'!D16 | E21: ='02_ISSUER_INPUTS'!G16 | F21: =IF($E$8="RIGHTS ISSUE",IF($B21="New investors (post)",0,IFERROR($E21*($F$10/$F$9)*$E$11*'02_ISSUER_INPUTS'!E16,0)),IFERROR($F$12*'02_ISSUER_INPUTS'!F16,0)) | G21: =$E21+F21 | H21: =IFERROR(G21/$F$13,0) | I21: =H21-D21
B22: ='02_ISSUER_INPUTS'!B17 | C22: ='02_ISSUER_INPUTS'!C17 | D22: ='02_ISSUER_INPUTS'!D17 | E22: ='02_ISSUER_INPUTS'!G17 | F22: =IF($E$8="RIGHTS ISSUE",IF($B22="New investors (post)",0,IFERROR($E22*($F$10/$F$9)*$E$11*'02_ISSUER_INPUTS'!E17,0)),IFERROR($F$12*'02_ISSUER_INPUTS'!F17,0)) | G22: =$E22+F22 | H22: =IFERROR(G22/$F$13,0) | I22: =H22-D22
B23: ='02_ISSUER_INPUTS'!B18 | C23: ='02_ISSUER_INPUTS'!C18 | D23: ='02_ISSUER_INPUTS'!D18 | E23: ='02_ISSUER_INPUTS'!G18 | F23: =IF($E$8="RIGHTS ISSUE",IF($B23="New investors (post)",0,IFERROR($E23*($F$10/$F$9)*$E$11*'02_ISSUER_INPUTS'!E18,0)),IFERROR($F$12*'02_ISSUER_INPUTS'!F18,0)) | G23: =$E23+F23 | H23: =IFERROR(G23/$F$13,0) | I23: =H23-D23
B24: ='02_ISSUER_INPUTS'!B19 | C24: ='02_ISSUER_INPUTS'!C19 | D24: ='02_ISSUER_INPUTS'!D19 | E24: ='02_ISSUER_INPUTS'!G19 | F24: =IF($E$8="RIGHTS ISSUE",IF($B24="New investors (post)",0,IFERROR($E24*($F$10/$F$9)*$E$11*'02_ISSUER_INPUTS'!E19,0)),IFERROR($F$12*'02_ISSUER_INPUTS'!F19,0)) | G24: =$E24+F24 | H24: =IFERROR(G24/$F$13,0) | I24: =H24-D24
B25: ='02_ISSUER_INPUTS'!B20 | C25: ='02_ISSUER_INPUTS'!C20 | D25: ='02_ISSUER_INPUTS'!D20 | E25: ='02_ISSUER_INPUTS'!G20 | F25: =IF($E$8="RIGHTS ISSUE",IF($B25="New investors (post)",0,IFERROR($E25*($F$10/$F$9)*$E$11*'02_ISSUER_INPUTS'!E20,0)),IFERROR($F$12*'02_ISSUER_INPUTS'!F20,0)) | G25: =$E25+F25 | H25: =IFERROR(G25/$F$13,0) | I25: =H25-D25
B26: ='02_ISSUER_INPUTS'!B21 | C26: ='02_ISSUER_INPUTS'!C21 | D26: ='02_ISSUER_INPUTS'!D21 | E26: ='02_ISSUER_INPUTS'!G21 | F26: =IF($E$8="RIGHTS ISSUE",IF('01_CONTROL'!$E$16="FULLY_UNDERWRITTEN",$E$28,0),MAX(0,$F$12-SUM(F20:F25))) | G26: =$E26+F26 | H26: =IFERROR(G26/$F$13,0) | I26: =H26-D26
B27: ='02_ISSUER_INPUTS'!B22 | C27: ='02_ISSUER_INPUTS'!C22 | D27: ='02_ISSUER_INPUTS'!D22 | E27: ='02_ISSUER_INPUTS'!G22 | F27: =IF($E$8="RIGHTS ISSUE",IF($B27="New investors (post)",0,IFERROR($E27*($F$10/$F$9)*$E$11*'02_ISSUER_INPUTS'!E22,0)),IFERROR($F$12*'02_ISSUER_INPUTS'!F22,0)) | G27: =$E27+F27 | H27: =IFERROR(G27/$F$13,0) | I27: =H27-D27
B28: Residual new shares (base) | C28: m sh | E28: =MAX(0,$F$12-SUM(F20:F25))
B29: TOTAL | D29: =SUM(D20:D27) | E29: =SUM(E20:E27) | F29: =SUM(F20:F27) | G29: =SUM(G20:G27) | H29: =SUM(H20:H27)
B32: FREE FLOAT (BASE)
B33: Free float % pre | C33: % | E33: =SUMIF('02_ISSUER_INPUTS'!$C$15:$C$22,"FREE_FLOAT",'02_ISSUER_INPUTS'!$D$15:$D$22) | F33: =E33 | G33: =E33
B34: Free float % post | C34: % | E34: =IFERROR((('02_ISSUER_INPUTS'!$E$7*SUMPRODUCT(('02_ISSUER_INPUTS'!$C$15:$C$22="FREE_FLOAT")*('02_ISSUER_INPUTS'!$D$15:$D$22)))+IF('01_CONTROL'!$E$8="RIGHTS ISSUE",(E$10*$E$11)*SUMPRODUCT(('02_ISSUER_INPUTS'!$C$15:$C$22="FREE_FLOAT")*('02_ISSUER_INPUTS'!$C$15:$C$22<>"NEW")*('02_ISSUER_INPUTS'!$D$15:$D$22)*('02_ISSUER_INPUTS'!$E$15:$E$22))/SUMPRODUCT(('02_ISSUER_INPUTS'!$C$15:$C$22<>"NEW")*('02_ISSUER_INPUTS'!$D$15:$D$22)*('02_ISSUER_INPUTS'!$E$15:$E$22)),(E$12)*SUMPRODUCT(('02_ISSUER_INPUTS'!$C$15:$C$22="FREE_FLOAT")*('02_ISSUER_INPUTS'!$F$15:$F$22))))/('02_ISSUER_INPUTS'!$E$7+(E$12)),0) | F34: =IFERROR((('02_ISSUER_INPUTS'!$E$7*SUMPRODUCT(('02_ISSUER_INPUTS'!$C$15:$C$22="FREE_FLOAT")*('02_ISSUER_INPUTS'!$D$15:$D$22)))+IF('01_CONTROL'!$E$8="RIGHTS ISSUE",(F$10*$E$11)*SUMPRODUCT(('02_ISSUER_INPUTS'!$C$15:$C$22="FREE_FLOAT")*('02_ISSUER_INPUTS'!$C$15:$C$22<>"NEW")*('02_ISSUER_INPUTS'!$D$15:$D$22)*('02_ISSUER_INPUTS'!$E$15:$E$22))/SUMPRODUCT(('02_ISSUER_INPUTS'!$C$15:$C$22<>"NEW")*('02_ISSUER_INPUTS'!$D$15:$D$22)*('02_ISSUER_INPUTS'!$E$15:$E$22)),(F$12)*SUMPRODUCT(('02_ISSUER_INPUTS'!$C$15:$C$22="FREE_FLOAT")*('02_ISSUER_INPUTS'!$F$15:$F$22))))/('02_ISSUER_INPUTS'!$E$7+(F$12)),0) | G34: =IFERROR((('02_ISSUER_INPUTS'!$E$7*SUMPRODUCT(('02_ISSUER_INPUTS'!$C$15:$C$22="FREE_FLOAT")*('02_ISSUER_INPUTS'!$D$15:$D$22)))+IF('01_CONTROL'!$E$8="RIGHTS ISSUE",(G$10*$E$11)*SUMPRODUCT(('02_ISSUER_INPUTS'!$C$15:$C$22="FREE_FLOAT")*('02_ISSUER_INPUTS'!$C$15:$C$22<>"NEW")*('02_ISSUER_INPUTS'!$D$15:$D$22)*('02_ISSUER_INPUTS'!$E$15:$E$22))/SUMPRODUCT(('02_ISSUER_INPUTS'!$C$15:$C$22<>"NEW")*('02_ISSUER_INPUTS'!$D$15:$D$22)*('02_ISSUER_INPUTS'!$E$15:$E$22)),(G$12)*SUMPRODUCT(('02_ISSUER_INPUTS'!$C$15:$C$22="FREE_FLOAT")*('02_ISSUER_INPUTS'!$F$15:$F$22))))/('02_ISSUER_INPUTS'!$E$7+(G$12)),0)

Sheet 07_PROCEEDS_AND_FEES
B1: Dashboard | C1: Control | D1: Issuer | E1: Offer | F1: Checks
B2: Proceeds and Fees | H2: CHECKS: | I2: ='90_CHECKS'!$E$4 | J2: Failed: | K2: ='90_CHECKS'!$E$5
B6: PROCEEDS WATERFALL (ISSUER)
E7: LOW | F7: BASE | G7: HIGH
B8: Gross proceeds (primary) | C8: DKKm | E8: ='04_OFFER_SETUP'!E$19 | F8: ='04_OFFER_SETUP'!F$19 | G8: ='04_OFFER_SETUP'!G$19
B9: Gross proceeds (secondary) | C9: DKKm | E9: ='04_OFFER_SETUP'!E$20 | F9: ='04_OFFER_SETUP'!F$20 | G9: ='04_OFFER_SETUP'!G$20
B10: Gross proceeds (total) | C10: DKKm | E10: ='04_OFFER_SETUP'!E$21 | F10: ='04_OFFER_SETUP'!F$21 | G10: ='04_OFFER_SETUP'!G$21
B12: Underwriting fee (on primary) | C12: DKKm | E12: =E$8*'01_CONTROL'!$E$38 | F12: =F$8*'01_CONTROL'!$E$38 | G12: =G$8*'01_CONTROL'!$E$38
B13: Advisory fee (on primary) | C13: DKKm | E13: =E$8*'01_CONTROL'!$E$39 | F13: =F$8*'01_CONTROL'!$E$39 | G13: =G$8*'01_CONTROL'!$E$39
B14: Other costs (fixed) | C14: DKKm | E14: ='01_CONTROL'!$E$40 | F14: ='01_CONTROL'!$E$40 | G14: ='01_CONTROL'!$E$40
B15: Total fees | C15: DKKm | E15: =E$12+E$13+E$14 | F15: =F$12+F$13+F$14 | G15: =G$12+G$13+G$14
B16: Net proceeds to issuer | C16: DKKm | E16: =E$8-E$15 | F16: =F$8-F$15 | G16: =G$8-G$15
B17: Proceeds to selling SHs | C17: DKKm | E17: =E$9 | F17: =F$9 | G17: =G$9

Sheet 08_PRO_FORMA_BS_LEVERAGE
B1: Dashboard | C1: Control | D1: Issuer | E1: Offer | F1: Checks
B2: Pro Forma Balance Sheet and Leverage | H2: CHECKS: | I2: ='90_CHECKS'!$E$4 | J2: Failed: | K2: ='90_CHECKS'!$E$5
B6: USE OF PROCEEDS
E7: LOW | F7: BASE | G7: HIGH
B8: Net proceeds to issuer | C8: DKKm | E8: ='07_PROCEEDS_AND_FEES'!E$16 | F8: ='07_PROCEEDS_AND_FEES'!F$16 | G8: ='07_PROCEEDS_AND_FEES'!G$16
B10: Debt paydown % | C10: % | E10: ='01_CONTROL'!$E$45
B11: Cash retained % | C11: % | E11: ='01_CONTROL'!$E$46
B12: Growth investment % | C12: % | E12: ='01_CONTROL'!$E$47
B14: Debt paydown | C14: DKKm | E14: =E$8*$E$10 | F14: =F$8*$E$10 | G14: =G$8*$E$10
B15: Cash retained | C15: DKKm | E15: =E$8*$E$11 | F15: =F$8*$E$11 | G15: =G$8*$E$11
B16: Growth investment | C16: DKKm | E16: =E$8*$E$12 | F16: =F$8*$E$12 | G16: =G$8*$E$12
B20: PRO FORMA BALANCE SHEET (DKKm)
B21: Cash (pre) | C21: DKKm | E21: ='02_ISSUER_INPUTS'!$E$27 | F21: ='02_ISSUER_INPUTS'!$E$27 | G21: ='02_ISSUER_INPUTS'!$E$27
B22: Gross debt (pre) | C22: DKKm | E22: ='02_ISSUER_INPUTS'!$E$28 | F22: ='02_ISSUER_INPUTS'!$E$28 | G22: ='02_ISSUER_INPUTS'!$E$28
B23: Net debt (pre) | C23: DKKm | E23: ='02_ISSUER_INPUTS'!$E$29 | F23: ='02_ISSUER_INPUTS'!$E$29 | G23: ='02_ISSUER_INPUTS'!$E$29
B25: Cash (post) | C25: DKKm | E25: =E$21+E$15-E$16 | F25: =F$21+F$15-F$16 | G25: =G$21+G$15-G$16
B26: Gross debt (post) | C26: DKKm | E26: =E$22-E$14 | F26: =F$22-F$14 | G26: =G$22-G$14
B27: Net debt (post) | C27: DKKm | E27: =E$26-E$25 | F27: =F$26-F$25 | G27: =G$26-G$25
B31: LEVERAGE
B32: EBITDA | C32: DKKm | E32: ='02_ISSUER_INPUTS'!$E$33 | F32: ='02_ISSUER_INPUTS'!$E$33 | G32: ='02_ISSUER_INPUTS'!$E$33
B33: ND/EBITDA (pre) | C33: x | E33: =IFERROR(E$23/E$32,0) | F33: =IFERROR(F$23/F$32,0) | G33: =IFERROR(G$23/G$32,0)
B34: ND/EBITDA (post) | C34: x | E34: =IFERROR(E$27/E$32,0) | F34: =IFERROR(F$27/F$32,0) | G34: =IFERROR(G$27/G$32,0)

Sheet 09_FREE_FLOAT_TRADING_MET
B1: Dashboard | C1: Control | D1: Issuer | E1: Offer | F1: Checks
B2: Free Float and Trading Metrics | H2: CHECKS: | I2: ='90_CHECKS'!$E$4 | J2: Failed: | K2: ='90_CHECKS'!$E$5
B6: MARKET CAP
E7: LOW | F7: BASE | G7: HIGH
B8: Market cap pre (at ref) | C8: DKKm | E8: ='02_ISSUER_INPUTS'!$E$7*'03_MARKET_DATA'!$E$7 | F8: ='02_ISSUER_INPUTS'!$E$7*'03_MARKET_DATA'!$E$7 | G8: ='02_ISSUER_INPUTS'!$E$7*'03_MARKET_DATA'!$E$7
B9: Market cap post (at issue price) | C9: DKKm | E9: ='06_CAP_TABLE_OWNERSHIP'!E$13*'04_OFFER_SETUP'!E$8 | F9: ='06_CAP_TABLE_OWNERSHIP'!F$13*'04_OFFER_SETUP'!F$8 | G9: ='06_CAP_TABLE_OWNERSHIP'!G$13*'04_OFFER_SETUP'!G$8
B10: Free float % pre (base) | C10: % | E10: ='06_CAP_TABLE_OWNERSHIP'!$E$33
B11: Free float % post (base) | C11: % | E11: ='06_CAP_TABLE_OWNERSHIP'!$E$34
B13: Free float shares pre (base) | C13: m sh | E13: ='02_ISSUER_INPUTS'!$E$7*$E$10
B14: Free float shares post (base) | C14: m sh | E14: ='06_CAP_TABLE_OWNERSHIP'!$F$13*$E$11
B18: LEVERAGE SUMMARY (BASE)
B19: Net debt post (base) | C19: DKKm | E19: ='08_PRO_FORMA_BS_LEVERAGE'!$F$27
B20: ND/EBITDA post (base) | C20: x | E20: ='08_PRO_FORMA_BS_LEVERAGE'!$F$34

Sheet 10_SENSITIVITIES
B1: Dashboard | C1: Control | D1: Issuer | E1: Offer | F1: Checks
B2: Sensitivities | H2: CHECKS: | I2: ='90_CHECKS'!$E$4 | J2: Failed: | K2: ='90_CHECKS'!$E$5
B6: DISCOUNT SENSITIVITY (ASSUMES TARGET GROSS BASE)
B7: Discount | C7: Issue price | D7: New shares (m) | E7: Net proceeds (DKKm) | F7: Dilution %
B8: 0 | C8: ='03_MARKET_DATA'!$E$7*(1-$B8) | D8: =IFERROR('01_CONTROL'!$F$30/$C8,0) | E8: ='01_CONTROL'!$F$30 - ('01_CONTROL'!$F$30*('01_CONTROL'!$E$38+'01_CONTROL'!$E$39) + '01_CONTROL'!$E$40) | F8: =IFERROR(1-('02_ISSUER_INPUTS'!$E$7/('02_ISSUER_INPUTS'!$E$7+$D8)),0)
B9: 0.05 | C9: ='03_MARKET_DATA'!$E$7*(1-$B9) | D9: =IFERROR('01_CONTROL'!$F$30/$C9,0) | E9: ='01_CONTROL'!$F$30 - ('01_CONTROL'!$F$30*('01_CONTROL'!$E$38+'01_CONTROL'!$E$39) + '01_CONTROL'!$E$40) | F9: =IFERROR(1-('02_ISSUER_INPUTS'!$E$7/('02_ISSUER_INPUTS'!$E$7+$D9)),0)
B10: 0.08 | C10: ='03_MARKET_DATA'!$E$7*(1-$B10) | D10: =IFERROR('01_CONTROL'!$F$30/$C10,0) | E10: ='01_CONTROL'!$F$30 - ('01_CONTROL'!$F$30*('01_CONTROL'!$E$38+'01_CONTROL'!$E$39) + '01_CONTROL'!$E$40) | F10: =IFERROR(1-('02_ISSUER_INPUTS'!$E$7/('02_ISSUER_INPUTS'!$E$7+$D10)),0)
B11: 0.1 | C11: ='03_MARKET_DATA'!$E$7*(1-$B11) | D11: =IFERROR('01_CONTROL'!$F$30/$C11,0) | E11: ='01_CONTROL'!$F$30 - ('01_CONTROL'!$F$30*('01_CONTROL'!$E$38+'01_CONTROL'!$E$39) + '01_CONTROL'!$E$40) | F11: =IFERROR(1-('02_ISSUER_INPUTS'!$E$7/('02_ISSUER_INPUTS'!$E$7+$D11)),0)
B12: 0.12 | C12: ='03_MARKET_DATA'!$E$7*(1-$B12) | D12: =IFERROR('01_CONTROL'!$F$30/$C12,0) | E12: ='01_CONTROL'!$F$30 - ('01_CONTROL'!$F$30*('01_CONTROL'!$E$38+'01_CONTROL'!$E$39) + '01_CONTROL'!$E$40) | F12: =IFERROR(1-('02_ISSUER_INPUTS'!$E$7/('02_ISSUER_INPUTS'!$E$7+$D12)),0)
B13: 0.15 | C13: ='03_MARKET_DATA'!$E$7*(1-$B13) | D13: =IFERROR('01_CONTROL'!$F$30/$C13,0) | E13: ='01_CONTROL'!$F$30 - ('01_CONTROL'!$F$30*('01_CONTROL'!$E$38+'01_CONTROL'!$E$39) + '01_CONTROL'!$E$40) | F13: =IFERROR(1-('02_ISSUER_INPUTS'!$E$7/('02_ISSUER_INPUTS'!$E$7+$D13)),0)
B15: Note: indicative quick table and does not re-run rights mechanics.

Sheet 80_ECM_LEARN_MAP
B1: Dashboard | C1: Control | D1: Issuer | E1: Offer | F1: Checks | G1: Learn
B2: ECM Fundraising Model - Learning Layer
B3: 80) Explainability Map (Top KPIs with drivers, intuition, pitfalls, checks, and meeting scripts)
B5: HOW TO USE THIS TAB
B6: Each KPI row links to the exact model cell. Use this to (i) understand drivers, (ii) sanity check outputs, and (iii) speak confidently in ECM discussions.
B8: TOP 30 KPIs / OUTPUTS
B9: KPI | C9: Where (tab!cell) | E9: Definition | F9: Primary drivers | G9: Directional intuition | H9: Common pitfalls | I9: Sanity checks | J9: CFO/board script
B10: 1. Offer type selected (Rights / Placement / ABB) | C10: 01_CONTROL!E8 | E10: Selected fundraising method that drives which mechanics activate. | F10: CTRL_OfferType (01_CONTROL!E8), flags (01_CONTROL!E10:E12), offer setup (04_OFFER_SETUP). | G10: Switching to Rights activates TERP + take-up; Placement/ABB keeps mechanics simple and speed-focused. | H10: Forgetting to update take-up/underwriting when switching; mixing rights-only inputs into placement. | I10: Dashboard offer type matches Control; 90_CHECKS shows no rights-only check failures when not Rights. | J10: We are modelling a {method} structure; this determines dilution mechanics, execution risk, and what we show on TERP/take-up.
B11: 2. Reference price definition | C11: 01_CONTROL!E10 | E11: What 'reference price' means for the discount calculation (Last close vs VWAP). | F11: CTRL_RefPriceType (01_CONTROL!E10), Ref price level (03_MARKET_DATA!E7). | G11: A higher reference price mechanically increases stated discount at same issue price. | H11: Using VWAP definition but inputting last close; mismatched date vs market data snapshot. | I11: Control definition matches Market Data notes; discount = 1 - Ps/P0 uses same P0. | J11: Discount defensibility depends on what we anchor P0 to; we state the definition explicitly to avoid confusion.
B12: 3. Reference price level (P0) | C12: 03_MARKET_DATA!E7 | E12: The share price level used as P0 in discount and rights TERP mechanics. | F12: MKT_RefPrice (03_MARKET_DATA!E7), scenario issue prices (04_OFFER_SETUP!E8:G8). | G12: Higher P0 increases gross proceeds per % discount and increases TERP for rights. | H12: Hardcoding P0 on multiple sheets; using different P0 for TERP vs discount. | I12: P0 appears once in 03_MARKET_DATA and is linked everywhere; no duplicate inputs. | J12: All pricing outputs reconcile to the same reference price input.
B13: 4. Issue price (Ps) LOW/BASE/HIGH | C13: 04_OFFER_SETUP!F8 | E13: Modelled issue price under each scenario (computed from discount or direct price). | F13: Price mode (01_CONTROL!E11), discount inputs (01_CONTROL!E31:G31), ref price (03_MARKET_DATA!E7). | G13: Lower Ps increases dilution for a fixed gross target, but can improve take-up probability. | H13: Discount mode but direct price entered; or discount sign wrong (adds instead of subtracts). | I13: Discount_s = 1 - Ps/P0; Ps stays > 0 and < P0 when discount > 0. | J13: We model a LOW/BASE/HIGH issue price range to show proceeds and dilution sensitivity to pricing.
B14: 5. Discount % LOW/BASE/HIGH | C14: 04_OFFER_SETUP!F9 | E14: Stated discount versus reference price for each scenario. | F14: Ps (04_OFFER_SETUP!E8:G8) and P0 (03_MARKET_DATA!E7). | G14: Higher discount usually improves execution certainty but increases dilution optics. | H14: Using inconsistent P0 definition; reporting discount on a different basis than clients expect. | I14: Discount = 1 - Ps/P0; check sign and magnitude (typical ECM discount few % to teens). | J14: We express pricing as discount to a defined reference price to align with market convention.
B15: 6. Raise sizing mode (Target gross / Target net / Shares) | C15: 01_CONTROL!E13 | E15: Defines whether the model solves for shares from a gross target, a net target, or takes shares as an input. | F15: CTRL_RaiseMode (01_CONTROL!E13), gross target (01_CONTROL!E30:G30), fees (07_PROCEEDS_AND_FEES). | G15: Target net requires 'gross-up' for fees, leading to more shares than target gross at same Ps. | H15: Leaving raise mode on net but interpreting as gross; fee assumptions then change share count unexpectedly. | I15: 90_CHECKS proceeds tie-out; gross-up logic produces Gross >= Net when fees > 0. | J15: We can size the deal off gross proceeds, net proceeds, or a fixed share issuance depending on mandate.
B16: 7. Target raise (Primary gross) LOW/BASE/HIGH | C16: 01_CONTROL!F30 | E16: The gross amount the issuer wants to raise from primary issuance (DKKm). | F16: Scenario targets (01_CONTROL!E30:G30), Ps (04_OFFER_SETUP!E8:G8), fee logic (07). | G16: Higher target mechanically increases new shares and dilution if priced at same Ps. | H16: Confusing DKKm with DKK; mixing gross target with net target interpretation. | I16: Gross proceeds from Offer Setup equals target when in TARGET_GROSS mode (04 and 07). | J16: The raise size is a direct lever on dilution and proceeds; we show it by scenario.
B17: 8. Secondary shares sold LOW/BASE/HIGH (if any) | C17: 01_CONTROL!F33 | E17: Secondary selling increases total deal size but does not add cash to the issuer. | F17: Secondary shares (01_CONTROL!E33:G33), Ps (04_OFFER_SETUP!E8:G8), proceeds split (07). | G17: More secondary increases gross proceeds headline but issuer net proceeds may be unchanged. | H17: Accidentally treating secondary as issuer cash; fee allocation across primary/secondary not clarified. | I17: Issuer net proceeds line is based on primary proceeds; secondary shown separately where relevant. | J17: We separate primary (issuer cash) from secondary (shareholder sell-down) to avoid misinterpretation.
B18: 9. New shares issued (Primary) LOW/BASE/HIGH | C18: 04_OFFER_SETUP!F15 | E18: Number of new shares issued by the company under each scenario. | F18: Raise mode (01_CONTROL!E13), target raise (01_CONTROL!E30:G30), Ps (04_OFFER_SETUP!E8:G8). | G18: For a fixed raise, lower Ps means more shares issued. | H18: Mixing shares units (shares vs m shares); rounding causing cap table mismatches. | I18: Cap table check: Pre + New = Post holds in 90_CHECKS. | J18: Share issuance is the core driver of dilution and ownership outcomes.
B19: 10. Gross proceeds (Total) LOW/BASE/HIGH | C19: 07_PROCEEDS_AND_FEES!F10 | E19: Total headline deal proceeds (primary + secondary if included). | F19: Ps (04_OFFER_SETUP!E8:G8), total sold shares (04 outputs), secondary inputs (01_CONTROL!E33:G33). | G19: Higher Ps or more shares increases gross proceeds. | H19: Double counting secondary; gross vs net confusion in conversations. | I19: Gross - Fees - Net tie-out check in 90_CHECKS. | J19: We distinguish the gross headline size from issuer net proceeds after fees.
B20: 11. Fees + other costs (Total) LOW/BASE/HIGH | C20: 07_PROCEEDS_AND_FEES!F15 | E20: Sum of underwriting, advisory, and other transaction costs. | F20: Fee % inputs (01_CONTROL!E37:E39), gross proceeds (07!E10:G10), fixed other costs (01_CONTROL!E40). | G20: Higher fees reduce issuer net proceeds and can force higher share issuance if targeting net. | H20: Fee % entered as whole number vs decimal; sign errors (fees added). | I20: Fees are non-negative; Net = Gross - Fees (90_CHECKS). | J20: Total cost of execution is a key driver of net proceeds and often negotiable.
... B38: 29. Sensitivity: Discount vs Net proceeds / Dilution | C38: 10_SENSITIVITIES!B7 | E38: Quick table showing how pricing (discount) moves issue price, shares, net proceeds and dilution. | F38: Ref price (03), raise mode and targets (01), fee assumptions (01/07). | G38: Lower discount (higher price) usually reduces dilution and can improve optics but may reduce certainty. | H38: Treating sensitivity table as scenario output without aligning to BASE controls. | I38: Check monotonicity: as discount increases, issue price falls; shares/dilution respond as expected. | J38: We use the sensitivity grid to answer 'what if pricing moves' questions fast in meetings.
B39: 30. Value of entitlement (Holder 1 total, base, DKKm) | C39: 80_ECM_LEARN_MAP!E46 | D39: Total value of rights attached to Holder 1’s existing shares (base scenario), in DKKm. | E39: Rights value transfer metric: value lost by a holder if they do not participate and cannot sell rights. | F39: Right value per share (05_RIGHTS_TERP_ENTITLE!F13); Holder 1 pre shares (06_CAP_TABLE_OWNERSHIP!E20). | G39: Increases with a larger rights value per share and a larger holder stake. | H39: Share unit mismatch (m vs shares); using post shares; not a cash flow to issuer; irrelevant for non-rights offers. | I39: Should be ≥0 in normal discounted rights; scales linearly with holder shares; check rights value per share is sensible. | J39: If the board asks: This quantifies the economic value a major holder preserves by participating (or by selling rights if tradable).
B41: Note: Scenario outputs are in columns E/F/G on calc sheets (LOW/BASE/HIGH). Dashboard shows LOW/BASE/HIGH by column.
B43: DERIVED RIGHTS VALUE TRANSFER (FOR LEARNING)
B44: Right value per existing share (base, DKK/share) | C44: 05_RIGHTS_TERP_ENTITLE!F13 | E44: ='05_RIGHTS_TERP_ENTITLE'!F13
B45: Holder 1 pre shares (base, m shares) | C45: 06_CAP_TABLE_OWNERSHIP!E20 | E45: ='06_CAP_TABLE_OWNERSHIP'!E20
B46: Entitlement value (Holder 1 total, base, DKKm) | C46: 80_ECM_LEARN_MAP!E46 | E46: =E44*E45

Sheet 81_ECM_LEARN_FORMULAS
B1: Dashboard | C1: Control | D1: Issuer | E1: Offer | F1: Checks | G1: Learn
B2: ECM Learning Layer
B3: 81) Formula Walkthrough (35 critical formulas traced to the model)
B5: HOW TO USE THIS TAB
B6: Use this as a 'formula debugger' and training aid. Each row links to the live model cell. Mini-examples use small numbers to build intuition.
B8: TOP 35 FORMULAS (TRACEABLE)
B9: Formula name | C9: Where (tab!cell) | E9: Formula | F9: Plain-language explanation | G9: Why it matters in ECM | H9: Typical mistake | I9: Mini-example
B10: 1. Discount % (pricing) | C10: 04_OFFER_SETUP!F9 | E10: =1 - (Issue_Price / Reference_Price) | F10: Computes stated discount vs the defined reference price. | G10: Discount is the core ECM pricing language used with investors and boards. | H10: Using a different reference price basis (VWAP vs last close) than you state; sign errors. | I10: Example: P0=100, Ps=92 -> Discount = 1-92/100 = 8%.
B11: 2. Issue price from discount | C11: 04_OFFER_SETUP!F8 | E11: =Reference_Price * (1 - Discount) | F11: Converts a discount input into an issue price. | G11: Many mandates are set as 'X% discount' so you need Ps immediately. | H11: Discount entered as 8 instead of 0.08 -> Ps becomes negative/too low. | I11: Example: P0=100, Disc=8% -> Ps=92.
B12: 3. New shares issued (primary) from target gross | C12: 04_OFFER_SETUP!F15 | E12: =Target_Gross_Primary / Issue_Price | F12: Solves for how many new shares the company must issue to raise a target gross amount. | G12: This is the main mechanical driver of dilution. | H12: Mixing DKKm with DKK (missing *1,000,000); rounding too early. | I12: Example: Target=700m, Ps=92 -> New=7.61m shares.
B13: 4. Gross proceeds total (primary + secondary) | C13: 07_PROCEEDS_AND_FEES!F10 | E13: =(Primary_New_Shares + Secondary_Shares) * Issue_Price | F13: Computes headline deal size before fees. | G13: Banker/client conversations often start with the gross deal size. | H13: Double counting secondary or including it when not in scope. | I13: Example: (7.61m + 1.00m)*92 = 793m.
B14: 5. Total fees (variable + fixed) | C14: 07_PROCEEDS_AND_FEES!F15 | E14: =Gross_Proceeds * Total_Fee_% + Fixed_Other_Costs | F14: Calculates total transaction costs. | G14: Fees determine net proceeds and can change share count when sizing to net. | H14: Fee % as whole number; negative fees; applying % to wrong base. | I14: Example: Gross=793m, fee%=3% -> 23.8m + other 1m = 24.8m.
B15: 6. Net proceeds to issuer (after fees) | C15: 07_PROCEEDS_AND_FEES!F16 | E15: =Gross_Primary_Proceeds - Fees_Charged_to_Issuer | F15: Computes cash received by the company. | G15: This funds use of proceeds and drives pro forma balance sheet impact. | H15: Charging issuer fees on secondary incorrectly; fee sign errors. | I15: Example: Primary=700m, fees=24.8m -> Net=675.2m.
B16: 7. Cap table roll-forward (post shares) | C16: 06_CAP_TABLE_OWNERSHIP!F13 | E16: =Pre_Shares + New_Shares_Issued | F16: Updates total shares after issuance. | G16: Everything downstream (ownership, dilution, float) depends on this reconciliation. | H16: Pre shares input not updated; referencing wrong scenario column. | I16: Example: Pre=90m, New=7.61m -> Post=97.61m.
B17: 8. Issuance dilution % | C17: 06_CAP_TABLE_OWNERSHIP!F14 | E17: =1 - (Pre_Shares / Post_Shares) | F17: Mechanical dilution from share issuance. | G17: This is the headline 'dilution optics' metric in ECM. | H17: Confusing with EPS dilution; mixing pre/post definitions. | I17: Example: 1 - 90/97.61 = 7.8%.
B18: 9. Post ownership % per holder | C18: 06_CAP_TABLE_OWNERSHIP!H20 | E18: =Holder_Post_Shares / Total_Post_Shares | F18: Computes each holder's ownership after the deal. | G18: Explains control, governance, and shareholder fairness outcomes. | H18: Not updating holder post shares logic when switching offer type. | I18: Example: Holder post 9.8m / 97.61m = 10.0%.
B19: 10. Free float % | C19: 06_CAP_TABLE_OWNERSHIP!F34 | E19: =Free_Float_Shares / Total_Shares_Post | F19: Computes post free float as a % of total shares. | G19: Float drives liquidity, index eligibility and investor demand. | H19: Treating all 'Other' as float when some is strategic; float flags wrong. | I19: Example: Float 45m / 97.61m = 46.1%.
B20: 11. Market cap pre | C20: 09_FREE_FLOAT_TRADING_MET!E8 | E20: =Pre_Shares * Reference_Price | F20: Computes equity value before the deal. | G20: Provides context for sizing and dilution versus company size. | H20: Using different price basis than discount; unit mismatch (m shares vs shares). | I20: Example: 90m * 100 = 9,000m.
B21: 12. Market cap post (at issue price) | C21: 09_FREE_FLOAT_TRADING_MET!F9 | E21: =Post_Shares * Issue_Price | F21: Mechanical post-deal equity value assuming trade at issue price. | G21: Useful sanity check on sizing and optics (not a forecast). | H21: Interpreting as true post-trade value; market may trade away from Ps/TERP. | I21: Example: 97.61m * 92 = 8,980m.
B22: 13. Rights subscription ratio (New per Existing) | C22: 05_RIGHTS_TERP_ENTITLE!F9 | E22: =New_Shares_M / Existing_Shares_N | F22: Defines how many new shares are offered relative to existing shares. | G22: Drives entitlement size and perceived 'offer size' to shareholders. | H22: Reporting inverse (rights needed per new). | I22: Example: M=7.61m, N=90m -> 0.0846 new per old.
B23: 14. TERP (theoretical ex-rights price) | C23: 05_RIGHTS_TERP_ENTITLE!F12 | E23: =(N*P0 + M*Ps) / (N + M) | F23: Weighted average price post-rights under mechanical assumptions. | G23: Benchmark for right value and value transfer discussions. | H23: Using different P0 than discount; inconsistent N/M. | I23: Example: (90*100 + 7.61*92)/(97.61)=99.4.
B24: 15. Right value per existing share | C24: 05_RIGHTS_TERP_ENTITLE!F13 | E24: =P0 - TERP | F24: Mechanical value per existing share of receiving a right. | G24: Explains why participating holders are protected in a rights issue. | H24: Negative values indicate Ps>=P0 or wrong sign. | I24: Example: 100 - 99.4 = 0.6 per share.
B25: 16. Take-up selected (numeric) | C25: 01_CONTROL!E19 | E25: =IF(TakeUpScenario="80%",0.8, ...) | F25: Converts the take-up dropdown into a numeric rate used in calculations. | G25: Ensures take-up scenarios flow through mechanically. | H25: Hardcoding take-up in multiple places; mismatch between label and numeric. | I25: Example: Scenario '60%' -> 0.6.
B26: 17. Subscribed shares (rights) | C26: 05_RIGHTS_TERP_ENTITLE!F21 | E26: =Entitled_Shares_M * TakeUp_Rate | F26: Computes how many new shares are subscribed by existing holders. | G26: Determines rump size and ownership outcomes. | H26: Applying take-up to total sold including secondary; wrong base. | I26: Example: M=7.61m, take-up=60% -> 4.57m subscribed.
B27: 18. Rump shares (rights) | C27: 05_RIGHTS_TERP_ENTITLE!F22 | E27: =Entitled_Shares_M - Subscribed_Shares | F27: Shares left over after take-up, to be placed as rump. | G27: Key execution risk and underwriting exposure metric. | H27: Sign error resulting in negative rump; forgetting to recalc when M changes. | I27: Example: 7.61m - 4.57m = 3.04m rump.
B28: 19. Issued shares (underwritten vs best efforts) | C28: 05_RIGHTS_TERP_ENTITLE!F23 | E28: =IF(Underwritten, Entitled_Shares_M, Subscribed_Shares) | F28: Underwritten deals issue full M even if take-up is low. | G28: Separates certainty of proceeds from participation uncertainty. | H28: Logic inverted; issued falling despite underwritten toggle. | I28: Example: Underwritten -> 7.61m issued; best efforts -> 4.57m.
B29: 20. Gross-up for target net proceeds | C29: 04_OFFER_SETUP!F14 | E29: =Target_Net / (1 - Fee_%_Issuer) | F29: Calculates required gross primary to deliver a net proceeds target. | G29: Common in mandates where 'net cash to issuer' is fixed. | H29: Fee % includes items not charged to issuer; divide-by-zero when fee%=100%. | I29: Example: TargetNet=675m, fee%=3.5% -> gross=699m.
B30: 21. Primary proceeds (gross) from shares | C30: 07_PROCEEDS_AND_FEES!F11 | E30: =Primary_New_Shares * Issue_Price | F30: Gross primary cash raised before fees. | G30: Used to separate issuer cash from secondary sell-down. | H30: Mixing with total proceeds that include secondary. | I30: Example: 7.61m*92 = 700m.
B31: 22. Fee split: underwriting fee | C31: 07_PROCEEDS_AND_FEES!F12 | E31: =Gross_Proceeds * Underwriting_Fee_% | F31: Calculates underwriting fee amount. | G31: Useful for negotiation and to estimate bank economics. | H31: Applying to primary only vs total without stating; wrong decimal. | I31: Example: 793m * 2% = 15.9m.
B32: 23. Other costs (fixed) | C32: 07_PROCEEDS_AND_FEES!F14 | E32: =Fixed_Costs_Input | F32: Adds fixed transaction costs (legal, listing, etc.). | G32: Ensures net proceeds are realistic even with small deal sizes. | H32: Putting fixed costs in % fee bucket; negative sign. | I32: Example: Other costs = 1.0m.
B33: 24. Free float shares post | C33: 06_CAP_TABLE_OWNERSHIP!F32 | E33: =Total_Post_Shares - Sum(Strategic_Holder_Post_Shares) | F33: Computes float shares after accounting for locked holders. | G33: Needed to translate % float into share count. | H33: Missing a strategic holder -> float overstated. | I33: Example: 97.61m - 52.6m = 45.0m float.
B34: 25. Cash allocation amount | C34: 08_PRO_FORMA_BS_LEVERAGE!F17 | E34: =Net_Proceeds * %Cash_Retained | F34: Portion of proceeds retained as cash. | G34: Directly impacts liquidity post deal. | H34: Splits not summing to 100%; using gross not net. | I34: Example: 675m * 30% = 203m.
B35: 26. Debt paydown amount | C35: 08_PRO_FORMA_BS_LEVERAGE!F15 | E35: =Net_Proceeds * %Debt_Paydown | F35: Amount of proceeds used to repay debt. | G35: Key lever to reduce leverage and covenant risk. | H35: Using negative %; paying down more debt than outstanding. | I35: Example: 675m * 70% = 472m.
B36: 27. Cash post (pro forma) | C36: 08_PRO_FORMA_BS_LEVERAGE!F25 | E36: =Cash_Pre + Cash_Allocation_Amount | F36: Updates cash after raising and allocating proceeds. | G36: Shows liquidity headroom. | H36: Double counting proceeds in both cash and growth investment lines. | I36: Example: 150m + 203m = 353m.
B37: 28. Debt post (pro forma) | C37: 08_PRO_FORMA_BS_LEVERAGE!F26 | E37: =Debt_Pre - Debt_Paydown_Amount | F37: Updates gross debt after paydown. | G37: Shows deleveraging effect of raise. | H37: Wrong sign (adding debt paydown); paying down beyond debt. | I37: Example: 1,200m - 472m = 728m.
B38: 29. Net debt post | C38: 08_PRO_FORMA_BS_LEVERAGE!F27 | E38: =Debt_Post - Cash_Post | F38: Computes post net debt. | G38: Central input to leverage, covenant and rating discussions. | H38: Inconsistent sign convention vs issuer definitions. | I38: Example: 728m - 353m = 375m.
B39: 30. Leverage post (Net debt / EBITDA) | C39: 08_PRO_FORMA_BS_LEVERAGE!F34 | E39: =Net_Debt_Post / EBITDA | F39: Computes post-transaction leverage. | G39: Headline metric for credit investors and boards. | H39: Using EBITDA that doesn't match the definition (LTM vs NTM); dividing by blank. | I39: Example: 375m / 300m = 1.25x.
B40: 31. Leverage delta (post minus pre) | C40: 08_PRO_FORMA_BS_LEVERAGE!F35 | E40: =Leverage_Post - Leverage_Pre | F40: Change in leverage due to the transaction. | G40: Communicates value of raise in a single number. | H40: Mixing scenarios; leverage pre computed on different net debt definition. | I40: Example: 1.25x - 2.00x = -0.75x.
B41: 32. Rump placement proceeds (rights) | C41: 05_RIGHTS_TERP_ENTITLE!F24 | E41: =Rump_Shares * Issue_Price | F41: Cash raised from rump placement (if underwritten and placed). | G41: Helps quantify underwriting exposure and placement requirement. | H41: Assuming rump placed at Ps without specifying; ignoring market impact. | I41: Example: 3.04m*92 = 280m.
B42: 33. Offer size as % of market cap | C42: 09_FREE_FLOAT_TRADING_MET!F13 | E42: =Gross_Proceeds / Market_Cap_Pre | F42: Normalises deal size vs company size. | G42: Used to discuss market absorption and feasibility. | H42: Using net proceeds instead of gross without stating; unit mismatch. | I42: Example: 793/9,000 = 8.8%.
B43: 34. Free float % change | C43: 09_FREE_FLOAT_TRADING_MET!F12 | E43: =Free_Float_%_Post - Free_Float_%_Pre | F43: Change in free float from the transaction. | G43: Key KPI when mandate includes liquidity/index objectives. | H43: Mixing % points with % change; using wrong pre float. | I43: Example: 46.1% - 44.0% = +2.1pp.
B44: 35. Proceeds bridge check | C44: 90_CHECKS!F15 | E44: =IF(ABS(Net_Proceeds - (Gross_Primary - Fees))<Tolerance, "PASS", "FAIL") | F44: Flags if proceeds math does not reconcile. | G44: Stops you from using outputs when basic cash math breaks. | H44: Tolerance too tight; ignoring fails. | I44: Example: if mismatch 0.1m and tol 0.5m -> PASS.

Sheet 82_ECM_LEARN_INTERPRETATION
B1: Dashboard | C1: Control | D1: Issuer | E1: Offer | F1: Checks | G1: Learn
B2: ECM Learning Layer
B3: 82) Interpretation Scripts (how to talk about outputs in banker/client conversations)
B5: DASHBOARD TILE INTERPRETATION (MEETING-READY)
B6: Tile | C6: Where (Dashboard cell) | E6: How to interpret | F6: What it signals | G6: What could mislead | H6: Follow-up question
B7: 1. Offer type | C7: 00_DASHBOARD!E8 | E7: Selected method drives which mechanics activate (TERP/take-up only for Rights). | F7: Signals execution route and timeline trade-offs (speed vs fairness/certainty). | G7: Misleading if rights-only inputs left active in placement/ABB or vice versa; always confirm Control toggles. | H7: Next: What is the mandate objective (cash vs float vs fairness) and what is timing/market window?
B8: 2. Reference price (P0) | C8: 00_DASHBOARD!E9 | E8: Price basis used for discount and (for Rights) TERP logic. | F8: Signals the market anchor for pricing and optics. | G8: Misleading if definition (last close/VWAP) or date differs from what you state. | H8: Next: Which reference definition are we using and as of what date/time?
B9: 3. Issue price (Ps) | C9: 00_DASHBOARD!E10 | E9: Offered price to investors / shareholders (scenario-based). | F9: Signals demand risk: lower Ps increases certainty but worsens dilution. | G9: Misleading if price mode and discount mode are mixed; confirm Ps comes from the right control. | H9: Next: What discount is defensible in this market and for this liquidity profile?
B10: 4. Discount % | C10: 00_DASHBOARD!E11 | E10: Stated discount: 1 - Ps/P0. | F10: Signals marketability vs dilution optics. | G10: Misleading if P0 definition mismatch; discount should be reported with explicit basis. | H10: Next: How does dilution move across the LOW/BASE/HIGH pricing range?
B11: 5. Gross proceeds (headline) | C11: 00_DASHBOARD!E16 | E11: Total deal size before fees (primary + secondary if any). | F11: Signals market absorption and execution size vs liquidity. | G11: Misleading if secondary included but discussed as issuer cash. | H11: Next: How much is primary vs secondary and what is issuer net cash?
B12: 6. Fees & costs | C12: 00_DASHBOARD!E17 | E12: Total execution costs deducted from issuer proceeds (definition shown in proceeds tab). | F12: Signals negotiability and bank economics. | G12: Misleading if fee % base differs (primary-only vs total). | H12: Next: Which parts are variable %, which fixed, and what is fee base?
B13: 7. Net proceeds to issuer | C13: 00_DASHBOARD!E18 | E13: Cash received by the company after costs. | F13: Signals ability to fund stated use of proceeds and de-risk balance sheet. | G13: Misleading if fee base wrong (charging issuer on secondary) or fixed costs omitted. | H13: Next: How are net proceeds allocated (debt paydown vs cash vs growth)?
B14: 8. New shares issued | C14: 00_DASHBOARD!E19 | E14: Primary shares issued by the company (mechanical). | F14: Signals dilution pressure and float impact. | G14: Misleading if raise sized to net and fees change; shares move even if target net stays constant. | H14: Next: How does share issuance change across pricing scenarios?
B15: 9. Dilution % | C15: 00_DASHBOARD!E20 | E15: Mechanical issuance dilution: 1 - pre/post. | F15: Signals dilution optics and shareholder impact. | G15: Misleading if interpreted as EPS dilution; this is share-count dilution only. | H15: Next: Which holders are diluted the most given participation/allocation assumptions?
B16: 10. Free float % post | C16: 00_DASHBOARD!E22 | E16: Post-transaction free float based on ownership table. | F16: Signals liquidity and index eligibility improvements. | G16: Misleading if float flags are wrong or if rump assumed to go to float when it may go to insiders. | H16: Next: What is the target float objective and investor base?
B17: 11. Net debt (pro forma) | C17: 00_DASHBOARD!E25 | E17: Post net debt after applying net proceeds and use-of-proceeds split. | F17: Signals deleveraging and covenant/rating comfort. | G17: Misleading if net debt definition differs (cash netting, leases) from issuer's definition. | H17: Next: What leverage metric does the board care about (ND/EBITDA, gross leverage, etc.)?
B18: 12. Leverage (ND/EBITDA) | C18: 00_DASHBOARD!E26 | E18: Post leverage using the model EBITDA definition. | F18: Signals credit story and financial flexibility post raise. | G18: Misleading if EBITDA basis (LTM vs NTM) inconsistent; stress EBITDA separately. | H18: Next: What happens under downside EBITDA and/or higher cost of debt?
B21: ECM MEETING-READY SCRIPTS (12 COMMON QUESTIONS)
B22: Question | C22: Script (2-3 sentences) | E22: Linked KPIs / tabs | F22: Checks to cite
B23: 1. Why rights vs placement vs ABB? | C23: Rights favours fairness to existing shareholders and can protect them via entitlements, but is slower and introduces take-up risk. Placement/ABB are faster and simpler mechanically, but can create fairness optics and higher dilution concentration. We recommend the method that best matches the mandate objective (cash, float, speed, certainty). | E23: See 80_MAP + 81_FORMULAS | F23: 90_CHECKS overall
B24: 2. Is the discount defensible? | C24: We anchor discount to a clear reference price definition (Control). We show sensitivity of proceeds and dilution across pricing scenarios. The defensible range depends on liquidity, volatility, and investor demand, so we frame discount as the minimum needed to clear the book while meeting proceeds. | E24: See 80_MAP + 81_FORMULAS | F24: 90_CHECKS overall
B25: 3. How does take-up risk show up? | C25: In a rights issue, take-up drives subscribed vs rump shares. Lower take-up increases rump placement volume and shifts ownership toward new investors/underwriters. The model shows the subscribed/rump split and highlights execution risk and potential value transfer. | E25: See 80_MAP + 81_FORMULAS | F25: 90_CHECKS overall
B26: 4. What is the value transfer between participants and non-participants? | C26: Rights protect participants by allowing them to buy at Ps and capture the right value implied by TERP. Non-participants experience effective dilution and may transfer value to participants. We quantify right value and tie it to TERP mechanics. | E26: See 80_MAP + 81_FORMULAS | F26: 90_CHECKS overall
B27: 5. Why underwrite/backstop? | C27: Underwriting converts take-up uncertainty into proceeds certainty at a cost (fees and potentially backstop fees). If the issuer prioritises certainty and timing, underwriting can be rational. The trade-off is cost and the need to place rump shares. | E27: See 80_MAP + 81_FORMULAS | F27: 90_CHECKS overall
B28: 6. What free float objective are we targeting? | C28: We show pre vs post free float and how allocations/take-up affect it. If the objective is index inclusion or liquidity improvement, we bias allocation toward float investors and reduce insider concentration within acceptable dilution limits. | E28: See 80_MAP + 81_FORMULAS | F28: 90_CHECKS overall
B29: 7. How do you justify use of proceeds? | C29: Net proceeds are allocated to debt paydown, cash retention, or growth investment per Control. We translate that split into a pro forma balance sheet and leverage change to show concrete impact and ensure the story is consistent with KPIs. | E29: See 80_MAP + 81_FORMULAS | F29: 90_CHECKS overall
B30: 8. How does leverage change and why does it matter? | C30: Leverage is computed from net debt post and the EBITDA definition used. Debt paydown reduces net debt and improves ND/EBITDA, creating covenant headroom and rating comfort. We also stress EBITDA to show downside resilience. | E30: See 80_MAP + 81_FORMULAS | F30: 90_CHECKS overall
B31: 9. Is dilution acceptable? | C31: We frame dilution relative to the raise size and market cap, and we show dilution under LOW/BASE/HIGH pricing. In rights, participation assumptions change who is diluted. Acceptability is assessed versus shareholder appetite, valuation, and strategic objectives. | E31: See 80_MAP + 81_FORMULAS | F31: 90_CHECKS overall
B32: 10. How do we manage timing and market risk? | C32: ABB minimises execution time but may require sharper discount. Rights takes longer and is exposed to market drift but can improve shareholder fairness. We map the method to execution window and recommend contingencies. | E32: See 80_MAP + 81_FORMULAS | F32: 90_CHECKS overall
B33: 11. What are the key pitfalls in interpreting outputs? | C33: Common pitfalls are gross vs net confusion, primary vs secondary mixing, reference price definition mismatch, and ignoring check failures. We explicitly label definitions and use 90_CHECKS as a gate before communicating numbers. | E33: See 80_MAP + 81_FORMULAS | F33: 90_CHECKS overall
B34: 12. What is the one-slide deal narrative? | C34: Method and pricing define shares issued and dilution; proceeds net of fees fund a stated allocation; allocation drives cash, debt and net debt; this changes leverage and float. Key risks are pricing, demand/take-up, and market window, with mitigants via underwriting and allocation. | E34: See 80_MAP + 81_FORMULAS | F34: 90_CHECKS overall

Sheet 83_ECM_LEARN_SCENARIOS
B1: Dashboard | C1: Control | D1: Issuer | E1: Offer | F1: Checks | G1: Learn
B2: ECM Learning Layer
B3: 83) Scenario Narratives (assumptions vs outputs, aggressiveness flags, and variance drivers)
B5: SCENARIO ASSUMPTIONS (TRACE TO INPUTS)
B6: Assumption | C6: Where (model) | E6: LOW | F6: BASE | G6: HIGH | H6: LOW flag | I6: BASE flag | J6: HIGH flag
B7: Discount % | C7: 04_OFFER_SETUP!E9:G9 | E7: ='04_OFFER_SETUP'!E9 | F7: ='04_OFFER_SETUP'!F9 | G7: ='04_OFFER_SETUP'!G9 | H7: =IF(E7<0.06,"AGGRESSIVE",IF(E7>0.12,"CONSERVATIVE","NEUTRAL")) | I7: =IF(F7<0.06,"AGGRESSIVE",IF(F7>0.12,"CONSERVATIVE","NEUTRAL")) | J7: =IF(G7<0.06,"AGGRESSIVE",IF(G7>0.12,"CONSERVATIVE","NEUTRAL"))
B8: Issue price (Ps) | C8: 04_OFFER_SETUP!E8:G8 | E8: ='04_OFFER_SETUP'!E8 | F8: ='04_OFFER_SETUP'!F8 | G8: ='04_OFFER_SETUP'!G8 | H8: =IF(E8>0.95*'03_MARKET_DATA'!E7,"AGGRESSIVE",IF(E8<0.88*'03_MARKET_DATA'!E7,"CONSERVATIVE","NEUTRAL")) | I8: =IF(F8>0.95*'03_MARKET_DATA'!E7,"AGGRESSIVE",IF(F8<0.88*'03_MARKET_DATA'!E7,"CONSERVATIVE","NEUTRAL")) | J8: =IF(G8>0.95*'03_MARKET_DATA'!E7,"AGGRESSIVE",IF(G8<0.88*'03_MARKET_DATA'!E7,"CONSERVATIVE","NEUTRAL"))
B9: Target gross primary (DKKm) | C9: 01_CONTROL!E30:G30 | E9: ='01_CONTROL'!E30 | F9: ='01_CONTROL'!F30 | G9: ='01_CONTROL'!G30 | H9: =IF(E9>('09_FREE_FLOAT_TRADING_MET'!E8*0.10),"AGGRESSIVE",IF(E9<('09_FREE_FLOAT_TRADING_MET'!E8*0.05),"CONSERVATIVE","NEUTRAL")) | I9: =IF(F9>('09_FREE_FLOAT_TRADING_MET'!E8*0.10),"AGGRESSIVE",IF(F9<('09_FREE_FLOAT_TRADING_MET'!E8*0.05),"CONSERVATIVE","NEUTRAL")) | J9: =IF(G9>('09_FREE_FLOAT_TRADING_MET'!E8*0.10),"AGGRESSIVE",IF(G9<('09_FREE_FLOAT_TRADING_MET'!E8*0.05),"CONSERVATIVE","NEUTRAL"))
B10: Total fee % (underwriting+advisory) | C10: 01_CONTROL!E37:E39 | E10: ='01_CONTROL'!E37+'01_CONTROL'!E38 | F10: ='01_CONTROL'!E37+'01_CONTROL'!E38 | G10: ='01_CONTROL'!E37+'01_CONTROL'!E38 | H10: =IF(E10<0.025,"AGGRESSIVE",IF(E10>0.04,"CONSERVATIVE","NEUTRAL")) | I10: =IF(F10<0.025,"AGGRESSIVE",IF(F10>0.04,"CONSERVATIVE","NEUTRAL")) | J10: =IF(G10<0.025,"AGGRESSIVE",IF(G10>0.04,"CONSERVATIVE","NEUTRAL"))
B11: Take-up rate (Rights only) | C11: 01_CONTROL!E19 | E11: ='01_CONTROL'!E19 | F11: ='01_CONTROL'!E19 | G11: ='01_CONTROL'!E19 | H11: =IF(E11>0.9,"AGGRESSIVE",IF(E11<0.7,"CONSERVATIVE","NEUTRAL")) | I11: =IF(F11>0.9,"AGGRESSIVE",IF(F11<0.7,"CONSERVATIVE","NEUTRAL")) | J11: =IF(G11>0.9,"AGGRESSIVE",IF(G11<0.7,"CONSERVATIVE","NEUTRAL"))
B12: Use of proceeds: % debt paydown | C12: 01_CONTROL!E46 | E12: ='01_CONTROL'!E46 | F12: ='01_CONTROL'!E46 | G12: ='01_CONTROL'!E46 | H12: =IF(E12>0.8,"AGGRESSIVE",IF(E12<0.4,"CONSERVATIVE","NEUTRAL")) | I12: =IF(F12>0.8,"AGGRESSIVE",IF(F12<0.4,"CONSERVATIVE","NEUTRAL")) | J12: =IF(G12>0.8,"AGGRESSIVE",IF(G12<0.4,"CONSERVATIVE","NEUTRAL"))
B15: SCENARIO OUTPUTS (FROM MODEL)
B16: Assumption | C16: Where (model) | E16: LOW | F16: BASE | G16: HIGH | H16: LOW flag | I16: BASE flag | J16: HIGH flag
B17: Net proceeds to issuer (DKKm) | C17: 07_PROCEEDS_AND_FEES!E16:G16 | E17: ='07_PROCEEDS_AND_FEES'!E16 | F17: ='07_PROCEEDS_AND_FEES'!F16 | G17: ='07_PROCEEDS_AND_FEES'!G16 | H17: N/A | I17: N/A | J17: N/A
B18: Dilution % | C18: 06_CAP_TABLE_OWNERSHIP!E14:G14 | E18: ='06_CAP_TABLE_OWNERSHIP'!E14 | F18: ='06_CAP_TABLE_OWNERSHIP'!F14 | G18: ='06_CAP_TABLE_OWNERSHIP'!G14 | H18: N/A | I18: N/A | J18: N/A
B19: Free float % post | C19: 06_CAP_TABLE_OWNERSHIP!E34:G34 | E19: ='06_CAP_TABLE_OWNERSHIP'!E34 | F19: ='06_CAP_TABLE_OWNERSHIP'!F34 | G19: ='06_CAP_TABLE_OWNERSHIP'!G34 | H19: N/A | I19: N/A | J19: N/A
B20: Net debt post (DKKm) | C20: 08_PRO_FORMA_BS_LEVERAGE!E27:G27 | E20: ='08_PRO_FORMA_BS_LEVERAGE'!E27 | F20: ='08_PRO_FORMA_BS_LEVERAGE'!F27 | G20: ='08_PRO_FORMA_BS_LEVERAGE'!G27 | H20: N/A | I20: N/A | J20: N/A
B21: Leverage post (ND/EBITDA) | C21: 08_PRO_FORMA_BS_LEVERAGE!E34:G34 | E21: ='08_PRO_FORMA_BS_LEVERAGE'!E34 | F21: ='08_PRO_FORMA_BS_LEVERAGE'!F34 | G21: ='08_PRO_FORMA_BS_LEVERAGE'!G34 | H21: N/A | I21: N/A | J21: N/A
B22: Checks status | C22: 90_CHECKS!E7 | E22: ='90_CHECKS'!E7 | F22: ='90_CHECKS'!F7 | G22: ='90_CHECKS'!G7 | H22: N/A | I22: N/A | J22: N/A
B25: SCENARIO NARRATIVES (WRITE-UP)
B26: What must be true for Upside:
B27: • Market clears near the BASE/HIGH price (tight discount) without reducing take-up/demand.
B28: • Fees stay within assumed range, so net proceeds are not eroded.
B29: • Execution window remains stable (no volatility spike) so allocation supports float objectives.
B31: What breaks first in Downside:
B32: • Price moves down or required discount widens, increasing shares issued and dilution.
B33: • For rights, take-up falls, increasing rump and shifting ownership/underwriting burden.
B34: • EBITDA stress reduces leverage improvement even if proceeds are raised.
B36: Which 3 assumptions drive 80% of the variance:
B37: • Issue price/discount, raise size, and fee % (these move shares issued, net proceeds, dilution, and leverage).

Sheet 84_ECM_LEARN_DRILLS
B2: ECM Learning Layer
B3: 84) Drills (hands-on exercises with PASS/FAIL checks and a daily drill mode)
B5: DAILY DRILL MODE
B6: Mode (type DAILY or RANDOM): | E6: DAILY | H6: Attempts | I6: =COUNTA($C$48:$C$200)
B7: Drill number: | E7: =IF($E$6="RANDOM",RANDBETWEEN(1,12),MOD(TODAY()-DATE(2026,1,1),12)+1) | H7: Passes | I7: =COUNTIF($D$48:$D$200,"Y")
B8: Drill title: | E8: =IFERROR(INDEX($B$32:$B$43,$E$7),"-")
B10: BASELINE CAPTURE (PASTE VALUES ONCE BEFORE STARTING A DRILL)
B11: Metric | C11: Where (model) | E11: Baseline (paste values) | F11: Current (live) | G11: Notes
B12: Discount % (BASE) | C12: 04_OFFER_SETUP!F9 | F12: ='04_OFFER_SETUP'!F9
B13: Issue price (BASE) | C13: 04_OFFER_SETUP!F8 | F13: ='04_OFFER_SETUP'!F8
B14: Net proceeds (BASE, DKKm) | C14: 07_PROCEEDS_AND_FEES!F16 | F14: ='07_PROCEEDS_AND_FEES'!F16
B15: Dilution % (BASE) | C15: 06_CAP_TABLE_OWNERSHIP!F14 | F15: ='06_CAP_TABLE_OWNERSHIP'!F14
B16: Free float % post (BASE) | C16: 06_CAP_TABLE_OWNERSHIP!F34 | F16: ='06_CAP_TABLE_OWNERSHIP'!F34
B17: Leverage (ND/EBITDA) post (BASE) | C17: 08_PRO_FORMA_BS_LEVERAGE!F34 | F17: ='08_PRO_FORMA_BS_LEVERAGE'!F34
B18: TERP (BASE, rights) | C18: 05_RIGHTS_TERP_ENTITLE!F12 | F18: ='05_RIGHTS_TERP_ENTITLE'!F12
B19: Subscription ratio M/N (BASE) | C19: 05_RIGHTS_TERP_ENTITLE (M/N) | F19: ='05_RIGHTS_TERP_ENTITLE'!F9/'05_RIGHTS_TERP_ENTITLE'!F8
B20: Take-up rate (selected) | C20: 01_CONTROL!E19 | F20: ='01_CONTROL'!E19
B21: New shares M (BASE, rights) | C21: 05_RIGHTS_TERP_ENTITLE!F9 | F21: ='05_RIGHTS_TERP_ENTITLE'!F9
B22: Subscribed shares (BASE, rights) | C22: 05_RIGHTS_TERP_ENTITLE!F21 | F22: ='05_RIGHTS_TERP_ENTITLE'!F21
B23: Rump shares (BASE, rights) | C23: 05_RIGHTS_TERP_ENTITLE!F22 | F23: ='05_RIGHTS_TERP_ENTITLE'!F22
B24: Issued shares (BASE, rights) | C24: 05_RIGHTS_TERP_ENTITLE!F23 | F24: ='05_RIGHTS_TERP_ENTITLE'!F23
B25: Offer type selected | C25: 01_CONTROL!E8 | F25: ='01_CONTROL'!E8
B26: Checks status (BASE) | C26: 90_CHECKS!F7 | F26: ='90_CHECKS'!F7
B27: EBITDA (input) | C27: 02_ISSUER_INPUTS!E29 | F27: ='02_ISSUER_INPUTS'!E29
B30: 12 DRILLS (CHANGE ONLY ALLOWED INPUTS)
B31: Drill | C31: Objective | F31: Forbidden inputs | G31: PASS/FAIL (formula) | H31: Driver logic (why this works) | I31: Notes
B32: 1. Net proceeds +10% without lowering discount | C32: Increase net proceeds by at least +10% vs baseline while discount (BASE) is not smaller (no tighter pricing). | E32: 01_CONTROL fees (E37:E39), fixed costs (E40), raise target (E30:G30) and raise mode (E13). | F32: Any calc cells; do not change discount or issue price directly. | G32: =IF(AND($F$14>=1.10*$E$14,$F$12>= $E$12,$F$26="PASS"),"PASS","FAIL") | H32: Net proceeds can rise via lower fees/costs or larger primary raise. Holding discount constant forces structural levers, not pricing.
B33: 2. Reduce dilution by 3pp, keep net proceeds constant | C33: Reduce dilution by at least 3 percentage points while keeping net proceeds within ±1% of baseline. | E33: Pricing/discount controls, raise sizing mode/target, and fees if needed, but keep net proceeds stable. | F33: Do not edit calculated ownership cells; do not change baseline capture cells. | G33: =IF(AND($F$15<= $E$15-0.03,ABS($F$14-$E$14)/$E$14<=0.01,$F$26="PASS"),"PASS","FAIL") | H33: Dilution is driven by shares issued. Keeping net constant means you must trade off price, fees, and sizing efficiently.
B34: 3. Increase free float +5pp, keep dilution within a cap | C34: Increase post free float by at least +5pp while keeping dilution at or below baseline +1pp. | E34: Offer type, secondary shares (if used), and any allocation inputs that shift shares toward public investors. | F34: Do not edit formula cells in ownership table. | G34: =IF(AND($F$16>= $E$16+0.05,$F$15<= $E$15+0.01,$F$26="PASS"),"PASS","FAIL") | H34: Float increases when shares are placed with public investors (sell-down or rump to float). Cap forces you to keep dilution optics under control.
B35: 4. Reduce leverage by -0.5x using use-of-proceeds only | C35: Achieve at least -0.5x leverage improvement versus baseline by changing only the use-of-proceeds split. | E35: 01_CONTROL use-of-proceeds % (E46:E48) only. | F35: Do not change proceeds inputs (price/fees/size). | G35: =IF(AND($F$17<= $E$17-0.5,ABS($F$14-$E$14)/$E$14<=0.005,$F$26="PASS"),"PASS","FAIL") | H35: Leverage improves when more net proceeds go to debt paydown. Net proceeds should stay unchanged if you only reallocate.
B36: 5. Rights: take-up 80% → 60% and observe rump | C36: Set take-up to 60% and show rump shares increase versus baseline. | E36: 01_CONTROL take-up scenario (E18) only. | F36: Do not change offer size or price for this drill. | G36: =IF(AND($F$20=0.6,$F$23>$E$23,$F$26="PASS"),"PASS","FAIL") | H36: Lower take-up reduces subscribed shares and increases rump, changing who buys the shares and shifting execution risk.
B37: 6. Rights: hold TERP stable while changing Ps and subscription ratio | C37: Change issue price and subscription ratio materially while keeping TERP within ±0.1% of baseline. | E37: Raise target and/or discount (to change Ps), and any rights sizing inputs that move M/N. | F37: Do not change reference price P0. | G37: =IF(AND(ABS($F$18-$E$18)/$E$18<=0.001,ABS($F$13-$E$13)/$E$13>=0.02,ABS($F$19-$E$19)/$E$19>=0.10,$F$26="PASS"),"PASS","FAIL") | H37: TERP is a weighted average. You can offset price changes with ratio changes to keep TERP approximately constant.
B38: 7. ABB: minimise discount while still raising the target | C38: Switch to ABB and reduce discount to at most 4% while keeping net proceeds at or above baseline. | E38: Offer type (01_CONTROL!E8), discount/price controls, and sizing to keep proceeds. | F38: Do not change reference price definition. | G38: =IF(AND('01_CONTROL'!E8="ABB",$F$12<=0.04,$F$14>=$E$14,$F$26="PASS"),"PASS","FAIL") | H38: Tighter pricing is harder to execute. To keep proceeds constant you must solve sizing and fee impacts without relying on a big discount.
B39: 8. Switch offer type and write a 6-bullet recommendation | C39: Switch offer type away from baseline and draft a 6-bullet recommendation referencing KPIs (dilution, float, proceeds, execution risk). | E39: Offer type toggle (01_CONTROL!E8) plus any method-specific inputs needed for coherence. | F39: Do not edit formula cells. | G39: =IF(AND('01_CONTROL'!E8<>$E$25,$F$26="PASS"),"PASS","FAIL") | H39: Offer type changes speed, certainty, and fairness. Your recommendation must connect method choice to KPIs and risks.
B40: 9. Fix a definition mismatch using controls | C40: Adjust controls/inputs to resolve an inconsistency so checks return PASS. | E40: Only definition and input cells in 01_CONTROL and 02_ISSUER_INPUTS. | F40: Do not patch formulas or links. | G40: =IF($F$26="PASS","PASS","FAIL") | H40: Most model failures are definition mismatches. Fix via inputs, then validate via 90_CHECKS before communicating numbers.
B41: 10. Stress: weaker EBITDA and show leverage impact | C41: Reduce EBITDA by 10% and confirm leverage worsens versus baseline (while checks remain PASS). | E41: EBITDA input (02_ISSUER_INPUTS!E29) only. | F41: Do not change proceeds inputs. | G41: =IF(AND($F$27<=0.9*$E$27,$F$17>$E$17,$F$26="PASS"),"PASS","FAIL") | H41: Leverage sensitivity is often driven by EBITDA. This drill builds intuition for denominator risk.
B42: 11. Underwriting: issued shares stay at M when take-up falls | C42: Set underwriting to FULLY UNDERWRITTEN and take-up to 60%, then show issued shares equals M (total new shares). | E42: 01_CONTROL underwriting toggle (E16) and take-up scenario (E18). | F42: Do not change offer size. | G42: =IF(AND('01_CONTROL'!E16="FULLY UNDERWRITTEN",$F$20=0.6,$F$24=$F$21,$F$22<$F$21,$F$26="PASS"),"PASS","FAIL") | H42: Underwriting converts take-up uncertainty into proceeds certainty. Issued shares remain M; the gap to subscribed is rump exposure.
B43: 12. Write a 6-bullet deal mechanics narrative | C43: Write a 6-bullet narrative explaining: method, price/discount, shares+dilution, float, proceeds+allocation, key risks+mitigants. | E43: No model changes required. | F43: None. | G43: =IF($F$26="PASS","PASS","FAIL") | H43: This trains you to synthesise mechanics into an IC-ready narrative using KPIs and scripts.
B46: SCORE TRACKER (LOG YOUR ATTEMPTS)
B47: Date | C47: Drill # | D47: Pass? (Y/N) | E47: Time (min) | F47: Notes

Sheet 85_ECM_LEARN_MISTAKES
B1: Dashboard | C1: Control | D1: Issuer | E1: Offer | F1: Checks | G1: Learn
B2: ECM Learning Layer
B3: 85) Mistake Library + Training Mode (common ECM modelling pitfalls, how to detect, and how to fix)
B5: OPTIONAL TRAINING MODE (SIMULATED)
B6: TRAINING_MODE (type ON/OFF): | E6: OFF
B7: If ON: the sheet shows 5 'planted' issues to hunt. To keep the base model outputs identical, issues are simulated (you create them via allowed input edits and confirm 90_CHECKS flags them).
B9: Simulated issues (when TRAINING_MODE=ON):
B10: 1) Share roll-forward mismatch: change pre shares input so pre + new ≠ post (expect a cap table / roll-forward check to fail).
B11: 2) TERP logic break: set reference price or issue price to blank/zero (expect rights checks to fail or TERP to show error).
B12: 3) Fee sign error: input a negative fee % or fixed cost (expect net proceeds sanity check to fail).
B13: 4) Reference price mismatch: switch reference definition without updating narrative (expect discount/TERP to look inconsistent vs stated basis).
B14: 5) Broken link placeholder: intentionally point an input to a wrong cell (expect a #REF or a missing input warning if checks exist).
B16: Answer key (what to do):
B17: • Use 90_CHECKS as your gate. You pass training mode only when you can (i) reproduce the issue, (ii) locate the root cause in inputs/definitions, (iii) restore PASS without touching calc cells.
B20: MISTAKE LIBRARY (25 COMMON ECM MODELLING ERRORS)
B21: Category | C21: Mistake | D21: What it breaks / causes | F21: How to detect (checks / symptoms) | G21: How to fix (action)
B22: Share mechanics | C22: Pre/post share roll-forward mismatch | D22: Post shares do not equal pre shares + new shares (dilution wrong). | F22: 90_CHECKS roll-forward FAIL; ownership totals ≠100%. | G22: Fix pre shares input; ensure new shares block is referenced consistently.
B23: Share mechanics | C23: Secondary shares treated as issuer cash | D23: Net proceeds overstated; issuer cash bridge wrong. | F23: Proceeds tab shows issuer cash > primary proceeds; CFO questions. | G23: Split primary vs secondary; only primary proceeds flow to cash.
B24: Share mechanics | C24: Free float flagging wrong (insiders marked as float) | D24: Free float % overstated; index eligibility wrong. | F24: Free float jumps unrealistically; top holder appears in float. | G24: Correct holder classification inputs; re-check ownership table.
B25: Share mechanics | C25: Mixing shares and % in ownership inputs | D25: Ownership percentages drift; sums not 100%. | F25: Ownership totals ≠100% or negative holder values. | G25: Standardise: input shares only, calculate %; use checks.
B26: Share mechanics | C26: Using share-count dilution as EPS dilution | D26: Overstates economic impact; wrong narrative. | F26: Stakeholders ask why EPS math missing. | G26: Clarify definition: share-count dilution only; add EPS module separately if needed.
B27: Rights mechanics | C27: Subscription ratio inverted (N/M vs M/N) | D27: Entitlements wrong; take-up, rump, TERP wrong. | F27: Rights outputs show impossible entitlements; check fails. | G27: Recompute ratio and label clearly (M new, N existing).
B28: Rights mechanics | C28: TERP uses wrong reference price definition | D28: Right value wrong; fairness analysis wrong. | F28: TERP inconsistent vs stated P0; discount optics odd. | G28: Lock reference price definition; document date/time.
B29: Rights mechanics | C29: Right value sign error (TERP - Ps vs Ps - TERP) | D29: Shows negative right value; wrong conclusion. | F29: Right value negative in normal cases. | G29: Use Right value = max(TERP - Ps,0) per right-share logic used.
B30: Rights mechanics | C30: Take-up applied to total new shares, not entitlement | D30: Subscribed shares overstated; rump understated. | F30: Rump too small even at low take-up. | G30: Subscribed = entitlement × take-up; rump = M - subscribed.
B31: Rights mechanics | C31: Rump shares not capped at 0 | D31: Negative rump; breaks allocation logic. | F31: Rump becomes negative at take-up>100% or rounding. | G31: Wrap with MAX(0,...) and validate take-up bounds.
B32: Rights mechanics | C32: Ignoring rounding rules (entitlements not integer) | D32: Minor mismatches accumulate; checks fail. | F32: Roll-forward differs by small number of shares. | G32: Apply rounding consistently and book rounding to rump.
... B46: Logic bugs | C46: Scenario toggle not applied everywhere | D46: Some blocks reflect BASE while others reflect LOW/HIGH. | F46: Outputs inconsistent across tabs. | G46: Centralise scenario selector and reference it from all blocks.

Sheet 86_ECM_SPECIAL_MODULE
B1: Dashboard | C1: Control | D1: Issuer | E1: Offer | F1: Checks | G1: Learn
B2: ECM Learning Layer
B3: 86) ECM Special Modules (decision guide, rights mechanics lab, pro forma bridge)
B5: 1) OFFER TYPE DECISION GUIDE (RIGHTS VS PLACEMENT VS ABB)
B6: Dimension | C6: Rights Issue | D6: Private Placement | E6: ABB | F6: Meeting script (what to say)
B7: Speed | C7: Slower (documentation + subscription period) | D7: Medium (bookbuild + docs) | E7: Fastest (overnight) | F7: Frame as trade-off: speed vs fairness vs certainty.
B8: Certainty of proceeds | C8: High if underwritten; otherwise take-up risk | D8: High if demand built; execution risk at pricing | E8: Moderate-high but depends on market window | F8: Use 'certainty' language: underwrite to de-risk, or size to demand.
B9: Shareholder fairness | C9: High: all holders can maintain % if they subscribe | D9: Medium: dilution concentrated on non-participants | E9: Low-medium: dilution concentrated; optics sensitive | F9: Explain value transfer and mitigation (rights, allocation, communication).
B10: Dilution optics | C10: Often more acceptable if rights allow participation | D10: Can be sensitive if strategic dilution | E10: Can be sensitive due to tighter timeline/discount | F10: Anchor dilution to use of proceeds and value creation plan.
B11: Typical discount | C11: Often larger to drive take-up (vs TERP/P0) | D11: Moderate (depends on anchor demand) | E11: Often wider than placement to clear overnight | F11: Use discount defensibility: volatility, liquidity, order book strength.
B12: Underwriting need | C12: Common (especially large deals) | D12: Optional | E12: Rare (usually not) | F12: State why underwriting: size, take-up, market risk.
B13: Market risk exposure | C13: Longer exposure to volatility | D13: Medium | E13: Highest sensitivity to window | F13: Tie to market conditions: vol, sector comps, investor sentiment.
B15: When each method is preferred (rules of thumb):
B16: • Rights: when fairness and shareholder participation are critical, and you can accept a longer process.
B17: • Placement: when you need speed and targeted investor demand, and dilution optics are manageable.
B18: • ABB: when you need maximum speed and can clear the deal overnight with a robust order book.
B21: 2) RIGHTS ISSUE MECHANICS LAB (TERP + VALUE TRANSFER)
B22: Step-by-step chain (each step links to the base model):
B23: Step | C23: Input / Output | F23: Why it matters (1–2 lines)
B24: 1 | C24: Reference price P0 | E24: 03_MARKET_DATA!E7 | F24: Anchors discount and TERP. Must match the stated basis/date.
B25: 2 | C25: Issue price Ps and discount % | E25: 04_OFFER_SETUP!F8 / F9 | F25: Defines economics and take-up incentives.
B26: 3 | C26: Share counts N (existing) and M (new) | E26: 05_RIGHTS_TERP_ENTITLE!F8 / F9 | F26: Defines subscription ratio and dilution mechanics.
B27: 4 | C27: TERP (weighted average) | E27: 05_RIGHTS_TERP_ENTITLE!F12 | F27: Fairness benchmark and the core rights mechanic.
B28: 5 | C28: Right value per existing share (P0 - TERP) | E28: 05_RIGHTS_TERP_ENTITLE!F13 | F28: Shows value transfer. Total entitlement value for a holder = right value × holder pre shares (see 80_ECM_LEARN_MAP!E46).
B29: 6 | C29: Take-up scenario and subscribed shares | E29: 01_CONTROL!E19 / 05_RIGHTS_TERP_ENTITLE!F21 | F29: Drives rump and underwriting exposure.
B30: 7 | C30: Rump shares and issued shares | E30: 05_RIGHTS_TERP_ENTITLE!F22 / F23 | F30: Drives who ends up owning the shares and execution risk.
B32: Rights sanity checks (quick checklist):
B33: • TERP should sit between P0 and Ps (if Ps < P0).
B34: • Right value should be positive when Ps is below TERP.
B35: • Subscribed shares = entitlement × take-up; rump = M - subscribed (not negative).
B36: • Post shares = N + M; ownership totals to 100%.
B39: 3) PRO FORMA BALANCE SHEET EXPLAINER (PROCEEDS → CASH → NET DEBT → LEVERAGE)
B40: Bridge steps (traceable):
B41: Step | C41: Bridge item | F41: Sanity check / pitfall
B42: 1 | C42: Net primary proceeds to issuer | E42: 07_PROCEEDS_AND_FEES!F16 | F42: Must exclude secondary and include fees.
B43: 2 | C43: Cash increases by net primary proceeds (or split) | E43: 08_PRO_FORMA_BS_LEVERAGE!F14 | F43: If you allocate to debt paydown, cash increase is lower.
B44: 3 | C44: Debt paydown uses allocated proceeds | E44: 08_PRO_FORMA_BS_LEVERAGE!F20 | F44: Check sign convention: paydown should reduce debt.
B45: 4 | C45: Net debt post = debt post - cash post | E45: 08_PRO_FORMA_BS_LEVERAGE!F27 | F45: Ensure net debt definition matches company reporting.
B46: 5 | C46: Leverage post = net debt post / EBITDA basis | E46: 08_PRO_FORMA_BS_LEVERAGE!F34 | F46: Confirm EBITDA basis (LTM/NTM) and currency consistency.
B48: Pro forma sanity checks:
B49: • Cash post should increase by at most net primary proceeds (less if allocated to debt paydown).
B50: • Net debt post should decrease when proceeds are used for debt paydown.
B51: • Leverage should improve when net debt decreases, unless EBITDA is stressed or definition changes.

Sheet 90_CHECKS
B1: Dashboard | C1: Control | D1: Issuer | E1: Offer | F1: Checks
B2: Checks | H2: CHECKS: | I2: ='90_CHECKS'!$E$4 | J2: Failed: | K2: ='90_CHECKS'!$E$5
E4: =E7
E5: =E8
B6: OVERALL STATUS
B7: Overall | E7: =IF(MIN($E$13:$E$22)=1,"PASS","FAIL")
B8: Failed checks | E8: =COUNTIF($D$13:$D$22,"FAIL")
B11: CHECK LIST
B12: Category | C12: Check name | D12: Status | E12: Flag (1=pass) | H12: Reference / Notes
B13: TIEOUT | C13: Issuer proceeds tie out (Primary gross - Fees - Net = 0) | D13: =IF($E13=1,"PASS","FAIL") | E13: =--(AND(ABS('07_PROCEEDS_AND_FEES'!E8-'07_PROCEEDS_AND_FEES'!E15-'07_PROCEEDS_AND_FEES'!E16)<0.01,ABS('07_PROCEEDS_AND_FEES'!F8-'07_PROCEEDS_AND_FEES'!F15-'07_PROCEEDS_AND_FEES'!F16)<0.01,ABS('07_PROCEEDS_AND_FEES'!G8-'07_PROCEEDS_AND_FEES'!G15-'07_PROCEEDS_AND_FEES'!G16)<0.01)) | H13: 07_PROCEEDS_AND_FEES rows 8-16
B14: TIEOUT | C14: Gross proceeds split (Total = Primary + Secondary) | D14: =IF($E14=1,"PASS","FAIL") | E14: =--(AND(ABS('07_PROCEEDS_AND_FEES'!E10-('07_PROCEEDS_AND_FEES'!E8+'07_PROCEEDS_AND_FEES'!E9))<0.01,ABS('07_PROCEEDS_AND_FEES'!F10-('07_PROCEEDS_AND_FEES'!F8+'07_PROCEEDS_AND_FEES'!F9))<0.01,ABS('07_PROCEEDS_AND_FEES'!G10-('07_PROCEEDS_AND_FEES'!G8+'07_PROCEEDS_AND_FEES'!G9))<0.01)) | H14: 07_PROCEEDS_AND_FEES rows 8-10
B15: TIEOUT | C15: Cap table tie (Pre + New = Post) | D15: =IF($E15=1,"PASS","FAIL") | E15: =--(AND(ABS('06_CAP_TABLE_OWNERSHIP'!E9+'06_CAP_TABLE_OWNERSHIP'!E12-'06_CAP_TABLE_OWNERSHIP'!E13)<0.001,ABS('06_CAP_TABLE_OWNERSHIP'!F9+'06_CAP_TABLE_OWNERSHIP'!F12-'06_CAP_TABLE_OWNERSHIP'!F13)<0.001,ABS('06_CAP_TABLE_OWNERSHIP'!G9+'06_CAP_TABLE_OWNERSHIP'!G12-'06_CAP_TABLE_OWNERSHIP'!G13)<0.001)) | H15: 06_CAP_TABLE_OWNERSHIP rows 9-13
B16: OWNERSHIP | C16: Shareholder pre % sums to 100% | D16: =IF($E16=1,"PASS","FAIL") | E16: =--(ABS('02_ISSUER_INPUTS'!D23-1)<0.0001) | H16: 02_ISSUER_INPUTS total row
B17: CONTROL | C17: Use of proceeds sums to 100% | D17: =IF($E17=1,"PASS","FAIL") | E17: =--(ABS('01_CONTROL'!E48-1)<0.0001) | H17: 01_CONTROL!E48
B18: RIGHTS | C18: TERP math valid (base) | D18: =IF($E18=1,"PASS","FAIL") | E18: =--(ABS('05_RIGHTS_TERP_ENTITLE'!F12-(('05_RIGHTS_TERP_ENTITLE'!F8*'05_RIGHTS_TERP_ENTITLE'!F10+'05_RIGHTS_TERP_ENTITLE'!F9*'05_RIGHTS_TERP_ENTITLE'!F11)/('05_RIGHTS_TERP_ENTITLE'!F8+'05_RIGHTS_TERP_ENTITLE'!F9)))<0.01) | H18: 05_RIGHTS_TERP_ENTITLE row 12
B19: INTEGRITY | C19: No errors in key output ranges | D19: =IF($E19=1,"PASS","FAIL") | E19: =--(SUMPRODUCT(--ISERROR('04_OFFER_SETUP'!E8:G21),--('04_OFFER_SETUP'!E8:G21<>""))+SUMPRODUCT(--ISERROR('06_CAP_TABLE_OWNERSHIP'!E9:G14),--('06_CAP_TABLE_OWNERSHIP'!E9:G14<>""))+SUMPRODUCT(--ISERROR('07_PROCEEDS_AND_FEES'!E8:G17),--('07_PROCEEDS_AND_FEES'!E8:G17<>""))+SUMPRODUCT(--ISERROR('08_PRO_FORMA_BS_LEVERAGE'!E25:G34),--('08_PRO_FORMA_BS_LEVERAGE'!E25:G34<>""))=0) | H19: ISERROR across key blocks
B20: MANUAL | C20: Iterative calculation OFF (manual) | D20: =IF($E20=1,"PASS","FAIL") | E20: =1 | H20: Manual: ensure iterative calc is OFF
B21: MANUAL | C21: No external links (manual) | D21: =IF($E21=1,"PASS","FAIL") | E21: =1 | H21: Manual: Data > Edit Links should show none
B22: MANUAL | C22: No merged cells (manual) | D22: =IF($E22=1,"PASS","FAIL") | E22: =1 | H22: Manual: Center Across Selection only (no merges)

Sheet 99_APPENDIX_DATA
B1: Dashboard | C1: Control | D1: Issuer | E1: Offer | F1: Checks
B2: Appendix (Paste / raw data) | H2: CHECKS: | I2: ='90_CHECKS'!$E$4 | J2: Failed: | K2: ='90_CHECKS'!$E$5
B4: Use this tab for pasted external data (e.g., shareholder lists, raw pulls). Avoid linking critical outputs here unless clearly labelled.
