Workbook

Sheet 00_DASHBOARD
B2: VALUATION DASHBOARD
B3: All tiles link to output cells in 08_TRIANGULATION_RANGE (or 90_CHECKS for status).
B9: BASE CASE OUTPUTS
B10: Current share price | C10: CCY | F10: ='08_TRIANGULATION_RANGE'!$F$47 | H10: Method | I10: Low | J10: Range
B11: Shares outstanding (mm) | C11: mm | F11: ='08_TRIANGULATION_RANGE'!$F$48 | H11: Comps | I11: ='08_TRIANGULATION_RANGE'!$F$16 | J11: =IFERROR('08_TRIANGULATION_RANGE'!$F$18-'08_TRIANGULATION_RANGE'!$F$16,"")
B12: Market cap | C12: m | F12: ='08_TRIANGULATION_RANGE'!$F$49 | H12: DCF | I12: ='08_TRIANGULATION_RANGE'!$F$26 | J12: =IFERROR('08_TRIANGULATION_RANGE'!$F$28-'08_TRIANGULATION_RANGE'!$F$26,"")
B13: Net debt | C13: m | F13: ='08_TRIANGULATION_RANGE'!$F$50 | H13: Combined | I13: ='08_TRIANGULATION_RANGE'!$F$34 | J13: =IFERROR('08_TRIANGULATION_RANGE'!$F$36-'08_TRIANGULATION_RANGE'!$F$34,"")
B14: Enterprise value | C14: m | F14: ='08_TRIANGULATION_RANGE'!$F$51
B15: Equity value (Base) | C15: m | F15: ='08_TRIANGULATION_RANGE'!$F$64
B16: Implied price per share (Base) | C16: CCY | F16: ='08_TRIANGULATION_RANGE'!$F$52
B17: Upside vs current | C17: % | F17: ='08_TRIANGULATION_RANGE'!$F$53
B18: Downside vs current (Downside) | C18: % | F18: ='08_TRIANGULATION_RANGE'!$F$54
B19: Trading comps multiple used (EV/EBITDA) | C19: x | F19: =08_TRIANGULATION_RANGE!F72
B20: DCF status (ON/OFF) | F20: =08_TRIANGULATION_RANGE!F66
B21: WACC (Base) | C21: % | F21: =08_TRIANGULATION_RANGE!F67
B22: Terminal method | F22: =08_TRIANGULATION_RANGE!F70
B23: Mid-year convention | F23: =08_TRIANGULATION_RANGE!F71
B26: RANGE OUTPUTS
B27: Comps equity value P25 | C27: m | F27: ='08_TRIANGULATION_RANGE'!$F$55
B28: Comps equity value Median | C28: m | F28: ='08_TRIANGULATION_RANGE'!$F$56
B29: Comps equity value P75 | C29: m | F29: ='08_TRIANGULATION_RANGE'!$F$57
B31: DCF equity value Downside | C31: m | F31: ='08_TRIANGULATION_RANGE'!$F$58
B32: DCF equity value Base | C32: m | F32: ='08_TRIANGULATION_RANGE'!$F$59 | H32: Scenario | I32: Combined implied price
B33: DCF equity value Upside | C33: m | F33: ='08_TRIANGULATION_RANGE'!$F$60 | H33: Downside | I33: =='08_TRIANGULATION_RANGE'!$F$61
H34: Base | I34: =='08_TRIANGULATION_RANGE'!$F$62
B35: Combined implied price Downside | C35: CCY | F35: ='08_TRIANGULATION_RANGE'!$F$61 | H35: Upside | I35: =='08_TRIANGULATION_RANGE'!$F$63
B36: Combined implied price Base | C36: CCY | F36: ='08_TRIANGULATION_RANGE'!$F$62
B37: Combined implied price Upside | C37: CCY | F37: ='08_TRIANGULATION_RANGE'!$F$63
B40: CHECKS STATUS (FROM 90_CHECKS) | H40: Sensitivity heatmap (Implied price)
B41: Overall status | F41: ='90_CHECKS'!$F$3 | I41: =IF('01_CONTROL'!$F$15=1,'09_SENSITIVITIES'!G15,'09_SENSITIVITIES'!G25) | J41: =IF('01_CONTROL'!$F$15=1,'09_SENSITIVITIES'!H15,'09_SENSITIVITIES'!H25) | K41: =IF('01_CONTROL'!$F$15=1,'09_SENSITIVITIES'!I15,'09_SENSITIVITIES'!I25) | L41: =IF('01_CONTROL'!$F$15=1,'09_SENSITIVITIES'!J15,'09_SENSITIVITIES'!J25) | M41: =IF('01_CONTROL'!$F$15=1,'09_SENSITIVITIES'!K15,'09_SENSITIVITIES'!K25) | N41: =IF('01_CONTROL'!$F$15=1,'09_SENSITIVITIES'!L15,'09_SENSITIVITIES'!L25)
B42: Fail count | F42: ='90_CHECKS'!$F$4 | H42: =IF('01_CONTROL'!$F$15=1,'09_SENSITIVITIES'!$F$16,'09_SENSITIVITIES'!$F$26) | I42: =IF('01_CONTROL'!$F$15=1,'09_SENSITIVITIES'!G16,'09_SENSITIVITIES'!G26) | J42: =IF('01_CONTROL'!$F$15=1,'09_SENSITIVITIES'!H16,'09_SENSITIVITIES'!H26) | K42: =IF('01_CONTROL'!$F$15=1,'09_SENSITIVITIES'!I16,'09_SENSITIVITIES'!I26) | L42: =IF('01_CONTROL'!$F$15=1,'09_SENSITIVITIES'!J16,'09_SENSITIVITIES'!J26) | M42: =IF('01_CONTROL'!$F$15=1,'09_SENSITIVITIES'!K16,'09_SENSITIVITIES'!K26) | N42: =IF('01_CONTROL'!$F$15=1,'09_SENSITIVITIES'!L16,'09_SENSITIVITIES'!L26)
H43: =IF('01_CONTROL'!$F$15=1,'09_SENSITIVITIES'!$F$17,'09_SENSITIVITIES'!$F$27) | I43: =IF('01_CONTROL'!$F$15=1,'09_SENSITIVITIES'!G17,'09_SENSITIVITIES'!G27) | J43: =IF('01_CONTROL'!$F$15=1,'09_SENSITIVITIES'!H17,'09_SENSITIVITIES'!H27) | K43: =IF('01_CONTROL'!$F$15=1,'09_SENSITIVITIES'!I17,'09_SENSITIVITIES'!I27) | L43: =IF('01_CONTROL'!$F$15=1,'09_SENSITIVITIES'!J17,'09_SENSITIVITIES'!J27) | M43: =IF('01_CONTROL'!$F$15=1,'09_SENSITIVITIES'!K17,'09_SENSITIVITIES'!K27) | N43: =IF('01_CONTROL'!$F$15=1,'09_SENSITIVITIES'!L17,'09_SENSITIVITIES'!L27)
B44: Top 5 checks | H44: =IF('01_CONTROL'!$F$15=1,'09_SENSITIVITIES'!$F$18,'09_SENSITIVITIES'!$F$28) | I44: =IF('01_CONTROL'!$F$15=1,'09_SENSITIVITIES'!G18,'09_SENSITIVITIES'!G28) | J44: =IF('01_CONTROL'!$F$15=1,'09_SENSITIVITIES'!H18,'09_SENSITIVITIES'!H28) | K44: =IF('01_CONTROL'!$F$15=1,'09_SENSITIVITIES'!I18,'09_SENSITIVITIES'!I28) | L44: =IF('01_CONTROL'!$F$15=1,'09_SENSITIVITIES'!J18,'09_SENSITIVITIES'!J28) | M44: =IF('01_CONTROL'!$F$15=1,'09_SENSITIVITIES'!K18,'09_SENSITIVITIES'!K28) | N44: =IF('01_CONTROL'!$F$15=1,'09_SENSITIVITIES'!L18,'09_SENSITIVITIES'!L28)
B45: 1. | C45: ='90_CHECKS'!$B$9 | F45: ='90_CHECKS'!$G$9 | H45: =IF('01_CONTROL'!$F$15=1,'09_SENSITIVITIES'!$F$19,'09_SENSITIVITIES'!$F$29) | I45: =IF('01_CONTROL'!$F$15=1,'09_SENSITIVITIES'!G19,'09_SENSITIVITIES'!G29) | J45: =IF('01_CONTROL'!$F$15=1,'09_SENSITIVITIES'!H19,'09_SENSITIVITIES'!H29) | K45: =IF('01_CONTROL'!$F$15=1,'09_SENSITIVITIES'!I19,'09_SENSITIVITIES'!I29) | L45: =IF('01_CONTROL'!$F$15=1,'09_SENSITIVITIES'!J19,'09_SENSITIVITIES'!J29) | M45: =IF('01_CONTROL'!$F$15=1,'09_SENSITIVITIES'!K19,'09_SENSITIVITIES'!K29) | N45: =IF('01_CONTROL'!$F$15=1,'09_SENSITIVITIES'!L19,'09_SENSITIVITIES'!L29)
B46: 2. | C46: ='90_CHECKS'!$B$10 | F46: ='90_CHECKS'!$G$10 | H46: =IF('01_CONTROL'!$F$15=1,'09_SENSITIVITIES'!$F$20,'09_SENSITIVITIES'!$F$30) | I46: =IF('01_CONTROL'!$F$15=1,'09_SENSITIVITIES'!G20,'09_SENSITIVITIES'!G30) | J46: =IF('01_CONTROL'!$F$15=1,'09_SENSITIVITIES'!H20,'09_SENSITIVITIES'!H30) | K46: =IF('01_CONTROL'!$F$15=1,'09_SENSITIVITIES'!I20,'09_SENSITIVITIES'!I30) | L46: =IF('01_CONTROL'!$F$15=1,'09_SENSITIVITIES'!J20,'09_SENSITIVITIES'!J30) | M46: =IF('01_CONTROL'!$F$15=1,'09_SENSITIVITIES'!K20,'09_SENSITIVITIES'!K30) | N46: =IF('01_CONTROL'!$F$15=1,'09_SENSITIVITIES'!L20,'09_SENSITIVITIES'!L30)
B47: 3. | C47: ='90_CHECKS'!$B$11 | F47: ='90_CHECKS'!$G$11 | H47: =IF('01_CONTROL'!$F$15=1,'09_SENSITIVITIES'!$F$21,'09_SENSITIVITIES'!$F$31) | I47: =IF('01_CONTROL'!$F$15=1,'09_SENSITIVITIES'!G21,'09_SENSITIVITIES'!G31) | J47: =IF('01_CONTROL'!$F$15=1,'09_SENSITIVITIES'!H21,'09_SENSITIVITIES'!H31) | K47: =IF('01_CONTROL'!$F$15=1,'09_SENSITIVITIES'!I21,'09_SENSITIVITIES'!I31) | L47: =IF('01_CONTROL'!$F$15=1,'09_SENSITIVITIES'!J21,'09_SENSITIVITIES'!J31) | M47: =IF('01_CONTROL'!$F$15=1,'09_SENSITIVITIES'!K21,'09_SENSITIVITIES'!K31) | N47: =IF('01_CONTROL'!$F$15=1,'09_SENSITIVITIES'!L21,'09_SENSITIVITIES'!L31)
B48: 4. | C48: ='90_CHECKS'!$B$12 | F48: ='90_CHECKS'!$G$12
B49: 5. | C49: ='90_CHECKS'!$B$13 | F49: ='90_CHECKS'!$G$13
B52: INTERPRETATION (AUTO FILLED WHERE POSSIBLE)
B53: What drives valuation today | F53: ="Comps EV/EBITDA x "&TEXT('05_TRADING_COMPS'!$F$32,"0.0")&", DCF "&'01_CONTROL'!$F$12
B54: Biggest sensitivities | F54: ="WACC "&TEXT('06_DCF_WACC'!$F$20,"0.0%")&" and terminal assumptions (see 09_SENSITIVITIES)"
B55: Red flag checks | F55: ="Status: "&'90_CHECKS'!$F$3&" (fails: "&TEXT('90_CHECKS'!$F$4,"0")&")"
B56: Key accounting adjustments used | F56: ="None (template). Add adjustments in 02_COMPANY_INPUTS if needed."
B57: What would change conclusion | F57: ="Change scenario (01_CONTROL) or update peer set / multiple selection (05_TRADING_COMPS)."

Sheet 01_CONTROL
B2: 01_CONTROL
B3: Model
B4: Company
B5: Version
B6: Last updated | F6: =TODAY()
B8: SECTION
B9: Scenario (Base/Upside/Downside) | F9: Base
B10: Scenario index | F10: =MATCH(F9,{"Base","Upside","Downside"},0)
B11: Forecast horizon (years) | F11: 5
B12: DCF (ON/OFF) | F12: ON
B13: DCF flag | F13: =IF(F12="ON",1,0)
B14: Terminal method | F14: Perpetuity
B15: TV method flag (1=Perpetuity) | F15: =IF(F14="Perpetuity",1,0)
B16: Mid-year convention (ON/OFF) | F16: OFF
B17: Mid-year flag | F17: =IF(F16="ON",1,0)
B18: Currency | F18: DKK
B19: Units | F19: DKKm
B20: Shares units | F20: Shares in millions
B23: WACC ASSUMPTIONS
B24: Tax rate | F24: 0.22
B25: Risk-free rate | F25: 0.03
B26: Equity risk premium | F26: 0.05
B27: Beta | F27: 1
B28: Size / country adj (optional) | F28: 0
B29: Pre-tax cost of debt | F29: 0.05
B30: Target debt weight | F30: 0.3
B31: Target equity weight | F31: 0.7
B32: Weights sum to 100% | F32: =F30+F31
B34: Cost of equity | F34: =F25 + F27*F26 + F28
B35: After-tax cost of debt | F35: =F29*(1-F24)
B36: WACC (base) | F36: =F31*F34 + F30*F35
B40: NET DEBT DEFINITION TOGGLES
B41: Include leases in net debt | E41: Flag | F41: YES | G41: =IF(F41="YES",1,0)
B42: Include pension | E42: Flag | F42: NO | G42: =IF(F42="YES",1,0)
B43: Include minorities | E43: Flag | F43: YES | G43: =IF(F43="YES",1,0)
B44: Include investments | E44: Flag | F44: NO | G44: =IF(F44="YES",1,0)
B45: Include other adjustments | E45: Flag | F45: YES | G45: =IF(F45="YES",1,0)
B47: MODEL CALENDAR
B48: Base year (FY0) | F48: 2025
B50: Period index | F50: 0 | G50: 1 | H50: 2 | I50: 3 | J50: 4 | K50: 5 | L50: 6 | M50: 7 | N50: 8 | O50: 9 | P50: 10
B51: Fiscal year | F51: =$F$48+F50 | G51: =$F$48+G50 | H51: =$F$48+H50 | I51: =$F$48+I50 | J51: =$F$48+J50 | K51: =$F$48+K50 | L51: =$F$48+L50 | M51: =$F$48+M50 | ... P51: =$F$48+P50
B52: Active horizon flag | F52: =IF(F50<=$F$11,1,0) | G52: =IF(G50<=$F$11,1,0) | H52: =IF(H50<=$F$11,1,0) | I52: =IF(I50<=$F$11,1,0) | J52: =IF(J50<=$F$11,1,0) | K52: =IF(K50<=$F$11,1,0) | L52: =IF(L50<=$F$11,1,0) | M52: =IF(M50<=$F$11,1,0) | ... P52: =IF(P50<=$F$11,1,0)
B53: Discount t | F53: =F50 | G53: =G50 | H53: =H50 | I53: =I50 | J53: =J50 | K53: =K50 | L53: =L50 | M53: =M50 | ... P53: =P50
B57: FORECAST DRIVER INPUTS (SCENARIO-BASED)
F58: BASE (FY0..FY10) | R58: UPSIDE (FY0..FY10) | AD58: DOWNSIDE (FY0..FY10)
B59: Driver | C59: Units
B60: Revenue growth | C60: % | F60: 0 | G60: 0.05 | H60: 0.05 | I60: 0.05 | J60: 0.05 | K60: 0.05 | L60: 0.05 | M60: 0.05 | N60: 0.05 | O60: 0.05 | P60: 0.05 | R60: 0 | S60: 0.07 | T60: 0.07 | U60: 0.07 | V60: 0.07 | W60: 0.07 | X60: 0.07 | Y60: 0.07 | Z60: 0.07 | AA60: 0.07 | AB60: 0.07 | AD60: 0 | AE60: 0.03 | AF60: 0.03 | AG60: 0.03 | AH60: 0.03 | AI60: 0.03 | AJ60: 0.03 | AK60: 0.03 | AL60: 0.03 | AM60: 0.03 | AN60: 0.03
B61: EBITDA margin | C61: % | F61: 0 | G61: 0.2 | H61: 0.2 | I61: 0.2 | J61: 0.2 | K61: 0.2 | L61: 0.2 | M61: 0.2 | N61: 0.2 | O61: 0.2 | P61: 0.2 | R61: 0 | S61: 0.22 | T61: 0.22 | U61: 0.22 | V61: 0.22 | W61: 0.22 | X61: 0.22 | Y61: 0.22 | Z61: 0.22 | AA61: 0.22 | AB61: 0.22 | AD61: 0 | AE61: 0.18 | AF61: 0.18 | AG61: 0.18 | AH61: 0.18 | AI61: 0.18 | AJ61: 0.18 | AK61: 0.18 | AL61: 0.18 | AM61: 0.18 | AN61: 0.18
B62: D&A % of revenue | C62: % | F62: 0 | G62: 0.03 | H62: 0.03 | I62: 0.03 | J62: 0.03 | K62: 0.03 | L62: 0.03 | M62: 0.03 | N62: 0.03 | O62: 0.03 | P62: 0.03 | R62: 0 | S62: 0.03 | T62: 0.03 | U62: 0.03 | V62: 0.03 | W62: 0.03 | X62: 0.03 | Y62: 0.03 | Z62: 0.03 | AA62: 0.03 | AB62: 0.03 | AD62: 0 | AE62: 0.03 | AF62: 0.03 | AG62: 0.03 | AH62: 0.03 | AI62: 0.03 | AJ62: 0.03 | AK62: 0.03 | AL62: 0.03 | AM62: 0.03 | AN62: 0.03
B63: Capex % of revenue | C63: % | F63: 0 | G63: 0.04 | H63: 0.04 | I63: 0.04 | J63: 0.04 | K63: 0.04 | L63: 0.04 | M63: 0.04 | N63: 0.04 | O63: 0.04 | P63: 0.04 | R63: 0 | S63: 0.05 | T63: 0.05 | U63: 0.05 | V63: 0.05 | W63: 0.05 | X63: 0.05 | Y63: 0.05 | Z63: 0.05 | AA63: 0.05 | AB63: 0.05 | AD63: 0 | AE63: 0.03 | AF63: 0.03 | AG63: 0.03 | AH63: 0.03 | AI63: 0.03 | AJ63: 0.03 | AK63: 0.03 | AL63: 0.03 | AM63: 0.03 | AN63: 0.03
B64: NWC % of revenue | C64: % | F64: 0 | G64: 0.05 | H64: 0.05 | I64: 0.05 | J64: 0.05 | K64: 0.05 | L64: 0.05 | M64: 0.05 | N64: 0.05 | O64: 0.05 | P64: 0.05 | R64: 0 | S64: 0.04 | T64: 0.04 | U64: 0.04 | V64: 0.04 | W64: 0.04 | X64: 0.04 | Y64: 0.04 | Z64: 0.04 | AA64: 0.04 | AB64: 0.04 | AD64: 0 | AE64: 0.06 | AF64: 0.06 | AG64: 0.06 | AH64: 0.06 | AI64: 0.06 | AJ64: 0.06 | AK64: 0.06 | AL64: 0.06 | AM64: 0.06 | AN64: 0.06
B67: Terminal growth g | C67: % | F67: 0.025 | R67: 0.03 | AD67: 0.02
B68: Exit multiple (EV/EBITDA) | C68: x | F68: 10 | R68: 11 | AD68: 9
B71: SELECTED SCENARIO VIEW (USED BY FORECAST)
B72: (auto: CHOOSE by scenario index)
B73: Revenue growth | C73: % | F73: =CHOOSE($F$10,F60,R60,AD60) | G73: =CHOOSE($F$10,G60,S60,AE60) | H73: =CHOOSE($F$10,H60,T60,AF60) | I73: =CHOOSE($F$10,I60,U60,AG60) | J73: =CHOOSE($F$10,J60,V60,AH60) | K73: =CHOOSE($F$10,K60,W60,AI60) | L73: =CHOOSE($F$10,L60,X60,AJ60) | M73: =CHOOSE($F$10,M60,Y60,AK60) | ... P73: =CHOOSE($F$10,P60,AB60,AN60)
B74: EBITDA margin | C74: % | F74: =CHOOSE($F$10,F61,R61,AD61) | G74: =CHOOSE($F$10,G61,S61,AE61) | H74: =CHOOSE($F$10,H61,T61,AF61) | I74: =CHOOSE($F$10,I61,U61,AG61) | J74: =CHOOSE($F$10,J61,V61,AH61) | K74: =CHOOSE($F$10,K61,W61,AI61) | L74: =CHOOSE($F$10,L61,X61,AJ61) | M74: =CHOOSE($F$10,M61,Y61,AK61) | ... P74: =CHOOSE($F$10,P61,AB61,AN61)
B75: D&A % of revenue | C75: % | F75: =CHOOSE($F$10,F62,R62,AD62) | G75: =CHOOSE($F$10,G62,S62,AE62) | H75: =CHOOSE($F$10,H62,T62,AF62) | I75: =CHOOSE($F$10,I62,U62,AG62) | J75: =CHOOSE($F$10,J62,V62,AH62) | K75: =CHOOSE($F$10,K62,W62,AI62) | L75: =CHOOSE($F$10,L62,X62,AJ62) | M75: =CHOOSE($F$10,M62,Y62,AK62) | ... P75: =CHOOSE($F$10,P62,AB62,AN62)
B76: Capex % of revenue | C76: % | F76: =CHOOSE($F$10,F63,R63,AD63) | G76: =CHOOSE($F$10,G63,S63,AE63) | H76: =CHOOSE($F$10,H63,T63,AF63) | I76: =CHOOSE($F$10,I63,U63,AG63) | J76: =CHOOSE($F$10,J63,V63,AH63) | K76: =CHOOSE($F$10,K63,W63,AI63) | L76: =CHOOSE($F$10,L63,X63,AJ63) | M76: =CHOOSE($F$10,M63,Y63,AK63) | ... P76: =CHOOSE($F$10,P63,AB63,AN63)
B77: NWC % of revenue | C77: % | F77: =CHOOSE($F$10,F64,R64,AD64) | G77: =CHOOSE($F$10,G64,S64,AE64) | H77: =CHOOSE($F$10,H64,T64,AF64) | I77: =CHOOSE($F$10,I64,U64,AG64) | J77: =CHOOSE($F$10,J64,V64,AH64) | K77: =CHOOSE($F$10,K64,W64,AI64) | L77: =CHOOSE($F$10,L64,X64,AJ64) | M77: =CHOOSE($F$10,M64,Y64,AK64) | ... P77: =CHOOSE($F$10,P64,AB64,AN64)
B79: Selected terminal growth g | C79: % | F79: =CHOOSE($F$10,F67,R67,AD67)
B80: Selected exit multiple | C80: x | F80: =CHOOSE($F$10,F68,R68,AD68)
B83: COMPS MULTIPLE OVERRIDE (OPTIONAL)
B84: Override comps multiple? (TRUE/FALSE) | F84: FALSE
B85: Override EV/EBITDA multiple (x) | C85: x | F85: 10
B86: Comps multiple used (output) | C86: x | F86: =05_TRADING_COMPS!F32

Sheet 02_COMPANY_INPUTS
B2: 02_COMPANY_INPUTS
B3: Model
B4: Company
B5: Version
B6: Last updated | F6: =TODAY()
B8: SECTION
B9: EQUITY AND MARKET DATA
B10: Current share price | C10: CCY
B11: Shares outstanding (mm) | C11: mm
B12: Market cap | C12: m | F12: =IF(OR(F10="",F11=""),"",F10*F11)
B15: NET DEBT BRIDGE INPUTS
B16: Cash and equivalents | C16: m
B17: Gross debt | C17: m
B18: Lease liabilities | C18: m
B19: Pension liabilities | C19: m
B20: Minority interests | C20: m
B21: Investments / associates | C21: m
B22: Other adjustments | C22: m
B24: NET DEBT (PER TOGGLES)
B25: Include flags (from 01_CONTROL)
B26: Net debt (output) | C26: m | F26: =IF(COUNTA(F16:F22)=0,"",IFERROR(F17+'01_CONTROL'!$G$41*F18+'01_CONTROL'!$G$42*F19+'01_CONTROL'!$G$43*F20-F16-'01_CONTROL'!$G$44*F21+'01_CONTROL'!$G$45*F22,""))
B29: LTM KEY METRICS (INPUTS)
B30: LTM revenue | C30: m
B31: LTM EBITDA | C31: m
B32: LTM EBIT | C32: m
B33: LTM D&A | C33: m
B34: LTM capex | C34: m
B35: LTM NWC | C35: m
B37: DERIVED RATIOS (CALC)
B38: EBITDA margin | C38: % | F38: =IF($F$30="","",IFERROR($F$31/$F$30,""))
B39: D&A % of revenue | C39: % | F39: =IF($F$30="","",IFERROR($F$33/$F$30,""))
B40: Capex % of revenue | C40: % | F40: =IF($F$30="","",IFERROR($F$34/$F$30,""))
B41: NWC % of revenue | C41: % | F41: =IF($F$30="","",IFERROR($F$35/$F$30,""))

Sheet 03_HISTORICALS
B2: 03_HISTORICALS
B3: Model
B4: Company
B5: Version
B6: Last updated | F6: =TODAY()
B8: SECTION
B9: INCOME STATEMENT (HISTORICAL)
F10: FY-2 | G10: FY-1 | H10: FY0 | I10: LTM
B11: Revenue | C11: m
B12: EBITDA | C12: m
B13: D&A | C13: m
B14: EBIT | C14: m
B15: Taxes | C15: m
B16: Net income | C16: m
B17: EBITDA margin | C17: % | F17: =IFERROR(F12/F11,"") | G17: =IFERROR(G12/G11,"") | H17: =IFERROR(H12/H11,"") | I17: =IFERROR(I12/I11,"")
B19: BALANCE SHEET (WORKING CAPITAL)
F20: FY-2 | G20: FY-1 | H20: FY0 | I20: LTM
B21: Accounts receivable | C21: m
B22: Inventory | C22: m
B23: Accounts payable | C23: m
B24: Other current assets | C24: m
B25: Other current liabilities | C25: m
B26: Net working capital | C26: m
B27: PP&E (net) | C27: m
B29: CASH FLOW (KEY LINES)
F30: FY-2 | G30: FY-1 | H30: FY0 | I30: LTM
B31: D&A | C31: m
B32: Capex | C32: m
B33: Change in NWC | C33: m
B34: Unlevered FCF (proxy) | C34: m

Sheet 04_DRIVERS_AND_FORECAST
B2: 04_DRIVERS_AND_FORECAST
B3: Model
B4: Company
B5: Version
B6: Last updated | F6: =TODAY()
B8: SECTION
B9: CALENDAR
B10: Fiscal year | F10: ='01_CONTROL'!F51 | G10: ='01_CONTROL'!G51 | H10: ='01_CONTROL'!H51 | I10: ='01_CONTROL'!I51 | J10: ='01_CONTROL'!J51 | K10: ='01_CONTROL'!K51 | L10: ='01_CONTROL'!L51 | M10: ='01_CONTROL'!M51 | ... P10: ='01_CONTROL'!P51
B12: BASE CASE FORECAST
B13: Revenue | C13: m | F13: =IF('02_COMPANY_INPUTS'!$F$30="","",'02_COMPANY_INPUTS'!$F$30) | G13: =IF(OR('01_CONTROL'!G52<>1,F13=""),"",F13*(1+'01_CONTROL'!G60)) | H13: =IF(OR('01_CONTROL'!H52<>1,G13=""),"",G13*(1+'01_CONTROL'!H60)) | I13: =IF(OR('01_CONTROL'!I52<>1,H13=""),"",H13*(1+'01_CONTROL'!I60)) | J13: =IF(OR('01_CONTROL'!J52<>1,I13=""),"",I13*(1+'01_CONTROL'!J60)) | K13: =IF(OR('01_CONTROL'!K52<>1,J13=""),"",J13*(1+'01_CONTROL'!K60)) | L13: =IF(OR('01_CONTROL'!L52<>1,K13=""),"",K13*(1+'01_CONTROL'!L60)) | M13: =IF(OR('01_CONTROL'!M52<>1,L13=""),"",L13*(1+'01_CONTROL'!M60)) | N13: =IF(OR('01_CONTROL'!N52<>1,M13=""),"",M13*(1+'01_CONTROL'!N60)) | ... P13: =IF(OR('01_CONTROL'!P52<>1,O13=""),"",O13*(1+'01_CONTROL'!P60))
B14: EBITDA | C14: m | F14: =IF('02_COMPANY_INPUTS'!$F$31="","",'02_COMPANY_INPUTS'!$F$31) | G14: =IF(G13="","",G13*'01_CONTROL'!G61) | H14: =IF(H13="","",H13*'01_CONTROL'!H61) | I14: =IF(I13="","",I13*'01_CONTROL'!I61) | J14: =IF(J13="","",J13*'01_CONTROL'!J61) | K14: =IF(K13="","",K13*'01_CONTROL'!K61) | L14: =IF(L13="","",L13*'01_CONTROL'!L61) | M14: =IF(M13="","",M13*'01_CONTROL'!M61) | N14: =IF(N13="","",N13*'01_CONTROL'!N61) | ... P14: =IF(P13="","",P13*'01_CONTROL'!P61)
B15: D&A | C15: m | F15: =IF('02_COMPANY_INPUTS'!$F$33="","",'02_COMPANY_INPUTS'!$F$33) | G15: =IF(G13="","",G13*'01_CONTROL'!G62) | H15: =IF(H13="","",H13*'01_CONTROL'!H62) | I15: =IF(I13="","",I13*'01_CONTROL'!I62) | J15: =IF(J13="","",J13*'01_CONTROL'!J62) | K15: =IF(K13="","",K13*'01_CONTROL'!K62) | L15: =IF(L13="","",L13*'01_CONTROL'!L62) | M15: =IF(M13="","",M13*'01_CONTROL'!M62) | N15: =IF(N13="","",N13*'01_CONTROL'!N62) | ... P15: =IF(P13="","",P13*'01_CONTROL'!P62)
B16: EBIT | C16: m | F16: =IF(F14="","",F14-F15) | G16: =IF(G14="","",G14-G15) | H16: =IF(H14="","",H14-H15) | I16: =IF(I14="","",I14-I15) | J16: =IF(J14="","",J14-J15) | K16: =IF(K14="","",K14-K15) | L16: =IF(L14="","",L14-L15) | M16: =IF(M14="","",M14-M15) | ... P16: =IF(P14="","",P14-P15)
B17: Taxes on EBIT | C17: m | F17: =IF(F16="","",MAX(0,F16)*'01_CONTROL'!$F$24) | G17: =IF(G16="","",MAX(0,G16)*'01_CONTROL'!$F$24) | H17: =IF(H16="","",MAX(0,H16)*'01_CONTROL'!$F$24) | I17: =IF(I16="","",MAX(0,I16)*'01_CONTROL'!$F$24) | J17: =IF(J16="","",MAX(0,J16)*'01_CONTROL'!$F$24) | K17: =IF(K16="","",MAX(0,K16)*'01_CONTROL'!$F$24) | L17: =IF(L16="","",MAX(0,L16)*'01_CONTROL'!$F$24) | M17: =IF(M16="","",MAX(0,M16)*'01_CONTROL'!$F$24) | ... P17: =IF(P16="","",MAX(0,P16)*'01_CONTROL'!$F$24)
B18: NOPAT | C18: m | F18: =IF(F16="","",F16*(1-'01_CONTROL'!$F$24)) | G18: =IF(G16="","",G16*(1-'01_CONTROL'!$F$24)) | H18: =IF(H16="","",H16*(1-'01_CONTROL'!$F$24)) | I18: =IF(I16="","",I16*(1-'01_CONTROL'!$F$24)) | J18: =IF(J16="","",J16*(1-'01_CONTROL'!$F$24)) | K18: =IF(K16="","",K16*(1-'01_CONTROL'!$F$24)) | L18: =IF(L16="","",L16*(1-'01_CONTROL'!$F$24)) | M18: =IF(M16="","",M16*(1-'01_CONTROL'!$F$24)) | ... P18: =IF(P16="","",P16*(1-'01_CONTROL'!$F$24))
B19: Net working capital | C19: m | F19: =IF('02_COMPANY_INPUTS'!$F$35="","",'02_COMPANY_INPUTS'!$F$35) | G19: =IF(G13="","",G13*'01_CONTROL'!G64) | H19: =IF(H13="","",H13*'01_CONTROL'!H64) | I19: =IF(I13="","",I13*'01_CONTROL'!I64) | J19: =IF(J13="","",J13*'01_CONTROL'!J64) | K19: =IF(K13="","",K13*'01_CONTROL'!K64) | L19: =IF(L13="","",L13*'01_CONTROL'!L64) | M19: =IF(M13="","",M13*'01_CONTROL'!M64) | N19: =IF(N13="","",N13*'01_CONTROL'!N64) | ... P19: =IF(P13="","",P13*'01_CONTROL'!P64)
B20: Change in NWC | C20: m | F20: ="" | G20: =IF(G19="","",G19-F19) | H20: =IF(H19="","",H19-G19) | I20: =IF(I19="","",I19-H19) | J20: =IF(J19="","",J19-I19) | K20: =IF(K19="","",K19-J19) | L20: =IF(L19="","",L19-K19) | M20: =IF(M19="","",M19-L19) | N20: =IF(N19="","",N19-M19) | ... P20: =IF(P19="","",P19-O19)
B21: Capex | C21: m | F21: =IF('02_COMPANY_INPUTS'!$F$34="","",'02_COMPANY_INPUTS'!$F$34) | G21: =IF(G13="","",G13*'01_CONTROL'!G63) | H21: =IF(H13="","",H13*'01_CONTROL'!H63) | I21: =IF(I13="","",I13*'01_CONTROL'!I63) | J21: =IF(J13="","",J13*'01_CONTROL'!J63) | K21: =IF(K13="","",K13*'01_CONTROL'!K63) | L21: =IF(L13="","",L13*'01_CONTROL'!L63) | M21: =IF(M13="","",M13*'01_CONTROL'!M63) | N21: =IF(N13="","",N13*'01_CONTROL'!N63) | ... P21: =IF(P13="","",P13*'01_CONTROL'!P63)
B22: Unlevered FCF | C22: m | F22: =IF(F18="","",F18+F15-F21-F20) | G22: =IF(G18="","",G18+G15-G21-G20) | H22: =IF(H18="","",H18+H15-H21-H20) | I22: =IF(I18="","",I18+I15-I21-I20) | J22: =IF(J18="","",J18+J15-J21-J20) | K22: =IF(K18="","",K18+K15-K21-K20) | L22: =IF(L18="","",L18+L15-L21-L20) | M22: =IF(M18="","",M18+M15-M21-M20) | ... P22: =IF(P18="","",P18+P15-P21-P20)
B25: UPSIDE FORECAST
B26: Revenue | C26: m | F26: =IF('02_COMPANY_INPUTS'!$F$30="","",'02_COMPANY_INPUTS'!$F$30) | G26: =IF(OR('01_CONTROL'!G52<>1,F26=""),"",F26*(1+'01_CONTROL'!S60)) | H26: =IF(OR('01_CONTROL'!H52<>1,G26=""),"",G26*(1+'01_CONTROL'!T60)) | I26: =IF(OR('01_CONTROL'!I52<>1,H26=""),"",H26*(1+'01_CONTROL'!U60)) | J26: =IF(OR('01_CONTROL'!J52<>1,I26=""),"",I26*(1+'01_CONTROL'!V60)) | K26: =IF(OR('01_CONTROL'!K52<>1,J26=""),"",J26*(1+'01_CONTROL'!W60)) | L26: =IF(OR('01_CONTROL'!L52<>1,K26=""),"",K26*(1+'01_CONTROL'!X60)) | M26: =IF(OR('01_CONTROL'!M52<>1,L26=""),"",L26*(1+'01_CONTROL'!Y60)) | N26: =IF(OR('01_CONTROL'!N52<>1,M26=""),"",M26*(1+'01_CONTROL'!Z60)) | ... P26: =IF(OR('01_CONTROL'!P52<>1,O26=""),"",O26*(1+'01_CONTROL'!AB60))
B27: EBITDA | C27: m | F27: =IF('02_COMPANY_INPUTS'!$F$31="","",'02_COMPANY_INPUTS'!$F$31) | G27: =IF(G26="","",G26*'01_CONTROL'!S61) | H27: =IF(H26="","",H26*'01_CONTROL'!T61) | I27: =IF(I26="","",I26*'01_CONTROL'!U61) | J27: =IF(J26="","",J26*'01_CONTROL'!V61) | K27: =IF(K26="","",K26*'01_CONTROL'!W61) | L27: =IF(L26="","",L26*'01_CONTROL'!X61) | M27: =IF(M26="","",M26*'01_CONTROL'!Y61) | N27: =IF(N26="","",N26*'01_CONTROL'!Z61) | ... P27: =IF(P26="","",P26*'01_CONTROL'!AB61)
B28: D&A | C28: m | F28: =IF('02_COMPANY_INPUTS'!$F$33="","",'02_COMPANY_INPUTS'!$F$33) | G28: =IF(G26="","",G26*'01_CONTROL'!S62) | H28: =IF(H26="","",H26*'01_CONTROL'!T62) | I28: =IF(I26="","",I26*'01_CONTROL'!U62) | J28: =IF(J26="","",J26*'01_CONTROL'!V62) | K28: =IF(K26="","",K26*'01_CONTROL'!W62) | L28: =IF(L26="","",L26*'01_CONTROL'!X62) | M28: =IF(M26="","",M26*'01_CONTROL'!Y62) | N28: =IF(N26="","",N26*'01_CONTROL'!Z62) | ... P28: =IF(P26="","",P26*'01_CONTROL'!AB62)
B29: EBIT | C29: m | F29: =IF(F27="","",F27-F28) | G29: =IF(G27="","",G27-G28) | H29: =IF(H27="","",H27-H28) | I29: =IF(I27="","",I27-I28) | J29: =IF(J27="","",J27-J28) | K29: =IF(K27="","",K27-K28) | L29: =IF(L27="","",L27-L28) | M29: =IF(M27="","",M27-M28) | ... P29: =IF(P27="","",P27-P28)
B30: Taxes on EBIT | C30: m | F30: =IF(F29="","",MAX(0,F29)*'01_CONTROL'!$F$24) | G30: =IF(G29="","",MAX(0,G29)*'01_CONTROL'!$F$24) | H30: =IF(H29="","",MAX(0,H29)*'01_CONTROL'!$F$24) | I30: =IF(I29="","",MAX(0,I29)*'01_CONTROL'!$F$24) | J30: =IF(J29="","",MAX(0,J29)*'01_CONTROL'!$F$24) | K30: =IF(K29="","",MAX(0,K29)*'01_CONTROL'!$F$24) | L30: =IF(L29="","",MAX(0,L29)*'01_CONTROL'!$F$24) | M30: =IF(M29="","",MAX(0,M29)*'01_CONTROL'!$F$24) | ... P30: =IF(P29="","",MAX(0,P29)*'01_CONTROL'!$F$24)
B31: NOPAT | C31: m | F31: =IF(F29="","",F29*(1-'01_CONTROL'!$F$24)) | G31: =IF(G29="","",G29*(1-'01_CONTROL'!$F$24)) | H31: =IF(H29="","",H29*(1-'01_CONTROL'!$F$24)) | I31: =IF(I29="","",I29*(1-'01_CONTROL'!$F$24)) | J31: =IF(J29="","",J29*(1-'01_CONTROL'!$F$24)) | K31: =IF(K29="","",K29*(1-'01_CONTROL'!$F$24)) | L31: =IF(L29="","",L29*(1-'01_CONTROL'!$F$24)) | M31: =IF(M29="","",M29*(1-'01_CONTROL'!$F$24)) | ... P31: =IF(P29="","",P29*(1-'01_CONTROL'!$F$24))
B32: Net working capital | C32: m | F32: =IF('02_COMPANY_INPUTS'!$F$35="","",'02_COMPANY_INPUTS'!$F$35) | G32: =IF(G26="","",G26*'01_CONTROL'!S64) | H32: =IF(H26="","",H26*'01_CONTROL'!T64) | I32: =IF(I26="","",I26*'01_CONTROL'!U64) | J32: =IF(J26="","",J26*'01_CONTROL'!V64) | K32: =IF(K26="","",K26*'01_CONTROL'!W64) | L32: =IF(L26="","",L26*'01_CONTROL'!X64) | M32: =IF(M26="","",M26*'01_CONTROL'!Y64) | N32: =IF(N26="","",N26*'01_CONTROL'!Z64) | ... P32: =IF(P26="","",P26*'01_CONTROL'!AB64)
B33: Change in NWC | C33: m | F33: ="" | G33: =IF(G32="","",G32-F32) | H33: =IF(H32="","",H32-G32) | I33: =IF(I32="","",I32-H32) | J33: =IF(J32="","",J32-I32) | K33: =IF(K32="","",K32-J32) | L33: =IF(L32="","",L32-K32) | M33: =IF(M32="","",M32-L32) | N33: =IF(N32="","",N32-M32) | ... P33: =IF(P32="","",P32-O32)
B34: Capex | C34: m | F34: =IF('02_COMPANY_INPUTS'!$F$34="","",'02_COMPANY_INPUTS'!$F$34) | G34: =IF(G26="","",G26*'01_CONTROL'!S63) | H34: =IF(H26="","",H26*'01_CONTROL'!T63) | I34: =IF(I26="","",I26*'01_CONTROL'!U63) | J34: =IF(J26="","",J26*'01_CONTROL'!V63) | K34: =IF(K26="","",K26*'01_CONTROL'!W63) | L34: =IF(L26="","",L26*'01_CONTROL'!X63) | M34: =IF(M26="","",M26*'01_CONTROL'!Y63) | N34: =IF(N26="","",N26*'01_CONTROL'!Z63) | ... P34: =IF(P26="","",P26*'01_CONTROL'!AB63)
B35: Unlevered FCF | C35: m | F35: =IF(F31="","",F31+F28-F34-F33) | G35: =IF(G31="","",G31+G28-G34-G33) | H35: =IF(H31="","",H31+H28-H34-H33) | I35: =IF(I31="","",I31+I28-I34-I33) | J35: =IF(J31="","",J31+J28-J34-J33) | K35: =IF(K31="","",K31+K28-K34-K33) | L35: =IF(L31="","",L31+L28-L34-L33) | M35: =IF(M31="","",M31+M28-M34-M33) | ... P35: =IF(P31="","",P31+P28-P34-P33)
B38: DOWNSIDE FORECAST
B39: Revenue | C39: m | F39: =IF('02_COMPANY_INPUTS'!$F$30="","",'02_COMPANY_INPUTS'!$F$30) | G39: =IF(OR('01_CONTROL'!G52<>1,F39=""),"",F39*(1+'01_CONTROL'!AE60)) | H39: =IF(OR('01_CONTROL'!H52<>1,G39=""),"",G39*(1+'01_CONTROL'!AF60)) | I39: =IF(OR('01_CONTROL'!I52<>1,H39=""),"",H39*(1+'01_CONTROL'!AG60)) | J39: =IF(OR('01_CONTROL'!J52<>1,I39=""),"",I39*(1+'01_CONTROL'!AH60)) | K39: =IF(OR('01_CONTROL'!K52<>1,J39=""),"",J39*(1+'01_CONTROL'!AI60)) | L39: =IF(OR('01_CONTROL'!L52<>1,K39=""),"",K39*(1+'01_CONTROL'!AJ60)) | M39: =IF(OR('01_CONTROL'!M52<>1,L39=""),"",L39*(1+'01_CONTROL'!AK60)) | N39: =IF(OR('01_CONTROL'!N52<>1,M39=""),"",M39*(1+'01_CONTROL'!AL60)) | ... P39: =IF(OR('01_CONTROL'!P52<>1,O39=""),"",O39*(1+'01_CONTROL'!AN60))
B40: EBITDA | C40: m | F40: =IF('02_COMPANY_INPUTS'!$F$31="","",'02_COMPANY_INPUTS'!$F$31) | G40: =IF(G39="","",G39*'01_CONTROL'!AE61) | H40: =IF(H39="","",H39*'01_CONTROL'!AF61) | I40: =IF(I39="","",I39*'01_CONTROL'!AG61) | J40: =IF(J39="","",J39*'01_CONTROL'!AH61) | K40: =IF(K39="","",K39*'01_CONTROL'!AI61) | L40: =IF(L39="","",L39*'01_CONTROL'!AJ61) | M40: =IF(M39="","",M39*'01_CONTROL'!AK61) | N40: =IF(N39="","",N39*'01_CONTROL'!AL61) | ... P40: =IF(P39="","",P39*'01_CONTROL'!AN61)
B41: D&A | C41: m | F41: =IF('02_COMPANY_INPUTS'!$F$33="","",'02_COMPANY_INPUTS'!$F$33) | G41: =IF(G39="","",G39*'01_CONTROL'!AE62) | H41: =IF(H39="","",H39*'01_CONTROL'!AF62) | I41: =IF(I39="","",I39*'01_CONTROL'!AG62) | J41: =IF(J39="","",J39*'01_CONTROL'!AH62) | K41: =IF(K39="","",K39*'01_CONTROL'!AI62) | L41: =IF(L39="","",L39*'01_CONTROL'!AJ62) | M41: =IF(M39="","",M39*'01_CONTROL'!AK62) | N41: =IF(N39="","",N39*'01_CONTROL'!AL62) | ... P41: =IF(P39="","",P39*'01_CONTROL'!AN62)
B42: EBIT | C42: m | F42: =IF(F40="","",F40-F41) | G42: =IF(G40="","",G40-G41) | H42: =IF(H40="","",H40-H41) | I42: =IF(I40="","",I40-I41) | J42: =IF(J40="","",J40-J41) | K42: =IF(K40="","",K40-K41) | L42: =IF(L40="","",L40-L41) | M42: =IF(M40="","",M40-M41) | ... P42: =IF(P40="","",P40-P41)
B43: Taxes on EBIT | C43: m | F43: =IF(F42="","",MAX(0,F42)*'01_CONTROL'!$F$24) | G43: =IF(G42="","",MAX(0,G42)*'01_CONTROL'!$F$24) | H43: =IF(H42="","",MAX(0,H42)*'01_CONTROL'!$F$24) | I43: =IF(I42="","",MAX(0,I42)*'01_CONTROL'!$F$24) | J43: =IF(J42="","",MAX(0,J42)*'01_CONTROL'!$F$24) | K43: =IF(K42="","",MAX(0,K42)*'01_CONTROL'!$F$24) | L43: =IF(L42="","",MAX(0,L42)*'01_CONTROL'!$F$24) | M43: =IF(M42="","",MAX(0,M42)*'01_CONTROL'!$F$24) | ... P43: =IF(P42="","",MAX(0,P42)*'01_CONTROL'!$F$24)
B44: NOPAT | C44: m | F44: =IF(F42="","",F42*(1-'01_CONTROL'!$F$24)) | G44: =IF(G42="","",G42*(1-'01_CONTROL'!$F$24)) | H44: =IF(H42="","",H42*(1-'01_CONTROL'!$F$24)) | I44: =IF(I42="","",I42*(1-'01_CONTROL'!$F$24)) | J44: =IF(J42="","",J42*(1-'01_CONTROL'!$F$24)) | K44: =IF(K42="","",K42*(1-'01_CONTROL'!$F$24)) | L44: =IF(L42="","",L42*(1-'01_CONTROL'!$F$24)) | M44: =IF(M42="","",M42*(1-'01_CONTROL'!$F$24)) | ... P44: =IF(P42="","",P42*(1-'01_CONTROL'!$F$24))
B45: Net working capital | C45: m | F45: =IF('02_COMPANY_INPUTS'!$F$35="","",'02_COMPANY_INPUTS'!$F$35) | G45: =IF(G39="","",G39*'01_CONTROL'!AE64) | H45: =IF(H39="","",H39*'01_CONTROL'!AF64) | I45: =IF(I39="","",I39*'01_CONTROL'!AG64) | J45: =IF(J39="","",J39*'01_CONTROL'!AH64) | K45: =IF(K39="","",K39*'01_CONTROL'!AI64) | L45: =IF(L39="","",L39*'01_CONTROL'!AJ64) | M45: =IF(M39="","",M39*'01_CONTROL'!AK64) | N45: =IF(N39="","",N39*'01_CONTROL'!AL64) | ... P45: =IF(P39="","",P39*'01_CONTROL'!AN64)
B46: Change in NWC | C46: m | F46: ="" | G46: =IF(G45="","",G45-F45) | H46: =IF(H45="","",H45-G45) | I46: =IF(I45="","",I45-H45) | J46: =IF(J45="","",J45-I45) | K46: =IF(K45="","",K45-J45) | L46: =IF(L45="","",L45-K45) | M46: =IF(M45="","",M45-L45) | N46: =IF(N45="","",N45-M45) | ... P46: =IF(P45="","",P45-O45)
B47: Capex | C47: m | F47: =IF('02_COMPANY_INPUTS'!$F$34="","",'02_COMPANY_INPUTS'!$F$34) | G47: =IF(G39="","",G39*'01_CONTROL'!AE63) | H47: =IF(H39="","",H39*'01_CONTROL'!AF63) | I47: =IF(I39="","",I39*'01_CONTROL'!AG63) | J47: =IF(J39="","",J39*'01_CONTROL'!AH63) | K47: =IF(K39="","",K39*'01_CONTROL'!AI63) | L47: =IF(L39="","",L39*'01_CONTROL'!AJ63) | M47: =IF(M39="","",M39*'01_CONTROL'!AK63) | N47: =IF(N39="","",N39*'01_CONTROL'!AL63) | ... P47: =IF(P39="","",P39*'01_CONTROL'!AN63)
B48: Unlevered FCF | C48: m | F48: =IF(F44="","",F44+F41-F47-F46) | G48: =IF(G44="","",G44+G41-G47-G46) | H48: =IF(H44="","",H44+H41-H47-H46) | I48: =IF(I44="","",I44+I41-I47-I46) | J48: =IF(J44="","",J44+J41-J47-J46) | K48: =IF(K44="","",K44+K41-K47-K46) | L48: =IF(L44="","",L44+L41-L47-L46) | M48: =IF(M44="","",M44+M41-M47-M46) | ... P48: =IF(P44="","",P44+P41-P47-P46)
B50: SELECTED SCENARIO OUTPUTS (FOR COMPS + DCF BASE)
B51: Revenue | C51: m | F51: =CHOOSE('01_CONTROL'!$F$10,F13,F26,F39) | G51: =CHOOSE('01_CONTROL'!$F$10,G13,G26,G39) | H51: =CHOOSE('01_CONTROL'!$F$10,H13,H26,H39) | I51: =CHOOSE('01_CONTROL'!$F$10,I13,I26,I39) | J51: =CHOOSE('01_CONTROL'!$F$10,J13,J26,J39) | K51: =CHOOSE('01_CONTROL'!$F$10,K13,K26,K39) | L51: =CHOOSE('01_CONTROL'!$F$10,L13,L26,L39) | M51: =CHOOSE('01_CONTROL'!$F$10,M13,M26,M39) | ... P51: =CHOOSE('01_CONTROL'!$F$10,P13,P26,P39)
B52: EBITDA | C52: m | F52: =CHOOSE('01_CONTROL'!$F$10,F14,F27,F40) | G52: =CHOOSE('01_CONTROL'!$F$10,G14,G27,G40) | H52: =CHOOSE('01_CONTROL'!$F$10,H14,H27,H40) | I52: =CHOOSE('01_CONTROL'!$F$10,I14,I27,I40) | J52: =CHOOSE('01_CONTROL'!$F$10,J14,J27,J40) | K52: =CHOOSE('01_CONTROL'!$F$10,K14,K27,K40) | L52: =CHOOSE('01_CONTROL'!$F$10,L14,L27,L40) | M52: =CHOOSE('01_CONTROL'!$F$10,M14,M27,M40) | ... P52: =CHOOSE('01_CONTROL'!$F$10,P14,P27,P40)
B53: D&A | C53: m | F53: =CHOOSE('01_CONTROL'!$F$10,F15,F28,F41) | G53: =CHOOSE('01_CONTROL'!$F$10,G15,G28,G41) | H53: =CHOOSE('01_CONTROL'!$F$10,H15,H28,H41) | I53: =CHOOSE('01_CONTROL'!$F$10,I15,I28,I41) | J53: =CHOOSE('01_CONTROL'!$F$10,J15,J28,J41) | K53: =CHOOSE('01_CONTROL'!$F$10,K15,K28,K41) | L53: =CHOOSE('01_CONTROL'!$F$10,L15,L28,L41) | M53: =CHOOSE('01_CONTROL'!$F$10,M15,M28,M41) | ... P53: =CHOOSE('01_CONTROL'!$F$10,P15,P28,P41)
B54: EBIT | C54: m | F54: =CHOOSE('01_CONTROL'!$F$10,F16,F29,F42) | G54: =CHOOSE('01_CONTROL'!$F$10,G16,G29,G42) | H54: =CHOOSE('01_CONTROL'!$F$10,H16,H29,H42) | I54: =CHOOSE('01_CONTROL'!$F$10,I16,I29,I42) | J54: =CHOOSE('01_CONTROL'!$F$10,J16,J29,J42) | K54: =CHOOSE('01_CONTROL'!$F$10,K16,K29,K42) | L54: =CHOOSE('01_CONTROL'!$F$10,L16,L29,L42) | M54: =CHOOSE('01_CONTROL'!$F$10,M16,M29,M42) | ... P54: =CHOOSE('01_CONTROL'!$F$10,P16,P29,P42)
B55: NOPAT | C55: m | F55: =CHOOSE('01_CONTROL'!$F$10,F18,F31,F44) | G55: =CHOOSE('01_CONTROL'!$F$10,G18,G31,G44) | H55: =CHOOSE('01_CONTROL'!$F$10,H18,H31,H44) | I55: =CHOOSE('01_CONTROL'!$F$10,I18,I31,I44) | J55: =CHOOSE('01_CONTROL'!$F$10,J18,J31,J44) | K55: =CHOOSE('01_CONTROL'!$F$10,K18,K31,K44) | L55: =CHOOSE('01_CONTROL'!$F$10,L18,L31,L44) | M55: =CHOOSE('01_CONTROL'!$F$10,M18,M31,M44) | ... P55: =CHOOSE('01_CONTROL'!$F$10,P18,P31,P44)
B56: Capex | C56: m | F56: =CHOOSE('01_CONTROL'!$F$10,F21,F34,F47) | G56: =CHOOSE('01_CONTROL'!$F$10,G21,G34,G47) | H56: =CHOOSE('01_CONTROL'!$F$10,H21,H34,H47) | I56: =CHOOSE('01_CONTROL'!$F$10,I21,I34,I47) | J56: =CHOOSE('01_CONTROL'!$F$10,J21,J34,J47) | K56: =CHOOSE('01_CONTROL'!$F$10,K21,K34,K47) | L56: =CHOOSE('01_CONTROL'!$F$10,L21,L34,L47) | M56: =CHOOSE('01_CONTROL'!$F$10,M21,M34,M47) | ... P56: =CHOOSE('01_CONTROL'!$F$10,P21,P34,P47)
B57: Change in NWC | C57: m | F57: =CHOOSE('01_CONTROL'!$F$10,F20,F33,F46) | G57: =CHOOSE('01_CONTROL'!$F$10,G20,G33,G46) | H57: =CHOOSE('01_CONTROL'!$F$10,H20,H33,H46) | I57: =CHOOSE('01_CONTROL'!$F$10,I20,I33,I46) | J57: =CHOOSE('01_CONTROL'!$F$10,J20,J33,J46) | K57: =CHOOSE('01_CONTROL'!$F$10,K20,K33,K46) | L57: =CHOOSE('01_CONTROL'!$F$10,L20,L33,L46) | M57: =CHOOSE('01_CONTROL'!$F$10,M20,M33,M46) | ... P57: =CHOOSE('01_CONTROL'!$F$10,P20,P33,P46)
B58: Unlevered FCF | C58: m | F58: =CHOOSE('01_CONTROL'!$F$10,F22,F35,F48) | G58: =CHOOSE('01_CONTROL'!$F$10,G22,G35,G48) | H58: =CHOOSE('01_CONTROL'!$F$10,H22,H35,H48) | I58: =CHOOSE('01_CONTROL'!$F$10,I22,I35,I48) | J58: =CHOOSE('01_CONTROL'!$F$10,J22,J35,J48) | K58: =CHOOSE('01_CONTROL'!$F$10,K22,K35,K48) | L58: =CHOOSE('01_CONTROL'!$F$10,L22,L35,L48) | M58: =CHOOSE('01_CONTROL'!$F$10,M22,M35,M48) | ... P58: =CHOOSE('01_CONTROL'!$F$10,P22,P35,P48)

Sheet 05_TRADING_COMPS
B2: 05_TRADING_COMPS
B3: Model
B4: Company
B5: Version
B6: Last updated | F6: =TODAY()
B8: SECTION
B9: PEER SET AND MARKET DATA (USER INPUT)
B11: Company | C11: Ticker | D11: CCY | E11: Share price | F11: Shares (mm) | G11: Market cap | H11: Net debt | I11: EV | J11: LTM Rev | K11: LTM EBITDA | L11: LTM EBIT | M11: P/E (optional) | N11: EV/Rev | O11: EV/EBITDA | P11: EV/EBIT
G12: =IFERROR(E12*F12,"") | I12: =IFERROR(G12+H12,"") | N12: =IFERROR(I12/J12,"") | O12: =IFERROR(I12/K12,"") | P12: =IFERROR(I12/L12,"")
G13: =IFERROR(E13*F13,"") | I13: =IFERROR(G13+H13,"") | N13: =IFERROR(I13/J13,"") | O13: =IFERROR(I13/K13,"") | P13: =IFERROR(I13/L13,"")
G14: =IFERROR(E14*F14,"") | I14: =IFERROR(G14+H14,"") | N14: =IFERROR(I14/J14,"") | O14: =IFERROR(I14/K14,"") | P14: =IFERROR(I14/L14,"")
G15: =IFERROR(E15*F15,"") | I15: =IFERROR(G15+H15,"") | N15: =IFERROR(I15/J15,"") | O15: =IFERROR(I15/K15,"") | P15: =IFERROR(I15/L15,"")
G16: =IFERROR(E16*F16,"") | I16: =IFERROR(G16+H16,"") | N16: =IFERROR(I16/J16,"") | O16: =IFERROR(I16/K16,"") | P16: =IFERROR(I16/L16,"")
G17: =IFERROR(E17*F17,"") | I17: =IFERROR(G17+H17,"") | N17: =IFERROR(I17/J17,"") | O17: =IFERROR(I17/K17,"") | P17: =IFERROR(I17/L17,"")
G18: =IFERROR(E18*F18,"") | I18: =IFERROR(G18+H18,"") | N18: =IFERROR(I18/J18,"") | O18: =IFERROR(I18/K18,"") | P18: =IFERROR(I18/L18,"")
G19: =IFERROR(E19*F19,"") | I19: =IFERROR(G19+H19,"") | N19: =IFERROR(I19/J19,"") | O19: =IFERROR(I19/K19,"") | P19: =IFERROR(I19/L19,"")
G20: =IFERROR(E20*F20,"") | I20: =IFERROR(G20+H20,"") | N20: =IFERROR(I20/J20,"") | O20: =IFERROR(I20/K20,"") | P20: =IFERROR(I20/L20,"")
G21: =IFERROR(E21*F21,"") | I21: =IFERROR(G21+H21,"") | N21: =IFERROR(I21/J21,"") | O21: =IFERROR(I21/K21,"") | P21: =IFERROR(I21/L21,"")
G22: =IFERROR(E22*F22,"") | I22: =IFERROR(G22+H22,"") | N22: =IFERROR(I22/J22,"") | O22: =IFERROR(I22/K22,"") | P22: =IFERROR(I22/L22,"")
G23: =IFERROR(E23*F23,"") | I23: =IFERROR(G23+H23,"") | N23: =IFERROR(I23/J23,"") | O23: =IFERROR(I23/K23,"") | P23: =IFERROR(I23/L23,"")
B26: SUMMARY STATISTICS (COMPUTED)
B27: EV/Rev | C27: x | D27: P25 | E27: Median | F27: =IFERROR(QUARTILE.INC(N12:N23,1),"") | G27: =IFERROR(MEDIAN(N12:N23),"") | H27: =IFERROR(QUARTILE.INC(N12:N23,3),"")
B28: EV/EBITDA | C28: x | D28: P25 | E28: Median | F28: =IFERROR(QUARTILE.INC(O12:O23,1),"") | G28: =IFERROR(MEDIAN(O12:O23),"") | H28: =IFERROR(QUARTILE.INC(O12:O23,3),"")
B29: EV/EBIT | C29: x | D29: P25 | E29: Median | F29: =IFERROR(QUARTILE.INC(P12:P23,1),"") | G29: =IFERROR(MEDIAN(P12:P23),"") | H29: =IFERROR(QUARTILE.INC(P12:P23,3),"")
B31: SELECTED MULTIPLE(S) (BASE CASE)
B32: Selected EV/EBITDA multiple | C32: x | F32: =IF('01_CONTROL'!$F$84,'01_CONTROL'!$F$85,$G$28)
B34: IMPLIED VALUATION (COMPANY)
B35: Company LTM EBITDA | C35: m | F35: ='02_COMPANY_INPUTS'!$F$31
B36: Implied enterprise value | C36: m | F36: =IF($F$35="","",IFERROR($F$32*$F$35,""))
B37: Net debt (per toggles) | C37: m | F37: ='02_COMPANY_INPUTS'!$F$26
B38: Implied equity value | C38: m | F38: =IF($F$36="","",IFERROR($F$36-$F$37,""))
B39: Shares outstanding (mm) | C39: mm | F39: ='02_COMPANY_INPUTS'!$F$11
B40: Implied price per share | C40: CCY | F40: =IF(OR($F$38="",$F$39="", $F$39=0),"",IFERROR($F$38/$F$39,""))
B42: COMPS IMPLIED RANGE (EV/EBITDA)
B43: Equity value P25 | C43: m | F43: =IF('02_COMPANY_INPUTS'!$F$31="","",IFERROR(F28*'02_COMPANY_INPUTS'!$F$31-'02_COMPANY_INPUTS'!$F$26,""))
B44: Equity value Median | C44: m | F44: =IF('02_COMPANY_INPUTS'!$F$31="","",IFERROR(G28*'02_COMPANY_INPUTS'!$F$31-'02_COMPANY_INPUTS'!$F$26,""))
B45: Equity value P75 | C45: m | F45: =IF('02_COMPANY_INPUTS'!$F$31="","",IFERROR(H28*'02_COMPANY_INPUTS'!$F$31-'02_COMPANY_INPUTS'!$F$26,""))

Sheet 06_DCF_WACC
B2: 06_DCF_WACC
B3: Model
B4: Company
B5: Version
B6: Last updated | F6: =TODAY()
B8: SECTION
B9: INPUTS (FROM 01_CONTROL)
B10: Tax rate | F10: ='01_CONTROL'!$F$24
B11: Risk-free rate | F11: ='01_CONTROL'!$F$25
B12: Equity risk premium | F12: ='01_CONTROL'!$F$26
B13: Beta | F13: ='01_CONTROL'!$F$27
B14: Size / country adj | F14: ='01_CONTROL'!$F$28
B15: Pre-tax cost of debt | F15: ='01_CONTROL'!$F$29
B16: Debt weight | F16: ='01_CONTROL'!$F$30
B17: Equity weight | F17: ='01_CONTROL'!$F$31
B19: WACC COMPUTATION
B20: WACC used (output) | C20: % | E20: WACC (output) | F20: ='01_CONTROL'!$F$36
B21: Cost of equity | C21: % | F21: ='01_CONTROL'!$F$34
B22: After-tax cost of debt | C22: % | F22: ='01_CONTROL'!$F$35
B24: SANITY CHECKS
B25: WACC min | C25: % | F25: 0.06
B26: WACC max | C26: % | F26: 0.12
B27: WACC within range | F27: =IF(AND($F$20>=$F$25,$F$20<=$F$26),1,0)

Sheet 07_DCF_FCF_AND_VALUATION
B2: 07_DCF_FCF_AND_VALUATION
B3: Model
B4: Company
B5: Version
B6: Last updated | F6: =TODAY()
B8: SECTION
B9: CALENDAR AND DISCOUNTING
B10: Fiscal year | F10: ='01_CONTROL'!F51 | G10: ='01_CONTROL'!G51 | H10: ='01_CONTROL'!H51 | I10: ='01_CONTROL'!I51 | J10: ='01_CONTROL'!J51 | K10: ='01_CONTROL'!K51 | L10: ='01_CONTROL'!L51 | M10: ='01_CONTROL'!M51 | ... P10: ='01_CONTROL'!P51
B11: t | F11: ='01_CONTROL'!F53 | G11: ='01_CONTROL'!G53 | H11: ='01_CONTROL'!H53 | I11: ='01_CONTROL'!I53 | J11: ='01_CONTROL'!J53 | K11: ='01_CONTROL'!K53 | L11: ='01_CONTROL'!L53 | M11: ='01_CONTROL'!M53 | ... P11: ='01_CONTROL'!P53
B12: Discount factor | G12: =IF('01_CONTROL'!G52=1,1/(1+'06_DCF_WACC'!$F$20)^('01_CONTROL'!G53-IF('01_CONTROL'!$F$17=1,0.5,0)),"") | H12: =IF('01_CONTROL'!H52=1,1/(1+'06_DCF_WACC'!$F$20)^('01_CONTROL'!H53-IF('01_CONTROL'!$F$17=1,0.5,0)),"") | I12: =IF('01_CONTROL'!I52=1,1/(1+'06_DCF_WACC'!$F$20)^('01_CONTROL'!I53-IF('01_CONTROL'!$F$17=1,0.5,0)),"") | J12: =IF('01_CONTROL'!J52=1,1/(1+'06_DCF_WACC'!$F$20)^('01_CONTROL'!J53-IF('01_CONTROL'!$F$17=1,0.5,0)),"") | K12: =IF('01_CONTROL'!K52=1,1/(1+'06_DCF_WACC'!$F$20)^('01_CONTROL'!K53-IF('01_CONTROL'!$F$17=1,0.5,0)),"") | L12: =IF('01_CONTROL'!L52=1,1/(1+'06_DCF_WACC'!$F$20)^('01_CONTROL'!L53-IF('01_CONTROL'!$F$17=1,0.5,0)),"") | M12: =IF('01_CONTROL'!M52=1,1/(1+'06_DCF_WACC'!$F$20)^('01_CONTROL'!M53-IF('01_CONTROL'!$F$17=1,0.5,0)),"") | N12: =IF('01_CONTROL'!N52=1,1/(1+'06_DCF_WACC'!$F$20)^('01_CONTROL'!N53-IF('01_CONTROL'!$F$17=1,0.5,0)),"") | ... P12: =IF('01_CONTROL'!P52=1,1/(1+'06_DCF_WACC'!$F$20)^('01_CONTROL'!P53-IF('01_CONTROL'!$F$17=1,0.5,0)),"")
B14: DCF DOWNSIDE
B15: EBITDA | C15: m | F15: ='04_DRIVERS_AND_FORECAST'!F40 | G15: ='04_DRIVERS_AND_FORECAST'!G40 | H15: ='04_DRIVERS_AND_FORECAST'!H40 | I15: ='04_DRIVERS_AND_FORECAST'!I40 | J15: ='04_DRIVERS_AND_FORECAST'!J40 | K15: ='04_DRIVERS_AND_FORECAST'!K40 | L15: ='04_DRIVERS_AND_FORECAST'!L40 | M15: ='04_DRIVERS_AND_FORECAST'!M40 | ... P15: ='04_DRIVERS_AND_FORECAST'!P40
B16: Unlevered FCF | C16: m | F16: ='04_DRIVERS_AND_FORECAST'!F48 | G16: ='04_DRIVERS_AND_FORECAST'!G48 | H16: ='04_DRIVERS_AND_FORECAST'!H48 | I16: ='04_DRIVERS_AND_FORECAST'!I48 | J16: ='04_DRIVERS_AND_FORECAST'!J48 | K16: ='04_DRIVERS_AND_FORECAST'!K48 | L16: ='04_DRIVERS_AND_FORECAST'!L48 | M16: ='04_DRIVERS_AND_FORECAST'!M48 | ... P16: ='04_DRIVERS_AND_FORECAST'!P48
B17: PV of FCF | C17: m | G17: =IF('01_CONTROL'!G52=1,IF(G16="","",G16*G12),"") | H17: =IF('01_CONTROL'!H52=1,IF(H16="","",H16*H12),"") | I17: =IF('01_CONTROL'!I52=1,IF(I16="","",I16*I12),"") | J17: =IF('01_CONTROL'!J52=1,IF(J16="","",J16*J12),"") | K17: =IF('01_CONTROL'!K52=1,IF(K16="","",K16*K12),"") | L17: =IF('01_CONTROL'!L52=1,IF(L16="","",L16*L12),"") | M17: =IF('01_CONTROL'!M52=1,IF(M16="","",M16*M12),"") | N17: =IF('01_CONTROL'!N52=1,IF(N16="","",N16*N12),"") | ... P17: =IF('01_CONTROL'!P52=1,IF(P16="","",P16*P12),"")
B19: PV of FCFs (sum) | C19: m | F19: =IF(OR('01_CONTROL'!$F$13<>1,'02_COMPANY_INPUTS'!$F$30=""),"",SUMPRODUCT(G17:P17,'01_CONTROL'!$G$52:$P$52))
B20: Terminal value | C20: m | F20: =IF('01_CONTROL'!$F$13=1,IF('01_CONTROL'!$F$15=1,IFERROR(INDEX($G$16:$P$16,'01_CONTROL'!$F$11)*(1+'01_CONTROL'!$AD$67)/('06_DCF_WACC'!$F$20-'01_CONTROL'!$AD$67),""),IFERROR(INDEX($G$15:$P$15,'01_CONTROL'!$F$11)*'01_CONTROL'!$AD$68,"")),"")
B21: PV of TV | C21: m | F21: =IF($F20="","",IFERROR($F20*INDEX($G$12:$P$12,'01_CONTROL'!$F$11),""))
B22: Enterprise value (DCF) | C22: m | F22: =IF($F19="","",IFERROR($F19+$F21,""))
B23: Equity value (DCF) | C23: m | F23: =IF($F22="","",IFERROR($F22-'02_COMPANY_INPUTS'!$F$26,""))
B24: Implied price per share (DCF) | C24: CCY | F24: =IF($F23="","",IFERROR($F23/'02_COMPANY_INPUTS'!$F$11,""))
B25: TV as % of EV | C25: % | F25: =IF($F22="","",IFERROR($F21/$F22,""))
B28: DCF BASE
B29: EBITDA | C29: m | F29: ='04_DRIVERS_AND_FORECAST'!F14 | G29: ='04_DRIVERS_AND_FORECAST'!G14 | H29: ='04_DRIVERS_AND_FORECAST'!H14 | I29: ='04_DRIVERS_AND_FORECAST'!I14 | J29: ='04_DRIVERS_AND_FORECAST'!J14 | K29: ='04_DRIVERS_AND_FORECAST'!K14 | L29: ='04_DRIVERS_AND_FORECAST'!L14 | M29: ='04_DRIVERS_AND_FORECAST'!M14 | ... P29: ='04_DRIVERS_AND_FORECAST'!P14
B30: Unlevered FCF | C30: m | F30: ='04_DRIVERS_AND_FORECAST'!F22 | G30: ='04_DRIVERS_AND_FORECAST'!G22 | H30: ='04_DRIVERS_AND_FORECAST'!H22 | I30: ='04_DRIVERS_AND_FORECAST'!I22 | J30: ='04_DRIVERS_AND_FORECAST'!J22 | K30: ='04_DRIVERS_AND_FORECAST'!K22 | L30: ='04_DRIVERS_AND_FORECAST'!L22 | M30: ='04_DRIVERS_AND_FORECAST'!M22 | ... P30: ='04_DRIVERS_AND_FORECAST'!P22
B31: PV of FCF | C31: m | G31: =IF('01_CONTROL'!G52=1,IF(G30="","",G30*G12),"") | H31: =IF('01_CONTROL'!H52=1,IF(H30="","",H30*H12),"") | I31: =IF('01_CONTROL'!I52=1,IF(I30="","",I30*I12),"") | J31: =IF('01_CONTROL'!J52=1,IF(J30="","",J30*J12),"") | K31: =IF('01_CONTROL'!K52=1,IF(K30="","",K30*K12),"") | L31: =IF('01_CONTROL'!L52=1,IF(L30="","",L30*L12),"") | M31: =IF('01_CONTROL'!M52=1,IF(M30="","",M30*M12),"") | N31: =IF('01_CONTROL'!N52=1,IF(N30="","",N30*N12),"") | ... P31: =IF('01_CONTROL'!P52=1,IF(P30="","",P30*P12),"")
B33: PV of FCFs (sum) | C33: m | F33: =IF(OR('01_CONTROL'!$F$13<>1,'02_COMPANY_INPUTS'!$F$30=""),"",SUMPRODUCT(G31:P31,'01_CONTROL'!$G$52:$P$52))
B34: Terminal value | C34: m | F34: =IF('01_CONTROL'!$F$13=1,IF('01_CONTROL'!$F$15=1,IFERROR(INDEX($G$30:$P$30,'01_CONTROL'!$F$11)*(1+'01_CONTROL'!$F$67)/('06_DCF_WACC'!$F$20-'01_CONTROL'!$F$67),""),IFERROR(INDEX($G$29:$P$29,'01_CONTROL'!$F$11)*'01_CONTROL'!$F$68,"")),"")
B35: PV of TV | C35: m | F35: =IF($F34="","",IFERROR($F34*INDEX($G$12:$P$12,'01_CONTROL'!$F$11),""))
B36: Enterprise value (DCF) | C36: m | F36: =IF($F33="","",IFERROR($F33+$F35,""))
B37: Equity value (DCF) | C37: m | F37: =IF($F36="","",IFERROR($F36-'02_COMPANY_INPUTS'!$F$26,""))
B38: Implied price per share (DCF) | C38: CCY | F38: =IF($F37="","",IFERROR($F37/'02_COMPANY_INPUTS'!$F$11,""))
B39: TV as % of EV | C39: % | F39: =IF($F36="","",IFERROR($F35/$F36,""))
B42: DCF UPSIDE
B43: EBITDA | C43: m | F43: ='04_DRIVERS_AND_FORECAST'!F27 | G43: ='04_DRIVERS_AND_FORECAST'!G27 | H43: ='04_DRIVERS_AND_FORECAST'!H27 | I43: ='04_DRIVERS_AND_FORECAST'!I27 | J43: ='04_DRIVERS_AND_FORECAST'!J27 | K43: ='04_DRIVERS_AND_FORECAST'!K27 | L43: ='04_DRIVERS_AND_FORECAST'!L27 | M43: ='04_DRIVERS_AND_FORECAST'!M27 | ... P43: ='04_DRIVERS_AND_FORECAST'!P27
B44: Unlevered FCF | C44: m | F44: ='04_DRIVERS_AND_FORECAST'!F35 | G44: ='04_DRIVERS_AND_FORECAST'!G35 | H44: ='04_DRIVERS_AND_FORECAST'!H35 | I44: ='04_DRIVERS_AND_FORECAST'!I35 | J44: ='04_DRIVERS_AND_FORECAST'!J35 | K44: ='04_DRIVERS_AND_FORECAST'!K35 | L44: ='04_DRIVERS_AND_FORECAST'!L35 | M44: ='04_DRIVERS_AND_FORECAST'!M35 | ... P44: ='04_DRIVERS_AND_FORECAST'!P35
B45: PV of FCF | C45: m | G45: =IF('01_CONTROL'!G52=1,IF(G44="","",G44*G12),"") | H45: =IF('01_CONTROL'!H52=1,IF(H44="","",H44*H12),"") | I45: =IF('01_CONTROL'!I52=1,IF(I44="","",I44*I12),"") | J45: =IF('01_CONTROL'!J52=1,IF(J44="","",J44*J12),"") | K45: =IF('01_CONTROL'!K52=1,IF(K44="","",K44*K12),"") | L45: =IF('01_CONTROL'!L52=1,IF(L44="","",L44*L12),"") | M45: =IF('01_CONTROL'!M52=1,IF(M44="","",M44*M12),"") | N45: =IF('01_CONTROL'!N52=1,IF(N44="","",N44*N12),"") | ... P45: =IF('01_CONTROL'!P52=1,IF(P44="","",P44*P12),"")
B47: PV of FCFs (sum) | C47: m | F47: =IF(OR('01_CONTROL'!$F$13<>1,'02_COMPANY_INPUTS'!$F$30=""),"",SUMPRODUCT(G45:P45,'01_CONTROL'!$G$52:$P$52))
B48: Terminal value | C48: m | F48: =IF('01_CONTROL'!$F$13=1,IF('01_CONTROL'!$F$15=1,IFERROR(INDEX($G$44:$P$44,'01_CONTROL'!$F$11)*(1+'01_CONTROL'!$R$67)/('06_DCF_WACC'!$F$20-'01_CONTROL'!$R$67),""),IFERROR(INDEX($G$43:$P$43,'01_CONTROL'!$F$11)*'01_CONTROL'!$R$68,"")),"")
B49: PV of TV | C49: m | F49: =IF($F48="","",IFERROR($F48*INDEX($G$12:$P$12,'01_CONTROL'!$F$11),""))
B50: Enterprise value (DCF) | C50: m | F50: =IF($F47="","",IFERROR($F47+$F49,""))
B51: Equity value (DCF) | C51: m | F51: =IF($F50="","",IFERROR($F50-'02_COMPANY_INPUTS'!$F$26,""))
B52: Implied price per share (DCF) | C52: CCY | F52: =IF($F51="","",IFERROR($F51/'02_COMPANY_INPUTS'!$F$11,""))
B53: TV as % of EV | C53: % | F53: =IF($F50="","",IFERROR($F49/$F50,""))
B55: DCF OUTPUTS (SINGLE CELLS)
B56: Downside equity value | F56: =F23
B57: Base equity value | F57: =F37
B58: Upside equity value | F58: =F51
B60: Downside implied price | F60: =F24
B61: Base implied price | F61: =F38
B62: Upside implied price | F62: =F52

Sheet 08_TRIANGULATION_RANGE
B2: 08_TRIANGULATION_RANGE
B3: Model
B4: Company
B5: Version
B6: Last updated | F6: =TODAY()
B8: SECTION
B9: COMPS OUTPUTS (FROM 05_TRADING_COMPS)
B10: Comps equity value P25 | C10: m | F10: ='05_TRADING_COMPS'!$F$43
B11: Comps equity value Median | C11: m | F11: ='05_TRADING_COMPS'!$F$44
B12: Comps equity value P75 | C12: m | F12: ='05_TRADING_COMPS'!$F$45
B14: Shares outstanding (mm) | C14: mm | F14: =IF('02_COMPANY_INPUTS'!$F$11="","",'02_COMPANY_INPUTS'!$F$11)
B16: Comps implied price P25 | C16: CCY | F16: =IF(OR($F$10="",$F$14="",N($F$14)=0),"",IFERROR(N($F$10)/N($F$14),""))
B17: Comps implied price Median | C17: CCY | F17: =IF(OR($F$11="",$F$14="",N($F$14)=0),"",IFERROR(N($F$11)/N($F$14),""))
B18: Comps implied price P75 | C18: CCY | F18: =IF(OR($F$12="",$F$14="",N($F$14)=0),"",IFERROR(N($F$12)/N($F$14),""))
B21: DCF OUTPUTS (FROM 07_DCF_FCF_AND_VALUATION)
B22: DCF equity value Downside | C22: m | F22: ='07_DCF_FCF_AND_VALUATION'!$F$56
B23: DCF equity value Base | C23: m | F23: ='07_DCF_FCF_AND_VALUATION'!$F$57
B24: DCF equity value Upside | C24: m | F24: ='07_DCF_FCF_AND_VALUATION'!$F$58
B26: DCF implied price Downside | C26: CCY | F26: ='07_DCF_FCF_AND_VALUATION'!$F$60
B27: DCF implied price Base | C27: CCY | F27: ='07_DCF_FCF_AND_VALUATION'!$F$61
B28: DCF implied price Upside | C28: CCY | F28: ='07_DCF_FCF_AND_VALUATION'!$F$62
B31: TRIANGULATION (OPTIONAL WEIGHTING)
B32: Weight DCF (0-1) | F32: 0.5
B34: Combined implied price Downside | C34: CCY | F34: =IF('01_CONTROL'!$F$13=1,IF(OR($F$26="",$F$16=""),"",IFERROR($F$32*N($F$26)+(1-$F$32)*N($F$16),"")),IF($F$16="","",N($F$16)))
B35: Combined implied price Base | C35: CCY | F35: =IF('01_CONTROL'!$F$13=1,IF(OR($F$27="",$F$17=""),"",IFERROR($F$32*N($F$27)+(1-$F$32)*N($F$17),"")),IF($F$17="","",N($F$17)))
B36: Combined implied price Upside | C36: CCY | F36: =IF('01_CONTROL'!$F$13=1,IF(OR($F$28="",$F$18=""),"",IFERROR($F$32*N($F$28)+(1-$F$32)*N($F$18),"")),IF($F$18="","",N($F$18)))
B39: REFERENCE POINT AND UPSIDE/DOWNSIDE
B40: Current share price | C40: CCY | F40: =IF('02_COMPANY_INPUTS'!$F$10="","",'02_COMPANY_INPUTS'!$F$10)
B41: Selected reference price (Base) | C41: CCY | F41: =$F$35
B42: Upside vs current | C42: % | F42: =IF(OR($F$41="",$F$40=""),"",IFERROR($F$41/$F$40-1,""))
B43: Downside vs current (Downside) | C43: % | F43: =IF(OR($F$34="",$F$40=""),"",IFERROR($F$34/$F$40-1,""))
B46: DASHBOARD SOURCE CELLS (SINGLE OUTPUTS)
B47: SRC_CurrentPrice | F47: =$F$40
B48: SRC_SharesMM | F48: =$F$14
B49: SRC_MarketCap | F49: =IF('02_COMPANY_INPUTS'!$F$12="","",'02_COMPANY_INPUTS'!$F$12)
B50: SRC_NetDebt | F50: =IF('02_COMPANY_INPUTS'!$F$26="","",'02_COMPANY_INPUTS'!$F$26)
B51: SRC_EnterpriseValue | F51: =IF(OR($F$49="",$F$50=""),"",$F$49+$F$50)
B52: SRC_ImpliedPrice_Base | F52: =$F$41
B53: SRC_UpsidePct | F53: =$F$42
B54: SRC_DownsidePct | F54: =$F$43
B55: SRC_CompsEq_P25 | F55: =$F$10
B56: SRC_CompsEq_Median | F56: =$F$11
B57: SRC_CompsEq_P75 | F57: =$F$12
B58: SRC_DCF_Eq_Down | F58: =$F$22
B59: SRC_DCF_Eq_Base | F59: =$F$23
B60: SRC_DCF_Eq_Up | F60: =$F$24
B61: SRC_Combined_Price_Down | F61: =$F$34
B62: SRC_Combined_Price_Base | F62: =$F$35
B63: SRC_Combined_Price_Up | C63: m | F63: =$F$36
B64: SRC_EquityValue_Base | C64: m | F64: =IF(OR($F$52="",$F$48=""),"",IFERROR(N($F$52)*N($F$48),""))
B65: DASHBOARD METADATA OUTPUTS
B66: SRC_DCF_Status | F66: =01_CONTROL!F12
B67: SRC_WACC_Base | C67: % | F67: =01_CONTROL!F36
B68: SRC_CostOfEquity | C68: % | F68: =01_CONTROL!F34
B69: SRC_AfterTaxCostOfDebt | C69: % | F69: =01_CONTROL!F35
B70: SRC_Terminal_Method | F70: =01_CONTROL!F14
B71: SRC_MidYear_Convention | F71: =01_CONTROL!F16
B72: SRC_Selected_Comps_Multiple_EV_EBITDA | C72: x | F72: =05_TRADING_COMPS!F32
B73: SRC_Terminal_g_Used | C73: % | F73: =01_CONTROL!F79
B74: SRC_Terminal_ExitMultiple_Used | C74: x | F74: =01_CONTROL!F80
B75: SRC_TaxRate | C75: % | F75: =01_CONTROL!F24

Sheet 09_SENSITIVITIES
B2: 09_SENSITIVITIES
B3: Model
B4: Company
B5: Version
B6: Last updated | F6: =TODAY()
B8: SECTION
B9: SENSITIVITY SETUP
B10: Terminal method (from 01_CONTROL) | F10: ='01_CONTROL'!$F$14
B11: Mid-year convention (from 01_CONTROL) | F11: ='01_CONTROL'!$F$16
B14: DCF SENSITIVITY: WACC VS TERMINAL GROWTH (PERPETUITY)
F15: g \ WACC | G15: ='06_DCF_WACC'!$F$20+(-0.02) | H15: ='06_DCF_WACC'!$F$20+(-0.01) | I15: ='06_DCF_WACC'!$F$20+(0.0) | J15: ='06_DCF_WACC'!$F$20+(0.01) | K15: ='06_DCF_WACC'!$F$20+(0.02) | L15: ='06_DCF_WACC'!$F$20+(0.03)
F16: 0.01 | G16: =IF(AND('01_CONTROL'!$F$13=1,'01_CONTROL'!$F$15=1),IFERROR(IFERROR(IFERROR(SUMPRODUCT('04_DRIVERS_AND_FORECAST'!$G$22:$P$22,1/(1+G15)^('01_CONTROL'!$G$53:$P$53-IF('01_CONTROL'!$F$17=1,0.5,0)),'01_CONTROL'!$G$52:$P$52)+IFERROR(IFERROR(INDEX('04_DRIVERS_AND_FORECAST'!$G$22:$P$22,'01_CONTROL'!$F$11)*(1+F16)/(G15-F16),"")*1/(1+G15)^('01_CONTROL'!$F$11-IF('01_CONTROL'!$F$17=1,0.5,0)),""),"")-'02_COMPANY_INPUTS'!$F$26,"")/'02_COMPANY_INPUTS'!$F$11,""),"") | H16: =IF(AND('01_CONTROL'!$F$13=1,'01_CONTROL'!$F$15=1),IFERROR(IFERROR(IFERROR(SUMPRODUCT('04_DRIVERS_AND_FORECAST'!$G$22:$P$22,1/(1+H15)^('01_CONTROL'!$G$53:$P$53-IF('01_CONTROL'!$F$17=1,0.5,0)),'01_CONTROL'!$G$52:$P$52)+IFERROR(IFERROR(INDEX('04_DRIVERS_AND_FORECAST'!$G$22:$P$22,'01_CONTROL'!$F$11)*(1+F16)/(H15-F16),"")*1/(1+H15)^('01_CONTROL'!$F$11-IF('01_CONTROL'!$F$17=1,0.5,0)),""),"")-'02_COMPANY_INPUTS'!$F$26,"")/'02_COMPANY_INPUTS'!$F$11,""),"") | I16: =IF(AND('01_CONTROL'!$F$13=1,'01_CONTROL'!$F$15=1),IFERROR(IFERROR(IFERROR(SUMPRODUCT('04_DRIVERS_AND_FORECAST'!$G$22:$P$22,1/(1+I15)^('01_CONTROL'!$G$53:$P$53-IF('01_CONTROL'!$F$17=1,0.5,0)),'01_CONTROL'!$G$52:$P$52)+IFERROR(IFERROR(INDEX('04_DRIVERS_AND_FORECAST'!$G$22:$P$22,'01_CONTROL'!$F$11)*(1+F16)/(I15-F16),"")*1/(1+I15)^('01_CONTROL'!$F$11-IF('01_CONTROL'!$F$17=1,0.5,0)),""),"")-'02_COMPANY_INPUTS'!$F$26,"")/'02_COMPANY_INPUTS'!$F$11,""),"") | J16: =IF(AND('01_CONTROL'!$F$13=1,'01_CONTROL'!$F$15=1),IFERROR(IFERROR(IFERROR(SUMPRODUCT('04_DRIVERS_AND_FORECAST'!$G$22:$P$22,1/(1+J15)^('01_CONTROL'!$G$53:$P$53-IF('01_CONTROL'!$F$17=1,0.5,0)),'01_CONTROL'!$G$52:$P$52)+IFERROR(IFERROR(INDEX('04_DRIVERS_AND_FORECAST'!$G$22:$P$22,'01_CONTROL'!$F$11)*(1+F16)/(J15-F16),"")*1/(1+J15)^('01_CONTROL'!$F$11-IF('01_CONTROL'!$F$17=1,0.5,0)),""),"")-'02_COMPANY_INPUTS'!$F$26,"")/'02_COMPANY_INPUTS'!$F$11,""),"") | K16: =IF(AND('01_CONTROL'!$F$13=1,'01_CONTROL'!$F$15=1),IFERROR(IFERROR(IFERROR(SUMPRODUCT('04_DRIVERS_AND_FORECAST'!$G$22:$P$22,1/(1+K15)^('01_CONTROL'!$G$53:$P$53-IF('01_CONTROL'!$F$17=1,0.5,0)),'01_CONTROL'!$G$52:$P$52)+IFERROR(IFERROR(INDEX('04_DRIVERS_AND_FORECAST'!$G$22:$P$22,'01_CONTROL'!$F$11)*(1+F16)/(K15-F16),"")*1/(1+K15)^('01_CONTROL'!$F$11-IF('01_CONTROL'!$F$17=1,0.5,0)),""),"")-'02_COMPANY_INPUTS'!$F$26,"")/'02_COMPANY_INPUTS'!$F$11,""),"") | L16: =IF(AND('01_CONTROL'!$F$13=1,'01_CONTROL'!$F$15=1),IFERROR(IFERROR(IFERROR(SUMPRODUCT('04_DRIVERS_AND_FORECAST'!$G$22:$P$22,1/(1+L15)^('01_CONTROL'!$G$53:$P$53-IF('01_CONTROL'!$F$17=1,0.5,0)),'01_CONTROL'!$G$52:$P$52)+IFERROR(IFERROR(INDEX('04_DRIVERS_AND_FORECAST'!$G$22:$P$22,'01_CONTROL'!$F$11)*(1+F16)/(L15-F16),"")*1/(1+L15)^('01_CONTROL'!$F$11-IF('01_CONTROL'!$F$17=1,0.5,0)),""),"")-'02_COMPANY_INPUTS'!$F$26,"")/'02_COMPANY_INPUTS'!$F$11,""),"")
F17: 0.015 | G17: =IF(AND('01_CONTROL'!$F$13=1,'01_CONTROL'!$F$15=1),IFERROR(IFERROR(IFERROR(SUMPRODUCT('04_DRIVERS_AND_FORECAST'!$G$22:$P$22,1/(1+G15)^('01_CONTROL'!$G$53:$P$53-IF('01_CONTROL'!$F$17=1,0.5,0)),'01_CONTROL'!$G$52:$P$52)+IFERROR(IFERROR(INDEX('04_DRIVERS_AND_FORECAST'!$G$22:$P$22,'01_CONTROL'!$F$11)*(1+F17)/(G15-F17),"")*1/(1+G15)^('01_CONTROL'!$F$11-IF('01_CONTROL'!$F$17=1,0.5,0)),""),"")-'02_COMPANY_INPUTS'!$F$26,"")/'02_COMPANY_INPUTS'!$F$11,""),"") | H17: =IF(AND('01_CONTROL'!$F$13=1,'01_CONTROL'!$F$15=1),IFERROR(IFERROR(IFERROR(SUMPRODUCT('04_DRIVERS_AND_FORECAST'!$G$22:$P$22,1/(1+H15)^('01_CONTROL'!$G$53:$P$53-IF('01_CONTROL'!$F$17=1,0.5,0)),'01_CONTROL'!$G$52:$P$52)+IFERROR(IFERROR(INDEX('04_DRIVERS_AND_FORECAST'!$G$22:$P$22,'01_CONTROL'!$F$11)*(1+F17)/(H15-F17),"")*1/(1+H15)^('01_CONTROL'!$F$11-IF('01_CONTROL'!$F$17=1,0.5,0)),""),"")-'02_COMPANY_INPUTS'!$F$26,"")/'02_COMPANY_INPUTS'!$F$11,""),"") | I17: =IF(AND('01_CONTROL'!$F$13=1,'01_CONTROL'!$F$15=1),IFERROR(IFERROR(IFERROR(SUMPRODUCT('04_DRIVERS_AND_FORECAST'!$G$22:$P$22,1/(1+I15)^('01_CONTROL'!$G$53:$P$53-IF('01_CONTROL'!$F$17=1,0.5,0)),'01_CONTROL'!$G$52:$P$52)+IFERROR(IFERROR(INDEX('04_DRIVERS_AND_FORECAST'!$G$22:$P$22,'01_CONTROL'!$F$11)*(1+F17)/(I15-F17),"")*1/(1+I15)^('01_CONTROL'!$F$11-IF('01_CONTROL'!$F$17=1,0.5,0)),""),"")-'02_COMPANY_INPUTS'!$F$26,"")/'02_COMPANY_INPUTS'!$F$11,""),"") | J17: =IF(AND('01_CONTROL'!$F$13=1,'01_CONTROL'!$F$15=1),IFERROR(IFERROR(IFERROR(SUMPRODUCT('04_DRIVERS_AND_FORECAST'!$G$22:$P$22,1/(1+J15)^('01_CONTROL'!$G$53:$P$53-IF('01_CONTROL'!$F$17=1,0.5,0)),'01_CONTROL'!$G$52:$P$52)+IFERROR(IFERROR(INDEX('04_DRIVERS_AND_FORECAST'!$G$22:$P$22,'01_CONTROL'!$F$11)*(1+F17)/(J15-F17),"")*1/(1+J15)^('01_CONTROL'!$F$11-IF('01_CONTROL'!$F$17=1,0.5,0)),""),"")-'02_COMPANY_INPUTS'!$F$26,"")/'02_COMPANY_INPUTS'!$F$11,""),"") | K17: =IF(AND('01_CONTROL'!$F$13=1,'01_CONTROL'!$F$15=1),IFERROR(IFERROR(IFERROR(SUMPRODUCT('04_DRIVERS_AND_FORECAST'!$G$22:$P$22,1/(1+K15)^('01_CONTROL'!$G$53:$P$53-IF('01_CONTROL'!$F$17=1,0.5,0)),'01_CONTROL'!$G$52:$P$52)+IFERROR(IFERROR(INDEX('04_DRIVERS_AND_FORECAST'!$G$22:$P$22,'01_CONTROL'!$F$11)*(1+F17)/(K15-F17),"")*1/(1+K15)^('01_CONTROL'!$F$11-IF('01_CONTROL'!$F$17=1,0.5,0)),""),"")-'02_COMPANY_INPUTS'!$F$26,"")/'02_COMPANY_INPUTS'!$F$11,""),"") | L17: =IF(AND('01_CONTROL'!$F$13=1,'01_CONTROL'!$F$15=1),IFERROR(IFERROR(IFERROR(SUMPRODUCT('04_DRIVERS_AND_FORECAST'!$G$22:$P$22,1/(1+L15)^('01_CONTROL'!$G$53:$P$53-IF('01_CONTROL'!$F$17=1,0.5,0)),'01_CONTROL'!$G$52:$P$52)+IFERROR(IFERROR(INDEX('04_DRIVERS_AND_FORECAST'!$G$22:$P$22,'01_CONTROL'!$F$11)*(1+F17)/(L15-F17),"")*1/(1+L15)^('01_CONTROL'!$F$11-IF('01_CONTROL'!$F$17=1,0.5,0)),""),"")-'02_COMPANY_INPUTS'!$F$26,"")/'02_COMPANY_INPUTS'!$F$11,""),"")
F18: 0.02 | G18: =IF(AND('01_CONTROL'!$F$13=1,'01_CONTROL'!$F$15=1),IFERROR(IFERROR(IFERROR(SUMPRODUCT('04_DRIVERS_AND_FORECAST'!$G$22:$P$22,1/(1+G15)^('01_CONTROL'!$G$53:$P$53-IF('01_CONTROL'!$F$17=1,0.5,0)),'01_CONTROL'!$G$52:$P$52)+IFERROR(IFERROR(INDEX('04_DRIVERS_AND_FORECAST'!$G$22:$P$22,'01_CONTROL'!$F$11)*(1+F18)/(G15-F18),"")*1/(1+G15)^('01_CONTROL'!$F$11-IF('01_CONTROL'!$F$17=1,0.5,0)),""),"")-'02_COMPANY_INPUTS'!$F$26,"")/'02_COMPANY_INPUTS'!$F$11,""),"") | H18: =IF(AND('01_CONTROL'!$F$13=1,'01_CONTROL'!$F$15=1),IFERROR(IFERROR(IFERROR(SUMPRODUCT('04_DRIVERS_AND_FORECAST'!$G$22:$P$22,1/(1+H15)^('01_CONTROL'!$G$53:$P$53-IF('01_CONTROL'!$F$17=1,0.5,0)),'01_CONTROL'!$G$52:$P$52)+IFERROR(IFERROR(INDEX('04_DRIVERS_AND_FORECAST'!$G$22:$P$22,'01_CONTROL'!$F$11)*(1+F18)/(H15-F18),"")*1/(1+H15)^('01_CONTROL'!$F$11-IF('01_CONTROL'!$F$17=1,0.5,0)),""),"")-'02_COMPANY_INPUTS'!$F$26,"")/'02_COMPANY_INPUTS'!$F$11,""),"") | I18: =IF(AND('01_CONTROL'!$F$13=1,'01_CONTROL'!$F$15=1),IFERROR(IFERROR(IFERROR(SUMPRODUCT('04_DRIVERS_AND_FORECAST'!$G$22:$P$22,1/(1+I15)^('01_CONTROL'!$G$53:$P$53-IF('01_CONTROL'!$F$17=1,0.5,0)),'01_CONTROL'!$G$52:$P$52)+IFERROR(IFERROR(INDEX('04_DRIVERS_AND_FORECAST'!$G$22:$P$22,'01_CONTROL'!$F$11)*(1+F18)/(I15-F18),"")*1/(1+I15)^('01_CONTROL'!$F$11-IF('01_CONTROL'!$F$17=1,0.5,0)),""),"")-'02_COMPANY_INPUTS'!$F$26,"")/'02_COMPANY_INPUTS'!$F$11,""),"") | J18: =IF(AND('01_CONTROL'!$F$13=1,'01_CONTROL'!$F$15=1),IFERROR(IFERROR(IFERROR(SUMPRODUCT('04_DRIVERS_AND_FORECAST'!$G$22:$P$22,1/(1+J15)^('01_CONTROL'!$G$53:$P$53-IF('01_CONTROL'!$F$17=1,0.5,0)),'01_CONTROL'!$G$52:$P$52)+IFERROR(IFERROR(INDEX('04_DRIVERS_AND_FORECAST'!$G$22:$P$22,'01_CONTROL'!$F$11)*(1+F18)/(J15-F18),"")*1/(1+J15)^('01_CONTROL'!$F$11-IF('01_CONTROL'!$F$17=1,0.5,0)),""),"")-'02_COMPANY_INPUTS'!$F$26,"")/'02_COMPANY_INPUTS'!$F$11,""),"") | K18: =IF(AND('01_CONTROL'!$F$13=1,'01_CONTROL'!$F$15=1),IFERROR(IFERROR(IFERROR(SUMPRODUCT('04_DRIVERS_AND_FORECAST'!$G$22:$P$22,1/(1+K15)^('01_CONTROL'!$G$53:$P$53-IF('01_CONTROL'!$F$17=1,0.5,0)),'01_CONTROL'!$G$52:$P$52)+IFERROR(IFERROR(INDEX('04_DRIVERS_AND_FORECAST'!$G$22:$P$22,'01_CONTROL'!$F$11)*(1+F18)/(K15-F18),"")*1/(1+K15)^('01_CONTROL'!$F$11-IF('01_CONTROL'!$F$17=1,0.5,0)),""),"")-'02_COMPANY_INPUTS'!$F$26,"")/'02_COMPANY_INPUTS'!$F$11,""),"") | L18: =IF(AND('01_CONTROL'!$F$13=1,'01_CONTROL'!$F$15=1),IFERROR(IFERROR(IFERROR(SUMPRODUCT('04_DRIVERS_AND_FORECAST'!$G$22:$P$22,1/(1+L15)^('01_CONTROL'!$G$53:$P$53-IF('01_CONTROL'!$F$17=1,0.5,0)),'01_CONTROL'!$G$52:$P$52)+IFERROR(IFERROR(INDEX('04_DRIVERS_AND_FORECAST'!$G$22:$P$22,'01_CONTROL'!$F$11)*(1+F18)/(L15-F18),"")*1/(1+L15)^('01_CONTROL'!$F$11-IF('01_CONTROL'!$F$17=1,0.5,0)),""),"")-'02_COMPANY_INPUTS'!$F$26,"")/'02_COMPANY_INPUTS'!$F$11,""),"")
F19: 0.025 | G19: =IF(AND('01_CONTROL'!$F$13=1,'01_CONTROL'!$F$15=1),IFERROR(IFERROR(IFERROR(SUMPRODUCT('04_DRIVERS_AND_FORECAST'!$G$22:$P$22,1/(1+G15)^('01_CONTROL'!$G$53:$P$53-IF('01_CONTROL'!$F$17=1,0.5,0)),'01_CONTROL'!$G$52:$P$52)+IFERROR(IFERROR(INDEX('04_DRIVERS_AND_FORECAST'!$G$22:$P$22,'01_CONTROL'!$F$11)*(1+F19)/(G15-F19),"")*1/(1+G15)^('01_CONTROL'!$F$11-IF('01_CONTROL'!$F$17=1,0.5,0)),""),"")-'02_COMPANY_INPUTS'!$F$26,"")/'02_COMPANY_INPUTS'!$F$11,""),"") | H19: =IF(AND('01_CONTROL'!$F$13=1,'01_CONTROL'!$F$15=1),IFERROR(IFERROR(IFERROR(SUMPRODUCT('04_DRIVERS_AND_FORECAST'!$G$22:$P$22,1/(1+H15)^('01_CONTROL'!$G$53:$P$53-IF('01_CONTROL'!$F$17=1,0.5,0)),'01_CONTROL'!$G$52:$P$52)+IFERROR(IFERROR(INDEX('04_DRIVERS_AND_FORECAST'!$G$22:$P$22,'01_CONTROL'!$F$11)*(1+F19)/(H15-F19),"")*1/(1+H15)^('01_CONTROL'!$F$11-IF('01_CONTROL'!$F$17=1,0.5,0)),""),"")-'02_COMPANY_INPUTS'!$F$26,"")/'02_COMPANY_INPUTS'!$F$11,""),"") | I19: =IF(AND('01_CONTROL'!$F$13=1,'01_CONTROL'!$F$15=1),IFERROR(IFERROR(IFERROR(SUMPRODUCT('04_DRIVERS_AND_FORECAST'!$G$22:$P$22,1/(1+I15)^('01_CONTROL'!$G$53:$P$53-IF('01_CONTROL'!$F$17=1,0.5,0)),'01_CONTROL'!$G$52:$P$52)+IFERROR(IFERROR(INDEX('04_DRIVERS_AND_FORECAST'!$G$22:$P$22,'01_CONTROL'!$F$11)*(1+F19)/(I15-F19),"")*1/(1+I15)^('01_CONTROL'!$F$11-IF('01_CONTROL'!$F$17=1,0.5,0)),""),"")-'02_COMPANY_INPUTS'!$F$26,"")/'02_COMPANY_INPUTS'!$F$11,""),"") | J19: =IF(AND('01_CONTROL'!$F$13=1,'01_CONTROL'!$F$15=1),IFERROR(IFERROR(IFERROR(SUMPRODUCT('04_DRIVERS_AND_FORECAST'!$G$22:$P$22,1/(1+J15)^('01_CONTROL'!$G$53:$P$53-IF('01_CONTROL'!$F$17=1,0.5,0)),'01_CONTROL'!$G$52:$P$52)+IFERROR(IFERROR(INDEX('04_DRIVERS_AND_FORECAST'!$G$22:$P$22,'01_CONTROL'!$F$11)*(1+F19)/(J15-F19),"")*1/(1+J15)^('01_CONTROL'!$F$11-IF('01_CONTROL'!$F$17=1,0.5,0)),""),"")-'02_COMPANY_INPUTS'!$F$26,"")/'02_COMPANY_INPUTS'!$F$11,""),"") | K19: =IF(AND('01_CONTROL'!$F$13=1,'01_CONTROL'!$F$15=1),IFERROR(IFERROR(IFERROR(SUMPRODUCT('04_DRIVERS_AND_FORECAST'!$G$22:$P$22,1/(1+K15)^('01_CONTROL'!$G$53:$P$53-IF('01_CONTROL'!$F$17=1,0.5,0)),'01_CONTROL'!$G$52:$P$52)+IFERROR(IFERROR(INDEX('04_DRIVERS_AND_FORECAST'!$G$22:$P$22,'01_CONTROL'!$F$11)*(1+F19)/(K15-F19),"")*1/(1+K15)^('01_CONTROL'!$F$11-IF('01_CONTROL'!$F$17=1,0.5,0)),""),"")-'02_COMPANY_INPUTS'!$F$26,"")/'02_COMPANY_INPUTS'!$F$11,""),"") | L19: =IF(AND('01_CONTROL'!$F$13=1,'01_CONTROL'!$F$15=1),IFERROR(IFERROR(IFERROR(SUMPRODUCT('04_DRIVERS_AND_FORECAST'!$G$22:$P$22,1/(1+L15)^('01_CONTROL'!$G$53:$P$53-IF('01_CONTROL'!$F$17=1,0.5,0)),'01_CONTROL'!$G$52:$P$52)+IFERROR(IFERROR(INDEX('04_DRIVERS_AND_FORECAST'!$G$22:$P$22,'01_CONTROL'!$F$11)*(1+F19)/(L15-F19),"")*1/(1+L15)^('01_CONTROL'!$F$11-IF('01_CONTROL'!$F$17=1,0.5,0)),""),"")-'02_COMPANY_INPUTS'!$F$26,"")/'02_COMPANY_INPUTS'!$F$11,""),"")
F20: 0.03 | G20: =IF(AND('01_CONTROL'!$F$13=1,'01_CONTROL'!$F$15=1),IFERROR(IFERROR(IFERROR(SUMPRODUCT('04_DRIVERS_AND_FORECAST'!$G$22:$P$22,1/(1+G15)^('01_CONTROL'!$G$53:$P$53-IF('01_CONTROL'!$F$17=1,0.5,0)),'01_CONTROL'!$G$52:$P$52)+IFERROR(IFERROR(INDEX('04_DRIVERS_AND_FORECAST'!$G$22:$P$22,'01_CONTROL'!$F$11)*(1+F20)/(G15-F20),"")*1/(1+G15)^('01_CONTROL'!$F$11-IF('01_CONTROL'!$F$17=1,0.5,0)),""),"")-'02_COMPANY_INPUTS'!$F$26,"")/'02_COMPANY_INPUTS'!$F$11,""),"") | H20: =IF(AND('01_CONTROL'!$F$13=1,'01_CONTROL'!$F$15=1),IFERROR(IFERROR(IFERROR(SUMPRODUCT('04_DRIVERS_AND_FORECAST'!$G$22:$P$22,1/(1+H15)^('01_CONTROL'!$G$53:$P$53-IF('01_CONTROL'!$F$17=1,0.5,0)),'01_CONTROL'!$G$52:$P$52)+IFERROR(IFERROR(INDEX('04_DRIVERS_AND_FORECAST'!$G$22:$P$22,'01_CONTROL'!$F$11)*(1+F20)/(H15-F20),"")*1/(1+H15)^('01_CONTROL'!$F$11-IF('01_CONTROL'!$F$17=1,0.5,0)),""),"")-'02_COMPANY_INPUTS'!$F$26,"")/'02_COMPANY_INPUTS'!$F$11,""),"") | I20: =IF(AND('01_CONTROL'!$F$13=1,'01_CONTROL'!$F$15=1),IFERROR(IFERROR(IFERROR(SUMPRODUCT('04_DRIVERS_AND_FORECAST'!$G$22:$P$22,1/(1+I15)^('01_CONTROL'!$G$53:$P$53-IF('01_CONTROL'!$F$17=1,0.5,0)),'01_CONTROL'!$G$52:$P$52)+IFERROR(IFERROR(INDEX('04_DRIVERS_AND_FORECAST'!$G$22:$P$22,'01_CONTROL'!$F$11)*(1+F20)/(I15-F20),"")*1/(1+I15)^('01_CONTROL'!$F$11-IF('01_CONTROL'!$F$17=1,0.5,0)),""),"")-'02_COMPANY_INPUTS'!$F$26,"")/'02_COMPANY_INPUTS'!$F$11,""),"") | J20: =IF(AND('01_CONTROL'!$F$13=1,'01_CONTROL'!$F$15=1),IFERROR(IFERROR(IFERROR(SUMPRODUCT('04_DRIVERS_AND_FORECAST'!$G$22:$P$22,1/(1+J15)^('01_CONTROL'!$G$53:$P$53-IF('01_CONTROL'!$F$17=1,0.5,0)),'01_CONTROL'!$G$52:$P$52)+IFERROR(IFERROR(INDEX('04_DRIVERS_AND_FORECAST'!$G$22:$P$22,'01_CONTROL'!$F$11)*(1+F20)/(J15-F20),"")*1/(1+J15)^('01_CONTROL'!$F$11-IF('01_CONTROL'!$F$17=1,0.5,0)),""),"")-'02_COMPANY_INPUTS'!$F$26,"")/'02_COMPANY_INPUTS'!$F$11,""),"") | K20: =IF(AND('01_CONTROL'!$F$13=1,'01_CONTROL'!$F$15=1),IFERROR(IFERROR(IFERROR(SUMPRODUCT('04_DRIVERS_AND_FORECAST'!$G$22:$P$22,1/(1+K15)^('01_CONTROL'!$G$53:$P$53-IF('01_CONTROL'!$F$17=1,0.5,0)),'01_CONTROL'!$G$52:$P$52)+IFERROR(IFERROR(INDEX('04_DRIVERS_AND_FORECAST'!$G$22:$P$22,'01_CONTROL'!$F$11)*(1+F20)/(K15-F20),"")*1/(1+K15)^('01_CONTROL'!$F$11-IF('01_CONTROL'!$F$17=1,0.5,0)),""),"")-'02_COMPANY_INPUTS'!$F$26,"")/'02_COMPANY_INPUTS'!$F$11,""),"") | L20: =IF(AND('01_CONTROL'!$F$13=1,'01_CONTROL'!$F$15=1),IFERROR(IFERROR(IFERROR(SUMPRODUCT('04_DRIVERS_AND_FORECAST'!$G$22:$P$22,1/(1+L15)^('01_CONTROL'!$G$53:$P$53-IF('01_CONTROL'!$F$17=1,0.5,0)),'01_CONTROL'!$G$52:$P$52)+IFERROR(IFERROR(INDEX('04_DRIVERS_AND_FORECAST'!$G$22:$P$22,'01_CONTROL'!$F$11)*(1+F20)/(L15-F20),"")*1/(1+L15)^('01_CONTROL'!$F$11-IF('01_CONTROL'!$F$17=1,0.5,0)),""),"")-'02_COMPANY_INPUTS'!$F$26,"")/'02_COMPANY_INPUTS'!$F$11,""),"")
F21: 0.035 | G21: =IF(AND('01_CONTROL'!$F$13=1,'01_CONTROL'!$F$15=1),IFERROR(IFERROR(IFERROR(SUMPRODUCT('04_DRIVERS_AND_FORECAST'!$G$22:$P$22,1/(1+G15)^('01_CONTROL'!$G$53:$P$53-IF('01_CONTROL'!$F$17=1,0.5,0)),'01_CONTROL'!$G$52:$P$52)+IFERROR(IFERROR(INDEX('04_DRIVERS_AND_FORECAST'!$G$22:$P$22,'01_CONTROL'!$F$11)*(1+F21)/(G15-F21),"")*1/(1+G15)^('01_CONTROL'!$F$11-IF('01_CONTROL'!$F$17=1,0.5,0)),""),"")-'02_COMPANY_INPUTS'!$F$26,"")/'02_COMPANY_INPUTS'!$F$11,""),"") | H21: =IF(AND('01_CONTROL'!$F$13=1,'01_CONTROL'!$F$15=1),IFERROR(IFERROR(IFERROR(SUMPRODUCT('04_DRIVERS_AND_FORECAST'!$G$22:$P$22,1/(1+H15)^('01_CONTROL'!$G$53:$P$53-IF('01_CONTROL'!$F$17=1,0.5,0)),'01_CONTROL'!$G$52:$P$52)+IFERROR(IFERROR(INDEX('04_DRIVERS_AND_FORECAST'!$G$22:$P$22,'01_CONTROL'!$F$11)*(1+F21)/(H15-F21),"")*1/(1+H15)^('01_CONTROL'!$F$11-IF('01_CONTROL'!$F$17=1,0.5,0)),""),"")-'02_COMPANY_INPUTS'!$F$26,"")/'02_COMPANY_INPUTS'!$F$11,""),"") | I21: =IF(AND('01_CONTROL'!$F$13=1,'01_CONTROL'!$F$15=1),IFERROR(IFERROR(IFERROR(SUMPRODUCT('04_DRIVERS_AND_FORECAST'!$G$22:$P$22,1/(1+I15)^('01_CONTROL'!$G$53:$P$53-IF('01_CONTROL'!$F$17=1,0.5,0)),'01_CONTROL'!$G$52:$P$52)+IFERROR(IFERROR(INDEX('04_DRIVERS_AND_FORECAST'!$G$22:$P$22,'01_CONTROL'!$F$11)*(1+F21)/(I15-F21),"")*1/(1+I15)^('01_CONTROL'!$F$11-IF('01_CONTROL'!$F$17=1,0.5,0)),""),"")-'02_COMPANY_INPUTS'!$F$26,"")/'02_COMPANY_INPUTS'!$F$11,""),"") | J21: =IF(AND('01_CONTROL'!$F$13=1,'01_CONTROL'!$F$15=1),IFERROR(IFERROR(IFERROR(SUMPRODUCT('04_DRIVERS_AND_FORECAST'!$G$22:$P$22,1/(1+J15)^('01_CONTROL'!$G$53:$P$53-IF('01_CONTROL'!$F$17=1,0.5,0)),'01_CONTROL'!$G$52:$P$52)+IFERROR(IFERROR(INDEX('04_DRIVERS_AND_FORECAST'!$G$22:$P$22,'01_CONTROL'!$F$11)*(1+F21)/(J15-F21),"")*1/(1+J15)^('01_CONTROL'!$F$11-IF('01_CONTROL'!$F$17=1,0.5,0)),""),"")-'02_COMPANY_INPUTS'!$F$26,"")/'02_COMPANY_INPUTS'!$F$11,""),"") | K21: =IF(AND('01_CONTROL'!$F$13=1,'01_CONTROL'!$F$15=1),IFERROR(IFERROR(IFERROR(SUMPRODUCT('04_DRIVERS_AND_FORECAST'!$G$22:$P$22,1/(1+K15)^('01_CONTROL'!$G$53:$P$53-IF('01_CONTROL'!$F$17=1,0.5,0)),'01_CONTROL'!$G$52:$P$52)+IFERROR(IFERROR(INDEX('04_DRIVERS_AND_FORECAST'!$G$22:$P$22,'01_CONTROL'!$F$11)*(1+F21)/(K15-F21),"")*1/(1+K15)^('01_CONTROL'!$F$11-IF('01_CONTROL'!$F$17=1,0.5,0)),""),"")-'02_COMPANY_INPUTS'!$F$26,"")/'02_COMPANY_INPUTS'!$F$11,""),"") | L21: =IF(AND('01_CONTROL'!$F$13=1,'01_CONTROL'!$F$15=1),IFERROR(IFERROR(IFERROR(SUMPRODUCT('04_DRIVERS_AND_FORECAST'!$G$22:$P$22,1/(1+L15)^('01_CONTROL'!$G$53:$P$53-IF('01_CONTROL'!$F$17=1,0.5,0)),'01_CONTROL'!$G$52:$P$52)+IFERROR(IFERROR(INDEX('04_DRIVERS_AND_FORECAST'!$G$22:$P$22,'01_CONTROL'!$F$11)*(1+F21)/(L15-F21),"")*1/(1+L15)^('01_CONTROL'!$F$11-IF('01_CONTROL'!$F$17=1,0.5,0)),""),"")-'02_COMPANY_INPUTS'!$F$26,"")/'02_COMPANY_INPUTS'!$F$11,""),"")
B24: DCF SENSITIVITY: WACC VS EXIT MULTIPLE (EXIT MULTIPLE)
F25: Exit \ WACC | G25: ='06_DCF_WACC'!$F$20+(-0.02) | H25: ='06_DCF_WACC'!$F$20+(-0.01) | I25: ='06_DCF_WACC'!$F$20+(0.0) | J25: ='06_DCF_WACC'!$F$20+(0.01) | K25: ='06_DCF_WACC'!$F$20+(0.02) | L25: ='06_DCF_WACC'!$F$20+(0.03)
F26: 8 | G26: =IF(AND('01_CONTROL'!$F$13=1,'01_CONTROL'!$F$15=0),IFERROR(IFERROR(IFERROR(SUMPRODUCT('04_DRIVERS_AND_FORECAST'!$G$22:$P$22,1/(1+G25)^('01_CONTROL'!$G$53:$P$53-IF('01_CONTROL'!$F$17=1,0.5,0)),'01_CONTROL'!$G$52:$P$52)+IFERROR(IFERROR(INDEX('04_DRIVERS_AND_FORECAST'!$G$14:$P$14,'01_CONTROL'!$F$11)*F26,"")*1/(1+G25)^('01_CONTROL'!$F$11-IF('01_CONTROL'!$F$17=1,0.5,0)),""),"")-'02_COMPANY_INPUTS'!$F$26,"")/'02_COMPANY_INPUTS'!$F$11,""),"") | H26: =IF(AND('01_CONTROL'!$F$13=1,'01_CONTROL'!$F$15=0),IFERROR(IFERROR(IFERROR(SUMPRODUCT('04_DRIVERS_AND_FORECAST'!$G$22:$P$22,1/(1+H25)^('01_CONTROL'!$G$53:$P$53-IF('01_CONTROL'!$F$17=1,0.5,0)),'01_CONTROL'!$G$52:$P$52)+IFERROR(IFERROR(INDEX('04_DRIVERS_AND_FORECAST'!$G$14:$P$14,'01_CONTROL'!$F$11)*F26,"")*1/(1+H25)^('01_CONTROL'!$F$11-IF('01_CONTROL'!$F$17=1,0.5,0)),""),"")-'02_COMPANY_INPUTS'!$F$26,"")/'02_COMPANY_INPUTS'!$F$11,""),"") | I26: =IF(AND('01_CONTROL'!$F$13=1,'01_CONTROL'!$F$15=0),IFERROR(IFERROR(IFERROR(SUMPRODUCT('04_DRIVERS_AND_FORECAST'!$G$22:$P$22,1/(1+I25)^('01_CONTROL'!$G$53:$P$53-IF('01_CONTROL'!$F$17=1,0.5,0)),'01_CONTROL'!$G$52:$P$52)+IFERROR(IFERROR(INDEX('04_DRIVERS_AND_FORECAST'!$G$14:$P$14,'01_CONTROL'!$F$11)*F26,"")*1/(1+I25)^('01_CONTROL'!$F$11-IF('01_CONTROL'!$F$17=1,0.5,0)),""),"")-'02_COMPANY_INPUTS'!$F$26,"")/'02_COMPANY_INPUTS'!$F$11,""),"") | J26: =IF(AND('01_CONTROL'!$F$13=1,'01_CONTROL'!$F$15=0),IFERROR(IFERROR(IFERROR(SUMPRODUCT('04_DRIVERS_AND_FORECAST'!$G$22:$P$22,1/(1+J25)^('01_CONTROL'!$G$53:$P$53-IF('01_CONTROL'!$F$17=1,0.5,0)),'01_CONTROL'!$G$52:$P$52)+IFERROR(IFERROR(INDEX('04_DRIVERS_AND_FORECAST'!$G$14:$P$14,'01_CONTROL'!$F$11)*F26,"")*1/(1+J25)^('01_CONTROL'!$F$11-IF('01_CONTROL'!$F$17=1,0.5,0)),""),"")-'02_COMPANY_INPUTS'!$F$26,"")/'02_COMPANY_INPUTS'!$F$11,""),"") | K26: =IF(AND('01_CONTROL'!$F$13=1,'01_CONTROL'!$F$15=0),IFERROR(IFERROR(IFERROR(SUMPRODUCT('04_DRIVERS_AND_FORECAST'!$G$22:$P$22,1/(1+K25)^('01_CONTROL'!$G$53:$P$53-IF('01_CONTROL'!$F$17=1,0.5,0)),'01_CONTROL'!$G$52:$P$52)+IFERROR(IFERROR(INDEX('04_DRIVERS_AND_FORECAST'!$G$14:$P$14,'01_CONTROL'!$F$11)*F26,"")*1/(1+K25)^('01_CONTROL'!$F$11-IF('01_CONTROL'!$F$17=1,0.5,0)),""),"")-'02_COMPANY_INPUTS'!$F$26,"")/'02_COMPANY_INPUTS'!$F$11,""),"") | L26: =IF(AND('01_CONTROL'!$F$13=1,'01_CONTROL'!$F$15=0),IFERROR(IFERROR(IFERROR(SUMPRODUCT('04_DRIVERS_AND_FORECAST'!$G$22:$P$22,1/(1+L25)^('01_CONTROL'!$G$53:$P$53-IF('01_CONTROL'!$F$17=1,0.5,0)),'01_CONTROL'!$G$52:$P$52)+IFERROR(IFERROR(INDEX('04_DRIVERS_AND_FORECAST'!$G$14:$P$14,'01_CONTROL'!$F$11)*F26,"")*1/(1+L25)^('01_CONTROL'!$F$11-IF('01_CONTROL'!$F$17=1,0.5,0)),""),"")-'02_COMPANY_INPUTS'!$F$26,"")/'02_COMPANY_INPUTS'!$F$11,""),"")
F27: 9 | G27: =IF(AND('01_CONTROL'!$F$13=1,'01_CONTROL'!$F$15=0),IFERROR(IFERROR(IFERROR(SUMPRODUCT('04_DRIVERS_AND_FORECAST'!$G$22:$P$22,1/(1+G25)^('01_CONTROL'!$G$53:$P$53-IF('01_CONTROL'!$F$17=1,0.5,0)),'01_CONTROL'!$G$52:$P$52)+IFERROR(IFERROR(INDEX('04_DRIVERS_AND_FORECAST'!$G$14:$P$14,'01_CONTROL'!$F$11)*F27,"")*1/(1+G25)^('01_CONTROL'!$F$11-IF('01_CONTROL'!$F$17=1,0.5,0)),""),"")-'02_COMPANY_INPUTS'!$F$26,"")/'02_COMPANY_INPUTS'!$F$11,""),"") | H27: =IF(AND('01_CONTROL'!$F$13=1,'01_CONTROL'!$F$15=0),IFERROR(IFERROR(IFERROR(SUMPRODUCT('04_DRIVERS_AND_FORECAST'!$G$22:$P$22,1/(1+H25)^('01_CONTROL'!$G$53:$P$53-IF('01_CONTROL'!$F$17=1,0.5,0)),'01_CONTROL'!$G$52:$P$52)+IFERROR(IFERROR(INDEX('04_DRIVERS_AND_FORECAST'!$G$14:$P$14,'01_CONTROL'!$F$11)*F27,"")*1/(1+H25)^('01_CONTROL'!$F$11-IF('01_CONTROL'!$F$17=1,0.5,0)),""),"")-'02_COMPANY_INPUTS'!$F$26,"")/'02_COMPANY_INPUTS'!$F$11,""),"") | I27: =IF(AND('01_CONTROL'!$F$13=1,'01_CONTROL'!$F$15=0),IFERROR(IFERROR(IFERROR(SUMPRODUCT('04_DRIVERS_AND_FORECAST'!$G$22:$P$22,1/(1+I25)^('01_CONTROL'!$G$53:$P$53-IF('01_CONTROL'!$F$17=1,0.5,0)),'01_CONTROL'!$G$52:$P$52)+IFERROR(IFERROR(INDEX('04_DRIVERS_AND_FORECAST'!$G$14:$P$14,'01_CONTROL'!$F$11)*F27,"")*1/(1+I25)^('01_CONTROL'!$F$11-IF('01_CONTROL'!$F$17=1,0.5,0)),""),"")-'02_COMPANY_INPUTS'!$F$26,"")/'02_COMPANY_INPUTS'!$F$11,""),"") | J27: =IF(AND('01_CONTROL'!$F$13=1,'01_CONTROL'!$F$15=0),IFERROR(IFERROR(IFERROR(SUMPRODUCT('04_DRIVERS_AND_FORECAST'!$G$22:$P$22,1/(1+J25)^('01_CONTROL'!$G$53:$P$53-IF('01_CONTROL'!$F$17=1,0.5,0)),'01_CONTROL'!$G$52:$P$52)+IFERROR(IFERROR(INDEX('04_DRIVERS_AND_FORECAST'!$G$14:$P$14,'01_CONTROL'!$F$11)*F27,"")*1/(1+J25)^('01_CONTROL'!$F$11-IF('01_CONTROL'!$F$17=1,0.5,0)),""),"")-'02_COMPANY_INPUTS'!$F$26,"")/'02_COMPANY_INPUTS'!$F$11,""),"") | K27: =IF(AND('01_CONTROL'!$F$13=1,'01_CONTROL'!$F$15=0),IFERROR(IFERROR(IFERROR(SUMPRODUCT('04_DRIVERS_AND_FORECAST'!$G$22:$P$22,1/(1+K25)^('01_CONTROL'!$G$53:$P$53-IF('01_CONTROL'!$F$17=1,0.5,0)),'01_CONTROL'!$G$52:$P$52)+IFERROR(IFERROR(INDEX('04_DRIVERS_AND_FORECAST'!$G$14:$P$14,'01_CONTROL'!$F$11)*F27,"")*1/(1+K25)^('01_CONTROL'!$F$11-IF('01_CONTROL'!$F$17=1,0.5,0)),""),"")-'02_COMPANY_INPUTS'!$F$26,"")/'02_COMPANY_INPUTS'!$F$11,""),"") | L27: =IF(AND('01_CONTROL'!$F$13=1,'01_CONTROL'!$F$15=0),IFERROR(IFERROR(IFERROR(SUMPRODUCT('04_DRIVERS_AND_FORECAST'!$G$22:$P$22,1/(1+L25)^('01_CONTROL'!$G$53:$P$53-IF('01_CONTROL'!$F$17=1,0.5,0)),'01_CONTROL'!$G$52:$P$52)+IFERROR(IFERROR(INDEX('04_DRIVERS_AND_FORECAST'!$G$14:$P$14,'01_CONTROL'!$F$11)*F27,"")*1/(1+L25)^('01_CONTROL'!$F$11-IF('01_CONTROL'!$F$17=1,0.5,0)),""),"")-'02_COMPANY_INPUTS'!$F$26,"")/'02_COMPANY_INPUTS'!$F$11,""),"")
F28: 10 | G28: =IF(AND('01_CONTROL'!$F$13=1,'01_CONTROL'!$F$15=0),IFERROR(IFERROR(IFERROR(SUMPRODUCT('04_DRIVERS_AND_FORECAST'!$G$22:$P$22,1/(1+G25)^('01_CONTROL'!$G$53:$P$53-IF('01_CONTROL'!$F$17=1,0.5,0)),'01_CONTROL'!$G$52:$P$52)+IFERROR(IFERROR(INDEX('04_DRIVERS_AND_FORECAST'!$G$14:$P$14,'01_CONTROL'!$F$11)*F28,"")*1/(1+G25)^('01_CONTROL'!$F$11-IF('01_CONTROL'!$F$17=1,0.5,0)),""),"")-'02_COMPANY_INPUTS'!$F$26,"")/'02_COMPANY_INPUTS'!$F$11,""),"") | H28: =IF(AND('01_CONTROL'!$F$13=1,'01_CONTROL'!$F$15=0),IFERROR(IFERROR(IFERROR(SUMPRODUCT('04_DRIVERS_AND_FORECAST'!$G$22:$P$22,1/(1+H25)^('01_CONTROL'!$G$53:$P$53-IF('01_CONTROL'!$F$17=1,0.5,0)),'01_CONTROL'!$G$52:$P$52)+IFERROR(IFERROR(INDEX('04_DRIVERS_AND_FORECAST'!$G$14:$P$14,'01_CONTROL'!$F$11)*F28,"")*1/(1+H25)^('01_CONTROL'!$F$11-IF('01_CONTROL'!$F$17=1,0.5,0)),""),"")-'02_COMPANY_INPUTS'!$F$26,"")/'02_COMPANY_INPUTS'!$F$11,""),"") | I28: =IF(AND('01_CONTROL'!$F$13=1,'01_CONTROL'!$F$15=0),IFERROR(IFERROR(IFERROR(SUMPRODUCT('04_DRIVERS_AND_FORECAST'!$G$22:$P$22,1/(1+I25)^('01_CONTROL'!$G$53:$P$53-IF('01_CONTROL'!$F$17=1,0.5,0)),'01_CONTROL'!$G$52:$P$52)+IFERROR(IFERROR(INDEX('04_DRIVERS_AND_FORECAST'!$G$14:$P$14,'01_CONTROL'!$F$11)*F28,"")*1/(1+I25)^('01_CONTROL'!$F$11-IF('01_CONTROL'!$F$17=1,0.5,0)),""),"")-'02_COMPANY_INPUTS'!$F$26,"")/'02_COMPANY_INPUTS'!$F$11,""),"") | J28: =IF(AND('01_CONTROL'!$F$13=1,'01_CONTROL'!$F$15=0),IFERROR(IFERROR(IFERROR(SUMPRODUCT('04_DRIVERS_AND_FORECAST'!$G$22:$P$22,1/(1+J25)^('01_CONTROL'!$G$53:$P$53-IF('01_CONTROL'!$F$17=1,0.5,0)),'01_CONTROL'!$G$52:$P$52)+IFERROR(IFERROR(INDEX('04_DRIVERS_AND_FORECAST'!$G$14:$P$14,'01_CONTROL'!$F$11)*F28,"")*1/(1+J25)^('01_CONTROL'!$F$11-IF('01_CONTROL'!$F$17=1,0.5,0)),""),"")-'02_COMPANY_INPUTS'!$F$26,"")/'02_COMPANY_INPUTS'!$F$11,""),"") | K28: =IF(AND('01_CONTROL'!$F$13=1,'01_CONTROL'!$F$15=0),IFERROR(IFERROR(IFERROR(SUMPRODUCT('04_DRIVERS_AND_FORECAST'!$G$22:$P$22,1/(1+K25)^('01_CONTROL'!$G$53:$P$53-IF('01_CONTROL'!$F$17=1,0.5,0)),'01_CONTROL'!$G$52:$P$52)+IFERROR(IFERROR(INDEX('04_DRIVERS_AND_FORECAST'!$G$14:$P$14,'01_CONTROL'!$F$11)*F28,"")*1/(1+K25)^('01_CONTROL'!$F$11-IF('01_CONTROL'!$F$17=1,0.5,0)),""),"")-'02_COMPANY_INPUTS'!$F$26,"")/'02_COMPANY_INPUTS'!$F$11,""),"") | L28: =IF(AND('01_CONTROL'!$F$13=1,'01_CONTROL'!$F$15=0),IFERROR(IFERROR(IFERROR(SUMPRODUCT('04_DRIVERS_AND_FORECAST'!$G$22:$P$22,1/(1+L25)^('01_CONTROL'!$G$53:$P$53-IF('01_CONTROL'!$F$17=1,0.5,0)),'01_CONTROL'!$G$52:$P$52)+IFERROR(IFERROR(INDEX('04_DRIVERS_AND_FORECAST'!$G$14:$P$14,'01_CONTROL'!$F$11)*F28,"")*1/(1+L25)^('01_CONTROL'!$F$11-IF('01_CONTROL'!$F$17=1,0.5,0)),""),"")-'02_COMPANY_INPUTS'!$F$26,"")/'02_COMPANY_INPUTS'!$F$11,""),"")
F29: 11 | G29: =IF(AND('01_CONTROL'!$F$13=1,'01_CONTROL'!$F$15=0),IFERROR(IFERROR(IFERROR(SUMPRODUCT('04_DRIVERS_AND_FORECAST'!$G$22:$P$22,1/(1+G25)^('01_CONTROL'!$G$53:$P$53-IF('01_CONTROL'!$F$17=1,0.5,0)),'01_CONTROL'!$G$52:$P$52)+IFERROR(IFERROR(INDEX('04_DRIVERS_AND_FORECAST'!$G$14:$P$14,'01_CONTROL'!$F$11)*F29,"")*1/(1+G25)^('01_CONTROL'!$F$11-IF('01_CONTROL'!$F$17=1,0.5,0)),""),"")-'02_COMPANY_INPUTS'!$F$26,"")/'02_COMPANY_INPUTS'!$F$11,""),"") | H29: =IF(AND('01_CONTROL'!$F$13=1,'01_CONTROL'!$F$15=0),IFERROR(IFERROR(IFERROR(SUMPRODUCT('04_DRIVERS_AND_FORECAST'!$G$22:$P$22,1/(1+H25)^('01_CONTROL'!$G$53:$P$53-IF('01_CONTROL'!$F$17=1,0.5,0)),'01_CONTROL'!$G$52:$P$52)+IFERROR(IFERROR(INDEX('04_DRIVERS_AND_FORECAST'!$G$14:$P$14,'01_CONTROL'!$F$11)*F29,"")*1/(1+H25)^('01_CONTROL'!$F$11-IF('01_CONTROL'!$F$17=1,0.5,0)),""),"")-'02_COMPANY_INPUTS'!$F$26,"")/'02_COMPANY_INPUTS'!$F$11,""),"") | I29: =IF(AND('01_CONTROL'!$F$13=1,'01_CONTROL'!$F$15=0),IFERROR(IFERROR(IFERROR(SUMPRODUCT('04_DRIVERS_AND_FORECAST'!$G$22:$P$22,1/(1+I25)^('01_CONTROL'!$G$53:$P$53-IF('01_CONTROL'!$F$17=1,0.5,0)),'01_CONTROL'!$G$52:$P$52)+IFERROR(IFERROR(INDEX('04_DRIVERS_AND_FORECAST'!$G$14:$P$14,'01_CONTROL'!$F$11)*F29,"")*1/(1+I25)^('01_CONTROL'!$F$11-IF('01_CONTROL'!$F$17=1,0.5,0)),""),"")-'02_COMPANY_INPUTS'!$F$26,"")/'02_COMPANY_INPUTS'!$F$11,""),"") | J29: =IF(AND('01_CONTROL'!$F$13=1,'01_CONTROL'!$F$15=0),IFERROR(IFERROR(IFERROR(SUMPRODUCT('04_DRIVERS_AND_FORECAST'!$G$22:$P$22,1/(1+J25)^('01_CONTROL'!$G$53:$P$53-IF('01_CONTROL'!$F$17=1,0.5,0)),'01_CONTROL'!$G$52:$P$52)+IFERROR(IFERROR(INDEX('04_DRIVERS_AND_FORECAST'!$G$14:$P$14,'01_CONTROL'!$F$11)*F29,"")*1/(1+J25)^('01_CONTROL'!$F$11-IF('01_CONTROL'!$F$17=1,0.5,0)),""),"")-'02_COMPANY_INPUTS'!$F$26,"")/'02_COMPANY_INPUTS'!$F$11,""),"") | K29: =IF(AND('01_CONTROL'!$F$13=1,'01_CONTROL'!$F$15=0),IFERROR(IFERROR(IFERROR(SUMPRODUCT('04_DRIVERS_AND_FORECAST'!$G$22:$P$22,1/(1+K25)^('01_CONTROL'!$G$53:$P$53-IF('01_CONTROL'!$F$17=1,0.5,0)),'01_CONTROL'!$G$52:$P$52)+IFERROR(IFERROR(INDEX('04_DRIVERS_AND_FORECAST'!$G$14:$P$14,'01_CONTROL'!$F$11)*F29,"")*1/(1+K25)^('01_CONTROL'!$F$11-IF('01_CONTROL'!$F$17=1,0.5,0)),""),"")-'02_COMPANY_INPUTS'!$F$26,"")/'02_COMPANY_INPUTS'!$F$11,""),"") | L29: =IF(AND('01_CONTROL'!$F$13=1,'01_CONTROL'!$F$15=0),IFERROR(IFERROR(IFERROR(SUMPRODUCT('04_DRIVERS_AND_FORECAST'!$G$22:$P$22,1/(1+L25)^('01_CONTROL'!$G$53:$P$53-IF('01_CONTROL'!$F$17=1,0.5,0)),'01_CONTROL'!$G$52:$P$52)+IFERROR(IFERROR(INDEX('04_DRIVERS_AND_FORECAST'!$G$14:$P$14,'01_CONTROL'!$F$11)*F29,"")*1/(1+L25)^('01_CONTROL'!$F$11-IF('01_CONTROL'!$F$17=1,0.5,0)),""),"")-'02_COMPANY_INPUTS'!$F$26,"")/'02_COMPANY_INPUTS'!$F$11,""),"")
F30: 12 | G30: =IF(AND('01_CONTROL'!$F$13=1,'01_CONTROL'!$F$15=0),IFERROR(IFERROR(IFERROR(SUMPRODUCT('04_DRIVERS_AND_FORECAST'!$G$22:$P$22,1/(1+G25)^('01_CONTROL'!$G$53:$P$53-IF('01_CONTROL'!$F$17=1,0.5,0)),'01_CONTROL'!$G$52:$P$52)+IFERROR(IFERROR(INDEX('04_DRIVERS_AND_FORECAST'!$G$14:$P$14,'01_CONTROL'!$F$11)*F30,"")*1/(1+G25)^('01_CONTROL'!$F$11-IF('01_CONTROL'!$F$17=1,0.5,0)),""),"")-'02_COMPANY_INPUTS'!$F$26,"")/'02_COMPANY_INPUTS'!$F$11,""),"") | H30: =IF(AND('01_CONTROL'!$F$13=1,'01_CONTROL'!$F$15=0),IFERROR(IFERROR(IFERROR(SUMPRODUCT('04_DRIVERS_AND_FORECAST'!$G$22:$P$22,1/(1+H25)^('01_CONTROL'!$G$53:$P$53-IF('01_CONTROL'!$F$17=1,0.5,0)),'01_CONTROL'!$G$52:$P$52)+IFERROR(IFERROR(INDEX('04_DRIVERS_AND_FORECAST'!$G$14:$P$14,'01_CONTROL'!$F$11)*F30,"")*1/(1+H25)^('01_CONTROL'!$F$11-IF('01_CONTROL'!$F$17=1,0.5,0)),""),"")-'02_COMPANY_INPUTS'!$F$26,"")/'02_COMPANY_INPUTS'!$F$11,""),"") | I30: =IF(AND('01_CONTROL'!$F$13=1,'01_CONTROL'!$F$15=0),IFERROR(IFERROR(IFERROR(SUMPRODUCT('04_DRIVERS_AND_FORECAST'!$G$22:$P$22,1/(1+I25)^('01_CONTROL'!$G$53:$P$53-IF('01_CONTROL'!$F$17=1,0.5,0)),'01_CONTROL'!$G$52:$P$52)+IFERROR(IFERROR(INDEX('04_DRIVERS_AND_FORECAST'!$G$14:$P$14,'01_CONTROL'!$F$11)*F30,"")*1/(1+I25)^('01_CONTROL'!$F$11-IF('01_CONTROL'!$F$17=1,0.5,0)),""),"")-'02_COMPANY_INPUTS'!$F$26,"")/'02_COMPANY_INPUTS'!$F$11,""),"") | J30: =IF(AND('01_CONTROL'!$F$13=1,'01_CONTROL'!$F$15=0),IFERROR(IFERROR(IFERROR(SUMPRODUCT('04_DRIVERS_AND_FORECAST'!$G$22:$P$22,1/(1+J25)^('01_CONTROL'!$G$53:$P$53-IF('01_CONTROL'!$F$17=1,0.5,0)),'01_CONTROL'!$G$52:$P$52)+IFERROR(IFERROR(INDEX('04_DRIVERS_AND_FORECAST'!$G$14:$P$14,'01_CONTROL'!$F$11)*F30,"")*1/(1+J25)^('01_CONTROL'!$F$11-IF('01_CONTROL'!$F$17=1,0.5,0)),""),"")-'02_COMPANY_INPUTS'!$F$26,"")/'02_COMPANY_INPUTS'!$F$11,""),"") | K30: =IF(AND('01_CONTROL'!$F$13=1,'01_CONTROL'!$F$15=0),IFERROR(IFERROR(IFERROR(SUMPRODUCT('04_DRIVERS_AND_FORECAST'!$G$22:$P$22,1/(1+K25)^('01_CONTROL'!$G$53:$P$53-IF('01_CONTROL'!$F$17=1,0.5,0)),'01_CONTROL'!$G$52:$P$52)+IFERROR(IFERROR(INDEX('04_DRIVERS_AND_FORECAST'!$G$14:$P$14,'01_CONTROL'!$F$11)*F30,"")*1/(1+K25)^('01_CONTROL'!$F$11-IF('01_CONTROL'!$F$17=1,0.5,0)),""),"")-'02_COMPANY_INPUTS'!$F$26,"")/'02_COMPANY_INPUTS'!$F$11,""),"") | L30: =IF(AND('01_CONTROL'!$F$13=1,'01_CONTROL'!$F$15=0),IFERROR(IFERROR(IFERROR(SUMPRODUCT('04_DRIVERS_AND_FORECAST'!$G$22:$P$22,1/(1+L25)^('01_CONTROL'!$G$53:$P$53-IF('01_CONTROL'!$F$17=1,0.5,0)),'01_CONTROL'!$G$52:$P$52)+IFERROR(IFERROR(INDEX('04_DRIVERS_AND_FORECAST'!$G$14:$P$14,'01_CONTROL'!$F$11)*F30,"")*1/(1+L25)^('01_CONTROL'!$F$11-IF('01_CONTROL'!$F$17=1,0.5,0)),""),"")-'02_COMPANY_INPUTS'!$F$26,"")/'02_COMPANY_INPUTS'!$F$11,""),"")
F31: 13 | G31: =IF(AND('01_CONTROL'!$F$13=1,'01_CONTROL'!$F$15=0),IFERROR(IFERROR(IFERROR(SUMPRODUCT('04_DRIVERS_AND_FORECAST'!$G$22:$P$22,1/(1+G25)^('01_CONTROL'!$G$53:$P$53-IF('01_CONTROL'!$F$17=1,0.5,0)),'01_CONTROL'!$G$52:$P$52)+IFERROR(IFERROR(INDEX('04_DRIVERS_AND_FORECAST'!$G$14:$P$14,'01_CONTROL'!$F$11)*F31,"")*1/(1+G25)^('01_CONTROL'!$F$11-IF('01_CONTROL'!$F$17=1,0.5,0)),""),"")-'02_COMPANY_INPUTS'!$F$26,"")/'02_COMPANY_INPUTS'!$F$11,""),"") | H31: =IF(AND('01_CONTROL'!$F$13=1,'01_CONTROL'!$F$15=0),IFERROR(IFERROR(IFERROR(SUMPRODUCT('04_DRIVERS_AND_FORECAST'!$G$22:$P$22,1/(1+H25)^('01_CONTROL'!$G$53:$P$53-IF('01_CONTROL'!$F$17=1,0.5,0)),'01_CONTROL'!$G$52:$P$52)+IFERROR(IFERROR(INDEX('04_DRIVERS_AND_FORECAST'!$G$14:$P$14,'01_CONTROL'!$F$11)*F31,"")*1/(1+H25)^('01_CONTROL'!$F$11-IF('01_CONTROL'!$F$17=1,0.5,0)),""),"")-'02_COMPANY_INPUTS'!$F$26,"")/'02_COMPANY_INPUTS'!$F$11,""),"") | I31: =IF(AND('01_CONTROL'!$F$13=1,'01_CONTROL'!$F$15=0),IFERROR(IFERROR(IFERROR(SUMPRODUCT('04_DRIVERS_AND_FORECAST'!$G$22:$P$22,1/(1+I25)^('01_CONTROL'!$G$53:$P$53-IF('01_CONTROL'!$F$17=1,0.5,0)),'01_CONTROL'!$G$52:$P$52)+IFERROR(IFERROR(INDEX('04_DRIVERS_AND_FORECAST'!$G$14:$P$14,'01_CONTROL'!$F$11)*F31,"")*1/(1+I25)^('01_CONTROL'!$F$11-IF('01_CONTROL'!$F$17=1,0.5,0)),""),"")-'02_COMPANY_INPUTS'!$F$26,"")/'02_COMPANY_INPUTS'!$F$11,""),"") | J31: =IF(AND('01_CONTROL'!$F$13=1,'01_CONTROL'!$F$15=0),IFERROR(IFERROR(IFERROR(SUMPRODUCT('04_DRIVERS_AND_FORECAST'!$G$22:$P$22,1/(1+J25)^('01_CONTROL'!$G$53:$P$53-IF('01_CONTROL'!$F$17=1,0.5,0)),'01_CONTROL'!$G$52:$P$52)+IFERROR(IFERROR(INDEX('04_DRIVERS_AND_FORECAST'!$G$14:$P$14,'01_CONTROL'!$F$11)*F31,"")*1/(1+J25)^('01_CONTROL'!$F$11-IF('01_CONTROL'!$F$17=1,0.5,0)),""),"")-'02_COMPANY_INPUTS'!$F$26,"")/'02_COMPANY_INPUTS'!$F$11,""),"") | K31: =IF(AND('01_CONTROL'!$F$13=1,'01_CONTROL'!$F$15=0),IFERROR(IFERROR(IFERROR(SUMPRODUCT('04_DRIVERS_AND_FORECAST'!$G$22:$P$22,1/(1+K25)^('01_CONTROL'!$G$53:$P$53-IF('01_CONTROL'!$F$17=1,0.5,0)),'01_CONTROL'!$G$52:$P$52)+IFERROR(IFERROR(INDEX('04_DRIVERS_AND_FORECAST'!$G$14:$P$14,'01_CONTROL'!$F$11)*F31,"")*1/(1+K25)^('01_CONTROL'!$F$11-IF('01_CONTROL'!$F$17=1,0.5,0)),""),"")-'02_COMPANY_INPUTS'!$F$26,"")/'02_COMPANY_INPUTS'!$F$11,""),"") | L31: =IF(AND('01_CONTROL'!$F$13=1,'01_CONTROL'!$F$15=0),IFERROR(IFERROR(IFERROR(SUMPRODUCT('04_DRIVERS_AND_FORECAST'!$G$22:$P$22,1/(1+L25)^('01_CONTROL'!$G$53:$P$53-IF('01_CONTROL'!$F$17=1,0.5,0)),'01_CONTROL'!$G$52:$P$52)+IFERROR(IFERROR(INDEX('04_DRIVERS_AND_FORECAST'!$G$14:$P$14,'01_CONTROL'!$F$11)*F31,"")*1/(1+L25)^('01_CONTROL'!$F$11-IF('01_CONTROL'!$F$17=1,0.5,0)),""),"")-'02_COMPANY_INPUTS'!$F$26,"")/'02_COMPANY_INPUTS'!$F$11,""),"")
B34: OPERATING SENSITIVITY (QUICK): GROWTH DELTA VS EBITDA MARGIN DELTA (EV/EBITDA)
F35: Margin Δ \ Growth Δ | G35: -0.02 | H35: -0.01 | I35: 0 | J35: 0.01 | K35: 0.02
F36: -0.02 | G36: IFERROR(IFERROR(IFERROR('05_TRADING_COMPS'!$F$32*IFERROR(IFERROR('02_COMPANY_INPUTS'!$F$30*(1+'01_CONTROL'!$G$71+G35),"")*('01_CONTROL'!$G$72+F36),""),"")-'02_COMPANY_INPUTS'!$F$26,"")/'02_COMPANY_INPUTS'!$F$11,"") | H36: IFERROR(IFERROR(IFERROR('05_TRADING_COMPS'!$F$32*IFERROR(IFERROR('02_COMPANY_INPUTS'!$F$30*(1+'01_CONTROL'!$G$71+H35),"")*('01_CONTROL'!$G$72+F36),""),"")-'02_COMPANY_INPUTS'!$F$26,"")/'02_COMPANY_INPUTS'!$F$11,"") | I36: IFERROR(IFERROR(IFERROR('05_TRADING_COMPS'!$F$32*IFERROR(IFERROR('02_COMPANY_INPUTS'!$F$30*(1+'01_CONTROL'!$G$71+I35),"")*('01_CONTROL'!$G$72+F36),""),"")-'02_COMPANY_INPUTS'!$F$26,"")/'02_COMPANY_INPUTS'!$F$11,"") | J36: IFERROR(IFERROR(IFERROR('05_TRADING_COMPS'!$F$32*IFERROR(IFERROR('02_COMPANY_INPUTS'!$F$30*(1+'01_CONTROL'!$G$71+J35),"")*('01_CONTROL'!$G$72+F36),""),"")-'02_COMPANY_INPUTS'!$F$26,"")/'02_COMPANY_INPUTS'!$F$11,"") | K36: IFERROR(IFERROR(IFERROR('05_TRADING_COMPS'!$F$32*IFERROR(IFERROR('02_COMPANY_INPUTS'!$F$30*(1+'01_CONTROL'!$G$71+K35),"")*('01_CONTROL'!$G$72+F36),""),"")-'02_COMPANY_INPUTS'!$F$26,"")/'02_COMPANY_INPUTS'!$F$11,"")
F37: -0.01 | G37: IFERROR(IFERROR(IFERROR('05_TRADING_COMPS'!$F$32*IFERROR(IFERROR('02_COMPANY_INPUTS'!$F$30*(1+'01_CONTROL'!$G$71+G35),"")*('01_CONTROL'!$G$72+F37),""),"")-'02_COMPANY_INPUTS'!$F$26,"")/'02_COMPANY_INPUTS'!$F$11,"") | H37: IFERROR(IFERROR(IFERROR('05_TRADING_COMPS'!$F$32*IFERROR(IFERROR('02_COMPANY_INPUTS'!$F$30*(1+'01_CONTROL'!$G$71+H35),"")*('01_CONTROL'!$G$72+F37),""),"")-'02_COMPANY_INPUTS'!$F$26,"")/'02_COMPANY_INPUTS'!$F$11,"") | I37: IFERROR(IFERROR(IFERROR('05_TRADING_COMPS'!$F$32*IFERROR(IFERROR('02_COMPANY_INPUTS'!$F$30*(1+'01_CONTROL'!$G$71+I35),"")*('01_CONTROL'!$G$72+F37),""),"")-'02_COMPANY_INPUTS'!$F$26,"")/'02_COMPANY_INPUTS'!$F$11,"") | J37: IFERROR(IFERROR(IFERROR('05_TRADING_COMPS'!$F$32*IFERROR(IFERROR('02_COMPANY_INPUTS'!$F$30*(1+'01_CONTROL'!$G$71+J35),"")*('01_CONTROL'!$G$72+F37),""),"")-'02_COMPANY_INPUTS'!$F$26,"")/'02_COMPANY_INPUTS'!$F$11,"") | K37: IFERROR(IFERROR(IFERROR('05_TRADING_COMPS'!$F$32*IFERROR(IFERROR('02_COMPANY_INPUTS'!$F$30*(1+'01_CONTROL'!$G$71+K35),"")*('01_CONTROL'!$G$72+F37),""),"")-'02_COMPANY_INPUTS'!$F$26,"")/'02_COMPANY_INPUTS'!$F$11,"")
F38: 0 | G38: IFERROR(IFERROR(IFERROR('05_TRADING_COMPS'!$F$32*IFERROR(IFERROR('02_COMPANY_INPUTS'!$F$30*(1+'01_CONTROL'!$G$71+G35),"")*('01_CONTROL'!$G$72+F38),""),"")-'02_COMPANY_INPUTS'!$F$26,"")/'02_COMPANY_INPUTS'!$F$11,"") | H38: IFERROR(IFERROR(IFERROR('05_TRADING_COMPS'!$F$32*IFERROR(IFERROR('02_COMPANY_INPUTS'!$F$30*(1+'01_CONTROL'!$G$71+H35),"")*('01_CONTROL'!$G$72+F38),""),"")-'02_COMPANY_INPUTS'!$F$26,"")/'02_COMPANY_INPUTS'!$F$11,"") | I38: IFERROR(IFERROR(IFERROR('05_TRADING_COMPS'!$F$32*IFERROR(IFERROR('02_COMPANY_INPUTS'!$F$30*(1+'01_CONTROL'!$G$71+I35),"")*('01_CONTROL'!$G$72+F38),""),"")-'02_COMPANY_INPUTS'!$F$26,"")/'02_COMPANY_INPUTS'!$F$11,"") | J38: IFERROR(IFERROR(IFERROR('05_TRADING_COMPS'!$F$32*IFERROR(IFERROR('02_COMPANY_INPUTS'!$F$30*(1+'01_CONTROL'!$G$71+J35),"")*('01_CONTROL'!$G$72+F38),""),"")-'02_COMPANY_INPUTS'!$F$26,"")/'02_COMPANY_INPUTS'!$F$11,"") | K38: IFERROR(IFERROR(IFERROR('05_TRADING_COMPS'!$F$32*IFERROR(IFERROR('02_COMPANY_INPUTS'!$F$30*(1+'01_CONTROL'!$G$71+K35),"")*('01_CONTROL'!$G$72+F38),""),"")-'02_COMPANY_INPUTS'!$F$26,"")/'02_COMPANY_INPUTS'!$F$11,"")
F39: 0.01 | G39: IFERROR(IFERROR(IFERROR('05_TRADING_COMPS'!$F$32*IFERROR(IFERROR('02_COMPANY_INPUTS'!$F$30*(1+'01_CONTROL'!$G$71+G35),"")*('01_CONTROL'!$G$72+F39),""),"")-'02_COMPANY_INPUTS'!$F$26,"")/'02_COMPANY_INPUTS'!$F$11,"") | H39: IFERROR(IFERROR(IFERROR('05_TRADING_COMPS'!$F$32*IFERROR(IFERROR('02_COMPANY_INPUTS'!$F$30*(1+'01_CONTROL'!$G$71+H35),"")*('01_CONTROL'!$G$72+F39),""),"")-'02_COMPANY_INPUTS'!$F$26,"")/'02_COMPANY_INPUTS'!$F$11,"") | I39: IFERROR(IFERROR(IFERROR('05_TRADING_COMPS'!$F$32*IFERROR(IFERROR('02_COMPANY_INPUTS'!$F$30*(1+'01_CONTROL'!$G$71+I35),"")*('01_CONTROL'!$G$72+F39),""),"")-'02_COMPANY_INPUTS'!$F$26,"")/'02_COMPANY_INPUTS'!$F$11,"") | J39: IFERROR(IFERROR(IFERROR('05_TRADING_COMPS'!$F$32*IFERROR(IFERROR('02_COMPANY_INPUTS'!$F$30*(1+'01_CONTROL'!$G$71+J35),"")*('01_CONTROL'!$G$72+F39),""),"")-'02_COMPANY_INPUTS'!$F$26,"")/'02_COMPANY_INPUTS'!$F$11,"") | K39: IFERROR(IFERROR(IFERROR('05_TRADING_COMPS'!$F$32*IFERROR(IFERROR('02_COMPANY_INPUTS'!$F$30*(1+'01_CONTROL'!$G$71+K35),"")*('01_CONTROL'!$G$72+F39),""),"")-'02_COMPANY_INPUTS'!$F$26,"")/'02_COMPANY_INPUTS'!$F$11,"")
F40: 0.02 | G40: IFERROR(IFERROR(IFERROR('05_TRADING_COMPS'!$F$32*IFERROR(IFERROR('02_COMPANY_INPUTS'!$F$30*(1+'01_CONTROL'!$G$71+G35),"")*('01_CONTROL'!$G$72+F40),""),"")-'02_COMPANY_INPUTS'!$F$26,"")/'02_COMPANY_INPUTS'!$F$11,"") | H40: IFERROR(IFERROR(IFERROR('05_TRADING_COMPS'!$F$32*IFERROR(IFERROR('02_COMPANY_INPUTS'!$F$30*(1+'01_CONTROL'!$G$71+H35),"")*('01_CONTROL'!$G$72+F40),""),"")-'02_COMPANY_INPUTS'!$F$26,"")/'02_COMPANY_INPUTS'!$F$11,"") | I40: IFERROR(IFERROR(IFERROR('05_TRADING_COMPS'!$F$32*IFERROR(IFERROR('02_COMPANY_INPUTS'!$F$30*(1+'01_CONTROL'!$G$71+I35),"")*('01_CONTROL'!$G$72+F40),""),"")-'02_COMPANY_INPUTS'!$F$26,"")/'02_COMPANY_INPUTS'!$F$11,"") | J40: IFERROR(IFERROR(IFERROR('05_TRADING_COMPS'!$F$32*IFERROR(IFERROR('02_COMPANY_INPUTS'!$F$30*(1+'01_CONTROL'!$G$71+J35),"")*('01_CONTROL'!$G$72+F40),""),"")-'02_COMPANY_INPUTS'!$F$26,"")/'02_COMPANY_INPUTS'!$F$11,"") | K40: IFERROR(IFERROR(IFERROR('05_TRADING_COMPS'!$F$32*IFERROR(IFERROR('02_COMPANY_INPUTS'!$F$30*(1+'01_CONTROL'!$G$71+K35),"")*('01_CONTROL'!$G$72+F40),""),"")-'02_COMPANY_INPUTS'!$F$26,"")/'02_COMPANY_INPUTS'!$F$11,"")
B43: COMPS SENSITIVITY (EV/EBITDA MULTIPLE QUARTILES)
B44: Implied price P25 | C44: CCY | F44: ='08_TRIANGULATION_RANGE'!$F$16
B45: Implied price Median | C45: CCY | F45: ='08_TRIANGULATION_RANGE'!$F$17
B46: Implied price P75 | C46: CCY | F46: ='08_TRIANGULATION_RANGE'!$F$18

Sheet 80_VAL_LEARN_MAP
B2: 80 Valuation Explainability Map
B3: Top KPIs and how to explain them in a deal setting.
B5: Learning Layer (additive). All refs tie to model cells. Do not edit calculation tabs unless fixing a confirmed error.
B7: CONTENT
B9: KPI / output | C9: Model ref | D9: Definition (what it is) | E9: Primary drivers (where to look) | F9: Directional intuition (what increases it) | G9: Common pitfalls | H9: Sanity checks (quick) | I9: VP/client script (how to say it)
B10: Current share price | C10: 08_TRIANGULATION_RANGE!F47 | D10: Spot price used to compute market cap and upside/downside. | E10: 02_COMPANY_INPUTS: share price input (if public); check data source + date. | F10: Higher price increases market cap, reduces upside % at same implied price. | G10: Using stale price or wrong currency; mixing ADR vs local listing. | H10: Matches Bloomberg/Refinitiv as-of date; currency matches model. | I10: We anchor to the current spot price to express upside/downside versus market.
B11: Shares outstanding (mm) | C11: 08_TRIANGULATION_RANGE!F48 | D11: Basic share count in millions used to convert equity value to price per share. | E11: 02_COMPANY_INPUTS: diluted vs basic; include options/convertibles if relevant. | F11: More shares lowers implied price per share for the same equity value. | G11: Mixing basic and fully diluted; forgetting treasury stock / buybacks. | H11: Market cap / share price ≈ shares; reconcile to latest filings. | I11: Share count drives the per share translation. We use the fully diluted count for decision making.
B12: Market cap | C12: 08_TRIANGULATION_RANGE!F49 | D12: Equity value at spot price: price × shares. | E12: Current price + shares outstanding. | F12: Moves one-for-one with price; also moves with share count changes. | G12: Currency mismatch; wrong share class included/excluded. | H12: Matches public market cap; confirm float vs total shares distinction. | I12: Market cap is today’s equity value, the starting point for our upside math.
B13: Net debt (as defined) | C13: 08_TRIANGULATION_RANGE!F50 | D13: Debt minus cash plus/minus selected adjustments (leases, pensions, minorities, investments). | E13: 02_COMPANY_INPUTS net debt bridge + 01_CONTROL toggles for adjustments. | F13: Higher net debt increases EV at constant equity, reduces equity value at constant EV. | G13: Double counting leases; mixing gross vs net; inconsistent peer definitions. | H13: Net debt/EBITDA within sector norms; tie to latest balance sheet date. | I13: Net debt is the bridge between EV and equity. The definition must match peers.
B14: Enterprise value (EV) | C14: 08_TRIANGULATION_RANGE!F51 | D14: Total firm value: market cap + net debt (plus/minus adjustments if included). | E14: Market cap + net debt; definition toggles. | F14: Higher EV implies higher multiple at constant EBITDA; or higher implied price at constant multiple. | G14: Using equity multiple to value EV; inconsistent treatment of minorities/associates. | H14: EV/EBITDA implied by spot price is sensible vs comps range. | I14: EV is the value of the operating business irrespective of capital structure.
B15: Trading comps multiple used (EV/EBITDA) | C15: 08_TRIANGULATION_RANGE!F72 | D15: Selected EV/EBITDA multiple used to imply valuation from peer set. | E15: 05_TRADING_COMPS peer list + outlier handling; selection choice (median vs adjusted). | F15: Higher multiple increases implied EV and implied price (all else equal). | G15: Selecting a multiple inconsistent with growth/margins; ignoring cycle/one-offs. | H15: Selected multiple sits within P25–P75 unless justified; check peer dispersion. | I15: We value the business off a peer multiple that reflects its growth and margin profile.
B16: Comps implied EV (P25) | C16: 05_TRADING_COMPS!F40 | D16: Implied EV using P25 peer multiple × company EBITDA. | E16: Peer P25 multiple + company LTM EBITDA input. | F16: Higher EBITDA or higher P25 multiple increases implied EV. | G16: Using unadjusted EBITDA when peers are adjusted; non-comparable LTM periods. | H16: Company EBITDA is LTM and consistent with peers’ definition. | I16: On the low end, applying the peer P25 multiple implies an EV of X.
B17: Comps implied EV (Median) | C17: 05_TRADING_COMPS!G40 | D17: Implied EV using median peer multiple × company EBITDA. | E17: Median peer multiple + company LTM EBITDA. | F17: Same as above; median is the neutral anchor. | G17: Median distorted by a few extreme peers; check distribution. | H17: Median multiple aligns with business quality vs peers. | I17: Our midpoint comps anchor is the peer median multiple, which implies EV of X.
B18: Comps implied EV (P75) | C18: 05_TRADING_COMPS!H40 | D18: Implied EV using P75 peer multiple × company EBITDA. | E18: Peer P75 multiple + company LTM EBITDA. | F18: Higher implied EV drives higher implied price. | G18: Using high-end multiple without a catalyst narrative. | H18: High-end multiple justified by growth / margin / scarcity premium. | I18: On the high end, the peer P75 multiple implies EV of X, requiring clear upside drivers.
B19: Comps equity value (Median) | C19: 08_TRIANGULATION_RANGE!F58 | D19: Implied equity value from comps EV minus net debt. | E19: Comps EV + net debt definition. | F19: Higher net debt reduces equity value; higher EV increases it. | G19: Inconsistent net debt vs peers; using wrong share count for per share translation. | H19: Equity value + net debt = EV (bridge holds). | I19: Translating EV to equity, we subtract net debt under a consistent definition.
B20: Comps implied price (Median) | C20: 08_TRIANGULATION_RANGE!F14 | D20: Comps equity value divided by shares outstanding. | E20: Comps equity value + shares outstanding. | F20: More shares lowers price; higher equity value increases price. | G20: Basic vs diluted share count mismatch; wrong currency per share. | H20: Implied market cap = implied price × shares (check). | I20: On a per share basis, the comps midpoint implies a value of X per share.
... B39: Terminal parameter used (g / exit multiple) | C39: 08_TRIANGULATION_RANGE!F73 | D39: Terminal g (if perpetuity) or exit multiple (if exit-multiple) used in DCF. | E39: 01_CONTROL: terminal g inputs (base/up/down) and exit multiple inputs; scenario selection. | F39: Higher g increases terminal value; higher exit multiple increases terminal value. | G39: Setting g too high relative to macro growth; exit multiple inconsistent with comps range. | H39: Check implied g / implied exit multiple bands (86). | I39: Our terminal assumption corresponds to ~X% long-run growth / ~Yx exit multiple, aligned with peers and macro.

Sheet 81_VAL_LEARN_FORMULAS
B2: 81 Formula Walkthrough
B3: Key formulas: what they do, why they matter, and what breaks them.
B5: Learning Layer (additive). All refs tie to model cells. Do not edit calculation tabs unless fixing a confirmed error.
B7: CONTENT
B9: Formula / concept | C9: Model ref | D9: Model formula (auto) | E9: Plain-English | F9: Why it matters | G9: Typical mistake | H9: Mini example / sanity
B10: Market cap | C10: 08_TRIANGULATION_RANGE!F49 | D10: =IFERROR(FORMULATEXT('08_TRIANGULATION_RANGE'!F49),"") | E10: Market cap = price × shares. | F10: Sets equity anchor and upside math. | G10: Wrong share count or currency. | H10: Check: Market cap / price ≈ shares.
B11: Net debt (definition) | C11: 02_COMPANY_INPUTS!F26 | D11: =IFERROR(FORMULATEXT('02_COMPANY_INPUTS'!F26),"") | E11: Net debt = Debt - Cash + selected adjustments. | F11: Bridges EV ↔ equity; affects multiples comparability. | G11: Inconsistent peer definition or double-counting leases. | H11: Check: Net debt/EBITDA vs peers.
B12: Enterprise value (EV) | C12: 08_TRIANGULATION_RANGE!F51 | D12: =IFERROR(FORMULATEXT('08_TRIANGULATION_RANGE'!F51),"") | E12: EV = market cap + net debt. | F12: Core valuation basis for EV multiples. | G12: Mixing equity multiples with EV basis. | H12: Check: EV - net debt = equity.
B13: EV/EBITDA P25 | C13: 05_TRADING_COMPS!F28 | D13: =IFERROR(FORMULATEXT('05_TRADING_COMPS'!F28),"") | E13: 25th percentile of peer EV/EBITDA. | F13: Defines low-end valuation anchor. | G13: Small peer set leads to unstable quartiles. | H13: Check: peer count ≥ 6 for quartiles.
B14: EV/EBITDA Median | C14: 05_TRADING_COMPS!G28 | D14: =IFERROR(FORMULATEXT('05_TRADING_COMPS'!G28),"") | E14: Median of peer EV/EBITDA. | F14: Neutral anchor for selection. | G14: Median distorted by outliers. | H14: Check: compare to trimmed median.
B15: EV/EBITDA P75 | C15: 05_TRADING_COMPS!H28 | D15: =IFERROR(FORMULATEXT('05_TRADING_COMPS'!H28),"") | E15: 75th percentile of peer EV/EBITDA. | F15: Defines high-end anchor. | G15: Using P75 without catalyst narrative. | H15: Check: justify premium.
B16: Selected comps multiple | C16: 05_TRADING_COMPS!F32 | D16: =IFERROR(FORMULATEXT('05_TRADING_COMPS'!F32),"") | E16: Chosen multiple (often median). | F16: Directly scales implied EV and price. | G16: Hard-coding instead of linking to stats. | H16: Check: within P25–P75 or justify.
B17: Implied EV (P25) | C17: 05_TRADING_COMPS!F40 | D17: =IFERROR(FORMULATEXT('05_TRADING_COMPS'!F40),"") | E17: EV = multiple × company EBITDA. | F17: Low-end EV implied by comps. | G17: Using wrong EBITDA (LTM vs NTM). | H17: Check: EBITDA definition matches peers.
B18: Implied EV (Median) | C18: 05_TRADING_COMPS!G40 | D18: =IFERROR(FORMULATEXT('05_TRADING_COMPS'!G40),"") | E18: EV = median multiple × EBITDA. | F18: Midpoint EV anchor. | G18: Not adjusting EBITDA for one-offs. | H18: Check: remove extraordinary items.
B19: Implied EV (P75) | C19: 05_TRADING_COMPS!H40 | D19: =IFERROR(FORMULATEXT('05_TRADING_COMPS'!H40),"") | E19: EV = P75 multiple × EBITDA. | F19: High-end EV anchor. | G19: Assuming premium without drivers. | H19: Check: premium vs growth/margins.
B20: Implied equity value (Median) | C20: 05_TRADING_COMPS!G43 | D20: =IFERROR(FORMULATEXT('05_TRADING_COMPS'!G43),"") | E20: Equity = EV - net debt. | F20: Bridge to per share. | G20: Wrong net debt date or definition. | H20: Check: equity + net debt = EV.
B21: Comps implied price (Median) | C21: 08_TRIANGULATION_RANGE!F14 | D21: =IFERROR(FORMULATEXT('08_TRIANGULATION_RANGE'!F14),"") | E21: Price = equity value / shares. | F21: Translate to per share output. | G21: Using basic shares instead of diluted. | H21: Check: price × shares = equity.
B22: DCF discount factor (Year 1) | C22: 07_DCF_FCF_AND_VALUATION!F12 | D22: =IFERROR(FORMULATEXT('07_DCF_FCF_AND_VALUATION'!F12),"") | E22: DF = 1 / (1+WACC)^(t - midyear_adj). | F22: Correctly times PV of cash flows. | G22: Mixing end-year vs mid-year timing. | H22: Check: DF decreases over time.
B23: Unlevered FCF (Year 1) | C23: 07_DCF_FCF_AND_VALUATION!F30 | D23: =IFERROR(FORMULATEXT('07_DCF_FCF_AND_VALUATION'!F30),"") | E23: FCF = NOPAT + D&A - Capex - ΔNWC. | F23: Drives DCF value; quality of forecast matters. | G23: Sign error on NWC or capex. | H23: Check: FCF conversion vs EBITDA.
B24: Terminal value (Base) | C24: 07_DCF_FCF_AND_VALUATION!F34 | D24: =IFERROR(FORMULATEXT('07_DCF_FCF_AND_VALUATION'!F34),"") | E24: TV via perpetuity or exit multiple (switch). | F24: Often majority of DCF value. | G24: Setting g too close to WACC. | H24: Check: implied exit multiple / implied g.
B25: PV of terminal value (Base) | C25: 07_DCF_FCF_AND_VALUATION!F35 | D25: =IFERROR(FORMULATEXT('07_DCF_FCF_AND_VALUATION'!F35),"") | E25: PV(TV) = TV × discount factor. | F25: Terminal dominance check. | G25: Using wrong DF or timing. | H25: Check: PV(TV) < TV.
B26: DCF enterprise value (Base) | C26: 07_DCF_FCF_AND_VALUATION!F36 | D26: =IFERROR(FORMULATEXT('07_DCF_FCF_AND_VALUATION'!F36),"") | E26: EV = PV(FCFs) + PV(TV). | F26: Core DCF output. | G26: Double counting PV terms. | H26: Check: ties to summary lines.
B27: DCF equity value (Base) | C27: 07_DCF_FCF_AND_VALUATION!F37 | D27: =IFERROR(FORMULATEXT('07_DCF_FCF_AND_VALUATION'!F37),"") | E27: Equity = EV - net debt. | F27: Bridge consistent with comps. | G27: Different net debt basis vs comps. | H27: Check: same definition toggles.
B28: DCF implied price (Base) | C28: 07_DCF_FCF_AND_VALUATION!F38 | D28: =IFERROR(FORMULATEXT('07_DCF_FCF_AND_VALUATION'!F38),"") | E28: Price = equity / shares. | F28: DCF per share output. | G28: Dilution inconsistent with forecast. | H28: Check: per share ties.
B29: Cost of equity (CAPM + adj) | C29: 01_CONTROL!F34 | D29: =IFERROR(FORMULATEXT('01_CONTROL'!F34),"") | E29: Ke = Rf + Beta×ERP + Adj. | F29: Main WACC driver. | G29: Using percent vs decimal inconsistency. | H29: Check: Ke reasonable vs peers.
B30: After-tax cost of debt | C30: 01_CONTROL!F35 | D30: =IFERROR(FORMULATEXT('01_CONTROL'!F35),"") | E30: Kd_after = Kd_pre × (1 - tax). | F30: Impacts WACC via debt leg. | G30: Using statutory tax when effective differs. | H30: Check: compare to interest coverage.
B31: WACC | C31: 01_CONTROL!F36 | D31: =IFERROR(FORMULATEXT('01_CONTROL'!F36),"") | E31: WACC = We×Ke + Wd×Kd_after. | F31: Discount rate in DCF. | G31: Weights not summing to 100%. | H31: Check: We+Wd=100%.
B32: Upside % (Base) | C32: 08_TRIANGULATION_RANGE!F53 | D32: =IFERROR(FORMULATEXT('08_TRIANGULATION_RANGE'!F53),"") | E32: Upside = implied/spot - 1. | F32: Communicates return potential. | G32: Using wrong spot price date. | H32: Check: recompute manually.
B33: Combined price (Base) | C33: 08_TRIANGULATION_RANGE!F61 | D33: =IFERROR(FORMULATEXT('08_TRIANGULATION_RANGE'!F61),"") | E33: Triangulated per share value (comps + DCF). | F33: Final decision anchor. | G33: Unclear weighting; mixing scenarios. | H33: Check: between comps and DCF anchors.
B34: Range low (Combined) | C34: 08_TRIANGULATION_RANGE!F63 | D34: =IFERROR(FORMULATEXT('08_TRIANGULATION_RANGE'!F63),"") | E34: Low = MIN(down, base, up). | F34: Range framing. | G34: Swapping downside/upside inputs. | H34: Check: low ≤ base ≤ high.
B35: Range high (Combined) | C35: 08_TRIANGULATION_RANGE!F64 | D35: =IFERROR(FORMULATEXT('08_TRIANGULATION_RANGE'!F64),"") | E35: High = MAX(down, base, up). | F35: Range framing. | G35: Not updating scenarios. | H35: Check: high ≥ base.
B36: TV % of EV | C36: 86_VAL_SPECIAL_MODULE!D53 | D36: =IFERROR(FORMULATEXT('86_VAL_SPECIAL_MODULE'!D53),"") | E36: TV% = PV(TV)/EV. | F36: Measures terminal dominance. | G36: Interpreting as exact; it’s a diagnostic. | H36: Check: 50–80% typical.
B37: Implied exit multiple (proxy) | C37: 86_VAL_SPECIAL_MODULE!D54 | D37: =IFERROR(FORMULATEXT('86_VAL_SPECIAL_MODULE'!D54),"") | E37: Implied mult = TV/EBITDA_n. | F37: Sanity vs comps. | G37: Using EBITDA not in terminal year. | H37: Check: compare to peer range.
B38: Implied terminal growth (proxy) | C38: 86_VAL_SPECIAL_MODULE!D55 | D38: =IFERROR(FORMULATEXT('86_VAL_SPECIAL_MODULE'!D55),"") | E38: g ≈ WACC - FCF_n/TV. | F38: Sanity vs macro growth. | G38: Treating proxy as forecast. | H38: Check: compare to GDP+inflation.
B39: Sensitivity cell example | C39: 09_SENSITIVITIES!H18 | D39: =IFERROR(FORMULATEXT('09_SENSITIVITIES'!H18),"") | E39: DCF price recalculated under alt WACC/g. | F39: Frames assumption debate. | G39: Reading table without matching base cell. | H39: Check: base cell = base DCF price.
B40: Net debt toggle: leases | C40: 01_CONTROL!G43 | D40: =IFERROR(FORMULATEXT('01_CONTROL'!G43),"") | E40: Include/exclude leases in net debt. | F40: Ensures EV basis matches peers. | G40: Forgetting peers’ lease treatment. | H40: Check: document definition.
B41: Scenario switch | C41: 01_CONTROL!F9 | D41: =IFERROR(FORMULATEXT('01_CONTROL'!F9),"") | E41: Selects base/up/down assumption set. | F41: Controls scenario outputs. | G41: Editing wrong scenario block. | H41: Check: scenario label matches outputs.
B42: Terminal g used (scenario) | C42: 01_CONTROL!F79 | D42: =IFERROR(FORMULATEXT('01_CONTROL'!F79),"") | E42: Picks g based on scenario selection. | F42: Scenario-specific terminal assumption. | G42: Changing g but not scenario selector. | H42: Check: g used updates with scenario.
B43: Exit multiple used (scenario) | C43: 01_CONTROL!F80 | D43: =IFERROR(FORMULATEXT('01_CONTROL'!F80),"") | E43: Picks exit multiple based on scenario. | F43: Scenario-specific exit multiple. | G43: Inconsistent with comps. | H43: Check: exit multiple within peer band.
B44: Overall checks status | C44: 90_CHECKS!F3 | D44: =IFERROR(FORMULATEXT('90_CHECKS'!F3),"") | E44: Aggregates model integrity checks. | F44: Prevents silent errors. | G44: Ignoring FAIL and sending output. | H44: Check: must be PASS before sharing.

Sheet 82_VAL_LEARN_INTERPRETATION
B2: 82 Interpretation Scripts
B3: Meeting-ready interpretation cues and follow-up questions.
B5: Learning Layer (additive). All refs tie to model cells. Do not edit calculation tabs unless fixing a confirmed error.
B7: CONTENT
B9: Topic | C9: Trigger question | D9: Answer script (meeting-ready) | E9: What to check (model refs) | F9: Common pushback and response
B10: Upside vs current | C10: What is the upside and what drives it? | D10: Our base case implies an equity value of =08_TRIANGULATION_RANGE!F56 and a per share value of =08_TRIANGULATION_RANGE!F52, which is =08_TRIANGULATION_RANGE!F53 above today’s price. The upside is mainly driven by the selected peer multiple and our normalized EBITDA, with DCF acting as a cross-check. The key debate is whether the company deserves the peer median multiple given its growth and margin profile. | E10: 08!F52,F53; 05!F32; 02!F31 (EBITDA); 01!F12 (DCF ON/OFF) | F10: Pushback: multiples are rich. Response: show P25 to P75 range and link to catalysts and quality metrics.
B11: Multiple selection | C11: Why did you pick that multiple? | D11: We selected the =05_TRADING_COMPS!F32 EV/EBITDA multiple because it sits near the peer median and best reflects the company’s growth and margin positioning. We excluded or down-weighted peers with one-off events or structural differences. As a check, the selected multiple remains within the peer P25 to P75 range unless explicitly justified. | E11: 05!F28,H28 and peer list; 80 sheet peer checklist | F11: Pushback: peer set is arbitrary. Response: walk through business model match and normalization steps.
B12: EBITDA normalization | C12: How did you normalize EBITDA and what is the impact? | D12: We start from reported LTM EBITDA and adjust for clearly non-recurring items to make it comparable to peers. The model lets us adjust the company LTM EBITDA in 02_COMPANY_INPUTS and immediately shows the impact on implied EV and price. This prevents overpaying based on inflated one-off earnings. | E12: 02!F31 (EBITDA); 05 implied EV rows; 08 implied price | F12: Pushback: adjustments are subjective. Response: keep to disclosed items and document each adjustment.
B13: Net debt definition | C13: What is included in net debt? | D13: Net debt is defined as debt minus cash, with optional adjustments for leases, pensions, minorities, and investments. We use the same definition across the target and peers to keep EV/EBITDA comparable. Changing the toggles shifts equity value while EV and operating value logic remains consistent. | E13: 02!F26 net debt bridge; 01!G43+ toggles; 08 EV bridge cells | F13: Pushback: leases should be excluded. Response: present both views and show sensitivity on equity value.
B14: DCF credibility | C14: How much do you rely on the DCF? | D14: DCF is a triangulation tool here, not the sole answer. We focus on whether the DCF implied value is broadly consistent with comps under reasonable WACC and terminal assumptions. We also check terminal dominance and implied exit multiples to avoid a DCF that is driven by aggressive terminal assumptions. | E14: 01 DCF ON/OFF; 07 DCF outputs; 86 sanity pack | F14: Pushback: DCF is too sensitive. Response: use the WACC vs g sensitivity table to frame the range.
B15: WACC assumption | C15: Why is WACC set there? | D15: WACC is built bottom-up from risk-free rate, equity risk premium, beta and a debt cost, combined with target capital structure weights. We benchmark the resulting WACC against sector and geography norms and cross-check the implied valuation sensitivity. A 100 bps move is material, especially when the terminal value is a large share of EV. | E15: 01!F25:F36; 86 WACC driver tree; 84 Drill 7 | F15: Pushback: beta or ERP is wrong. Response: show alternative cases and quantify impact.
B16: Terminal method | C16: Why perpetuity growth vs exit multiple? | D16: We use the terminal method that best matches how the market prices mature cash flows in this sector. Perpetuity growth is intuitive but sensitive to (WACC - g); exit multiple anchors to observable market multiples. We sanity-check both by looking at implied exit multiple and implied long-run growth. | E16: 01!F14,F79,F80; 86 implied multiple and implied g | F16: Pushback: g is too high. Response: benchmark to macro growth and show what g would need to be to match market comps.
B17: Terminal dominance | C17: Is the DCF mostly terminal value? | D17: We compute the share of EV coming from terminal value as PV(TV) divided by EV. If terminal value dominates, we extend the forecast horizon or temper terminal assumptions so that more value is supported by explicit cash flows. This improves robustness and reduces reliance on long-run assumptions. | E17: 86 TV% of EV; 07 PV(TV) and EV | F17: Pushback: long-dated businesses are terminal-heavy. Response: accept higher TV% but document why, and keep terminal assumptions conservative.
B18: Scenario range | C18: What is your downside and upside case? | D18: Downside reflects multiple compression and higher discount rates plus more conservative operating assumptions. Upside reflects improvement in fundamentals and valuation support. We present a range to express uncertainty and to highlight which levers truly matter for value creation. | E18: 01 scenario; 08 combined prices; 83 scenarios sheet | F18: Pushback: range is too wide. Response: tighten assumptions to realistic bands and show sensitivity drivers.
B19: Key risks | C19: What could make this a pass? | D19: The main risks are multiple compression, margin pressure and higher rates increasing WACC, plus any balance sheet items that change net debt materially. If the company cannot sustain its growth or margin trajectory, it will not deserve the selected multiple and upside evaporates. We define a clear pass condition based on downside IRR or price floor. | E19: 05 multiple range; 01 WACC; 02 EBITDA; 09 sensitivities | F19: Pushback: risks are generic. Response: map risks to specific model drivers and quantify them.
B20: What to do next | C20: What due diligence closes the gap? | D20: Focus on validating the key value drivers: sustainable growth, margin durability, and cash conversion. Confirm EBITDA normalization items, working capital dynamics, and the right net debt definition. Then refine peers and update the multiple selection and terminal assumptions with evidence. | E20: 80 KPI map + 86 peer playbook; 84 drill list | F20: Pushback: too much work. Response: prioritize top 3 drivers and quantify their impact.
... B24: Integrity check | C24: How do we know the model is not broken? | D24: We run automated checks for broken links, missing inputs, inconsistent time series and invalid ranges. The model must show PASS before we share outputs. If a check fails, we fix the root cause and re-validate outputs. | E24: 90_CHECKS overall status + detail checks; 84 Drill 12 | F24: Pushback: checks are superficial. Response: explain what is covered and do spot reconciliations (EV bridge, per share ties).

Sheet 83_VAL_LEARN_SCENARIOS
B2: 83 Scenario Narratives
B3: Compare Base/Upside/Downside assumptions and outputs.
B5: Learning Layer (additive). All refs tie to model cells. Do not edit calculation tabs unless fixing a confirmed error.
B7: CONTENT
B9: Item | C9: Downside | D9: Base | E9: Upside | F9: Notes / narrative
B10: Revenue growth (avg FY1-FY10) | C10: =AVERAGE(01_CONTROL!AE60:AN60) | D10: =AVERAGE(01_CONTROL!G60:P60) | E10: =AVERAGE(01_CONTROL!S60:AB60) | F10: Use avg for a quick narrative. Drill down to year-by-year if story relies on a ramp.
B11: EBITDA margin (terminal year FY10) | C11: =01_CONTROL!AN61 | D11: =01_CONTROL!P61 | E11: =01_CONTROL!AB61 | F11: Terminal-year margin drives the terminal cash flow base.
B12: Capex % of revenue (avg FY1-FY10) | C12: =AVERAGE(01_CONTROL!AE63:AN63) | D12: =AVERAGE(01_CONTROL!G63:P63) | E12: =AVERAGE(01_CONTROL!S63:AB63) | F12: Capex intensity is a key lever for FCF conversion.
B13: NWC % of revenue (avg FY1-FY10) | C13: =AVERAGE(01_CONTROL!AE64:AN64) | D13: =AVERAGE(01_CONTROL!G64:P64) | E13: =AVERAGE(01_CONTROL!S64:AB64) | F13: Working capital drag can dominate near-term cash flows.
B14: Terminal growth g (selected) | C14: =01_CONTROL!AD67 | D14: =01_CONTROL!F67 | E14: =01_CONTROL!R67 | F14: Only used if terminal method is Perpetuity.
B15: Exit multiple EV/EBITDA (selected) | C15: =01_CONTROL!AD68 | D15: =01_CONTROL!F68 | E15: =01_CONTROL!R68 | F15: Only used if terminal method is Exit multiple.
B16: WACC (constant in this model) | C16: =01_CONTROL!F36 | D16: =01_CONTROL!F36 | E16: =01_CONTROL!F36 | F16: If you want scenario WACC, create an assumption delta and feed it into 06/07.
B17: DCF implied price per share | C17: =08_TRIANGULATION_RANGE!F19 | D17: =08_TRIANGULATION_RANGE!F23 | E17: =08_TRIANGULATION_RANGE!F27 | F17: From the DCF blocks (Down/Base/Up).
B18: Comps implied price per share (median) | C18: =08_TRIANGULATION_RANGE!F14 | D18: =08_TRIANGULATION_RANGE!F14 | E18: =08_TRIANGULATION_RANGE!F14 | F18: Comps is held constant; use P25/P75 as comps range.
B19: Combined price per share | C19: =08_TRIANGULATION_RANGE!F60 | D19: =08_TRIANGULATION_RANGE!F61 | E19: =08_TRIANGULATION_RANGE!F62 | F19: This is what the dashboard range is built on.
B20: Upside vs current (%) | C20: =08_TRIANGULATION_RANGE!F60/08_TRIANGULATION_RANGE!F47-1 | D20: =08_TRIANGULATION_RANGE!F61/08_TRIANGULATION_RANGE!F47-1 | E20: =08_TRIANGULATION_RANGE!F62/08_TRIANGULATION_RANGE!F47-1 | F20: Communicate upside vs the current price consistently.
B21: TV % of EV (Base DCF) | D21: =86_VAL_SPECIAL_MODULE!D53 | F21: Use as a robustness diagnostic. High TV% increases sensitivity.
B22: Implied exit multiple (Base DCF) | D22: =86_VAL_SPECIAL_MODULE!D54 | F22: Compare to peer range; justify any premium.

Sheet 84_VAL_LEARN_DRILLS
B2: 84 Drills
B3: Hands-on drills with PASS/FAIL checks (edit allowed inputs only).
B5: Learning Layer (additive). All refs tie to model cells. Do not edit calculation tabs unless fixing a confirmed error.
B7: CONTENT
B9: Drill | C9: Objective | D9: Steps (what to do) | E9: Inputs to edit (only blue cells) | F9: Expected behavior | G9: PASS/FAIL (auto) | H9: Notes
B10: D1 | C10: EV bridge must always hold | D10: Do nothing. This should be PASS at all times. | E10: None | F10: EV equals Market cap plus Net debt. | G10: =IF(ABS('08_TRIANGULATION_RANGE'!$F$51-('08_TRIANGULATION_RANGE'!$F$49+'08_TRIANGULATION_RANGE'!$F$50))<0.01,"PASS","FAIL") | H10: If FAIL, you have broken links or definition mismatch.
B11: D2 | C11: Market cap math check | D11: Do nothing. This should be PASS at all times. | E11: 02_COMPANY_INPUTS share price, shares (if editable). | F11: Market cap equals price times shares. | G11: =IF(ABS('08_TRIANGULATION_RANGE'!$F$49-('08_TRIANGULATION_RANGE'!$F$47*'08_TRIANGULATION_RANGE'!$F$48))<0.01,"PASS","FAIL") | H11: If share count is in mm, ensure units are consistent.
B12: D3 | C12: Net debt toggle sensitivity | D12: Flip 01_CONTROL net debt toggles (leases, pensions, minorities, investments) one at a time. Observe equity value changes while EV stays consistent by definition. | E12: 01_CONTROL!G43:G47 | F12: Including more items increases net debt and reduces equity value for a fixed EV. | G12: =IF('90_CHECKS'!$F$3="PASS","PASS","CHECK 90_CHECKS") | H12: Reset toggles to your standard peer definition after the drill.
B13: D4 | C13: Override comps multiple safely | D13: Turn ON Override comps multiple. Set an override multiple and confirm the used multiple follows it. Then turn override OFF to revert to median. | E13: 01_CONTROL!F84 (TRUE/FALSE), 01_CONTROL!F85 (x) | F13: When override is TRUE, 05_TRADING_COMPS!F32 equals the override value. | G13: =IF(AND('01_CONTROL'!$F$84=TRUE,ABS('05_TRADING_COMPS'!$F$32-'01_CONTROL'!$F$85)<0.0001),"PASS",IF('01_CONTROL'!$F$84=FALSE,"PASS","FAIL")) | H13: This avoids editing formulas in the comps tab.
B14: D5 | C14: WACC sensitivity | D14: Increase risk-free rate by +50 bps and observe DCF price decrease. Then revert. | E14: 01_CONTROL!F25 (Rf) | F14: Higher WACC lowers DCF EV and DCF implied price. | G14: =IF('01_CONTROL'!$F$36>0,"PASS","FAIL") | H14: Use 09_SENSITIVITIES to quantify the impact.
B15: D6 | C15: Terminal method switch sanity | D15: Switch terminal method between Perpetuity and Exit multiple. Observe DCF price changes and update terminal parameter inputs accordingly. | E15: 01_CONTROL!F14 (method), 01_CONTROL!F79/F80 (terminal inputs) | F15: Method switch changes terminal value logic; implied exit multiple and implied g should remain sensible. | G15: =IF(OR('01_CONTROL'!$F$14="Perpetuity",'01_CONTROL'!$F$14="Exit multiple"),"PASS","FAIL") | H15: Always sanity-check in 86 after switching.
B16: D7 | C16: PV sum tie-out | D16: Do nothing. This should be PASS at all times. | E16: None | F16: DCF EV equals PV of explicit FCFs plus PV of terminal value. | G16: =IF(ABS('07_DCF_FCF_AND_VALUATION'!$F$36-('07_DCF_FCF_AND_VALUATION'!$F$33+'07_DCF_FCF_AND_VALUATION'!$F$35))<0.01,"PASS","FAIL") | H16: If FAIL, discounting timing or terminal logic may be broken.
B17: D8 | C17: Capital structure weights must sum to 100% | D17: Do nothing. This should be PASS unless weights were edited. | E17: 01_CONTROL!F30 (Wd) and 01_CONTROL!F31 (We) if editable. | F17: Debt weight plus equity weight equals 1. | G17: =IF(ABS(('01_CONTROL'!$F$30+'01_CONTROL'!$F$31)-1)<0.0001,"PASS","FAIL") | H17: If weights are derived, fix upstream inputs rather than hard-coding.
B18: D9 | C18: DCF equity bridge tie-out | D18: Do nothing. This should be PASS at all times. | E18: None | F18: Net debt equals DCF EV minus DCF equity value. | G18: =IF(ABS(('07_DCF_FCF_AND_VALUATION'!$F$36-'07_DCF_FCF_AND_VALUATION'!$F$37)-'08_TRIANGULATION_RANGE'!$F$50)<0.01,"PASS","FAIL") | H18: If FAIL, net debt definition differs between tabs.
B19: D10 | C19: Scenario switch drives outputs | D19: Change scenario selector (Base, Upside, Downside). Confirm the combined price and DCF price change accordingly. | E19: 01_CONTROL!F10 (Scenario selector) | F19: Downside should be lowest, upside highest in normal cases. | G19: =IF('01_CONTROL'!$F$10>=1,"PASS","FAIL") | H19: Use 83 sheet to see assumptions behind each scenario.
B20: D11 | C20: Sensitivity base cell matches base DCF price | D20: Do nothing. This should be PASS if sensitivity table is wired correctly. | E20: None | F20: The sensitivity table value at (Base g, Base WACC) equals the base DCF implied price. | G20: =IFERROR(IF(ABS(INDEX('09_SENSITIVITIES'!$G$16:$K$21, MATCH('01_CONTROL'!$F$79,'09_SENSITIVITIES'!$F$16:$F$21,0), MATCH('01_CONTROL'!$F$36,'09_SENSITIVITIES'!$G$15:$K$15,0))-'08_TRIANGULATION_RANGE'!$F$23)<0.01,"PASS","FAIL"),"CHECK") | H20: If CHECK, your base WACC or g is not in the sensitivity grid.
B21: D12 | C21: Model must be PASS before sharing | D21: Do nothing. This must be PASS before sending outputs to anyone. | E21: None | F21: Overall checks are PASS. | G21: =IF('90_CHECKS'!$F$3="PASS","PASS","FAIL") | H21: If FAIL, fix the root cause. Do not publish outputs.

Sheet 85_VAL_LEARN_MISTAKES
B2: 85 Mistake Library
B3: Common valuation modelling mistakes and how to avoid them.
B5: Learning Layer (additive). All refs tie to model cells. Do not edit calculation tabs unless fixing a confirmed error.
B7: CONTENT

Sheet 86_VAL_SPECIAL_MODULE
B2: 86 Valuation Special Modules
B3: Peer selection, WACC intuition, terminal value sanity pack.
B5: Learning Layer (additive). All refs tie to model cells. Do not edit calculation tabs unless fixing a confirmed error.
B7: CONTENT
B9: 1) PEER SELECTION & NORMALIZATION PLAYBOOK
B10: Checklist (use in comps selection memo / pitch):
B11: 1. Business model match (revenue mix, customer type, end markets).
B12: 2. Unit economics / margin structure comparable (gross margin, EBITDA margin).
B13: 3. Growth regime comparable (LTM/NTM growth and cycle position).
B14: 4. Size / liquidity comparable (market cap, free float, analyst coverage).
B15: 5. Accounting comparability (IFRS vs local GAAP, leases, SBC, capitalized R&D).
B16: 6. Capital structure & leverage comparable (net debt/EBITDA, lease intensity).
... B23: 2) WACC DRIVER TREE + SENSITIVITY INTUITION
B25: Driver | C25: Model ref | D25: Current value | E25: What moves it | F25: Valuation intuition
B26: Risk-free rate (Rf) | C26: 01_CONTROL!F25 | D26: =01_CONTROL!F25 | E26: Rates / government bonds | F26: ↑Rf → ↑Ke → ↑WACC → ↓PV
B27: Equity risk premium (ERP) | C27: 01_CONTROL!F26 | D27: =01_CONTROL!F26 | E27: Market risk sentiment | F27: ↑ERP → ↑Ke → ↓valuation
B28: Beta | C28: 01_CONTROL!F27 | D28: =01_CONTROL!F27 | E28: Cyclicality + leverage | F28: ↑Beta → ↑Ke → ↓valuation
B29: Equity adjustment | C29: 01_CONTROL!F28 | D29: =01_CONTROL!F28 | E29: Size/country/illiquidity add-ons | F29: ↑Adj → ↓valuation
B30: Pre-tax cost of debt | C30: 01_CONTROL!F29 | D30: =01_CONTROL!F29 | E30: Credit spreads / rating | F30: ↑Kd → ↑WACC → ↓valuation
B31: Tax rate | C31: 01_CONTROL!F24 | D31: =01_CONTROL!F24 | E31: Statutory + effective | F31: ↑Tax → ↓after-tax Kd → slightly ↑valuation
B32: Debt weight (Wd) | C32: 01_CONTROL!F30 | D32: =01_CONTROL!F30 | E32: Target capital structure | F32: ↑Wd lowers WACC until distress risk
B33: Equity weight (We) | C33: 01_CONTROL!F31 | D33: =01_CONTROL!F31 | E33: 1-Wd | F33: Higher We → higher WACC (usually)
B34: Cost of equity (Ke) | C34: 01_CONTROL!F34 | D34: =01_CONTROL!F34 | E34: Rf + Beta*ERP + Adj | F34: Direct DCF driver
B35: After-tax cost of debt | C35: 01_CONTROL!F35 | D35: =01_CONTROL!F35 | E35: Kd*(1-tax) | F35: Direct DCF driver
B36: WACC used | C36: 01_CONTROL!F36 | D36: =01_CONTROL!F36 | E36: Weights + Ke + Kd | F36: 10 bps matters a lot in terminal-heavy DCF
B40: 3) TERMINAL VALUE DOMINANCE & SANITY PACK
B42: Acceptable bands (inputs) | F42: 8
B43: Exit multiple band (x) - Low | F43: 14
B44: Exit multiple band (x) - High | F44: 0.01
B45: Implied terminal growth band (%) - Low | F45: 0.04
B46: Implied terminal growth band (%) - High | F46: 0.5
B47: TV % of EV band - Low | F47: 0.8
B48: TV % of EV band - High
B51: Sanity outputs (Base scenario)
B52: Metric | C52: Model ref / calc | D52: Value | E52: Flag vs band
B53: TV % of EV (PV(TV)/EV) | C53: 07_DCF_FCF_AND_VALUATION!F35 / F36 | D53: =C53 | E53: =IF(OR(C53="",$F$46="",$F$47=""),"",IF(OR(C53<$F$46,C53>$F$47),"FLAG","OK"))
B54: Implied exit multiple (TV/EBITDA_n) | C54: 07_DCF_FCF_AND_VALUATION!F34 and EBITDA terminal year | D54: =C54 | E54: =IF(OR(C54="",$F$42="",$F$43=""),"",IF(OR(C54<$F$42,C54>$F$43),"FLAG","OK"))
B55: Implied terminal growth proxy (WACC - FCF_n/TV) | C55: Proxy: g = WACC - FCF_n/TV | D55: =C55 | E55: =IF(OR(C55="",$F$44="",$F$45=""),"",IF(OR(C55<$F$44,C55>$F$45),"FLAG","OK"))

Sheet 90_CHECKS
B2: CHECKS HUB
B3: Overall status | F3: =IF($F$4=0,"PASS","FAIL")
B4: Fail count | F4: =COUNTIF(F9:F18,0)
B5: Version
B6: Circular ref flag (manual, must be 0) | F6: 0
B8: Check | C8: Description | D8: Expected | E8: Actual | F8: Pass (1/0) | G8: Status
B9: Forecast: Revenue populated | C9: No blanks in Revenue for active years (selected scenario) | D9: 0 blanks | E9: =SUMPRODUCT(('01_CONTROL'!$G$52:$P$52=1)*('04_DRIVERS_AND_FORECAST'!$G$51:$P$51="")) | F9: =IF(E9=0,1,0) | G9: =IF(F9=1,"PASS","FAIL")
B10: Forecast: FCF populated | C10: No blanks in Unlevered FCF for active years (selected scenario) | D10: 0 blanks | E10: =SUMPRODUCT(('01_CONTROL'!$G$52:$P$52=1)*('04_DRIVERS_AND_FORECAST'!$G$58:$P$58="")) | F10: =IF(E10=0,1,0) | G10: =IF(F10=1,"PASS","FAIL")
B11: Net debt: bridge tie-out | C11: Net debt equals sum of bridge components with toggles | D11: difference = 0 | E11: =IF('02_COMPANY_INPUTS'!$F$26="","",IFERROR(ABS('02_COMPANY_INPUTS'!$F$26-('02_COMPANY_INPUTS'!$F$17 + '01_CONTROL'!$G$41*'02_COMPANY_INPUTS'!$F$18 + '01_CONTROL'!$G$42*'02_COMPANY_INPUTS'!$F$19 + '01_CONTROL'!$G$43*'02_COMPANY_INPUTS'!$F$20 - '02_COMPANY_INPUTS'!$F$16 - '01_CONTROL'!$G$44*'02_COMPANY_INPUTS'!$F$21 + '01_CONTROL'!$G$45*'02_COMPANY_INPUTS'!$F$22)),999)) | F11: =IF(E11<0.01,1,0) | G11: =IF(F11=1,"PASS","FAIL")
B12: Comps: EV tie-out | C12: EV equals market cap + net debt for all peer rows (within 0.01) | D12: 0 mismatches | E12: =SUMPRODUCT(--(ABS('05_TRADING_COMPS'!$I$12:$I$23-('05_TRADING_COMPS'!$G$12:$G$23+'05_TRADING_COMPS'!$H$12:$H$23))>0.01)) | F12: =IF(E12=0,1,0) | G12: =IF(F12=1,"PASS","FAIL")
B13: DCF: EV tie-out | C13: EV equals PV(FCFs) + PV(TV) for base scenario (within 0.01) | D13: difference < 0.01 | E13: =IFERROR(ABS('07_DCF_FCF_AND_VALUATION'!$F$36-('07_DCF_FCF_AND_VALUATION'!$F$33+'07_DCF_FCF_AND_VALUATION'!$F$35)),999) | F13: =IF(E13<0.01,1,0) | G13: =IF(F13=1,"PASS","FAIL")
B14: DCF: terminal method toggle | C14: Selected TV equals perpetuity TV if Perpetuity selected else exit-multiple TV | D14: difference < 0.01 | E14: =IFERROR(ABS('07_DCF_FCF_AND_VALUATION'!$F$34-IF('01_CONTROL'!$F$15=1,INDEX('07_DCF_FCF_AND_VALUATION'!$G$30:$P$30,'01_CONTROL'!$F$11)*(1+'01_CONTROL'!$F$67)/('06_DCF_WACC'!$F$20-'01_CONTROL'!$F$67),INDEX('07_DCF_FCF_AND_VALUATION'!$G$29:$P$29,'01_CONTROL'!$F$11)*'01_CONTROL'!$F$68)),999) | F14: =IF(E14<0.01,1,0) | G14: =IF(F14=1,"PASS","FAIL")
B15: DCF: mid-year toggle | C15: Discount factor for FY1 equals formula implied by mid-year flag | D15: difference < 0.0001 | E15: =IFERROR(ABS('07_DCF_FCF_AND_VALUATION'!$G$12-IF('01_CONTROL'!$F$17=1,1/(1+'06_DCF_WACC'!$F$20)^(1-0.5),1/(1+'06_DCF_WACC'!$F$20)^1)),999) | F15: =IF(E15<0.0001,1,0) | G15: =IF(F15=1,"PASS","FAIL")
B16: Model: circular references | C16: Manual confirmation that there are no circular references (flag must be 0) | D16: 0 | E16: =$F$6 | F16: =IF(E16=0,1,0) | G16: =IF(F16=1,"PASS","FAIL")
B17: Outputs: no errors | C17: Triangulation base price and current price not #VALUE/#REF | D17: 1 | E17: =IF(AND(ISERROR('08_TRIANGULATION_RANGE'!$F$41)=FALSE,ISERROR('08_TRIANGULATION_RANGE'!$F$40)=FALSE),1,0) | F17: =IF(E17=1,1,0) | G17: =IF(F17=1,"PASS","FAIL")
B18: Dashboard: traceability | C18: Dashboard base implied price equals triangulation source cell | D18: difference < 0.01 | E18: =IFERROR(ABS('00_DASHBOARD'!$F$16-'08_TRIANGULATION_RANGE'!$F$41),999) | F18: =IF(E18<0.01,1,0) | G18: =IF(F18=1,"PASS","FAIL")

Sheet 99_APPENDIX_DATA
B2: 99_APPENDIX_DATA
B3: Model
B4: Company
B5: Version
B6: Last updated | F6: =TODAY()
B8: SECTION
