Workbook

Sheet 00_Dashboard
A1: BioMar IPO Bookbuilding Dashboard
A2: Illustrative analyst-grade bookbuild model for training: pricing, demand curve, account quality, allocation and QC checks.
A4: Deal snapshot | F4: Pricing diagnostics
A5: Selected IPO price | B5: ='01_Deal_Inputs'!B8 -> 106 | C5: DKK / share | D5: Change on 01_Deal_Inputs | F5: Metric | G5: Value | H5: Read | J5: Metric | K5: Value | L5: Read
A6: Base offer shares | B6: ='01_Deal_Inputs'!B11 -> 25.2 | C6: m shares | D6: New + existing shares | F6: Total demand at selected price | G6: =INDEX('04_Demand_Curve'!B7:B15,MATCH($B$5,'04_Demand_Curve'!A7:A15,0)) -> 5940 | H6: =IF(K6<1,"Not covered",IF(K6<1.5,"Thin",IF(K6<2,"Covered","Strong"))) -> Strong | J6: Coverage | K6: =INDEX('04_Demand_Curve'!D7:D15,MATCH($B$5,'04_Demand_Curve'!A7:A15,0)) -> 2.2237197 | L6: =IF(K6>=2,"Optionality",IF(K6>=1,"Clears but less flexible","Reprice")) -> Optionality
A7: Base offer value | B7: ='01_Deal_Inputs'!H6 -> 2671.2 | C7: mDKK | D7: Selected price x shares | F7: Quality-adjusted coverage | G7: =INDEX('04_Demand_Curve'!F7:F15,MATCH($B$5,'04_Demand_Curve'!A7:A15,0)) -> 1.7385445 | H7: =IF(G7>=1.2,"Good quality","Needs judgement") -> Good quality | J7: Sticky demand share | K7: =INDEX('04_Demand_Curve'!G7:G15,MATCH($B$5,'04_Demand_Curve'!A7:A15,0)) -> 0.83501684 | L7: =IF(K7>=0.55,"Sticky book","Watch flip risk") -> Sticky book
A8: Company primary proceeds | B8: ='01_Deal_Inputs'!H7 -> 53 | C8: mDKK | D8: Small primary component | F8: Fast-money demand share | G8: =INDEX('04_Demand_Curve'!I7:I15,MATCH($B$5,'04_Demand_Curve'!A7:A15,0))/G6 -> 0.14309764 | H8: =IF(G8>0.25,"High fast-money share","Manageable") -> Manageable | J8: Scorecard best price | K8: =INDEX('06_Pricing_Scorecard'!A14:A22,MATCH(MAX('06_Pricing_Scorecard'!I14:I22),'06_Pricing_Scorecard'!I14:I22,0)) -> 106 | L8: =IF(K8=$B$5,"Selected = model best","Consider scorecard") -> Selected = model best
A9: Secondary sell-down proceeds | B9: ='01_Deal_Inputs'!H8 -> 2618.2 | C9: mDKK | D9: Main monetisation for Schouw
A10: Cornerstone commitments | B10: ='01_Deal_Inputs'!B13 -> 1350 | C10: mDKK | D10: ATP, Danske AM, DNB AM, Nykredit AM, TIND
A13: Demand curve and pricing decision table
A14: Price | B14: Demand | C14: Deal value | D14: Coverage | E14: Quality coverage | F14: Sticky share | G14: Long-only demand | H14: Fast-money demand | I14: Pricing read | J14: Score | K14: Selected
A15: ='04_Demand_Curve'!A7 -> 108 | B15: ='04_Demand_Curve'!B7 -> 2980 | C15: ='04_Demand_Curve'!C7 -> 2721.6 | D15: ='04_Demand_Curve'!D7 -> 1.0949442 | E15: ='04_Demand_Curve'!F7 -> 0.89506173 | F15: ='04_Demand_Curve'!G7 -> 0.86912752 | G15: ='04_Demand_Curve'!H7 -> 2550 | H15: ='04_Demand_Curve'!I7 -> 350 | I15: ='04_Demand_Curve'!K7 -> Usable / judgement | J15: ='06_Pricing_Scorecard'!I14 -> 0.78800705 | K15: =IF(A15=$B$5,"Selected","")
A16: ='04_Demand_Curve'!A8 -> 107 | B16: ='04_Demand_Curve'!B8 -> 4235 | C16: ='04_Demand_Curve'!C8 -> 2696.4 | D16: ='04_Demand_Curve'!D8 -> 1.5706127 | E16: ='04_Demand_Curve'!F8 -> 1.2533192 | F16: ='04_Demand_Curve'!G8 -> 0.85123967 | G16: ='04_Demand_Curve'!H8 -> 3555 | H16: ='04_Demand_Curve'!I8 -> 550 | I16: ='04_Demand_Curve'!K8 -> Usable / judgement | J16: ='06_Pricing_Scorecard'!I15 -> 0.9105919 | K16: =IF(A16=$B$5,"Selected","")
A17: ='04_Demand_Curve'!A9 -> 106 | B17: ='04_Demand_Curve'!B9 -> 5940 | C17: ='04_Demand_Curve'!C9 -> 2671.2 | D17: ='04_Demand_Curve'!D9 -> 2.2237197 | E17: ='04_Demand_Curve'!F9 -> 1.7385445 | F17: ='04_Demand_Curve'!G9 -> 0.83501684 | G17: ='04_Demand_Curve'!H9 -> 4870 | H17: ='04_Demand_Curve'!I9 -> 850 | I17: ='04_Demand_Curve'!K9 -> Good balance | J17: ='06_Pricing_Scorecard'!I16 -> 0.95 | K17: =IF(A17=$B$5,"Selected","") -> Selected
A18: ='04_Demand_Curve'!A10 -> 105 | B18: ='04_Demand_Curve'!B10 -> 7945 | C18: ='04_Demand_Curve'!C10 -> 2646 | D18: ='04_Demand_Curve'!D10 -> 3.0026455 | E18: ='04_Demand_Curve'!F10 -> 2.3085223 | F18: ='04_Demand_Curve'!G10 -> 0.81875393 | G18: ='04_Demand_Curve'!H10 -> 6365 | H18: ='04_Demand_Curve'!I10 -> 1250 | I18: ='04_Demand_Curve'!K10 -> Good balance | J18: ='06_Pricing_Scorecard'!I17 -> 0.925 | K18: =IF(A18=$B$5,"Selected","")
A19: ='04_Demand_Curve'!A11 -> 104 | B19: ='04_Demand_Curve'!B11 -> 10130 | C19: ='04_Demand_Curve'!C11 -> 2620.8 | D19: ='04_Demand_Curve'!D11 -> 3.865232 | E19: ='04_Demand_Curve'!F11 -> 2.9291819 | F19: ='04_Demand_Curve'!G11 -> 0.80157947 | G19: ='04_Demand_Curve'!H11 -> 7930 | H19: ='04_Demand_Curve'!I11 -> 1750 | I19: ='04_Demand_Curve'!K11 -> Good balance | J19: ='06_Pricing_Scorecard'!I18 -> 0.9 | K19: =IF(A19=$B$5,"Selected","")
A20: ='04_Demand_Curve'!A12 -> 103 | B20: ='04_Demand_Curve'!B12 -> 12120 | C20: ='04_Demand_Curve'!C12 -> 2595.6 | D20: ='04_Demand_Curve'!D12 -> 4.6694406 | E20: ='04_Demand_Curve'!F12 -> 3.4861689 | F20: ='04_Demand_Curve'!G12 -> 0.7830033 | G20: ='04_Demand_Curve'!H12 -> 9250 | H20: ='04_Demand_Curve'!I12 -> 2300 | I20: ='04_Demand_Curve'!K12 -> Good balance | J20: ='06_Pricing_Scorecard'!I19 -> 0.875 | K20: =IF(A20=$B$5,"Selected","")
A21: ='04_Demand_Curve'!A13 -> 102 | B21: ='04_Demand_Curve'!B13 -> 14020 | C21: ='04_Demand_Curve'!C13 -> 2570.4 | D21: ='04_Demand_Curve'!D13 -> 5.454404 | E21: ='04_Demand_Curve'!F13 -> 4.0320184 | F21: ='04_Demand_Curve'!G13 -> 0.77175464 | G21: ='04_Demand_Curve'!H13 -> 10520 | H21: ='04_Demand_Curve'!I13 -> 2800 | I21: ='04_Demand_Curve'!K13 -> Good balance | J21: ='06_Pricing_Scorecard'!I20 -> 0.85 | K21: =IF(A21=$B$5,"Selected","")
A22: ='04_Demand_Curve'!A14 -> 101 | B22: ='04_Demand_Curve'!B14 -> 15780 | C22: ='04_Demand_Curve'!C14 -> 2545.2 | D22: ='04_Demand_Curve'!D14 -> 6.1999057 | E22: ='04_Demand_Curve'!F14 -> 4.5464796 | F22: ='04_Demand_Curve'!G14 -> 0.76108999 | G22: ='04_Demand_Curve'!H14 -> 11660 | H22: ='04_Demand_Curve'!I14 -> 3300 | I22: ='04_Demand_Curve'!K14 -> Good balance | J22: ='06_Pricing_Scorecard'!I21 -> 0.825 | K22: =IF(A22=$B$5,"Selected","")
A23: ='04_Demand_Curve'!A15 -> 100 | B23: ='04_Demand_Curve'!B15 -> 17390 | C23: ='04_Demand_Curve'!C15 -> 2520 | D23: ='04_Demand_Curve'!D15 -> 6.9007937 | E23: ='04_Demand_Curve'!F15 -> 5.0395238 | F23: ='04_Demand_Curve'!G15 -> 0.75618171 | G23: ='04_Demand_Curve'!H15 -> 12740 | H23: ='04_Demand_Curve'!I15 -> 3700 | I23: ='04_Demand_Curve'!K15 -> Good balance | J23: ='06_Pricing_Scorecard'!I22 -> 0.8 | K23: =IF(A23=$B$5,"Selected","")
A27: Analyst interpretation | F27: Demand curve chart
A28: 1 | B28: Selected price of DKK 106 gives a strong illustrative book: 2.2x headline coverage and 1.7x quality-adjusted coverage.
A29: 2 | B29: The pricing call is not purely mathematical: seller proceeds must be balanced against aftermarket stability and investor quality.
A30: 3 | B30: Allocation should be weighted toward sticky long-only accounts and cornerstones, while hedge-fund / fast-money demand is useful but scaled.
A31: 4 | B31: Investor demand and scores are hypothetical. Prospectus inputs are actual offer terms; the order book is built for training only.

Sheet 01_Deal_Inputs
A1: BioMar IPO Bookbuild Model | Deal Inputs
A2: Illustrative training model. Hardcoded blue cells can be changed; formulas are black/green links.
A4: Core IPO parameters
A5: Input | B5: Value | C5: Unit | D5: Source / note | F5: Key output | G5: Formula | H5: Value
A6: Offer price range low | B6: 100 | C6: DKK / share | D6: Offering Circular, Offer Price Range | F6: Base offer value at selected price | G6: =B9*B7 -> 54 | H6: =B11*B8 -> 2671.2
A7: Offer price range high | B7: 108 | C7: DKK / share | D7: Offering Circular, Offer Price Range | F7: Primary proceeds | G7: =B7*B5 | H7: =B8*B9 -> 53
A8: Selected IPO price | B8: 106 | C8: DKK / share | D8: User / scenario input | F8: Secondary sell-down proceeds | G8: =B7*B6 -> 10800 | H8: =B8*B10 -> 2618.2
A9: New shares | B9: 0.5 | C9: m shares | D9: Company offering up to 500,000 new shares | F9: Max offer shares incl. greenshoe | G9: =B9+B10 -> 25.2 | H9: =B16 -> 28.98
A10: Existing offer shares | B10: 24.7 | C10: m shares | D10: Selling Shareholder offering up to 24.7m existing shares | F10: Max offer value incl. greenshoe | G10: =B13*B7 -> 145800 | H10: =B16*B8 -> 3071.88
A11: Base offer shares | B11: =SUM(B9:B10) -> 25.2 | C11: m shares | D11: New + existing offer shares | F11: Cornerstone commitments | G11: =B11 -> 25.2 | H11: =B13 -> 1350
A12: Overallotment / greenshoe shares | B12: 3.78 | C12: m shares | D12: Option shares to cover over-allotments / shorts | F12: Cornerstone % of base offer value | G12: =B11/(B9*B7) -> 0.46666667 | H12: =B13/(B11*B8) -> 0.50539084
A13: Cornerstone commitments | B13: 1350 | C13: mDKK | D13: ATP, Danske AM, DNB AM, Nykredit AM, TIND AM | F13: Primary % of base offer | G13: =B5/B9 | H13: =B9/B11 -> 0.01984127
A14: Nominal value per share | B14: 2.5 | C14: DKK / share | D14: Nominal value per share | F14: Secondary % of base offer | G14: =B6/B9 -> 200 | H14: =B10/B11 -> 0.98015873
A15: Current shares before IPO | B15: 100 | C15: m shares | D15: Selling shareholder holds 100m shares pre-offering | F15: Post-offer registered share capital | G15: =(B12+B5)*B12 | H15: =(B15+B9)*B14 -> 251.25
A16: Max offer shares incl. greenshoe | B16: =B11+B12 -> 28.98 | C16: m shares | D16: Base offer shares + overallotment option
A20: Model controls
A21: Control | B21: Value | C21: Unit | D21: Use in model | F21: Threshold | G21: Value | H21: Note
A22: Minimum headline coverage | B22: 1.5 | C22: x | D22: Red flag if book is too thin | F22: Good quality-adjusted coverage | G22: 1.2 | H22: Quality-adjusted demand / deal value
A23: Preferred headline coverage | B23: 2 | C23: x | D23: Useful allocation optionality | F23: Preferred sticky demand share | G23: 0.55 | H23: Share of demand from sticky investors
A24: Target first-day IPO return | B24: 0.08 | C24: % | D24: Illustrative, not used as hard assumption | F24: Max fast-money share | G24: 0.25 | H24: Used qualitatively in scorecard

Sheet 02_Investor_Master
A1: Investor Master | Account Quality & Allocation Priority
A2: Illustrative investor universe for BioMar IPO. Scores are hypothetical training assumptions, not confirmed orders.
A5: Investor scoring framework
A6: Investor | B6: Region | C6: Type | D6: Mandate | E6: Cornerstone? | F6: Relationship strength | G6: Quality score | H6: Stickiness | I6: Price discipline | J6: Flip risk | K6: Allocation priority | L6: Notes
A7: ATP | B7: Denmark | C7: Pension / Long-only | D7: Nordic equities / pension capital | E7: Yes | F7: 5 | G7: 5 | H7: 5 | I7: 4 | J7: 1 | K7: =ROUND((F7*0.2+G7*0.3+H7*0.25+I7*0.15+(6-J7)*0.1)*20,0) -> 97 | L7: Cornerstone; high signalling value
A8: Danske Bank Asset Management | B8: Denmark | C8: Nordic Long-only | D8: Danish/Nordic equities | E8: Yes | F8: 5 | G8: 5 | H8: 5 | I8: 4 | J8: 1 | K8: =ROUND((F8*0.2+G8*0.3+H8*0.25+I8*0.15+(6-J8)*0.1)*20,0) -> 97 | L8: Cornerstone; local distribution signal
A9: DNB Asset Management | B9: Norway | C9: Nordic Long-only | D9: Nordic equities | E9: Yes | F9: 5 | G9: 5 | H9: 5 | I9: 4 | J9: 1 | K9: =ROUND((F9*0.2+G9*0.3+H9*0.25+I9*0.15+(6-J9)*0.1)*20,0) -> 97 | L9: Cornerstone; Norwegian/Nordic account
A10: Nykredit Asset Management | B10: Denmark | C10: Nordic Long-only | D10: Danish/Nordic equities | E10: Yes | F10: 5 | G10: 5 | H10: 5 | I10: 4 | J10: 1 | K10: =ROUND((F10*0.2+G10*0.3+H10*0.25+I10*0.15+(6-J10)*0.1)*20,0) -> 97 | L10: Cornerstone; sticky domestic account
A11: TIND Asset Management | B11: Nordics | C11: Nordic Long-only | D11: Quality / growth | E11: Yes | F11: 4 | G11: 4 | H11: 4 | I11: 4 | J11: 2 | K11: =ROUND((F11*0.2+G11*0.3+H11*0.25+I11*0.15+(6-J11)*0.1)*20,0) -> 80 | L11: Cornerstone; quality-growth profile
A12: PFA Pension | B12: Denmark | C12: Pension / Long-only | D12: Danish listed equities | E12: No | F12: 4 | G12: 5 | H12: 5 | I12: 4 | J12: 1 | K12: =ROUND((F12*0.2+G12*0.3+H12*0.25+I12*0.15+(6-J12)*0.1)*20,0) -> 93 | L12: Likely relevant due to long-term Danish allocation
A13: Velliv | B13: Denmark | C13: Pension / Long-only | D13: Danish/Nordic equities | E13: No | F13: 3 | G13: 4 | H13: 5 | I13: 4 | J13: 1 | K13: =ROUND((F13*0.2+G13*0.3+H13*0.25+I13*0.15+(6-J13)*0.1)*20,0) -> 83 | L13: Sticky pension capital
A14: Danica Pension | B14: Denmark | C14: Pension / Long-only | D14: Danish equities | E14: No | F14: 4 | G14: 4 | H14: 5 | I14: 4 | J14: 1 | K14: =ROUND((F14*0.2+G14*0.3+H14*0.25+I14*0.15+(6-J14)*0.1)*20,0) -> 87 | L14: Domestic pension investor
A15: Sampension | B15: Denmark | C15: Pension / Long-only | D15: Danish/Nordic equities | E15: No | F15: 3 | G15: 4 | H15: 5 | I15: 3 | J15: 1 | K15: =ROUND((F15*0.2+G15*0.3+H15*0.25+I15*0.15+(6-J15)*0.1)*20,0) -> 80 | L15: Domestic long-only
A16: KLP Kapitalforvaltning | B16: Norway | C16: Pension / Long-only | D16: ESG / Nordic equities | E16: No | F16: 3 | G16: 4 | H16: 5 | I16: 4 | J16: 1 | K16: =ROUND((F16*0.2+G16*0.3+H16*0.25+I16*0.15+(6-J16)*0.1)*20,0) -> 83 | L16: Sustainability angle
A17: Storebrand Asset Management | B17: Norway | C17: ESG Long-only | D17: ESG / Nordic equities | E17: No | F17: 3 | G17: 4 | H17: 4 | I17: 4 | J17: 2 | K17: =ROUND((F17*0.2+G17*0.3+H17*0.25+I17*0.15+(6-J17)*0.1)*20,0) -> 76 | L17: ESG-quality account
A18: Folketrygdfondet | B18: Norway | C18: Nordic Long-only | D18: Nordic public equities | E18: No | F18: 3 | G18: 5 | H18: 5 | I18: 4 | J18: 1 | K18: =ROUND((F18*0.2+G18*0.3+H18*0.25+I18*0.15+(6-J18)*0.1)*20,0) -> 89 | L18: Large Nordic institutional account
... A31: Sector Specialist Fund | B31: Global | C31: Sector Specialist | D31: Food / agri / aquaculture | E31: No | F31: 3 | G31: 4 | H31: 4 | I31: 4 | J31: 2 | K31: =ROUND((F31*0.2+G31*0.3+H31*0.25+I31*0.15+(6-J31)*0.1)*20,0) -> 76 | L31: High sector relevance

Sheet 03_Order_Book
A1: Order Book | Indications of Interest by Price
A2: Demand is shown in mDKK by price point. Blue cells are illustrative manual order indications. Totals feed the demand curve and pricing scorecard.
A5: Indicated demand by investor and offer price
A6: Investor | B6: Type | C6: Region | D6: Priority | E6: 108 | F6: 107 | G6: 106 | H6: 105 | I6: 104 | J6: 103 | K6: 102 | L6: 101 | M6: 100 | N6: Total indicated
A7: ATP | B7: =INDEX('02_Investor_Master'!$C$7:$C$31,MATCH(A7,'02_Investor_Master'!$A$7:$A$31,0)) -> Pension / Long-only | C7: =INDEX('02_Investor_Master'!$B$7:$B$31,MATCH(A7,'02_Investor_Master'!$A$7:$A$31,0)) -> Denmark | D7: =INDEX('02_Investor_Master'!$K$7:$K$31,MATCH(A7,'02_Investor_Master'!$A$7:$A$31,0)) -> 97 | E7: 300 | F7: 330 | G7: 360 | H7: 380 | I7: 400 | J7: 400 | K7: 400 | L7: 400 | M7: 400 | N7: =SUM(E7:M7) -> 3370
A8: Danske Bank Asset Management | B8: =INDEX('02_Investor_Master'!$C$7:$C$31,MATCH(A8,'02_Investor_Master'!$A$7:$A$31,0)) -> Nordic Long-only | C8: =INDEX('02_Investor_Master'!$B$7:$B$31,MATCH(A8,'02_Investor_Master'!$A$7:$A$31,0)) -> Denmark | D8: =INDEX('02_Investor_Master'!$K$7:$K$31,MATCH(A8,'02_Investor_Master'!$A$7:$A$31,0)) -> 97 | E8: 250 | F8: 275 | G8: 300 | H8: 325 | I8: 350 | J8: 350 | K8: 350 | L8: 350 | M8: 350 | N8: =SUM(E8:M8) -> 2900
A9: DNB Asset Management | B9: =INDEX('02_Investor_Master'!$C$7:$C$31,MATCH(A9,'02_Investor_Master'!$A$7:$A$31,0)) -> Nordic Long-only | C9: =INDEX('02_Investor_Master'!$B$7:$B$31,MATCH(A9,'02_Investor_Master'!$A$7:$A$31,0)) -> Norway | D9: =INDEX('02_Investor_Master'!$K$7:$K$31,MATCH(A9,'02_Investor_Master'!$A$7:$A$31,0)) -> 97 | E9: 200 | F9: 225 | G9: 250 | H9: 275 | I9: 300 | J9: 300 | K9: 300 | L9: 300 | M9: 300 | N9: =SUM(E9:M9) -> 2450
A10: Nykredit Asset Management | B10: =INDEX('02_Investor_Master'!$C$7:$C$31,MATCH(A10,'02_Investor_Master'!$A$7:$A$31,0)) -> Nordic Long-only | C10: =INDEX('02_Investor_Master'!$B$7:$B$31,MATCH(A10,'02_Investor_Master'!$A$7:$A$31,0)) -> Denmark | D10: =INDEX('02_Investor_Master'!$K$7:$K$31,MATCH(A10,'02_Investor_Master'!$A$7:$A$31,0)) -> 97 | E10: 250 | F10: 275 | G10: 300 | H10: 325 | I10: 350 | J10: 350 | K10: 350 | L10: 350 | M10: 350 | N10: =SUM(E10:M10) -> 2900
A11: TIND Asset Management | B11: =INDEX('02_Investor_Master'!$C$7:$C$31,MATCH(A11,'02_Investor_Master'!$A$7:$A$31,0)) -> Nordic Long-only | C11: =INDEX('02_Investor_Master'!$B$7:$B$31,MATCH(A11,'02_Investor_Master'!$A$7:$A$31,0)) -> Nordics | D11: =INDEX('02_Investor_Master'!$K$7:$K$31,MATCH(A11,'02_Investor_Master'!$A$7:$A$31,0)) -> 80 | E11: 120 | F11: 140 | G11: 150 | H11: 170 | I11: 190 | J11: 200 | K11: 200 | L11: 200 | M11: 200 | N11: =SUM(E11:M11) -> 1570
A12: PFA Pension | B12: =INDEX('02_Investor_Master'!$C$7:$C$31,MATCH(A12,'02_Investor_Master'!$A$7:$A$31,0)) -> Pension / Long-only | C12: =INDEX('02_Investor_Master'!$B$7:$B$31,MATCH(A12,'02_Investor_Master'!$A$7:$A$31,0)) -> Denmark | D12: =INDEX('02_Investor_Master'!$K$7:$K$31,MATCH(A12,'02_Investor_Master'!$A$7:$A$31,0)) -> 93 | E12: 150 | F12: 220 | G12: 300 | H12: 380 | I12: 450 | J12: 500 | K12: 550 | L12: 600 | M12: 650 | N12: =SUM(E12:M12) -> 3800
A13: Velliv | B13: =INDEX('02_Investor_Master'!$C$7:$C$31,MATCH(A13,'02_Investor_Master'!$A$7:$A$31,0)) -> Pension / Long-only | C13: =INDEX('02_Investor_Master'!$B$7:$B$31,MATCH(A13,'02_Investor_Master'!$A$7:$A$31,0)) -> Denmark | D13: =INDEX('02_Investor_Master'!$K$7:$K$31,MATCH(A13,'02_Investor_Master'!$A$7:$A$31,0)) -> 83 | E13: 80 | F13: 120 | G13: 180 | H13: 240 | I13: 300 | J13: 350 | K13: 400 | L13: 450 | M13: 500 | N13: =SUM(E13:M13) -> 2620
A14: Danica Pension | B14: =INDEX('02_Investor_Master'!$C$7:$C$31,MATCH(A14,'02_Investor_Master'!$A$7:$A$31,0)) -> Pension / Long-only | C14: =INDEX('02_Investor_Master'!$B$7:$B$31,MATCH(A14,'02_Investor_Master'!$A$7:$A$31,0)) -> Denmark | D14: =INDEX('02_Investor_Master'!$K$7:$K$31,MATCH(A14,'02_Investor_Master'!$A$7:$A$31,0)) -> 87 | E14: 100 | F14: 160 | G14: 220 | H14: 300 | I14: 380 | J14: 450 | K14: 500 | L14: 550 | M14: 600 | N14: =SUM(E14:M14) -> 3260
A15: Sampension | B15: =INDEX('02_Investor_Master'!$C$7:$C$31,MATCH(A15,'02_Investor_Master'!$A$7:$A$31,0)) -> Pension / Long-only | C15: =INDEX('02_Investor_Master'!$B$7:$B$31,MATCH(A15,'02_Investor_Master'!$A$7:$A$31,0)) -> Denmark | D15: =INDEX('02_Investor_Master'!$K$7:$K$31,MATCH(A15,'02_Investor_Master'!$A$7:$A$31,0)) -> 80 | E15: 60 | F15: 100 | G15: 150 | H15: 220 | I15: 280 | J15: 330 | K15: 380 | L15: 420 | M15: 460 | N15: =SUM(E15:M15) -> 2400
A16: KLP Kapitalforvaltning | B16: =INDEX('02_Investor_Master'!$C$7:$C$31,MATCH(A16,'02_Investor_Master'!$A$7:$A$31,0)) -> Pension / Long-only | C16: =INDEX('02_Investor_Master'!$B$7:$B$31,MATCH(A16,'02_Investor_Master'!$A$7:$A$31,0)) -> Norway | D16: =INDEX('02_Investor_Master'!$K$7:$K$31,MATCH(A16,'02_Investor_Master'!$A$7:$A$31,0)) -> 83 | E16: 80 | F16: 120 | G16: 180 | H16: 250 | I16: 320 | J16: 380 | K16: 430 | L16: 480 | M16: 520 | N16: =SUM(E16:M16) -> 2760
A17: Storebrand Asset Management | B17: =INDEX('02_Investor_Master'!$C$7:$C$31,MATCH(A17,'02_Investor_Master'!$A$7:$A$31,0)) -> ESG Long-only | C17: =INDEX('02_Investor_Master'!$B$7:$B$31,MATCH(A17,'02_Investor_Master'!$A$7:$A$31,0)) -> Norway | D17: =INDEX('02_Investor_Master'!$K$7:$K$31,MATCH(A17,'02_Investor_Master'!$A$7:$A$31,0)) -> 76 | E17: 60 | F17: 100 | G17: 150 | H17: 220 | I17: 280 | J17: 330 | K17: 380 | L17: 420 | M17: 460 | N17: =SUM(E17:M17) -> 2400
A18: Folketrygdfondet | B18: =INDEX('02_Investor_Master'!$C$7:$C$31,MATCH(A18,'02_Investor_Master'!$A$7:$A$31,0)) -> Nordic Long-only | C18: =INDEX('02_Investor_Master'!$B$7:$B$31,MATCH(A18,'02_Investor_Master'!$A$7:$A$31,0)) -> Norway | D18: =INDEX('02_Investor_Master'!$K$7:$K$31,MATCH(A18,'02_Investor_Master'!$A$7:$A$31,0)) -> 89 | E18: 100 | F18: 150 | G18: 230 | H18: 320 | I18: 420 | J18: 500 | K18: 560 | L18: 620 | M18: 680 | N18: =SUM(E18:M18) -> 3580
... A31: Sector Specialist Fund | B31: =INDEX('02_Investor_Master'!$C$7:$C$31,MATCH(A31,'02_Investor_Master'!$A$7:$A$31,0)) -> Sector Specialist | C31: =INDEX('02_Investor_Master'!$B$7:$B$31,MATCH(A31,'02_Investor_Master'!$A$7:$A$31,0)) -> Global | D31: =INDEX('02_Investor_Master'!$K$7:$K$31,MATCH(A31,'02_Investor_Master'!$A$7:$A$31,0)) -> 76 | E31: 80 | F31: 130 | G31: 220 | H31: 330 | I31: 450 | J31: 570 | K31: 700 | L31: 820 | M31: 950 | N31: =SUM(E31:M31) -> 4250
A34: Demand | E34: =SUM(E7:E31) -> 2980 | F34: =SUM(F7:F31) -> 4235 | G34: =SUM(G7:G31) -> 5940 | H34: =SUM(H7:H31) -> 7945 | I34: =SUM(I7:I31) -> 10130 | J34: =SUM(J7:J31) -> 12120 | K34: =SUM(K7:K31) -> 14020 | L34: =SUM(L7:L31) -> 15780 | M34: =SUM(M7:M31) -> 17390
A35: Deal value | E35: =E6*'01_Deal_Inputs'!$B$11 -> 2721.6 | F35: =F6*'01_Deal_Inputs'!$B$11 -> 2696.4 | G35: =G6*'01_Deal_Inputs'!$B$11 -> 2671.2 | H35: =H6*'01_Deal_Inputs'!$B$11 -> 2646 | I35: =I6*'01_Deal_Inputs'!$B$11 -> 2620.8 | J35: =J6*'01_Deal_Inputs'!$B$11 -> 2595.6 | K35: =K6*'01_Deal_Inputs'!$B$11 -> 2570.4 | L35: =L6*'01_Deal_Inputs'!$B$11 -> 2545.2 | M35: =M6*'01_Deal_Inputs'!$B$11 -> 2520
A36: Coverage | E36: =E34/E35 -> 1.0949442 | F36: =F34/F35 -> 1.5706127 | G36: =G34/G35 -> 2.2237197 | H36: =H34/H35 -> 3.0026455 | I36: =I34/I35 -> 3.865232 | J36: =J34/J35 -> 4.6694406 | K36: =K34/K35 -> 5.454404 | L36: =L34/L35 -> 6.1999057 | M36: =M34/M35 -> 6.9007937
A37: Quality-adj. demand | E37: =SUMPRODUCT(E7:E31,$D$7:$D$31)/100 -> 2436 | F37: =SUMPRODUCT(F7:F31,$D$7:$D$31)/100 -> 3379.45 | G37: =SUMPRODUCT(G7:G31,$D$7:$D$31)/100 -> 4644 | H37: =SUMPRODUCT(H7:H31,$D$7:$D$31)/100 -> 6108.35 | I37: =SUMPRODUCT(I7:I31,$D$7:$D$31)/100 -> 7676.8 | J37: =SUMPRODUCT(J7:J31,$D$7:$D$31)/100 -> 9048.7 | K37: =SUMPRODUCT(K7:K31,$D$7:$D$31)/100 -> 10363.9 | L37: =SUMPRODUCT(L7:L31,$D$7:$D$31)/100 -> 11571.7 | M37: =SUMPRODUCT(M7:M31,$D$7:$D$31)/100 -> 12699.6
A38: Quality-adj. coverage | E38: =E37/E35 -> 0.89506173 | F38: =F37/F35 -> 1.2533192 | G38: =G37/G35 -> 1.7385445 | H38: =H37/H35 -> 2.3085223 | I38: =I37/I35 -> 2.9291819 | J38: =J37/J35 -> 3.4861689 | K38: =K37/K35 -> 4.0320184 | L38: =L37/L35 -> 4.5464796 | M38: =M37/M35 -> 5.0395238
A39: Long-only + pension demand | E39: =SUMIFS(E7:E31,$B$7:$B$31,"Pension / Long-only")+SUMIFS(E7:E31,$B$7:$B$31,"Nordic Long-only")+SUMIFS(E7:E31,$B$7:$B$31,"ESG Long-only")+SUMIFS(E7:E31,$B$7:$B$31,"Global Long-only") -> 2550 | F39: =SUMIFS(F7:F31,$B$7:$B$31,"Pension / Long-only")+SUMIFS(F7:F31,$B$7:$B$31,"Nordic Long-only")+SUMIFS(F7:F31,$B$7:$B$31,"ESG Long-only")+SUMIFS(F7:F31,$B$7:$B$31,"Global Long-only") -> 3555 | G39: =SUMIFS(G7:G31,$B$7:$B$31,"Pension / Long-only")+SUMIFS(G7:G31,$B$7:$B$31,"Nordic Long-only")+SUMIFS(G7:G31,$B$7:$B$31,"ESG Long-only")+SUMIFS(G7:G31,$B$7:$B$31,"Global Long-only") -> 4870 | H39: =SUMIFS(H7:H31,$B$7:$B$31,"Pension / Long-only")+SUMIFS(H7:H31,$B$7:$B$31,"Nordic Long-only")+SUMIFS(H7:H31,$B$7:$B$31,"ESG Long-only")+SUMIFS(H7:H31,$B$7:$B$31,"Global Long-only") -> 6365 | I39: =SUMIFS(I7:I31,$B$7:$B$31,"Pension / Long-only")+SUMIFS(I7:I31,$B$7:$B$31,"Nordic Long-only")+SUMIFS(I7:I31,$B$7:$B$31,"ESG Long-only")+SUMIFS(I7:I31,$B$7:$B$31,"Global Long-only") -> 7930 | J39: =SUMIFS(J7:J31,$B$7:$B$31,"Pension / Long-only")+SUMIFS(J7:J31,$B$7:$B$31,"Nordic Long-only")+SUMIFS(J7:J31,$B$7:$B$31,"ESG Long-only")+SUMIFS(J7:J31,$B$7:$B$31,"Global Long-only") -> 9250 | K39: =SUMIFS(K7:K31,$B$7:$B$31,"Pension / Long-only")+SUMIFS(K7:K31,$B$7:$B$31,"Nordic Long-only")+SUMIFS(K7:K31,$B$7:$B$31,"ESG Long-only")+SUMIFS(K7:K31,$B$7:$B$31,"Global Long-only") -> 10520 | L39: =SUMIFS(L7:L31,$B$7:$B$31,"Pension / Long-only")+SUMIFS(L7:L31,$B$7:$B$31,"Nordic Long-only")+SUMIFS(L7:L31,$B$7:$B$31,"ESG Long-only")+SUMIFS(L7:L31,$B$7:$B$31,"Global Long-only") -> 11660 | M39: =SUMIFS(M7:M31,$B$7:$B$31,"Pension / Long-only")+SUMIFS(M7:M31,$B$7:$B$31,"Nordic Long-only")+SUMIFS(M7:M31,$B$7:$B$31,"ESG Long-only")+SUMIFS(M7:M31,$B$7:$B$31,"Global Long-only") -> 12740
A40: Hedge fund demand | E40: =SUMIFS(E7:E31,$B$7:$B$31,"Hedge Fund") -> 350 | F40: =SUMIFS(F7:F31,$B$7:$B$31,"Hedge Fund") -> 550 | G40: =SUMIFS(G7:G31,$B$7:$B$31,"Hedge Fund") -> 850 | H40: =SUMIFS(H7:H31,$B$7:$B$31,"Hedge Fund") -> 1250 | I40: =SUMIFS(I7:I31,$B$7:$B$31,"Hedge Fund") -> 1750 | J40: =SUMIFS(J7:J31,$B$7:$B$31,"Hedge Fund") -> 2300 | K40: =SUMIFS(K7:K31,$B$7:$B$31,"Hedge Fund") -> 2800 | L40: =SUMIFS(L7:L31,$B$7:$B$31,"Hedge Fund") -> 3300 | M40: =SUMIFS(M7:M31,$B$7:$B$31,"Hedge Fund") -> 3700

Sheet 04_Demand_Curve
A1: Demand Curve | Coverage, Quality and Pricing Diagnostics
A2: This tab converts mDKK demand into coverage vs. deal value. It is the central pricing diagnostic.
A5: Demand curve by offer price
A6: Price | B6: Total demand (mDKK) | C6: Deal value (mDKK) | D6: Coverage | E6: Demand (m shares) | F6: Quality-adj. coverage | G6: Sticky demand share | H6: Long-only demand | I6: Fast-money demand | J6: Demand uplift | K6: Pricing read
A7: 108 | B7: ='03_Order_Book'!E34 -> 2980 | C7: =A7*'01_Deal_Inputs'!$B$11 -> 2721.6 | D7: =B7/C7 -> 1.0949442 | E7: =B7/A7 -> 27.592593 | F7: ='03_Order_Book'!E38 -> 0.89506173 | G7: =SUMPRODUCT('03_Order_Book'!$E$7:$E$31,--('02_Investor_Master'!$H$7:$H$31>=4))/B7 -> 0.86912752 | H7: ='03_Order_Book'!E39 -> 2550 | I7: ='03_Order_Book'!E40 -> 350 | J7: =0 -> 0 | K7: =IF(D7<1,"Not covered",IF(AND(D7>='01_Deal_Inputs'!$B$23,F7>='01_Deal_Inputs'!$G$22,G7>='01_Deal_Inputs'!$G$23),"Good balance",IF(D7>4,"Likely underpriced","Usable / judgement"))) -> Usable / judgement
A8: 107 | B8: ='03_Order_Book'!F34 -> 4235 | C8: =A8*'01_Deal_Inputs'!$B$11 -> 2696.4 | D8: =B8/C8 -> 1.5706127 | E8: =B8/A8 -> 39.579439 | F8: ='03_Order_Book'!F38 -> 1.2533192 | G8: =SUMPRODUCT('03_Order_Book'!$F$7:$F$31,--('02_Investor_Master'!$H$7:$H$31>=4))/B8 -> 0.85123967 | H8: ='03_Order_Book'!F39 -> 3555 | I8: ='03_Order_Book'!F40 -> 550 | J8: =B8/B7-1 -> 0.42114094 | K8: =IF(D8<1,"Not covered",IF(AND(D8>='01_Deal_Inputs'!$B$23,F8>='01_Deal_Inputs'!$G$22,G8>='01_Deal_Inputs'!$G$23),"Good balance",IF(D8>4,"Likely underpriced","Usable / judgement"))) -> Usable / judgement
A9: 106 | B9: ='03_Order_Book'!G34 -> 5940 | C9: =A9*'01_Deal_Inputs'!$B$11 -> 2671.2 | D9: =B9/C9 -> 2.2237197 | E9: =B9/A9 -> 56.037736 | F9: ='03_Order_Book'!G38 -> 1.7385445 | G9: =SUMPRODUCT('03_Order_Book'!$G$7:$G$31,--('02_Investor_Master'!$H$7:$H$31>=4))/B9 -> 0.83501684 | H9: ='03_Order_Book'!G39 -> 4870 | I9: ='03_Order_Book'!G40 -> 850 | J9: =B9/B8-1 -> 0.4025974 | K9: =IF(D9<1,"Not covered",IF(AND(D9>='01_Deal_Inputs'!$B$23,F9>='01_Deal_Inputs'!$G$22,G9>='01_Deal_Inputs'!$G$23),"Good balance",IF(D9>4,"Likely underpriced","Usable / judgement"))) -> Good balance
A10: 105 | B10: ='03_Order_Book'!H34 -> 7945 | C10: =A10*'01_Deal_Inputs'!$B$11 -> 2646 | D10: =B10/C10 -> 3.0026455 | E10: =B10/A10 -> 75.666667 | F10: ='03_Order_Book'!H38 -> 2.3085223 | G10: =SUMPRODUCT('03_Order_Book'!$H$7:$H$31,--('02_Investor_Master'!$H$7:$H$31>=4))/B10 -> 0.81875393 | H10: ='03_Order_Book'!H39 -> 6365 | I10: ='03_Order_Book'!H40 -> 1250 | J10: =B10/B9-1 -> 0.33754209 | K10: =IF(D10<1,"Not covered",IF(AND(D10>='01_Deal_Inputs'!$B$23,F10>='01_Deal_Inputs'!$G$22,G10>='01_Deal_Inputs'!$G$23),"Good balance",IF(D10>4,"Likely underpriced","Usable / judgement"))) -> Good balance
A11: 104 | B11: ='03_Order_Book'!I34 -> 10130 | C11: =A11*'01_Deal_Inputs'!$B$11 -> 2620.8 | D11: =B11/C11 -> 3.865232 | E11: =B11/A11 -> 97.403846 | F11: ='03_Order_Book'!I38 -> 2.9291819 | G11: =SUMPRODUCT('03_Order_Book'!$I$7:$I$31,--('02_Investor_Master'!$H$7:$H$31>=4))/B11 -> 0.80157947 | H11: ='03_Order_Book'!I39 -> 7930 | I11: ='03_Order_Book'!I40 -> 1750 | J11: =B11/B10-1 -> 0.27501573 | K11: =IF(D11<1,"Not covered",IF(AND(D11>='01_Deal_Inputs'!$B$23,F11>='01_Deal_Inputs'!$G$22,G11>='01_Deal_Inputs'!$G$23),"Good balance",IF(D11>4,"Likely underpriced","Usable / judgement"))) -> Good balance
A12: 103 | B12: ='03_Order_Book'!J34 -> 12120 | C12: =A12*'01_Deal_Inputs'!$B$11 -> 2595.6 | D12: =B12/C12 -> 4.6694406 | E12: =B12/A12 -> 117.6699 | F12: ='03_Order_Book'!J38 -> 3.4861689 | G12: =SUMPRODUCT('03_Order_Book'!$J$7:$J$31,--('02_Investor_Master'!$H$7:$H$31>=4))/B12 -> 0.7830033 | H12: ='03_Order_Book'!J39 -> 9250 | I12: ='03_Order_Book'!J40 -> 2300 | J12: =B12/B11-1 -> 0.1964462 | K12: =IF(D12<1,"Not covered",IF(AND(D12>='01_Deal_Inputs'!$B$23,F12>='01_Deal_Inputs'!$G$22,G12>='01_Deal_Inputs'!$G$23),"Good balance",IF(D12>4,"Likely underpriced","Usable / judgement"))) -> Good balance
A13: 102 | B13: ='03_Order_Book'!K34 -> 14020 | C13: =A13*'01_Deal_Inputs'!$B$11 -> 2570.4 | D13: =B13/C13 -> 5.454404 | E13: =B13/A13 -> 137.45098 | F13: ='03_Order_Book'!K38 -> 4.0320184 | G13: =SUMPRODUCT('03_Order_Book'!$K$7:$K$31,--('02_Investor_Master'!$H$7:$H$31>=4))/B13 -> 0.77175464 | H13: ='03_Order_Book'!K39 -> 10520 | I13: ='03_Order_Book'!K40 -> 2800 | J13: =B13/B12-1 -> 0.15676568 | K13: =IF(D13<1,"Not covered",IF(AND(D13>='01_Deal_Inputs'!$B$23,F13>='01_Deal_Inputs'!$G$22,G13>='01_Deal_Inputs'!$G$23),"Good balance",IF(D13>4,"Likely underpriced","Usable / judgement"))) -> Good balance
A14: 101 | B14: ='03_Order_Book'!L34 -> 15780 | C14: =A14*'01_Deal_Inputs'!$B$11 -> 2545.2 | D14: =B14/C14 -> 6.1999057 | E14: =B14/A14 -> 156.23762 | F14: ='03_Order_Book'!L38 -> 4.5464796 | G14: =SUMPRODUCT('03_Order_Book'!$L$7:$L$31,--('02_Investor_Master'!$H$7:$H$31>=4))/B14 -> 0.76108999 | H14: ='03_Order_Book'!L39 -> 11660 | I14: ='03_Order_Book'!L40 -> 3300 | J14: =B14/B13-1 -> 0.12553495 | K14: =IF(D14<1,"Not covered",IF(AND(D14>='01_Deal_Inputs'!$B$23,F14>='01_Deal_Inputs'!$G$22,G14>='01_Deal_Inputs'!$G$23),"Good balance",IF(D14>4,"Likely underpriced","Usable / judgement"))) -> Good balance
A15: 100 | B15: ='03_Order_Book'!M34 -> 17390 | C15: =A15*'01_Deal_Inputs'!$B$11 -> 2520 | D15: =B15/C15 -> 6.9007937 | E15: =B15/A15 -> 173.9 | F15: ='03_Order_Book'!M38 -> 5.0395238 | G15: =SUMPRODUCT('03_Order_Book'!$M$7:$M$31,--('02_Investor_Master'!$H$7:$H$31>=4))/B15 -> 0.75618171 | H15: ='03_Order_Book'!M39 -> 12740 | I15: ='03_Order_Book'!M40 -> 3700 | J15: =B15/B14-1 -> 0.10202788 | K15: =IF(D15<1,"Not covered",IF(AND(D15>='01_Deal_Inputs'!$B$23,F15>='01_Deal_Inputs'!$G$22,G15>='01_Deal_Inputs'!$G$23),"Good balance",IF(D15>4,"Likely underpriced","Usable / judgement"))) -> Good balance

Sheet 05_Allocation
A1: Allocation Model | Proposed Investor Allocations
A2: Allocation is illustrative: allocations are weighted by investor priority and demand at the selected IPO price.
A4: Selected pricing scenario
A5: Selected IPO price | B5: ='01_Deal_Inputs'!$B$8 -> 106 | C5: DKK / share | D5: Linked from deal inputs
A6: Base offer value | B6: =B5*'01_Deal_Inputs'!$B$11 -> 2671.2 | C6: mDKK | D6: Selected price x base offer shares
A7: Base offer shares | B7: ='01_Deal_Inputs'!$B$11 -> 25.2 | C7: m shares | D7: New + existing offer shares
A10: Proposed allocation by investor
A11: Investor | B11: Type | C11: Priority | D11: Demand at selected price | E11: Eligible | F11: Weighted demand | G11: Proposed allocation | H11: Allocated shares | I11: % of offer | J11: Demand fill | K11: Status | L11: Comment
A12: ATP | B12: =INDEX('02_Investor_Master'!$C$7:$C$31,MATCH(A12,'02_Investor_Master'!$A$7:$A$31,0)) -> Pension / Long-only | C12: =INDEX('02_Investor_Master'!$K$7:$K$31,MATCH(A12,'02_Investor_Master'!$A$7:$A$31,0)) -> 97 | D12: =SUMPRODUCT(('03_Order_Book'!$E$6:$M$6=$B$5)*'03_Order_Book'!$E7:$M7) -> 360 | E12: =IF(D12>0,"Yes","No") -> Yes | F12: =D12*C12/100 -> 349.2 | G12: =IF(D12=0,0,$B$6*F12/SUM($F$12:$F$36)) -> 200.85767 | H12: =G12/$B$5 -> 1.8948837 | I12: =H12/$B$7 -> 0.075193798 | J12: =IF(D12=0,0,G12/D12) -> 0.55793798 | K12: =IF(G12=0,"Out",IF(J12>0.75,"High allocation",IF(J12>0.35,"Core allocation","Scaled allocation"))) -> Core allocation | L12: =IF(B12="Hedge Fund","Cap if book is strong",IF(C12>=85,"Prioritise sticky capital","Standard scaling")) -> Prioritise sticky capital
A13: Danske Bank Asset Management | B13: =INDEX('02_Investor_Master'!$C$7:$C$31,MATCH(A13,'02_Investor_Master'!$A$7:$A$31,0)) -> Nordic Long-only | C13: =INDEX('02_Investor_Master'!$K$7:$K$31,MATCH(A13,'02_Investor_Master'!$A$7:$A$31,0)) -> 97 | D13: =SUMPRODUCT(('03_Order_Book'!$E$6:$M$6=$B$5)*'03_Order_Book'!$E8:$M8) -> 300 | E13: =IF(D13>0,"Yes","No") -> Yes | F13: =D13*C13/100 -> 291 | G13: =IF(D13=0,0,$B$6*F13/SUM($F$12:$F$36)) -> 167.3814 | H13: =G13/$B$5 -> 1.5790698 | I13: =H13/$B$7 -> 0.062661499 | J13: =IF(D13=0,0,G13/D13) -> 0.55793798 | K13: =IF(G13=0,"Out",IF(J13>0.75,"High allocation",IF(J13>0.35,"Core allocation","Scaled allocation"))) -> Core allocation | L13: =IF(B13="Hedge Fund","Cap if book is strong",IF(C13>=85,"Prioritise sticky capital","Standard scaling")) -> Prioritise sticky capital
A14: DNB Asset Management | B14: =INDEX('02_Investor_Master'!$C$7:$C$31,MATCH(A14,'02_Investor_Master'!$A$7:$A$31,0)) -> Nordic Long-only | C14: =INDEX('02_Investor_Master'!$K$7:$K$31,MATCH(A14,'02_Investor_Master'!$A$7:$A$31,0)) -> 97 | D14: =SUMPRODUCT(('03_Order_Book'!$E$6:$M$6=$B$5)*'03_Order_Book'!$E9:$M9) -> 250 | E14: =IF(D14>0,"Yes","No") -> Yes | F14: =D14*C14/100 -> 242.5 | G14: =IF(D14=0,0,$B$6*F14/SUM($F$12:$F$36)) -> 139.4845 | H14: =G14/$B$5 -> 1.3158915 | I14: =H14/$B$7 -> 0.052217916 | J14: =IF(D14=0,0,G14/D14) -> 0.55793798 | K14: =IF(G14=0,"Out",IF(J14>0.75,"High allocation",IF(J14>0.35,"Core allocation","Scaled allocation"))) -> Core allocation | L14: =IF(B14="Hedge Fund","Cap if book is strong",IF(C14>=85,"Prioritise sticky capital","Standard scaling")) -> Prioritise sticky capital
A15: Nykredit Asset Management | B15: =INDEX('02_Investor_Master'!$C$7:$C$31,MATCH(A15,'02_Investor_Master'!$A$7:$A$31,0)) -> Nordic Long-only | C15: =INDEX('02_Investor_Master'!$K$7:$K$31,MATCH(A15,'02_Investor_Master'!$A$7:$A$31,0)) -> 97 | D15: =SUMPRODUCT(('03_Order_Book'!$E$6:$M$6=$B$5)*'03_Order_Book'!$E10:$M10) -> 300 | E15: =IF(D15>0,"Yes","No") -> Yes | F15: =D15*C15/100 -> 291 | G15: =IF(D15=0,0,$B$6*F15/SUM($F$12:$F$36)) -> 167.3814 | H15: =G15/$B$5 -> 1.5790698 | I15: =H15/$B$7 -> 0.062661499 | J15: =IF(D15=0,0,G15/D15) -> 0.55793798 | K15: =IF(G15=0,"Out",IF(J15>0.75,"High allocation",IF(J15>0.35,"Core allocation","Scaled allocation"))) -> Core allocation | L15: =IF(B15="Hedge Fund","Cap if book is strong",IF(C15>=85,"Prioritise sticky capital","Standard scaling")) -> Prioritise sticky capital
A16: TIND Asset Management | B16: =INDEX('02_Investor_Master'!$C$7:$C$31,MATCH(A16,'02_Investor_Master'!$A$7:$A$31,0)) -> Nordic Long-only | C16: =INDEX('02_Investor_Master'!$K$7:$K$31,MATCH(A16,'02_Investor_Master'!$A$7:$A$31,0)) -> 80 | D16: =SUMPRODUCT(('03_Order_Book'!$E$6:$M$6=$B$5)*'03_Order_Book'!$E11:$M11) -> 150 | E16: =IF(D16>0,"Yes","No") -> Yes | F16: =D16*C16/100 -> 120 | G16: =IF(D16=0,0,$B$6*F16/SUM($F$12:$F$36)) -> 69.023256 | H16: =G16/$B$5 -> 0.65116279 | I16: =H16/$B$7 -> 0.025839793 | J16: =IF(D16=0,0,G16/D16) -> 0.46015504 | K16: =IF(G16=0,"Out",IF(J16>0.75,"High allocation",IF(J16>0.35,"Core allocation","Scaled allocation"))) -> Core allocation | L16: =IF(B16="Hedge Fund","Cap if book is strong",IF(C16>=85,"Prioritise sticky capital","Standard scaling")) -> Standard scaling
A17: PFA Pension | B17: =INDEX('02_Investor_Master'!$C$7:$C$31,MATCH(A17,'02_Investor_Master'!$A$7:$A$31,0)) -> Pension / Long-only | C17: =INDEX('02_Investor_Master'!$K$7:$K$31,MATCH(A17,'02_Investor_Master'!$A$7:$A$31,0)) -> 93 | D17: =SUMPRODUCT(('03_Order_Book'!$E$6:$M$6=$B$5)*'03_Order_Book'!$E12:$M12) -> 300 | E17: =IF(D17>0,"Yes","No") -> Yes | F17: =D17*C17/100 -> 279 | G17: =IF(D17=0,0,$B$6*F17/SUM($F$12:$F$36)) -> 160.47907 | H17: =G17/$B$5 -> 1.5139535 | I17: =H17/$B$7 -> 0.060077519 | J17: =IF(D17=0,0,G17/D17) -> 0.53493023 | K17: =IF(G17=0,"Out",IF(J17>0.75,"High allocation",IF(J17>0.35,"Core allocation","Scaled allocation"))) -> Core allocation | L17: =IF(B17="Hedge Fund","Cap if book is strong",IF(C17>=85,"Prioritise sticky capital","Standard scaling")) -> Prioritise sticky capital
A18: Velliv | B18: =INDEX('02_Investor_Master'!$C$7:$C$31,MATCH(A18,'02_Investor_Master'!$A$7:$A$31,0)) -> Pension / Long-only | C18: =INDEX('02_Investor_Master'!$K$7:$K$31,MATCH(A18,'02_Investor_Master'!$A$7:$A$31,0)) -> 83 | D18: =SUMPRODUCT(('03_Order_Book'!$E$6:$M$6=$B$5)*'03_Order_Book'!$E13:$M13) -> 180 | E18: =IF(D18>0,"Yes","No") -> Yes | F18: =D18*C18/100 -> 149.4 | G18: =IF(D18=0,0,$B$6*F18/SUM($F$12:$F$36)) -> 85.933953 | H18: =G18/$B$5 -> 0.81069767 | I18: =H18/$B$7 -> 0.032170543 | J18: =IF(D18=0,0,G18/D18) -> 0.47741085 | K18: =IF(G18=0,"Out",IF(J18>0.75,"High allocation",IF(J18>0.35,"Core allocation","Scaled allocation"))) -> Core allocation | L18: =IF(B18="Hedge Fund","Cap if book is strong",IF(C18>=85,"Prioritise sticky capital","Standard scaling")) -> Standard scaling
A19: Danica Pension | B19: =INDEX('02_Investor_Master'!$C$7:$C$31,MATCH(A19,'02_Investor_Master'!$A$7:$A$31,0)) -> Pension / Long-only | C19: =INDEX('02_Investor_Master'!$K$7:$K$31,MATCH(A19,'02_Investor_Master'!$A$7:$A$31,0)) -> 87 | D19: =SUMPRODUCT(('03_Order_Book'!$E$6:$M$6=$B$5)*'03_Order_Book'!$E14:$M14) -> 220 | E19: =IF(D19>0,"Yes","No") -> Yes | F19: =D19*C19/100 -> 191.4 | G19: =IF(D19=0,0,$B$6*F19/SUM($F$12:$F$36)) -> 110.09209 | H19: =G19/$B$5 -> 1.0386047 | I19: =H19/$B$7 -> 0.04121447 | J19: =IF(D19=0,0,G19/D19) -> 0.5004186 | K19: =IF(G19=0,"Out",IF(J19>0.75,"High allocation",IF(J19>0.35,"Core allocation","Scaled allocation"))) -> Core allocation | L19: =IF(B19="Hedge Fund","Cap if book is strong",IF(C19>=85,"Prioritise sticky capital","Standard scaling")) -> Prioritise sticky capital
A20: Sampension | B20: =INDEX('02_Investor_Master'!$C$7:$C$31,MATCH(A20,'02_Investor_Master'!$A$7:$A$31,0)) -> Pension / Long-only | C20: =INDEX('02_Investor_Master'!$K$7:$K$31,MATCH(A20,'02_Investor_Master'!$A$7:$A$31,0)) -> 80 | D20: =SUMPRODUCT(('03_Order_Book'!$E$6:$M$6=$B$5)*'03_Order_Book'!$E15:$M15) -> 150 | E20: =IF(D20>0,"Yes","No") -> Yes | F20: =D20*C20/100 -> 120 | G20: =IF(D20=0,0,$B$6*F20/SUM($F$12:$F$36)) -> 69.023256 | H20: =G20/$B$5 -> 0.65116279 | I20: =H20/$B$7 -> 0.025839793 | J20: =IF(D20=0,0,G20/D20) -> 0.46015504 | K20: =IF(G20=0,"Out",IF(J20>0.75,"High allocation",IF(J20>0.35,"Core allocation","Scaled allocation"))) -> Core allocation | L20: =IF(B20="Hedge Fund","Cap if book is strong",IF(C20>=85,"Prioritise sticky capital","Standard scaling")) -> Standard scaling
A21: KLP Kapitalforvaltning | B21: =INDEX('02_Investor_Master'!$C$7:$C$31,MATCH(A21,'02_Investor_Master'!$A$7:$A$31,0)) -> Pension / Long-only | C21: =INDEX('02_Investor_Master'!$K$7:$K$31,MATCH(A21,'02_Investor_Master'!$A$7:$A$31,0)) -> 83 | D21: =SUMPRODUCT(('03_Order_Book'!$E$6:$M$6=$B$5)*'03_Order_Book'!$E16:$M16) -> 180 | E21: =IF(D21>0,"Yes","No") -> Yes | F21: =D21*C21/100 -> 149.4 | G21: =IF(D21=0,0,$B$6*F21/SUM($F$12:$F$36)) -> 85.933953 | H21: =G21/$B$5 -> 0.81069767 | I21: =H21/$B$7 -> 0.032170543 | J21: =IF(D21=0,0,G21/D21) -> 0.47741085 | K21: =IF(G21=0,"Out",IF(J21>0.75,"High allocation",IF(J21>0.35,"Core allocation","Scaled allocation"))) -> Core allocation | L21: =IF(B21="Hedge Fund","Cap if book is strong",IF(C21>=85,"Prioritise sticky capital","Standard scaling")) -> Standard scaling
A22: Storebrand Asset Management | B22: =INDEX('02_Investor_Master'!$C$7:$C$31,MATCH(A22,'02_Investor_Master'!$A$7:$A$31,0)) -> ESG Long-only | C22: =INDEX('02_Investor_Master'!$K$7:$K$31,MATCH(A22,'02_Investor_Master'!$A$7:$A$31,0)) -> 76 | D22: =SUMPRODUCT(('03_Order_Book'!$E$6:$M$6=$B$5)*'03_Order_Book'!$E17:$M17) -> 150 | E22: =IF(D22>0,"Yes","No") -> Yes | F22: =D22*C22/100 -> 114 | G22: =IF(D22=0,0,$B$6*F22/SUM($F$12:$F$36)) -> 65.572093 | H22: =G22/$B$5 -> 0.61860465 | I22: =H22/$B$7 -> 0.024547804 | J22: =IF(D22=0,0,G22/D22) -> 0.43714729 | K22: =IF(G22=0,"Out",IF(J22>0.75,"High allocation",IF(J22>0.35,"Core allocation","Scaled allocation"))) -> Core allocation | L22: =IF(B22="Hedge Fund","Cap if book is strong",IF(C22>=85,"Prioritise sticky capital","Standard scaling")) -> Standard scaling
A23: Folketrygdfondet | B23: =INDEX('02_Investor_Master'!$C$7:$C$31,MATCH(A23,'02_Investor_Master'!$A$7:$A$31,0)) -> Nordic Long-only | C23: =INDEX('02_Investor_Master'!$K$7:$K$31,MATCH(A23,'02_Investor_Master'!$A$7:$A$31,0)) -> 89 | D23: =SUMPRODUCT(('03_Order_Book'!$E$6:$M$6=$B$5)*'03_Order_Book'!$E18:$M18) -> 230 | E23: =IF(D23>0,"Yes","No") -> Yes | F23: =D23*C23/100 -> 204.7 | G23: =IF(D23=0,0,$B$6*F23/SUM($F$12:$F$36)) -> 117.74217 | H23: =G23/$B$5 -> 1.1107752 | I23: =H23/$B$7 -> 0.044078381 | J23: =IF(D23=0,0,G23/D23) -> 0.51192248 | K23: =IF(G23=0,"Out",IF(J23>0.75,"High allocation",IF(J23>0.35,"Core allocation","Scaled allocation"))) -> Core allocation | L23: =IF(B23="Hedge Fund","Cap if book is strong",IF(C23>=85,"Prioritise sticky capital","Standard scaling")) -> Prioritise sticky capital
... A36: Sector Specialist Fund | B36: =INDEX('02_Investor_Master'!$C$7:$C$31,MATCH(A36,'02_Investor_Master'!$A$7:$A$31,0)) -> Sector Specialist | C36: =INDEX('02_Investor_Master'!$K$7:$K$31,MATCH(A36,'02_Investor_Master'!$A$7:$A$31,0)) -> 76 | D36: =SUMPRODUCT(('03_Order_Book'!$E$6:$M$6=$B$5)*'03_Order_Book'!$E31:$M31) -> 220 | E36: =IF(D36>0,"Yes","No") -> Yes | F36: =D36*C36/100 -> 167.2 | G36: =IF(D36=0,0,$B$6*F36/SUM($F$12:$F$36)) -> 96.172403 | H36: =G36/$B$5 -> 0.90728682 | I36: =H36/$B$7 -> 0.036003445 | J36: =IF(D36=0,0,G36/D36) -> 0.43714729 | K36: =IF(G36=0,"Out",IF(J36>0.75,"High allocation",IF(J36>0.35,"Core allocation","Scaled allocation"))) -> Core allocation | L36: =IF(B36="Hedge Fund","Cap if book is strong",IF(C36>=85,"Prioritise sticky capital","Standard scaling")) -> Standard scaling
A38: Total | D38: =SUM(D12:D36) -> 5940 | F38: =SUM(F12:F36) -> 4644 | G38: =SUM(G12:G36) -> 2671.2 | H38: =SUM(H12:H36) -> 25.2 | I38: =SUM(I12:I36) -> 1 | J38: =G38/D38 -> 0.44969697
A39: Check vs deal value | G39: =G38-$B$6 -> 4.5474735e-13 | H39: =H38-$B$7 -> 0
A40: Allocation gap | G40: =$B$6-G38 -> -4.5474735e-13 | H40: =$B$7-H38 -> 0

Sheet 06_Pricing_Scorecard
A1: Pricing Scorecard | Clearing Price Decision Support
A2: This scorecard converts book quality into a pricing recommendation. It is illustrative, not a legal or actual IPO pricing model.
A4: Score weights
A5: Criterion | B5: Weight | C5: Higher is better? | D5: Logic
A6: Headline coverage | B6: 0.3 | C6: Yes | D6: Book depth and execution certainty
A7: Quality-adj. coverage | B7: 0.3 | C7: Yes | D7: Long-term capital / lower flip risk
A8: Sticky demand share | B8: 0.2 | C8: Yes | D8: Aftermarket stability
A9: Offer price | B9: 0.2 | C9: Yes | D9: Seller proceeds maximisation
A12: Pricing score by offer price
A13: Price | B13: Coverage | C13: Coverage score | D13: Quality-adj. coverage | E13: Quality score | F13: Sticky share | G13: Sticky score | H13: Price score | I13: Overall score | J13: Pricing read | K13: Selected?
A14: 108 | B14: ='04_Demand_Curve'!D7 -> 1.0949442 | C14: =MIN(B14/'01_Deal_Inputs'!$B$23,1) -> 0.54747208 | D14: ='04_Demand_Curve'!F7 -> 0.89506173 | E14: =MIN(D14/'01_Deal_Inputs'!$G$22,1) -> 0.74588477 | F14: ='04_Demand_Curve'!G7 -> 0.86912752 | G14: =MIN(F14/'01_Deal_Inputs'!$G$23,1) -> 1 | H14: =(A14-'01_Deal_Inputs'!$B$6)/('01_Deal_Inputs'!$B$7-'01_Deal_Inputs'!$B$6) -> 1 | I14: =C14*$B$6+E14*$B$7+G14*$B$8+H14*$B$9 -> 0.78800705 | J14: =IF(B14<1,"Reject: not covered",IF(I14=MAX($I$14:$I$22),"Model-implied best",IF(B14<1.5,"Thin",IF(B14>4,"Potentially cheap","Acceptable")))) -> Thin | K14: =IF(A14='01_Deal_Inputs'!$B$8,"Selected","")
A15: 107 | B15: ='04_Demand_Curve'!D8 -> 1.5706127 | C15: =MIN(B15/'01_Deal_Inputs'!$B$23,1) -> 0.78530633 | D15: ='04_Demand_Curve'!F8 -> 1.2533192 | E15: =MIN(D15/'01_Deal_Inputs'!$G$22,1) -> 1 | F15: ='04_Demand_Curve'!G8 -> 0.85123967 | G15: =MIN(F15/'01_Deal_Inputs'!$G$23,1) -> 1 | H15: =(A15-'01_Deal_Inputs'!$B$6)/('01_Deal_Inputs'!$B$7-'01_Deal_Inputs'!$B$6) -> 0.875 | I15: =C15*$B$6+E15*$B$7+G15*$B$8+H15*$B$9 -> 0.9105919 | J15: =IF(B15<1,"Reject: not covered",IF(I15=MAX($I$14:$I$22),"Model-implied best",IF(B15<1.5,"Thin",IF(B15>4,"Potentially cheap","Acceptable")))) -> Acceptable | K15: =IF(A15='01_Deal_Inputs'!$B$8,"Selected","")
A16: 106 | B16: ='04_Demand_Curve'!D9 -> 2.2237197 | C16: =MIN(B16/'01_Deal_Inputs'!$B$23,1) -> 1 | D16: ='04_Demand_Curve'!F9 -> 1.7385445 | E16: =MIN(D16/'01_Deal_Inputs'!$G$22,1) -> 1 | F16: ='04_Demand_Curve'!G9 -> 0.83501684 | G16: =MIN(F16/'01_Deal_Inputs'!$G$23,1) -> 1 | H16: =(A16-'01_Deal_Inputs'!$B$6)/('01_Deal_Inputs'!$B$7-'01_Deal_Inputs'!$B$6) -> 0.75 | I16: =C16*$B$6+E16*$B$7+G16*$B$8+H16*$B$9 -> 0.95 | J16: =IF(B16<1,"Reject: not covered",IF(I16=MAX($I$14:$I$22),"Model-implied best",IF(B16<1.5,"Thin",IF(B16>4,"Potentially cheap","Acceptable")))) -> Model-implied best | K16: =IF(A16='01_Deal_Inputs'!$B$8,"Selected","") -> Selected
A17: 105 | B17: ='04_Demand_Curve'!D10 -> 3.0026455 | C17: =MIN(B17/'01_Deal_Inputs'!$B$23,1) -> 1 | D17: ='04_Demand_Curve'!F10 -> 2.3085223 | E17: =MIN(D17/'01_Deal_Inputs'!$G$22,1) -> 1 | F17: ='04_Demand_Curve'!G10 -> 0.81875393 | G17: =MIN(F17/'01_Deal_Inputs'!$G$23,1) -> 1 | H17: =(A17-'01_Deal_Inputs'!$B$6)/('01_Deal_Inputs'!$B$7-'01_Deal_Inputs'!$B$6) -> 0.625 | I17: =C17*$B$6+E17*$B$7+G17*$B$8+H17*$B$9 -> 0.925 | J17: =IF(B17<1,"Reject: not covered",IF(I17=MAX($I$14:$I$22),"Model-implied best",IF(B17<1.5,"Thin",IF(B17>4,"Potentially cheap","Acceptable")))) -> Acceptable | K17: =IF(A17='01_Deal_Inputs'!$B$8,"Selected","")
A18: 104 | B18: ='04_Demand_Curve'!D11 -> 3.865232 | C18: =MIN(B18/'01_Deal_Inputs'!$B$23,1) -> 1 | D18: ='04_Demand_Curve'!F11 -> 2.9291819 | E18: =MIN(D18/'01_Deal_Inputs'!$G$22,1) -> 1 | F18: ='04_Demand_Curve'!G11 -> 0.80157947 | G18: =MIN(F18/'01_Deal_Inputs'!$G$23,1) -> 1 | H18: =(A18-'01_Deal_Inputs'!$B$6)/('01_Deal_Inputs'!$B$7-'01_Deal_Inputs'!$B$6) -> 0.5 | I18: =C18*$B$6+E18*$B$7+G18*$B$8+H18*$B$9 -> 0.9 | J18: =IF(B18<1,"Reject: not covered",IF(I18=MAX($I$14:$I$22),"Model-implied best",IF(B18<1.5,"Thin",IF(B18>4,"Potentially cheap","Acceptable")))) -> Acceptable | K18: =IF(A18='01_Deal_Inputs'!$B$8,"Selected","")
A19: 103 | B19: ='04_Demand_Curve'!D12 -> 4.6694406 | C19: =MIN(B19/'01_Deal_Inputs'!$B$23,1) -> 1 | D19: ='04_Demand_Curve'!F12 -> 3.4861689 | E19: =MIN(D19/'01_Deal_Inputs'!$G$22,1) -> 1 | F19: ='04_Demand_Curve'!G12 -> 0.7830033 | G19: =MIN(F19/'01_Deal_Inputs'!$G$23,1) -> 1 | H19: =(A19-'01_Deal_Inputs'!$B$6)/('01_Deal_Inputs'!$B$7-'01_Deal_Inputs'!$B$6) -> 0.375 | I19: =C19*$B$6+E19*$B$7+G19*$B$8+H19*$B$9 -> 0.875 | J19: =IF(B19<1,"Reject: not covered",IF(I19=MAX($I$14:$I$22),"Model-implied best",IF(B19<1.5,"Thin",IF(B19>4,"Potentially cheap","Acceptable")))) -> Potentially cheap | K19: =IF(A19='01_Deal_Inputs'!$B$8,"Selected","")
A20: 102 | B20: ='04_Demand_Curve'!D13 -> 5.454404 | C20: =MIN(B20/'01_Deal_Inputs'!$B$23,1) -> 1 | D20: ='04_Demand_Curve'!F13 -> 4.0320184 | E20: =MIN(D20/'01_Deal_Inputs'!$G$22,1) -> 1 | F20: ='04_Demand_Curve'!G13 -> 0.77175464 | G20: =MIN(F20/'01_Deal_Inputs'!$G$23,1) -> 1 | H20: =(A20-'01_Deal_Inputs'!$B$6)/('01_Deal_Inputs'!$B$7-'01_Deal_Inputs'!$B$6) -> 0.25 | I20: =C20*$B$6+E20*$B$7+G20*$B$8+H20*$B$9 -> 0.85 | J20: =IF(B20<1,"Reject: not covered",IF(I20=MAX($I$14:$I$22),"Model-implied best",IF(B20<1.5,"Thin",IF(B20>4,"Potentially cheap","Acceptable")))) -> Potentially cheap | K20: =IF(A20='01_Deal_Inputs'!$B$8,"Selected","")
A21: 101 | B21: ='04_Demand_Curve'!D14 -> 6.1999057 | C21: =MIN(B21/'01_Deal_Inputs'!$B$23,1) -> 1 | D21: ='04_Demand_Curve'!F14 -> 4.5464796 | E21: =MIN(D21/'01_Deal_Inputs'!$G$22,1) -> 1 | F21: ='04_Demand_Curve'!G14 -> 0.76108999 | G21: =MIN(F21/'01_Deal_Inputs'!$G$23,1) -> 1 | H21: =(A21-'01_Deal_Inputs'!$B$6)/('01_Deal_Inputs'!$B$7-'01_Deal_Inputs'!$B$6) -> 0.125 | I21: =C21*$B$6+E21*$B$7+G21*$B$8+H21*$B$9 -> 0.825 | J21: =IF(B21<1,"Reject: not covered",IF(I21=MAX($I$14:$I$22),"Model-implied best",IF(B21<1.5,"Thin",IF(B21>4,"Potentially cheap","Acceptable")))) -> Potentially cheap | K21: =IF(A21='01_Deal_Inputs'!$B$8,"Selected","")
A22: 100 | B22: ='04_Demand_Curve'!D15 -> 6.9007937 | C22: =MIN(B22/'01_Deal_Inputs'!$B$23,1) -> 1 | D22: ='04_Demand_Curve'!F15 -> 5.0395238 | E22: =MIN(D22/'01_Deal_Inputs'!$G$22,1) -> 1 | F22: ='04_Demand_Curve'!G15 -> 0.75618171 | G22: =MIN(F22/'01_Deal_Inputs'!$G$23,1) -> 1 | H22: =(A22-'01_Deal_Inputs'!$B$6)/('01_Deal_Inputs'!$B$7-'01_Deal_Inputs'!$B$6) -> 0 | I22: =C22*$B$6+E22*$B$7+G22*$B$8+H22*$B$9 -> 0.8 | J22: =IF(B22<1,"Reject: not covered",IF(I22=MAX($I$14:$I$22),"Model-implied best",IF(B22<1.5,"Thin",IF(B22>4,"Potentially cheap","Acceptable")))) -> Potentially cheap | K22: =IF(A22='01_Deal_Inputs'!$B$8,"Selected","")

Sheet 90_Checks
A1: Model Checks | IPO Bookbuild QC
A4: Checks
A5: Check | B5: Formula / logic | C5: Value | D5: Tolerance | E5: Status | F5: Comment
A6: Base offer shares tie | B6: New shares + existing shares = base offer shares | C6: ='01_Deal_Inputs'!B11-SUM('01_Deal_Inputs'!B9:B10) -> 0 | D6: 0.001 | E6: =IF(ABS(C6)<=D6,"PASS","FAIL") -> PASS | F6: Should be zero
A7: Max offer shares tie | B7: Base shares + greenshoe = max offer shares | C7: ='01_Deal_Inputs'!B16-'01_Deal_Inputs'!B11-'01_Deal_Inputs'!B12 -> 1.3322676e-15 | D7: 0.001 | E7: =IF(ABS(C7)<=D7,"PASS","FAIL") -> PASS | F7: Should be zero
A8: Selected price in range | B8: Selected price between low and high | C8: =AND('01_Deal_Inputs'!B8>='01_Deal_Inputs'!B6,'01_Deal_Inputs'!B8<='01_Deal_Inputs'!B7) -> TRUE | D8: 0 | E8: =IF(C8=TRUE,"PASS","FAIL") -> PASS | F8: Boolean
A9: Allocation value tie | B9: Allocated mDKK = deal value | C9: ='05_Allocation'!G38-'05_Allocation'!B6 -> 4.5474735e-13 | D9: 0.1 | E9: =IF(ABS(C9)<=D9,"PASS","FAIL") -> PASS | F9: Should be close to zero
A10: Allocation shares tie | B10: Allocated shares = base offer shares | C10: ='05_Allocation'!H38-'05_Allocation'!B7 -> 0 | D10: 0.001 | E10: =IF(ABS(C10)<=D10,"PASS","FAIL") -> PASS | F10: Should be close to zero
A11: Order book selected price coverage | B11: Selected price demand / deal value | C11: =INDEX('04_Demand_Curve'!D7:D15,MATCH('01_Deal_Inputs'!B8,'04_Demand_Curve'!A7:A15,0)) -> 2.2237197 | D11: 1 | E11: =IF(C11>=D11,"PASS","FAIL") -> PASS | F11: Must be >1.0x to be covered
A12: Investor score min | B12: All quality scores >=1 | C12: =MIN('02_Investor_Master'!F7:J31) -> 1 | D12: 1 | E12: =IF(C12>=D12,"PASS","FAIL") -> PASS | F12: Boolean
A13: Investor score max | B13: All quality scores <=5 | C13: =MAX('02_Investor_Master'!F7:J31) -> 5 | D13: 5 | E13: =IF(C13<=D13,"PASS","FAIL") -> PASS | F13: Boolean
A14: Weights sum to 100% | B14: Scorecard weights sum to 100% | C14: =SUM('06_Pricing_Scorecard'!B6:B9)-1 -> 0 | D14: 0.001 | E14: =IF(ABS(C14)<=D14,"PASS","FAIL") -> PASS | F14: Should be zero

Sheet 99_Sources
A1: Sources & Notes
A4: Source log
A5: Source | B5: Type | C5: Used for | D5: URL / file | E5: Notes
A6: BioMar Group A/S Offering Circular | B6: Uploaded PDF | C6: Offer size, price range, cornerstones, greenshoe, timetable | D6: prospectus_2026.pdf | E6: Uploaded in this ChatGPT conversation
A7: BioMar investor IPO page | B7: Public IR page | C7: Prospectus location / IPO documents | D7: https://investors.biomar.com/ipo | E7: Plain URL for traceability
A8: Model authoring note | B8: Internal | C8: Investor demand, scores and allocations | D8: N/A | E8: All order book demand and investor scores are illustrative training assumptions
