Workbook

Sheet 00_Guide_Framework
B2: TRADING COMPARABLES — IB Guide & Framework
B4: A. WHAT IS TRADING COMPS?
B5: Trading comps is a relative valuation method based on the principle that similar companies should trade at similar multiples. The objective is not to determine intrinsic value, but to benchmark a company's valuation relative to how the market prices comparable peers. Peer selection is more important than the Excel model itself.
B7: B. PEER SELECTION FRAMEWORK | F7: C. MULTIPLE SELECTION FRAMEWORK
B8: Dimension | C8: Why It Matters | D8: Risk if Ignored | F8: Sector | G8: Primary Multiple | H8: Rationale
B9: Business Model | C9: Determines the valuation regime | D9: Misleading benchmark | F9: Industrials | G9: EV / EBIT | H9: Capital-intensive; depreciation meaningful
B10: Growth Profile | C10: Drives multiple expansion | D10: Under- or overvaluation | F10: SaaS | G10: EV / Revenue | H10: Negative EBITDA; growth valued on top-line
B11: Margin Profile | C11: Reflects quality of earnings | D11: Skewed comparison | F11: Pharma | G11: EV / EBITDA | H11: Stable cash flow; R&D capitalized
B12: Size | C12: Liquidity & size premium | D12: Wrong peer level | F12: Energy | G12: EV / EBITDA | H12: Asset-driven; capex drives value
B13: Geography | C13: Market premium differences | D13: Regional bias | F13: Banks | G13: P / BV | H13: Debt is raw material; equity-focused
B14: Cyclicality | C14: Risk pricing & earnings volatility | D14: Volatility mismatch | F14: Retail | G14: EV / EBITDA | H14: Working capital intensive; store comps
B16: Priority Order: Business Model › Growth › Margin › Size › Geography | F16: Forward (NTM) multiples preferred; use LTM when visibility is limited or cyclicality is high.
B18: D. PEER SELECTION — DECISION TREE | F18: E. WORKFLOW — STEP BY STEP
B19: START: Potential Peer Identified | F19: Step | G19: Action | H19: Guidance
B20: ▼ | F20: 01 | G20: Define objective | H20: M&A target, IPO benchmark, strategic review
B21: ① Same Business Model? | F21: 02 | G21: Broad screening | H21: Sector, sub-sector, size range, geography
B22: Same revenue model (subscription / transactional / product) · Same end-market & customer type · Similar capex intensity | F22: 03 | G22: Qualitative peer review | H22: Value drivers, customers, pricing power
B23: YES ▼ NO → EXCLUDE | F23: 04 | G23: Split Primary / Secondary | H23: Primary → median; Secondary → sanity check
B24: ② Similar Growth Profile? | F24: 05 | G24: Collect market data | H24: Equity value, debt, cash, minorities, leases
B25: Revenue CAGR within ±10 pp · EBITDA growth within ±15 pp · Same growth stage (early growth vs. mature / declining) | F25: 06 | G25: Calculate Enterprise Value | H25: EV = Equity + Net Debt + Minorities
B26: YES ▼ NO → EXCLUDE | F26: 07 | G26: Calculate multiples | H26: EV/EBITDA, EV/EBIT, EV/Rev, P/E — NTM preferred
B27: ③ Similar Margin Profile? | F27: 08 | G27: Remove outliers | H27: Flag & explain; document, don't silently drop
B28: EBITDA margin within ±8 pp · Gross margin within ±10 pp · Similar R&D / SG&A cost structure | F28: 09 | G28: Compute statistics | H28: Median + 25th–75th percentile range
B29: YES ▼ NO → SECONDARY | F29: 10 | G29: Apply to target & sanity | H29: Cross-check vs DCF and precedent transactions
B30: ④ Comparable Size?
B31: Market cap: 0.3x–3x of target · Revenue: 0.5x–2x of target · Large-cap vs. small-cap distinction matters (size premium ~1–2x turn)
B32: YES ▼ NO → SECONDARY
B33: ⑤ Same Geography / Market?
B34: US typically trades at 1–3x EV/EBITDA premium to Europe · EM discount: ~2–4x vs. DM · Local comps preferred for domestic targets
B35: YES ▼ NO → SECONDARY
B36: ✓ PRIMARY PEER
B38: F. COMMON PITFALLS | F38: G. QC CHECKLIST
B39: ❌ | C39: Peer group too broad or too narrow | F39: ☐ | G39: EV = Equity Value + Net Debt + Minorities?
B40: ❌ | C40: Ignoring growth differences between peers | F40: ☐ | G40: All multiples on same time basis (NTM/LTM)?
B41: ❌ | C41: Mixing LTM and NTM multiples | F41: ☐ | G41: Negative EBITDA peers excluded or flagged?
B42: ❌ | C42: Including peers with negative EBITDA | F42: ☐ | G42: Outliers identified and explained?
B43: ❌ | C43: Ignoring cyclicality in peer selection | F43: ☐ | G43: Is the target actually comparable to peers?
B44: ❌ | C44: Incorrect EV calculation (missing minorities/leases) | F44: ☐ | G44: Primary vs Secondary split documented?
B45: ❌ | C45: Dropping outliers without explanation | F45: ☐ | G45: Median and 25–75th percentile computed?
B48: Comps is not a mathematical truth — it is a structured way to use the market's own pricing as a reference.

Sheet 01_Control
A1: CONTROL PANEL (Trading Comps | Novo Nordisk | Illustrative template)
A3: Model status | B3: Illustrative only
A4: As-of date | B4: 2026-02-20
A6: Common currency | B6: EUR
A7: Units | B7: EUR m (unless stated)
A9: Notes | B9: Replace blue inputs with Bloomberg / Capital IQ market data + consensus. Model forces full calc on open.

Sheet 02_Peer_Screen
A1: PEER SCREEN (Selection flags)
A3: Company | B3: Ticker | C3: Country | D3: Sector | E3: Metabolic Exposure | F3: Mkt Cap Bucket | G3: Include | H3: Primary | I3: Notes
A4: Eli Lilly | B4: LLY | C4: US | D4: Pharma | E4: High | F4: Mega | G4: 1 | H4: 1 | I4: Direct obesity/diabetes peer
A5: Sanofi | B5: SAN | C5: FR | D5: Pharma | E5: Medium | F5: Mega | G5: 1 | H5: 1 | I5: Diabetes exposure, broader mix
A6: AstraZeneca | B6: AZN | C6: UK | D6: Pharma | E6: Medium | F6: Mega | G6: 1 | H6: 1 | I6: Broad pharma, cardiometabolic exposure
A7: Roche | B7: ROG | C7: CH | D7: Pharma | E7: Low | F7: Mega | G7: 1 | H7: 0 | I7: Broad pharma anchor
A8: Novartis | B8: NVS | C8: CH | D8: Pharma | E8: Low | F8: Mega | G8: 1 | H8: 0 | I8: Broad pharma anchor
A9: Merck & Co. | B9: MRK | C9: US | D9: Pharma | E9: Low | F9: Mega | G9: 1 | H9: 0 | I9: Broad pharma anchor
A10: AbbVie | B10: ABBV | C10: US | D10: Pharma | E10: Low | F10: Mega | G10: 1 | H10: 0 | I10: Patent/LOE sensitivity, cross-check only
A11: Amgen | B11: AMGN | C11: US | D11: Pharma | E11: Medium | F11: Large | G11: 1 | H11: 0 | I11: Pipeline relevance, metabolic optionality
A12: Bristol Myers Squibb | B12: BMY | C12: US | D12: Pharma | E12: Low | F12: Large | G12: 1 | H12: 0 | I12: Broad pharma anchor
A13: Zealand Pharma | B13: ZEAL | C13: DK | D13: Biotech | E13: High | F13: Small/Mid | G13: 0 | H13: 0 | I13: Thematic only, often excluded from headline stats

Sheet 03_Market_Data
A1: MARKET DATA (As-of | Equity value and Enterprise value)
A3: Company | B3: Ticker | C3: CCY | D3: FX (CCY/EUR) | E3: Price (CCY) | F3: Shares (m) | G3: Equity Value (CCY m) | H3: Equity Value (EUR m) | I3: Net Debt (EUR m) | J3: Minorities (EUR m) | K3: Enterprise Value (EUR m)
A4: ='02_Peer_Screen'!A4 -> Eli Lilly | B4: ='02_Peer_Screen'!B4 -> LLY | C4: USD | D4: 1.1 | E4: 780 | F4: 950 | G4: =E4*F4 -> 741000 | H4: =IF(D4=0,"",G4/D4) -> 673636.36 | I4: 10000 | J4: 0 | K4: =H4+I4+J4 -> 683636.36
A5: ='02_Peer_Screen'!A5 -> Sanofi | B5: ='02_Peer_Screen'!B5 -> SAN | C5: EUR | D5: 1 | E5: 90 | F5: 1250 | G5: =E5*F5 -> 112500 | H5: =IF(D5=0,"",G5/D5) -> 112500 | I5: 12000 | J5: 0 | K5: =H5+I5+J5 -> 124500
A6: ='02_Peer_Screen'!A6 -> AstraZeneca | B6: ='02_Peer_Screen'!B6 -> AZN | C6: GBP | D6: 0.86 | E6: 110 | F6: 3100 | G6: =E6*F6 -> 341000 | H6: =IF(D6=0,"",G6/D6) -> 396511.63 | I6: 25000 | J6: 0 | K6: =H6+I6+J6 -> 421511.63
A7: ='02_Peer_Screen'!A7 -> Roche | B7: ='02_Peer_Screen'!B7 -> ROG | C7: CHF | D7: 0.96 | E7: 260 | F7: 850 | G7: =E7*F7 -> 221000 | H7: =IF(D7=0,"",G7/D7) -> 230208.33 | I7: -5000 | J7: 1000 | K7: =H7+I7+J7 -> 226208.33
A8: ='02_Peer_Screen'!A8 -> Novartis | B8: ='02_Peer_Screen'!B8 -> NVS | C8: CHF | D8: 0.96 | E8: 92 | F8: 2060 | G8: =E8*F8 -> 189520 | H8: =IF(D8=0,"",G8/D8) -> 197416.67 | I8: 5000 | J8: 0 | K8: =H8+I8+J8 -> 202416.67
A9: ='02_Peer_Screen'!A9 -> Merck & Co. | B9: ='02_Peer_Screen'!B9 -> MRK | C9: USD | D9: 1.1 | E9: 125 | F9: 2540 | G9: =E9*F9 -> 317500 | H9: =IF(D9=0,"",G9/D9) -> 288636.36 | I9: 15000 | J9: 0 | K9: =H9+I9+J9 -> 303636.36
A10: ='02_Peer_Screen'!A10 -> AbbVie | B10: ='02_Peer_Screen'!B10 -> ABBV | C10: USD | D10: 1.1 | E10: 165 | F10: 1770 | G10: =E10*F10 -> 292050 | H10: =IF(D10=0,"",G10/D10) -> 265500 | I10: 55000 | J10: 0 | K10: =H10+I10+J10 -> 320500
A11: ='02_Peer_Screen'!A11 -> Amgen | B11: ='02_Peer_Screen'!B11 -> AMGN | C11: USD | D11: 1.1 | E11: 290 | F11: 540 | G11: =E11*F11 -> 156600 | H11: =IF(D11=0,"",G11/D11) -> 142363.64 | I11: 35000 | J11: 0 | K11: =H11+I11+J11 -> 177363.64
A12: ='02_Peer_Screen'!A12 -> Bristol Myers Squibb | B12: ='02_Peer_Screen'!B12 -> BMY | C12: USD | D12: 1.1 | E12: 54 | F12: 2060 | G12: =E12*F12 -> 111240 | H12: =IF(D12=0,"",G12/D12) -> 101127.27 | I12: 45000 | J12: 0 | K12: =H12+I12+J12 -> 146127.27
A13: ='02_Peer_Screen'!A13 -> Zealand Pharma | B13: ='02_Peer_Screen'!B13 -> ZEAL | C13: DKK | D13: 7.45 | E13: 620 | F13: 75 | G13: =E13*F13 -> 46500 | H13: =IF(D13=0,"",G13/D13) -> 6241.6107 | I13: -1000 | J13: 0 | K13: =H13+I13+J13 -> 5241.6107

Sheet 04_Consensus
A1: CONSENSUS (NTM estimates | EUR m unless stated)
A3: Company | B3: NTM Revenue (EUR m) | C3: NTM EBITDA (EUR m) | D3: NTM EBIT (EUR m) | E3: NTM EPS (EUR) | F3: 2Y Rev CAGR | G3: NTM EBIT Margin | H3: Notes
A4: ='03_Market_Data'!A4 -> Eli Lilly | B4: 54000 | C4: 18500 | D4: 16500 | E4: 11.5 | F4: 0.18 | G4: =IF(B4=0,"",D4/B4) -> 0.30555556
A5: ='03_Market_Data'!A5 -> Sanofi | B5: 45000 | C5: 12500 | D5: 10500 | E5: 6.2 | F5: 0.06 | G5: =IF(B5=0,"",D5/B5) -> 0.23333333
A6: ='03_Market_Data'!A6 -> AstraZeneca | B6: 50000 | C6: 15000 | D6: 13000 | E6: 3.8 | F6: 0.09 | G6: =IF(B6=0,"",D6/B6) -> 0.26
A7: ='03_Market_Data'!A7 -> Roche | B7: 62000 | C7: 19000 | D7: 16000 | E7: 17 | F7: 0.04 | G7: =IF(B7=0,"",D7/B7) -> 0.25806452
A8: ='03_Market_Data'!A8 -> Novartis | B8: 55000 | C8: 20000 | D8: 17000 | E8: 7.5 | F8: 0.05 | G8: =IF(B8=0,"",D8/B8) -> 0.30909091
A9: ='03_Market_Data'!A9 -> Merck & Co. | B9: 60000 | C9: 25000 | D9: 22000 | E9: 6.8 | F9: 0.06 | G9: =IF(B9=0,"",D9/B9) -> 0.36666667
A10: ='03_Market_Data'!A10 -> AbbVie | B10: 55000 | C10: 25500 | D10: 22500 | E10: 5.9 | F10: 0.03 | G10: =IF(B10=0,"",D10/B10) -> 0.40909091
A11: ='03_Market_Data'!A11 -> Amgen | B11: 31000 | C11: 14000 | D11: 12000 | E11: 15 | F11: 0.04 | G11: =IF(B11=0,"",D11/B11) -> 0.38709677
A12: ='03_Market_Data'!A12 -> Bristol Myers Squibb | B12: 43000 | C12: 18000 | D12: 15500 | E12: 3.2 | F12: 0.02 | G12: =IF(B12=0,"",D12/B12) -> 0.36046512
A13: ='03_Market_Data'!A13 -> Zealand Pharma | B13: 800 | C13: 50 | D13: 0 | E13: 0.1 | F13: 0.25 | G13: =IF(B13=0,"",D13/B13) -> 0

Sheet 05_Multiples
A1: MULTIPLES (Trading comps | auto-calculated)
A2: Bør også have LTM
A3: Company | B3: Inc | C3: Prim | D3: Metab | E3: EV (EUR m) | F3: NTM Rev | G3: NTM EBITDA | H3: NTM EBIT | I3: Price (EUR) | J3: EPS (EUR) | L3: EV/Sales | M3: EV/EBITDA | N3: EV/EBIT | O3: P/E
A4: ='03_Market_Data'!A4 -> Eli Lilly | B4: ='02_Peer_Screen'!G4 -> 1 | C4: ='02_Peer_Screen'!H4 -> 1 | D4: =IF(OR('02_Peer_Screen'!E4="High",'02_Peer_Screen'!E4="Medium"),1,0) -> 1 | E4: ='03_Market_Data'!K4 -> 683636.36 | F4: ='04_Consensus'!B4 -> 54000 | G4: ='04_Consensus'!C4 -> 18500 | H4: ='04_Consensus'!D4 -> 16500 | I4: =IF('03_Market_Data'!D4=0,"",'03_Market_Data'!E4/'03_Market_Data'!D4) -> 709.09091 | J4: ='04_Consensus'!E4 -> 11.5 | L4: =IF(F4=0,"",E4/F4) -> 12.659933 | M4: =IF(G4=0,"",E4/G4) -> 36.953317 | N4: =IF(H4=0,"",E4/H4) -> 41.432507 | O4: =IF(J4=0,"",I4/J4) -> 61.660079
A5: ='03_Market_Data'!A5 -> Sanofi | B5: ='02_Peer_Screen'!G5 -> 1 | C5: ='02_Peer_Screen'!H5 -> 1 | D5: =IF(OR('02_Peer_Screen'!E5="High",'02_Peer_Screen'!E5="Medium"),1,0) -> 1 | E5: ='03_Market_Data'!K5 -> 124500 | F5: ='04_Consensus'!B5 -> 45000 | G5: ='04_Consensus'!C5 -> 12500 | H5: ='04_Consensus'!D5 -> 10500 | I5: =IF('03_Market_Data'!D5=0,"",'03_Market_Data'!E5/'03_Market_Data'!D5) -> 90 | J5: ='04_Consensus'!E5 -> 6.2 | L5: =IF(F5=0,"",E5/F5) -> 2.7666667 | M5: =IF(G5=0,"",E5/G5) -> 9.96 | N5: =IF(H5=0,"",E5/H5) -> 11.857143 | O5: =IF(J5=0,"",I5/J5) -> 14.516129
A6: ='03_Market_Data'!A6 -> AstraZeneca | B6: ='02_Peer_Screen'!G6 -> 1 | C6: ='02_Peer_Screen'!H6 -> 1 | D6: =IF(OR('02_Peer_Screen'!E6="High",'02_Peer_Screen'!E6="Medium"),1,0) -> 1 | E6: ='03_Market_Data'!K6 -> 421511.63 | F6: ='04_Consensus'!B6 -> 50000 | G6: ='04_Consensus'!C6 -> 15000 | H6: ='04_Consensus'!D6 -> 13000 | I6: =IF('03_Market_Data'!D6=0,"",'03_Market_Data'!E6/'03_Market_Data'!D6) -> 127.90698 | J6: ='04_Consensus'!E6 -> 3.8 | L6: =IF(F6=0,"",E6/F6) -> 8.4302326 | M6: =IF(G6=0,"",E6/G6) -> 28.100775 | N6: =IF(H6=0,"",E6/H6) -> 32.423971 | O6: =IF(J6=0,"",I6/J6) -> 33.659731
A7: ='03_Market_Data'!A7 -> Roche | B7: ='02_Peer_Screen'!G7 -> 1 | C7: ='02_Peer_Screen'!H7 -> 0 | D7: =IF(OR('02_Peer_Screen'!E7="High",'02_Peer_Screen'!E7="Medium"),1,0) -> 0 | E7: ='03_Market_Data'!K7 -> 226208.33 | F7: ='04_Consensus'!B7 -> 62000 | G7: ='04_Consensus'!C7 -> 19000 | H7: ='04_Consensus'!D7 -> 16000 | I7: =IF('03_Market_Data'!D7=0,"",'03_Market_Data'!E7/'03_Market_Data'!D7) -> 270.83333 | J7: ='04_Consensus'!E7 -> 17 | L7: =IF(F7=0,"",E7/F7) -> 3.6485215 | M7: =IF(G7=0,"",E7/G7) -> 11.905702 | N7: =IF(H7=0,"",E7/H7) -> 14.138021 | O7: =IF(J7=0,"",I7/J7) -> 15.931373
A8: ='03_Market_Data'!A8 -> Novartis | B8: ='02_Peer_Screen'!G8 -> 1 | C8: ='02_Peer_Screen'!H8 -> 0 | D8: =IF(OR('02_Peer_Screen'!E8="High",'02_Peer_Screen'!E8="Medium"),1,0) -> 0 | E8: ='03_Market_Data'!K8 -> 202416.67 | F8: ='04_Consensus'!B8 -> 55000 | G8: ='04_Consensus'!C8 -> 20000 | H8: ='04_Consensus'!D8 -> 17000 | I8: =IF('03_Market_Data'!D8=0,"",'03_Market_Data'!E8/'03_Market_Data'!D8) -> 95.833333 | J8: ='04_Consensus'!E8 -> 7.5 | L8: =IF(F8=0,"",E8/F8) -> 3.680303 | M8: =IF(G8=0,"",E8/G8) -> 10.120833 | N8: =IF(H8=0,"",E8/H8) -> 11.906863 | O8: =IF(J8=0,"",I8/J8) -> 12.777778
A9: ='03_Market_Data'!A9 -> Merck & Co. | B9: ='02_Peer_Screen'!G9 -> 1 | C9: ='02_Peer_Screen'!H9 -> 0 | D9: =IF(OR('02_Peer_Screen'!E9="High",'02_Peer_Screen'!E9="Medium"),1,0) -> 0 | E9: ='03_Market_Data'!K9 -> 303636.36 | F9: ='04_Consensus'!B9 -> 60000 | G9: ='04_Consensus'!C9 -> 25000 | H9: ='04_Consensus'!D9 -> 22000 | I9: =IF('03_Market_Data'!D9=0,"",'03_Market_Data'!E9/'03_Market_Data'!D9) -> 113.63636 | J9: ='04_Consensus'!E9 -> 6.8 | L9: =IF(F9=0,"",E9/F9) -> 5.0606061 | M9: =IF(G9=0,"",E9/G9) -> 12.145455 | N9: =IF(H9=0,"",E9/H9) -> 13.801653 | O9: =IF(J9=0,"",I9/J9) -> 16.71123
A10: ='03_Market_Data'!A10 -> AbbVie | B10: ='02_Peer_Screen'!G10 -> 1 | C10: ='02_Peer_Screen'!H10 -> 0 | D10: =IF(OR('02_Peer_Screen'!E10="High",'02_Peer_Screen'!E10="Medium"),1,0) -> 0 | E10: ='03_Market_Data'!K10 -> 320500 | F10: ='04_Consensus'!B10 -> 55000 | G10: ='04_Consensus'!C10 -> 25500 | H10: ='04_Consensus'!D10 -> 22500 | I10: =IF('03_Market_Data'!D10=0,"",'03_Market_Data'!E10/'03_Market_Data'!D10) -> 150 | J10: ='04_Consensus'!E10 -> 5.9 | L10: =IF(F10=0,"",E10/F10) -> 5.8272727 | M10: =IF(G10=0,"",E10/G10) -> 12.568627 | N10: =IF(H10=0,"",E10/H10) -> 14.244444 | O10: =IF(J10=0,"",I10/J10) -> 25.423729
A11: ='03_Market_Data'!A11 -> Amgen | B11: ='02_Peer_Screen'!G11 -> 1 | C11: ='02_Peer_Screen'!H11 -> 0 | D11: =IF(OR('02_Peer_Screen'!E11="High",'02_Peer_Screen'!E11="Medium"),1,0) -> 1 | E11: ='03_Market_Data'!K11 -> 177363.64 | F11: ='04_Consensus'!B11 -> 31000 | G11: ='04_Consensus'!C11 -> 14000 | H11: ='04_Consensus'!D11 -> 12000 | I11: =IF('03_Market_Data'!D11=0,"",'03_Market_Data'!E11/'03_Market_Data'!D11) -> 263.63636 | J11: ='04_Consensus'!E11 -> 15 | L11: =IF(F11=0,"",E11/F11) -> 5.7214076 | M11: =IF(G11=0,"",E11/G11) -> 12.668831 | N11: =IF(H11=0,"",E11/H11) -> 14.780303 | O11: =IF(J11=0,"",I11/J11) -> 17.575758
A12: ='03_Market_Data'!A12 -> Bristol Myers Squibb | B12: ='02_Peer_Screen'!G12 -> 1 | C12: ='02_Peer_Screen'!H12 -> 0 | D12: =IF(OR('02_Peer_Screen'!E12="High",'02_Peer_Screen'!E12="Medium"),1,0) -> 0 | E12: ='03_Market_Data'!K12 -> 146127.27 | F12: ='04_Consensus'!B12 -> 43000 | G12: ='04_Consensus'!C12 -> 18000 | H12: ='04_Consensus'!D12 -> 15500 | I12: =IF('03_Market_Data'!D12=0,"",'03_Market_Data'!E12/'03_Market_Data'!D12) -> 49.090909 | J12: ='04_Consensus'!E12 -> 3.2 | L12: =IF(F12=0,"",E12/F12) -> 3.3983087 | M12: =IF(G12=0,"",E12/G12) -> 8.1181818 | N12: =IF(H12=0,"",E12/H12) -> 9.427566 | O12: =IF(J12=0,"",I12/J12) -> 15.340909
A13: ='03_Market_Data'!A13 -> Zealand Pharma | B13: ='02_Peer_Screen'!G13 -> 0 | C13: ='02_Peer_Screen'!H13 -> 0 | D13: =IF(OR('02_Peer_Screen'!E13="High",'02_Peer_Screen'!E13="Medium"),1,0) -> 1 | E13: ='03_Market_Data'!K13 -> 5241.6107 | F13: ='04_Consensus'!B13 -> 800 | G13: ='04_Consensus'!C13 -> 50 | H13: ='04_Consensus'!D13 -> 0 | I13: =IF('03_Market_Data'!D13=0,"",'03_Market_Data'!E13/'03_Market_Data'!D13) -> 83.221477 | J13: ='04_Consensus'!E13 -> 0.1 | L13: =IF(F13=0,"",E13/F13) -> 6.5520134 | M13: =IF(G13=0,"",E13/G13) -> 104.83221 | N13: =IF(H13=0,"",E13/H13) | O13: =IF(J13=0,"",I13/J13) -> 832.21477

Sheet 06_Stats
A1: STATS (Auto | Include / Primary / Metabolic flags)
A3: INPUT FLAGS (linked)
A4: Company | B4: Include | C4: Primary | D4: Metabolic | M4: All EV/Sales | N4: All EV/EBITDA | O4: All EV/EBIT | P4: All P/E | Q4: Primary EV/Sales | R4: Primary EV/EBITDA | S4: Primary EV/EBIT | T4: Primary P/E | U4: Metabolic EV/Sales | V4: Metabolic EV/EBITDA | W4: Metabolic EV/EBIT | X4: Metabolic P/E
A5: ='05_Multiples'!A4 -> Eli Lilly | B5: ='05_Multiples'!B4 -> 1 | C5: ='05_Multiples'!C4 -> 1 | D5: ='05_Multiples'!D4 -> 1 | M5: =IF($B5=1,'05_Multiples'!L4,"") -> 12.659933 | N5: =IF($B5=1,'05_Multiples'!M4,"") -> 36.953317 | O5: =IF($B5=1,'05_Multiples'!N4,"") -> 41.432507 | P5: =IF($B5=1,'05_Multiples'!O4,"") -> 61.660079 | Q5: =IF(AND($B5=1,$C5=1),'05_Multiples'!L4,"") -> 12.659933 | R5: =IF(AND($B5=1,$C5=1),'05_Multiples'!M4,"") -> 36.953317 | S5: =IF(AND($B5=1,$C5=1),'05_Multiples'!N4,"") -> 41.432507 | T5: =IF(AND($B5=1,$C5=1),'05_Multiples'!O4,"") -> 61.660079 | U5: =IF(AND($B5=1,$D5=1),'05_Multiples'!L4,"") -> 12.659933 | V5: =IF(AND($B5=1,$D5=1),'05_Multiples'!M4,"") -> 36.953317 | W5: =IF(AND($B5=1,$D5=1),'05_Multiples'!N4,"") -> 41.432507 | X5: =IF(AND($B5=1,$D5=1),'05_Multiples'!O4,"") -> 61.660079
A6: ='05_Multiples'!A5 -> Sanofi | B6: ='05_Multiples'!B5 -> 1 | C6: ='05_Multiples'!C5 -> 1 | D6: ='05_Multiples'!D5 -> 1 | M6: =IF($B6=1,'05_Multiples'!L5,"") -> 2.7666667 | N6: =IF($B6=1,'05_Multiples'!M5,"") -> 9.96 | O6: =IF($B6=1,'05_Multiples'!N5,"") -> 11.857143 | P6: =IF($B6=1,'05_Multiples'!O5,"") -> 14.516129 | Q6: =IF(AND($B6=1,$C6=1),'05_Multiples'!L5,"") -> 2.7666667 | R6: =IF(AND($B6=1,$C6=1),'05_Multiples'!M5,"") -> 9.96 | S6: =IF(AND($B6=1,$C6=1),'05_Multiples'!N5,"") -> 11.857143 | T6: =IF(AND($B6=1,$C6=1),'05_Multiples'!O5,"") -> 14.516129 | U6: =IF(AND($B6=1,$D6=1),'05_Multiples'!L5,"") -> 2.7666667 | V6: =IF(AND($B6=1,$D6=1),'05_Multiples'!M5,"") -> 9.96 | W6: =IF(AND($B6=1,$D6=1),'05_Multiples'!N5,"") -> 11.857143 | X6: =IF(AND($B6=1,$D6=1),'05_Multiples'!O5,"") -> 14.516129
A7: ='05_Multiples'!A6 -> AstraZeneca | B7: ='05_Multiples'!B6 -> 1 | C7: ='05_Multiples'!C6 -> 1 | D7: ='05_Multiples'!D6 -> 1 | M7: =IF($B7=1,'05_Multiples'!L6,"") -> 8.4302326 | N7: =IF($B7=1,'05_Multiples'!M6,"") -> 28.100775 | O7: =IF($B7=1,'05_Multiples'!N6,"") -> 32.423971 | P7: =IF($B7=1,'05_Multiples'!O6,"") -> 33.659731 | Q7: =IF(AND($B7=1,$C7=1),'05_Multiples'!L6,"") -> 8.4302326 | R7: =IF(AND($B7=1,$C7=1),'05_Multiples'!M6,"") -> 28.100775 | S7: =IF(AND($B7=1,$C7=1),'05_Multiples'!N6,"") -> 32.423971 | T7: =IF(AND($B7=1,$C7=1),'05_Multiples'!O6,"") -> 33.659731 | U7: =IF(AND($B7=1,$D7=1),'05_Multiples'!L6,"") -> 8.4302326 | V7: =IF(AND($B7=1,$D7=1),'05_Multiples'!M6,"") -> 28.100775 | W7: =IF(AND($B7=1,$D7=1),'05_Multiples'!N6,"") -> 32.423971 | X7: =IF(AND($B7=1,$D7=1),'05_Multiples'!O6,"") -> 33.659731
A8: ='05_Multiples'!A7 -> Roche | B8: ='05_Multiples'!B7 -> 1 | C8: ='05_Multiples'!C7 -> 0 | D8: ='05_Multiples'!D7 -> 0 | M8: =IF($B8=1,'05_Multiples'!L7,"") -> 3.6485215 | N8: =IF($B8=1,'05_Multiples'!M7,"") -> 11.905702 | O8: =IF($B8=1,'05_Multiples'!N7,"") -> 14.138021 | P8: =IF($B8=1,'05_Multiples'!O7,"") -> 15.931373 | Q8: =IF(AND($B8=1,$C8=1),'05_Multiples'!L7,"") | R8: =IF(AND($B8=1,$C8=1),'05_Multiples'!M7,"") | S8: =IF(AND($B8=1,$C8=1),'05_Multiples'!N7,"") | T8: =IF(AND($B8=1,$C8=1),'05_Multiples'!O7,"") | U8: =IF(AND($B8=1,$D8=1),'05_Multiples'!L7,"") | V8: =IF(AND($B8=1,$D8=1),'05_Multiples'!M7,"") | W8: =IF(AND($B8=1,$D8=1),'05_Multiples'!N7,"") | X8: =IF(AND($B8=1,$D8=1),'05_Multiples'!O7,"")
A9: ='05_Multiples'!A8 -> Novartis | B9: ='05_Multiples'!B8 -> 1 | C9: ='05_Multiples'!C8 -> 0 | D9: ='05_Multiples'!D8 -> 0 | M9: =IF($B9=1,'05_Multiples'!L8,"") -> 3.680303 | N9: =IF($B9=1,'05_Multiples'!M8,"") -> 10.120833 | O9: =IF($B9=1,'05_Multiples'!N8,"") -> 11.906863 | P9: =IF($B9=1,'05_Multiples'!O8,"") -> 12.777778 | Q9: =IF(AND($B9=1,$C9=1),'05_Multiples'!L8,"") | R9: =IF(AND($B9=1,$C9=1),'05_Multiples'!M8,"") | S9: =IF(AND($B9=1,$C9=1),'05_Multiples'!N8,"") | T9: =IF(AND($B9=1,$C9=1),'05_Multiples'!O8,"") | U9: =IF(AND($B9=1,$D9=1),'05_Multiples'!L8,"") | V9: =IF(AND($B9=1,$D9=1),'05_Multiples'!M8,"") | W9: =IF(AND($B9=1,$D9=1),'05_Multiples'!N8,"") | X9: =IF(AND($B9=1,$D9=1),'05_Multiples'!O8,"")
A10: ='05_Multiples'!A9 -> Merck & Co. | B10: ='05_Multiples'!B9 -> 1 | C10: ='05_Multiples'!C9 -> 0 | D10: ='05_Multiples'!D9 -> 0 | M10: =IF($B10=1,'05_Multiples'!L9,"") -> 5.0606061 | N10: =IF($B10=1,'05_Multiples'!M9,"") -> 12.145455 | O10: =IF($B10=1,'05_Multiples'!N9,"") -> 13.801653 | P10: =IF($B10=1,'05_Multiples'!O9,"") -> 16.71123 | Q10: =IF(AND($B10=1,$C10=1),'05_Multiples'!L9,"") | R10: =IF(AND($B10=1,$C10=1),'05_Multiples'!M9,"") | S10: =IF(AND($B10=1,$C10=1),'05_Multiples'!N9,"") | T10: =IF(AND($B10=1,$C10=1),'05_Multiples'!O9,"") | U10: =IF(AND($B10=1,$D10=1),'05_Multiples'!L9,"") | V10: =IF(AND($B10=1,$D10=1),'05_Multiples'!M9,"") | W10: =IF(AND($B10=1,$D10=1),'05_Multiples'!N9,"") | X10: =IF(AND($B10=1,$D10=1),'05_Multiples'!O9,"")
A11: ='05_Multiples'!A10 -> AbbVie | B11: ='05_Multiples'!B10 -> 1 | C11: ='05_Multiples'!C10 -> 0 | D11: ='05_Multiples'!D10 -> 0 | M11: =IF($B11=1,'05_Multiples'!L10,"") -> 5.8272727 | N11: =IF($B11=1,'05_Multiples'!M10,"") -> 12.568627 | O11: =IF($B11=1,'05_Multiples'!N10,"") -> 14.244444 | P11: =IF($B11=1,'05_Multiples'!O10,"") -> 25.423729 | Q11: =IF(AND($B11=1,$C11=1),'05_Multiples'!L10,"") | R11: =IF(AND($B11=1,$C11=1),'05_Multiples'!M10,"") | S11: =IF(AND($B11=1,$C11=1),'05_Multiples'!N10,"") | T11: =IF(AND($B11=1,$C11=1),'05_Multiples'!O10,"") | U11: =IF(AND($B11=1,$D11=1),'05_Multiples'!L10,"") | V11: =IF(AND($B11=1,$D11=1),'05_Multiples'!M10,"") | W11: =IF(AND($B11=1,$D11=1),'05_Multiples'!N10,"") | X11: =IF(AND($B11=1,$D11=1),'05_Multiples'!O10,"")
A12: ='05_Multiples'!A11 -> Amgen | B12: ='05_Multiples'!B11 -> 1 | C12: ='05_Multiples'!C11 -> 0 | D12: ='05_Multiples'!D11 -> 1 | M12: =IF($B12=1,'05_Multiples'!L11,"") -> 5.7214076 | N12: =IF($B12=1,'05_Multiples'!M11,"") -> 12.668831 | O12: =IF($B12=1,'05_Multiples'!N11,"") -> 14.780303 | P12: =IF($B12=1,'05_Multiples'!O11,"") -> 17.575758 | Q12: =IF(AND($B12=1,$C12=1),'05_Multiples'!L11,"") | R12: =IF(AND($B12=1,$C12=1),'05_Multiples'!M11,"") | S12: =IF(AND($B12=1,$C12=1),'05_Multiples'!N11,"") | T12: =IF(AND($B12=1,$C12=1),'05_Multiples'!O11,"") | U12: =IF(AND($B12=1,$D12=1),'05_Multiples'!L11,"") -> 5.7214076 | V12: =IF(AND($B12=1,$D12=1),'05_Multiples'!M11,"") -> 12.668831 | W12: =IF(AND($B12=1,$D12=1),'05_Multiples'!N11,"") -> 14.780303 | X12: =IF(AND($B12=1,$D12=1),'05_Multiples'!O11,"") -> 17.575758
A13: ='05_Multiples'!A12 -> Bristol Myers Squibb | B13: ='05_Multiples'!B12 -> 1 | C13: ='05_Multiples'!C12 -> 0 | D13: ='05_Multiples'!D12 -> 0 | M13: =IF($B13=1,'05_Multiples'!L12,"") -> 3.3983087 | N13: =IF($B13=1,'05_Multiples'!M12,"") -> 8.1181818 | O13: =IF($B13=1,'05_Multiples'!N12,"") -> 9.427566 | P13: =IF($B13=1,'05_Multiples'!O12,"") -> 15.340909 | Q13: =IF(AND($B13=1,$C13=1),'05_Multiples'!L12,"") | R13: =IF(AND($B13=1,$C13=1),'05_Multiples'!M12,"") | S13: =IF(AND($B13=1,$C13=1),'05_Multiples'!N12,"") | T13: =IF(AND($B13=1,$C13=1),'05_Multiples'!O12,"") | U13: =IF(AND($B13=1,$D13=1),'05_Multiples'!L12,"") | V13: =IF(AND($B13=1,$D13=1),'05_Multiples'!M12,"") | W13: =IF(AND($B13=1,$D13=1),'05_Multiples'!N12,"") | X13: =IF(AND($B13=1,$D13=1),'05_Multiples'!O12,"")
A14: ='05_Multiples'!A13 -> Zealand Pharma | B14: ='05_Multiples'!B13 -> 0 | C14: ='05_Multiples'!C13 -> 0 | D14: ='05_Multiples'!D13 -> 1 | M14: =IF($B14=1,'05_Multiples'!L13,"") | N14: =IF($B14=1,'05_Multiples'!M13,"") | O14: =IF($B14=1,'05_Multiples'!N13,"") | P14: =IF($B14=1,'05_Multiples'!O13,"") | Q14: =IF(AND($B14=1,$C14=1),'05_Multiples'!L13,"") | R14: =IF(AND($B14=1,$C14=1),'05_Multiples'!M13,"") | S14: =IF(AND($B14=1,$C14=1),'05_Multiples'!N13,"") | T14: =IF(AND($B14=1,$C14=1),'05_Multiples'!O13,"") | U14: =IF(AND($B14=1,$D14=1),'05_Multiples'!L13,"") | V14: =IF(AND($B14=1,$D14=1),'05_Multiples'!M13,"") | W14: =IF(AND($B14=1,$D14=1),'05_Multiples'!N13,"") | X14: =IF(AND($B14=1,$D14=1),'05_Multiples'!O13,"")
A17: STATS: All Included
A18: Metric | B18: Min | C18: 25th | D18: Median | E18: Mean | F18: 75th | G18: Max | H18: Count
A19: EV/Sales | B19: =MIN($M$5:$M$14) -> 2.7666667 | C19: =_xlfn.PERCENTILE.INC($M$5:$M$14,0.25) -> 3.6485215 | D19: =MEDIAN($M$5:$M$14) -> 5.0606061 | E19: =AVERAGE($M$5:$M$14) -> 5.6881391 | F19: =_xludf.PERCENTILE.INC($M$5:$M$14,0.75) -> #NAME? | G19: =MAX($M$5:$M$14) -> 12.659933 | H19: =COUNT($M$5:$M$14) -> 9
A20: EV/EBITDA | B20: =MIN($N$5:$N$14) -> 8.1181818 | C20: =_xlfn.PERCENTILE.INC($N$5:$N$14,0.25) -> 10.120833 | D20: =MEDIAN($N$5:$N$14) -> 12.145455 | E20: =AVERAGE($N$5:$N$14) -> 15.837969 | F20: =_xludf.PERCENTILE.INC($N$5:$N$14,0.75) -> #NAME? | G20: =MAX($N$5:$N$14) -> 36.953317 | H20: =COUNT($N$5:$N$14) -> 9
A21: EV/EBIT | B21: =MIN($O$5:$O$14) -> 9.427566 | C21: =_xludf.PERCENTILE.INC($O$5:$O$14,0.25) -> #NAME? | D21: =MEDIAN($O$5:$O$14) -> 14.138021 | E21: =AVERAGE($O$5:$O$14) -> 18.223608 | F21: =_xludf.PERCENTILE.INC($O$5:$O$14,0.75) -> #NAME? | G21: =MAX($O$5:$O$14) -> 41.432507 | H21: =COUNT($O$5:$O$14) -> 9
A22: P/E | B22: =MIN($P$5:$P$14) -> 12.777778 | C22: =_xludf.PERCENTILE.INC($P$5:$P$14,0.25) -> #NAME? | D22: =MEDIAN($P$5:$P$14) -> 16.71123 | E22: =AVERAGE($P$5:$P$14) -> 23.732968 | F22: =_xludf.PERCENTILE.INC($P$5:$P$14,0.75) -> #NAME? | G22: =MAX($P$5:$P$14) -> 61.660079 | H22: =COUNT($P$5:$P$14) -> 9
A25: STATS: Primary Only
A26: Metric | B26: Min | C26: 25th | D26: Median | E26: Mean | F26: 75th | G26: Max | H26: Count
A27: EV/Sales | B27: =MIN($Q$5:$Q$14) -> 2.7666667 | C27: =_xludf.PERCENTILE.INC($Q$5:$Q$14,0.25) -> #NAME? | D27: =MEDIAN($Q$5:$Q$14) -> 8.4302326 | E27: =AVERAGE($Q$5:$Q$14) -> 7.9522773 | F27: =_xludf.PERCENTILE.INC($Q$5:$Q$14,0.75) -> #NAME? | G27: =MAX($Q$5:$Q$14) -> 12.659933 | H27: =COUNT($Q$5:$Q$14) -> 3
A28: EV/EBITDA | B28: =MIN($R$5:$R$14) -> 9.96 | C28: =_xludf.PERCENTILE.INC($R$5:$R$14,0.25) -> #NAME? | D28: =MEDIAN($R$5:$R$14) -> 28.100775 | E28: =AVERAGE($R$5:$R$14) -> 25.004697 | F28: =_xludf.PERCENTILE.INC($R$5:$R$14,0.75) -> #NAME? | G28: =MAX($R$5:$R$14) -> 36.953317 | H28: =COUNT($R$5:$R$14) -> 3
A29: EV/EBIT | B29: =MIN($S$5:$S$14) -> 11.857143 | C29: =_xludf.PERCENTILE.INC($S$5:$S$14,0.25) -> #NAME? | D29: =MEDIAN($S$5:$S$14) -> 32.423971 | E29: =AVERAGE($S$5:$S$14) -> 28.571207 | F29: =_xludf.PERCENTILE.INC($S$5:$S$14,0.75) -> #NAME? | G29: =MAX($S$5:$S$14) -> 41.432507 | H29: =COUNT($S$5:$S$14) -> 3
A30: P/E | B30: =MIN($T$5:$T$14) -> 14.516129 | C30: =_xludf.PERCENTILE.INC($T$5:$T$14,0.25) -> #NAME? | D30: =MEDIAN($T$5:$T$14) -> 33.659731 | E30: =AVERAGE($T$5:$T$14) -> 36.61198 | F30: =_xludf.PERCENTILE.INC($T$5:$T$14,0.75) -> #NAME? | G30: =MAX($T$5:$T$14) -> 61.660079 | H30: =COUNT($T$5:$T$14) -> 3
A33: STATS: Metabolic Only
A34: Metric | B34: Min | C34: 25th | D34: Median | E34: Mean | F34: 75th | G34: Max | H34: Count
A35: EV/Sales | B35: =MIN($U$5:$U$14) -> 2.7666667 | C35: =_xludf.PERCENTILE.INC($U$5:$U$14,0.25) -> #NAME? | D35: =MEDIAN($U$5:$U$14) -> 7.0758201 | E35: =AVERAGE($U$5:$U$14) -> 7.3945599 | F35: =_xludf.PERCENTILE.INC($U$5:$U$14,0.75) -> #NAME? | G35: =MAX($U$5:$U$14) -> 12.659933 | H35: =COUNT($U$5:$U$14) -> 4
A36: EV/EBITDA | B36: =MIN($V$5:$V$14) -> 9.96 | C36: =_xludf.PERCENTILE.INC($V$5:$V$14,0.25) -> #NAME? | D36: =MEDIAN($V$5:$V$14) -> 20.384803 | E36: =AVERAGE($V$5:$V$14) -> 21.920731 | F36: =_xludf.PERCENTILE.INC($V$5:$V$14,0.75) -> #NAME? | G36: =MAX($V$5:$V$14) -> 36.953317 | H36: =COUNT($V$5:$V$14) -> 4
A37: EV/EBIT | B37: =MIN($W$5:$W$14) -> 11.857143 | C37: =_xludf.PERCENTILE.INC($W$5:$W$14,0.25) -> #NAME? | D37: =MEDIAN($W$5:$W$14) -> 23.602137 | E37: =AVERAGE($W$5:$W$14) -> 25.123481 | F37: =_xludf.PERCENTILE.INC($W$5:$W$14,0.75) -> #NAME? | G37: =MAX($W$5:$W$14) -> 41.432507 | H37: =COUNT($W$5:$W$14) -> 4
A38: P/E | B38: =MIN($X$5:$X$14) -> 14.516129 | C38: =_xludf.PERCENTILE.INC($X$5:$X$14,0.25) -> #NAME? | D38: =MEDIAN($X$5:$X$14) -> 25.617744 | E38: =AVERAGE($X$5:$X$14) -> 31.852924 | F38: =_xludf.PERCENTILE.INC($X$5:$X$14,0.75) -> #NAME? | G38: =MAX($X$5:$X$14) -> 61.660079 | H38: =COUNT($X$5:$X$14) -> 4

Sheet 07_Novo_Valuation
A1: NOVO VALUATION (Trading comps | EUR m / EUR per share)
A3: NOVO INPUTS (Blue = input)
A4: Novo NTM Revenue (EUR m) | B4: 40000
A5: Novo NTM EBIT (EUR m) | B5: 20000
A6: Novo NTM EPS (EUR) | B6: 9.5
A7: Novo Net Debt (EUR m) | B7: -5000
A8: Novo Shares (m) | B8: 2200
A10: VALUATION RANGES (25th / Median / 75th)
A11: Method | B11: Multiple | C11: Low | D11: Mid | E11: High | F11: Implied EV (Low) | G11: Implied EV (Mid) | H11: Implied EV (High)
A12: Primary | EV/EBIT | B12: EV/EBIT | C12: ='06_Stats'!C29 -> #NAME? | D12: ='06_Stats'!D29 -> 32.423971 | E12: ='06_Stats'!F29 -> #NAME? | F12: =$B$5*C12 -> #NAME? | G12: =$B$5*D12 -> 648479.43 | H12: =$B$5*E12 -> #NAME?
A13: Primary | EV/Sales | B13: EV/Sales | C13: ='06_Stats'!C27 -> #NAME? | D13: ='06_Stats'!D27 -> 8.4302326 | E13: ='06_Stats'!F27 -> #NAME? | F13: =$B$4*C13 -> #NAME? | G13: =$B$4*D13 -> 337209.3 | H13: =$B$4*E13 -> #NAME?
A14: Metabolic | EV/EBIT | B14: EV/EBIT | C14: ='06_Stats'!C37 -> #NAME? | D14: ='06_Stats'!D37 -> 23.602137 | E14: ='06_Stats'!F37 -> #NAME? | F14: =$B$5*C14 -> #NAME? | G14: =$B$5*D14 -> 472042.74 | H14: =$B$5*E14 -> #NAME?
A16: HEADLINE OUTPUT (based on Primary EV/EBIT)
A17: Case | B17: EV (EUR m) | C17: Less: Net Debt (EUR m) | D17: Equity Value (EUR m) | E17: Shares (m) | F17: Value / Share (EUR)
A18: Low | B18: =F12 -> #NAME? | C18: =$B$7 -> -5000 | D18: =B18-C18 -> #NAME? | E18: =$B$8 -> 2200 | F18: =IF(E18=0,"",D18/E18) -> #NAME?
A19: Mid | B19: =G12 -> 648479.43 | C19: =$B$7 -> -5000 | D19: =B19-C19 -> 653479.43 | E19: =$B$8 -> 2200 | F19: =IF(E19=0,"",D19/E19) -> 297.0361
A20: High | B20: =H12 -> #NAME? | C20: =$B$7 -> -5000 | D20: =B20-C20 -> #NAME? | E20: =$B$8 -> 2200 | F20: =IF(E20=0,"",D20/E20) -> #NAME?

Sheet 08_Football_Field
A1: FOOTBALL FIELD (Auto | Value per share, EUR)
A3: Method | B3: Low | C3: High | D3: Show | F3: Start (hidden) | G3: Range
A4: Trading Comps (Primary EV/EBIT) | B4: ='07_Novo_Valuation'!F18 -> #NAME? | C4: ='07_Novo_Valuation'!F20 -> #NAME? | D4: 1 | F4: =IF(D4=1,B4,"") -> #NAME? | G4: =IF(D4=1,C4-B4,"") -> #NAME?
A5: Trading Comps (Primary EV/Sales) | B5: =('07_Novo_Valuation'!F13-$B$7)/$B$8 -> #NAME? | C5: =('07_Novo_Valuation'!H13-$B$7)/$B$8 -> #NAME? | D5: 1 | F5: =IF(D5=1,B5,"") -> #NAME? | G5: =IF(D5=1,C5-B5,"") -> #NAME?
A6: Metabolic Overlay (EV/EBIT) | B6: =('07_Novo_Valuation'!F14-$B$7)/$B$8 -> #NAME? | C6: =('07_Novo_Valuation'!H14-$B$7)/$B$8 -> #NAME? | D6: 1 | F6: =IF(D6=1,B6,"") -> #NAME? | G6: =IF(D6=1,C6-B6,"") -> #NAME?
A7: DCF (placeholder) | B7: 16 | C7: 24 | D7: 1 | F7: =IF(D7=1,B7,"") -> 16 | G7: =IF(D7=1,C7-B7,"") -> 8
A9: Novo Net Debt (EUR m) | B9: ='07_Novo_Valuation'!B7 -> -5000
A10: Novo Shares (m) | B10: ='07_Novo_Valuation'!B8 -> 2200

Sheet 09_QC
A1: QC CHECKS (Flag issues before using in deck)
A3: Check | B3: Status | C3: Detail
A4: Missing EV values? | B4: =IF(COUNTBLANK('03_Market_Data'!K4:K13)>0,"FAIL","OK") -> OK | C4: =COUNTBLANK('03_Market_Data'!K4:K13) -> 0
A5: Missing consensus revenue/EBIT? | B5: =IF(COUNTBLANK('04_Consensus'!B4:B13)+COUNTBLANK('04_Consensus'!D4:D13)>0,"FAIL","OK") -> OK | C5: =COUNTBLANK('04_Consensus'!B4:B13)+COUNTBLANK('04_Consensus'!D4:D13) -> 0
A6: Included peers >= 5? | B6: =IF(COUNTIF('02_Peer_Screen'!G4:G13,1)>=5,"OK","REVIEW") -> OK | C6: =COUNTIF('02_Peer_Screen'!G4:G13,1) -> 9
A7: Primary peers >= 3? | B7: =IF(SUMPRODUCT(--('02_Peer_Screen'!G4:G13=1),--('02_Peer_Screen'!H4:H13=1))>=3,"OK","REVIEW") -> OK | C7: =SUMPRODUCT(--('02_Peer_Screen'!G4:G13=1),--('02_Peer_Screen'!H4:H13=1)) -> 3

Sheet Peer Rationale
A1: PEER SELECTION RATIONALE — Novo Nordisk Comparable Company Analysis
A2: Six-dimension framework: Business Model | Growth | Margin | Size | Geography | Risk/Cyclicality
A3: Company | B3: Ticker | C3: Business Model | D3: Growth Profile | E3: Margin Profile | F3: Size | G3: Geography | H3: Inclusion Rationale
A4: Novo Nordisk | B4: NVO | C4: GLP-1 / Diabetes / Obesity | D4: High (24%+ NTM) | E4: 49% EBITDA | F4: Large Cap | G4: Europe (US-listed) | H4: TARGET
A5: Eli Lilly | B5: LLY | C5: GLP-1 / Oncology / Diabetes | D5: High (34%+ NTM) | E5: 42% EBITDA | F5: Mega Cap | G5: US | H5: PRIMARY — Closest GLP-1 peer; Mounjaro/Zepbound direct competitor. Same high-growth, high-multiple regime.
A6: AstraZeneca | B6: AZN | C6: Oncology / BioPharmaceuticals | D6: Medium (8% NTM) | E6: 31% EBITDA | F6: Large Cap | G6: Europe (US-listed) | H6: PRIMARY — Large-cap EU pharma, similar R&D model, comparable margin structure. Useful geography comp.
A7: Roche | B7: ROG | C7: Diagnostics / Oncology | D7: Medium (4% NTM) | E7: 38% EBITDA | F7: Large Cap | G7: Europe | H7: PRIMARY — Premier EU pharma, strong IP moat, high margins. Slightly lower growth; useful as anchor peer.
A8: Sanofi | B8: SNY | C8: Immunology / Vaccines / CHC | D8: Low-Medium (6% NTM) | E8: 28% EBITDA | F8: Large Cap | G8: Europe (US-listed) | H8: SECONDARY — EU pharma, lower growth. Useful as valuation floor reference. Different end-markets.
A9: AbbVie | B9: ABBV | C9: Immunology / Oncology / Neuro | D9: Medium (5% NTM) | E9: 40% EBITDA | F9: Large Cap | G9: US | H9: PRIMARY — High-margin, branded pharma with strong FCF. Useful multiple anchor despite Humira headwinds.
A10: Merck | B10: MRK | C10: Oncology / Vaccines (Keytruda) | D10: Medium (6% NTM) | E10: 36% EBITDA | F10: Large Cap | G10: US | H10: PRIMARY — Keytruda growth profile has some analogy to Ozempic ramp. Strong R&D pipeline comp.
