Workbook
Name IPO_YEAR: '01_CONTROL'!$C$6
Name CTRL_SCEN: '01_CONTROL'!$C$14
Name CTRL_PX_CASE: '01_CONTROL'!$C$15
Name CTRL_VAL_METHOD: '01_CONTROL'!$C$16
Name CTRL_GS_ON: '01_CONTROL'!$C$17
Name CTRL_FEE_ALLOC: '01_CONTROL'!$C$18
Name CTRL_SEC_ALLOC: '01_CONTROL'!$C$19
Name IPO_PX_LOW: '01_CONTROL'!$C$24
Name IPO_PX_BASE: '01_CONTROL'!$C$25
Name IPO_PX_HIGH: '01_CONTROL'!$C$26
Name GROSS_PROCEEDS_BASE: '01_CONTROL'!$C$27
Name PRIMARY_PCT: '01_CONTROL'!$C$28
Name SECONDARY_PCT: '01_CONTROL'!$C$29
Name GS_PCT: '01_CONTROL'!$C$30
Name FEE_PCT: '01_CONTROL'!$C$31
Name OTHER_COSTS: '01_CONTROL'!$C$32
Name UOP_DEBT_PCT: '01_CONTROL'!$C$37
Name UOP_CASH_PCT: '01_CONTROL'!$C$38
Name UOP_GROWTH_PCT: '01_CONTROL'!$C$39
Name W_COMPS: '01_CONTROL'!$C$45
Name W_DCF: '01_CONTROL'!$C$46
Name WACC: '01_CONTROL'!$C$47
Name TERM_G: '01_CONTROL'!$C$48
Name TERM_METHOD: '01_CONTROL'!$C$49
Name EXIT_MULT: '01_CONTROL'!$C$50
Name IPO_PX_SEL: '01_CONTROL'!$C$56
Name LTM_REV: '05_FORECAST'!$F$52
Name NTM_REV: '05_FORECAST'!$F$53
Name LTM_EBITDA: '05_FORECAST'!$F$54
Name NTM_EBITDA: '05_FORECAST'!$F$55
Name NETDEBT_PRE: '05_FORECAST'!$F$56
Name NEW_PRIMARY_SHARES: '09_OFFER_STRUCTURE'!$C$38
Name SHARES_SOLD_PUBLIC: '09_OFFER_STRUCTURE'!$C$39
Name NET_PROCEEDS_CO: '09_OFFER_STRUCTURE'!$C$40
Name TXN_COSTS: '09_OFFER_STRUCTURE'!$C$41
Name DEBT_PAYDOWN: '12_USE_OF_PROCEEDS'!$C$17
Name CASH_RETAINED: '12_USE_OF_PROCEEDS'!$C$18
Name GROWTH_INVEST: '12_USE_OF_PROCEEDS'!$C$19
Name NETDEBT_POST: '11_PRO_FORMA_BS'!$C$25
Name PRE_SHARES: '10_CAP_TABLE'!$C$8
Name OPT_SHARES: '10_CAP_TABLE'!$C$9
Name POST_SHARES: '10_CAP_TABLE'!$C$23
Name POST_SHARES_FD: '10_CAP_TABLE'!$C$24
Name FREE_FLOAT_PCT: '10_CAP_TABLE'!$C$25
Name PRIMARY_DILUTION: '10_CAP_TABLE'!$C$26
Name MULT_SEL: '06_VALUATION_COMPS'!$C$21
Name EV_COMPS_LOW: '06_VALUATION_COMPS'!$C$26
Name EV_COMPS_BASE: '06_VALUATION_COMPS'!$C$27
Name EV_COMPS_HIGH: '06_VALUATION_COMPS'!$C$28
Name EV_DCF_BASE: '07_VALUATION_DCF'!$C$27
Name EV_TRI_LOW: '08_VALUATION_TRIANGULATION'!$C$17
Name EV_TRI_BASE: '08_VALUATION_TRIANGULATION'!$C$18
Name EV_TRI_HIGH: '08_VALUATION_TRIANGULATION'!$C$19
Name EQ_LOW: '08_VALUATION_TRIANGULATION'!$C$26
Name EQ_BASE: '08_VALUATION_TRIANGULATION'!$C$27
Name EQ_HIGH: '08_VALUATION_TRIANGULATION'!$C$28
Name PX_IMP_LOW: '08_VALUATION_TRIANGULATION'!$C$29
Name PX_IMP_BASE: '08_VALUATION_TRIANGULATION'!$C$30
Name PX_IMP_HIGH: '08_VALUATION_TRIANGULATION'!$C$31
Name MKT_CAP: '13_METRICS_AND_KPIS'!$C$19

Sheet 00_DASHBOARD
B2: IPO DASHBOARD (TRAINING) - PRICE RANGE, VALUATION, DILUTION
B4: Scenario | C4: =CTRL_SCEN | D4: Price case | E4: =CTRL_PX_CASE
B5: All numbers trace to calc tabs. Blue cells = inputs (in relevant tabs).
B7: KEY OUTPUTS
B8: Metric | C8: Low | D8: Base | E8: High | F8: Learning cue (click)
B9: IPO price (DKK/share) | C9: =IPO_PX_LOW | D9: =IPO_PX_BASE | E9: =IPO_PX_HIGH | F9: =HYPERLINK("#'80_IPO_LEARN_MAP'!B11","Price range: defend the discount vs comps and demand.")
B10: Implied price (DKK/share) | C10: =PX_IMP_LOW | D10: =PX_IMP_BASE | E10: =PX_IMP_HIGH | F10: =HYPERLINK("#'80_IPO_LEARN_MAP'!B12","Implied price: triangulated valuation output, not the offer price.")
B11: Equity value (DKKm) | C11: =EQ_LOW | D11: =EQ_BASE | E11: =EQ_HIGH | F11: =HYPERLINK("#'80_IPO_LEARN_MAP'!B13","Equity value: market cap at price point (watch share count definition).")
B12: Enterprise value (DKKm) | C12: =EV_TRI_LOW | D12: =EV_TRI_BASE | E12: =EV_TRI_HIGH | F12: =HYPERLINK("#'80_IPO_LEARN_MAP'!B14","EV: equity value + net debt (definition drives the bridge).")
B13: Net debt post (DKKm) | D13: =NETDEBT_POST | F13: =HYPERLINK("#'80_IPO_LEARN_MAP'!B15","Net debt post: pro forma bridge from proceeds and debt paydown.")
B14: Free float post (%) | D14: =FREE_FLOAT_PCT | F14: =HYPERLINK("#'80_IPO_LEARN_MAP'!B16","Free float: liquidity metric; balance with dilution and sell-down.")
B15: Net primary proceeds (DKKm) | D15: =NET_PROCEEDS_CO | F15: =HYPERLINK("#'80_IPO_LEARN_MAP'!B17","Net primary proceeds: cash to company after fees and costs.")
B16: Secondary proceeds gross (DKKm) | D16: ='09_OFFER_STRUCTURE'!$C$25
B17: Total costs (DKKm) | D17: =TXN_COSTS | F17: =HYPERLINK("#'80_IPO_LEARN_MAP'!B19","Costs: sanity check net proceeds vs gross; watch sign conventions.")
B18: EV / NTM EBITDA at offer (x) | D18: =EV_EBITDA_OFFER | F18: =HYPERLINK("#'80_IPO_LEARN_MAP'!B24","Offer multiple: quick marketability check vs peers.")
B19: LTM Revenue (DKKm) | D19: =LTM_REV
B20: NTM EBITDA (DKKm) | D20: =NTM_EBITDA | F20: =HYPERLINK("#'80_IPO_LEARN_MAP'!B23","Issuer metric: NTM EBITDA is the denominator for EV/EBITDA.")
B22: WHAT THIS MEANS (AUTO)
B24: • | C24: ='99_APPENDIX_DATA'!$C$8
B25: • | C25: ='99_APPENDIX_DATA'!$C$9
B26: • | C26: ='99_APPENDIX_DATA'!$C$10
B27: • | C27: ='99_APPENDIX_DATA'!$C$11
B28: • | C28: ='99_APPENDIX_DATA'!$C$12
B30: CHECKS STATUS
B32: Overall | C32: =CHECKS_OVERALL
B35: CHART DATA - EV RANGE
B37: Case | C37: EV (DKKm)
B38: Low | C38: =EV_TRI_LOW
B39: Base | C39: =EV_TRI_BASE
B40: High | C40: =EV_TRI_HIGH
B43: CHART DATA - OWNERSHIP (POST IPO)
B45: Holder | C45: Post %
B46: ='10_CAP_TABLE'!$B$12 | C46: ='10_CAP_TABLE'!$G$12
B47: ='10_CAP_TABLE'!$B$13 | C47: ='10_CAP_TABLE'!$G$13
B48: ='10_CAP_TABLE'!$B$14 | C48: ='10_CAP_TABLE'!$G$14
B49: ='10_CAP_TABLE'!$B$15 | C49: ='10_CAP_TABLE'!$G$15
B50: ='10_CAP_TABLE'!$B$16 | C50: ='10_CAP_TABLE'!$G$16
B51: ='10_CAP_TABLE'!$B$17 | C51: ='10_CAP_TABLE'!$G$17

Sheet 01_CONTROL
B2: IPO FINANCIAL MODEL (DENMARK) - CONTROL CENTER
B4: Case | C4: Illustrative training IPO
B5: Units | C5: DKKm (shares in m)
B6: IPO Year (FY) | C6: 2026
B10: TIMELINE | G10: FY2023A | H10: FY2024A | I10: FY2025A | J10: FY2026E | K10: FY2027E | L10: FY2028E | M10: FY2029E | N10: FY2030E
B12: KEY TOGGLES (INPUTS)
B14: Scenario (1=Base,2=Upside,3=Downside) | C14: 1
B15: Price case (1=Low,2=Base,3=High) | C15: 2
B16: Valuation method (1=Comps only,2=Comps+DCF) | C16: 2
B17: Greenshoe on/off (0/1) | C17: 1
B18: Fee allocation (1=all to primary,2=pro-rata) | C18: 2
B19: Secondary allocation (1=pro-rata sellers,2=specified) | C19: 1
B22: IPO PRICING & DEAL PARAMETERS (INPUTS)
B24: IPO Price - Low (DKK/share) | C24: 400
B25: IPO Price - Base (DKK/share) | C25: 450
B26: IPO Price - High (DKK/share) | C26: 500
B27: Gross Proceeds Target at Base Price (DKKm) | C27: 15000
B28: Primary % of offer shares | C28: 0.6
B29: Secondary % of offer shares | C29: 0.4
B30: Greenshoe % of base offer shares | C30: 0.15
B31: Underwriting fee % of gross (total) | C31: 0.035
B32: Other transaction costs (DKKm) | C32: 150
B35: USE OF PROCEEDS (INPUTS)
B37: Debt paydown % of net company proceeds | C37: 0.5
B38: Cash retained % of net company proceeds | C38: 0.3
B39: Growth investment % of net company proceeds | C39: 0.2
B43: DCF (ONLY IF ENABLED)
B45: Comps weight (if method=2) | C45: 0.7
B46: DCF weight (if method=2) | C46: 0.3
B47: WACC | C47: 0.085
B48: Terminal growth g | C48: 0.025
B49: Terminal method (1=Perpetuity,2=Exit multiple) | C49: 1
B50: Exit multiple (if TERM_METHOD=2) | C50: 12
B54: DERIVED (DO NOT TYPE)
B56: Selected IPO price (DKK/share) | C56: =CHOOSE(CTRL_PX_CASE;IPO_PX_LOW;IPO_PX_BASE;IPO_PX_HIGH)
B57: Use of proceeds sums to 100% | C57: =IF(ABS(UOP_DEBT_PCT+UOP_CASH_PCT+UOP_GROWTH_PCT-1)<0,0001;"PASS";"FAIL")

Sheet 02_COVER_AND_TOC
B2: IPO FINANCIAL MODEL (DENMARK) - COVER + TOC
B4: Company: | C4: TrainingCo A/S (illustrative)
B5: Prepared for: | C5: ECM Training Simulation
B6: Version: | C6: v1.00
B8: Dashboard | C8: 00_DASHBOARD
B9: TABLE OF CONTENTS | C9: 01_CONTROL
B10: Historical inputs | C10: 03_HISTORICALS
B11: Tab | C11: Description
B12: 00_DASHBOARD | C12: IC-style dashboard with valuation, ownership and checks
B13: 01_CONTROL | C13: All toggles and core assumptions (only input area)
B14: 02_COVER_AND_TOC | C14: Cover and navigation
B15: 03_HISTORICALS | C15: Historical IS / BS / CF inputs and standardization
B16: 04_DRIVERS | C16: Forecast drivers by scenario
... B28: 99_APPENDIX_DATA | C28: Optional narrative cells and scratch
B31: INPUT CHECKLIST (PASTE INTO 03_HISTORICALS / 01_CONTROL)
B33: □ | C33: 3 FY revenue + EBITDA (DKKm)
B34: □ | C34: Cash and debt at IPO reference date (DKKm)
B35: □ | C35: Working capital proxy (DSO/DIO/DPO or NWC % revenue)
B36: □ | C36: Capex % revenue (or absolute capex, DKKm)
B37: □ | C37: Tax rate (%)
B38: □ | C38: Pre-IPO share count (m shares) and owner split (%)
B39: □ | C39: IPO price range (DKK/share) and target gross proceeds (DKKm)
B40: □ | C40: Primary/secondary mix, greenshoe toggle (%)
B41: □ | C41: Underwriting fee (%) and other costs (DKKm)
B42: □ | C42: Selected multiple or peer multiple assumption (EV/EBITDA)

Sheet 03_HISTORICALS
B2: HISTORICAL FINANCIALS (INPUTS) - DKKm
B6: INCOME STATEMENT | G6: FY2023A | H6: FY2024A | I6: FY2025A
B8: Revenue | G8: 80000 | H8: 86000 | I8: 92000
B9: COGS | G9: -32000 | H9: -34400 | I9: -36800
B10: Opex | G10: -24000 | H10: -25800 | I10: -27600
B11: EBITDA | G11: =G8+G9+G10 | H11: =H8+H9+H10 | I11: =I8+I9+I10
B12: D&A | G12: -2500 | H12: -2600 | I12: -2700
B13: EBIT | G13: =G11+G12 | H13: =H11+H12 | I13: =I11+I12
B14: Net interest | G14: -300 | H14: -320 | I14: -340
B15: Taxes | G15: -5200 | H15: -5600 | I15: -6000
B16: Net income | G16: =G13+G14+G15 | H16: =H13+H14+H15 | I16: =I13+I14+I15
B20: BALANCE SHEET | G20: FY2023A | H20: FY2024A | I20: FY2025A | J20: FY2026E | K20: FY2027E | L20: FY2028E | M20: FY2029E | N20: FY2030E
B22: Cash | G22: 5000 | H22: 5200 | I22: 5400
B23: Debt | G23: 8000 | H23: 7600 | I23: 7200
B24: Accounts receivable | G24: 9000 | H24: 9800 | I24: 10500
B25: Inventory | G25: 7000 | H25: 7400 | I25: 7800
B26: Accounts payable | G26: -6000 | H26: -6400 | I26: -6800
B27: PPE, net | G27: 12000 | H27: 12500 | I27: 13000
B28: Equity | G28: 17000 | H28: 19000 | I28: 21000
B29: Net debt | G29: =G23-G22 | H29: =H23-H22 | I29: =I23-I22

Sheet 04_DRIVERS
B2: FORECAST DRIVERS (INPUTS) - SCENARIO BASED
B6: Driver | C6: Base | D6: Upside | E6: Downside | G6: FY2023A | H6: FY2024A | I6: FY2025A | J6: FY2026E | K6: FY2027E | L6: FY2028E | M6: FY2029E | N6: FY2030E
B8: Revenue growth % | C8: 0.05 | D8: 0.07 | E8: 0.03 | I8: =CHOOSE(CTRL_SCEN;$C8;$D8;$E8) | J8: =CHOOSE(CTRL_SCEN;$C8;$D8;$E8) | K8: =CHOOSE(CTRL_SCEN;$C8;$D8;$E8) | L8: =CHOOSE(CTRL_SCEN;$C8;$D8;$E8) | M8: =CHOOSE(CTRL_SCEN;$C8;$D8;$E8) | N8: =CHOOSE(CTRL_SCEN;$C8;$D8;$E8)
B9: Gross margin % | C9: 0.6 | D9: 0.61 | E9: 0.59 | I9: =CHOOSE(CTRL_SCEN;$C9;$D9;$E9) | J9: =CHOOSE(CTRL_SCEN;$C9;$D9;$E9) | K9: =CHOOSE(CTRL_SCEN;$C9;$D9;$E9) | L9: =CHOOSE(CTRL_SCEN;$C9;$D9;$E9) | M9: =CHOOSE(CTRL_SCEN;$C9;$D9;$E9) | N9: =CHOOSE(CTRL_SCEN;$C9;$D9;$E9)
B10: Opex % of revenue | C10: 0.26 | D10: 0.25 | E10: 0.27 | I10: =CHOOSE(CTRL_SCEN;$C10;$D10;$E10) | J10: =CHOOSE(CTRL_SCEN;$C10;$D10;$E10) | K10: =CHOOSE(CTRL_SCEN;$C10;$D10;$E10) | L10: =CHOOSE(CTRL_SCEN;$C10;$D10;$E10) | M10: =CHOOSE(CTRL_SCEN;$C10;$D10;$E10) | N10: =CHOOSE(CTRL_SCEN;$C10;$D10;$E10)
B11: DSO (days) | C11: 40 | D11: 38 | E11: 42 | I11: =CHOOSE(CTRL_SCEN;$C11;$D11;$E11) | J11: =CHOOSE(CTRL_SCEN;$C11;$D11;$E11) | K11: =CHOOSE(CTRL_SCEN;$C11;$D11;$E11) | L11: =CHOOSE(CTRL_SCEN;$C11;$D11;$E11) | M11: =CHOOSE(CTRL_SCEN;$C11;$D11;$E11) | N11: =CHOOSE(CTRL_SCEN;$C11;$D11;$E11)
B12: DIO (days) | C12: 60 | D12: 58 | E12: 62 | I12: =CHOOSE(CTRL_SCEN;$C12;$D12;$E12) | J12: =CHOOSE(CTRL_SCEN;$C12;$D12;$E12) | K12: =CHOOSE(CTRL_SCEN;$C12;$D12;$E12) | L12: =CHOOSE(CTRL_SCEN;$C12;$D12;$E12) | M12: =CHOOSE(CTRL_SCEN;$C12;$D12;$E12) | N12: =CHOOSE(CTRL_SCEN;$C12;$D12;$E12)
B13: DPO (days) | C13: 50 | D13: 52 | E13: 48 | I13: =CHOOSE(CTRL_SCEN;$C13;$D13;$E13) | J13: =CHOOSE(CTRL_SCEN;$C13;$D13;$E13) | K13: =CHOOSE(CTRL_SCEN;$C13;$D13;$E13) | L13: =CHOOSE(CTRL_SCEN;$C13;$D13;$E13) | M13: =CHOOSE(CTRL_SCEN;$C13;$D13;$E13) | N13: =CHOOSE(CTRL_SCEN;$C13;$D13;$E13)
B14: Capex % of revenue | C14: 0.03 | D14: 0.035 | E14: 0.025 | I14: =CHOOSE(CTRL_SCEN;$C14;$D14;$E14) | J14: =CHOOSE(CTRL_SCEN;$C14;$D14;$E14) | K14: =CHOOSE(CTRL_SCEN;$C14;$D14;$E14) | L14: =CHOOSE(CTRL_SCEN;$C14;$D14;$E14) | M14: =CHOOSE(CTRL_SCEN;$C14;$D14;$E14) | N14: =CHOOSE(CTRL_SCEN;$C14;$D14;$E14)
B15: D&A % of revenue | C15: 0.03 | D15: 0.03 | E15: 0.03 | I15: =CHOOSE(CTRL_SCEN;$C15;$D15;$E15) | J15: =CHOOSE(CTRL_SCEN;$C15;$D15;$E15) | K15: =CHOOSE(CTRL_SCEN;$C15;$D15;$E15) | L15: =CHOOSE(CTRL_SCEN;$C15;$D15;$E15) | M15: =CHOOSE(CTRL_SCEN;$C15;$D15;$E15) | N15: =CHOOSE(CTRL_SCEN;$C15;$D15;$E15)
B16: Tax rate % | C16: 0.22 | D16: 0.22 | E16: 0.22 | I16: =CHOOSE(CTRL_SCEN;$C16;$D16;$E16) | J16: =CHOOSE(CTRL_SCEN;$C16;$D16;$E16) | K16: =CHOOSE(CTRL_SCEN;$C16;$D16;$E16) | L16: =CHOOSE(CTRL_SCEN;$C16;$D16;$E16) | M16: =CHOOSE(CTRL_SCEN;$C16;$D16;$E16) | N16: =CHOOSE(CTRL_SCEN;$C16;$D16;$E16)

Sheet 05_FORECAST
B2: INTEGRATED FORECAST (IS / BS / CF) - DKKm
B6: YEARS | G6: FY2023A | H6: FY2024A | I6: FY2025A | J6: FY2026E | K6: FY2027E | L6: FY2028E | M6: FY2029E | N6: FY2030E
B8: INCOME STATEMENT
B10: Revenue | G10: ='03_HISTORICALS'!G8 | H10: ='03_HISTORICALS'!H8 | I10: ='03_HISTORICALS'!I8 | J10: =I10*(1+'04_DRIVERS'!J8) | K10: =J10*(1+'04_DRIVERS'!K8) | L10: =K10*(1+'04_DRIVERS'!L8) | M10: =L10*(1+'04_DRIVERS'!M8) | N10: =M10*(1+'04_DRIVERS'!N8)
B11: COGS | G11: ='03_HISTORICALS'!G9 | H11: ='03_HISTORICALS'!H9 | I11: ='03_HISTORICALS'!I9 | J11: =-J10*(1-'04_DRIVERS'!J9) | K11: =-K10*(1-'04_DRIVERS'!K9) | L11: =-L10*(1-'04_DRIVERS'!L9) | M11: =-M10*(1-'04_DRIVERS'!M9) | N11: =-N10*(1-'04_DRIVERS'!N9)
B12: Gross profit | G12: =G10+G11 | H12: =H10+H11 | I12: =I10+I11 | J12: =J10+J11 | K12: =K10+K11 | L12: =L10+L11 | M12: =M10+M11 | N12: =N10+N11
B13: Opex | G13: ='03_HISTORICALS'!G10 | H13: ='03_HISTORICALS'!H10 | I13: ='03_HISTORICALS'!I10 | J13: =-J10*'04_DRIVERS'!J10 | K13: =-K10*'04_DRIVERS'!K10 | L13: =-L10*'04_DRIVERS'!L10 | M13: =-M10*'04_DRIVERS'!M10 | N13: =-N10*'04_DRIVERS'!N10
B14: EBITDA | G14: ='03_HISTORICALS'!G11 | H14: ='03_HISTORICALS'!H11 | I14: ='03_HISTORICALS'!I11 | J14: =J12+J13 | K14: =K12+K13 | L14: =L12+L13 | M14: =M12+M13 | N14: =N12+N13
B15: D&A | G15: ='03_HISTORICALS'!G12 | H15: ='03_HISTORICALS'!H12 | I15: ='03_HISTORICALS'!I12 | J15: =-J10*'04_DRIVERS'!J15 | K15: =-K10*'04_DRIVERS'!K15 | L15: =-L10*'04_DRIVERS'!L15 | M15: =-M10*'04_DRIVERS'!M15 | N15: =-N10*'04_DRIVERS'!N15
B16: EBIT | G16: ='03_HISTORICALS'!G13 | H16: ='03_HISTORICALS'!H13 | I16: ='03_HISTORICALS'!I13 | J16: =J14+J15 | K16: =K14+K15 | L16: =L14+L15 | M16: =M14+M15 | N16: =N14+N15
B17: Taxes | G17: ='03_HISTORICALS'!G15 | H17: ='03_HISTORICALS'!H15 | I17: ='03_HISTORICALS'!I15 | J17: =-MAX(0;J16)*'04_DRIVERS'!J16 | K17: =-MAX(0;K16)*'04_DRIVERS'!K16 | L17: =-MAX(0;L16)*'04_DRIVERS'!L16 | M17: =-MAX(0;M16)*'04_DRIVERS'!M16 | N17: =-MAX(0;N16)*'04_DRIVERS'!N16
B18: Net income | G18: ='03_HISTORICALS'!G16 | H18: ='03_HISTORICALS'!H16 | I18: ='03_HISTORICALS'!I16 | J18: =J16+J17 | K18: =K16+K17 | L18: =L16+L17 | M18: =M16+M17 | N18: =N16+N17
B22: BALANCE SHEET
B24: Cash | G24: ='03_HISTORICALS'!G22 | H24: ='03_HISTORICALS'!H22 | I24: ='03_HISTORICALS'!I22 | J24: =J46 | K24: =K46 | L24: =L46 | M24: =M46 | N24: =N46
B25: Debt | G25: ='03_HISTORICALS'!G23 | H25: ='03_HISTORICALS'!H23 | I25: ='03_HISTORICALS'!I23 | J25: =I25 | K25: =J25 | L25: =K25 | M25: =L25 | N25: =M25
B26: Accounts receivable | G26: ='03_HISTORICALS'!G24 | H26: ='03_HISTORICALS'!H24 | I26: ='03_HISTORICALS'!I24 | J26: =J10/365*'04_DRIVERS'!J11 | K26: =K10/365*'04_DRIVERS'!K11 | L26: =L10/365*'04_DRIVERS'!L11 | M26: =M10/365*'04_DRIVERS'!M11 | N26: =N10/365*'04_DRIVERS'!N11
B27: Inventory | G27: ='03_HISTORICALS'!G25 | H27: ='03_HISTORICALS'!H25 | I27: ='03_HISTORICALS'!I25 | J27: =-J11/365*'04_DRIVERS'!J12 | K27: =-K11/365*'04_DRIVERS'!K12 | L27: =-L11/365*'04_DRIVERS'!L12 | M27: =-M11/365*'04_DRIVERS'!M12 | N27: =-N11/365*'04_DRIVERS'!N12
B28: Accounts payable | G28: ='03_HISTORICALS'!G26 | H28: ='03_HISTORICALS'!H26 | I28: ='03_HISTORICALS'!I26 | J28: =J11/365*'04_DRIVERS'!J13 | K28: =K11/365*'04_DRIVERS'!K13 | L28: =L11/365*'04_DRIVERS'!L13 | M28: =M11/365*'04_DRIVERS'!M13 | N28: =N11/365*'04_DRIVERS'!N13
B29: Net working capital | G29: =G26+G27+G28 | H29: =H26+H27+H28 | I29: =I26+I27+I28 | J29: =J26+J27+J28 | K29: =K26+K27+K28 | L29: =L26+L27+L28 | M29: =M26+M27+M28 | N29: =N26+N27+N28
B30: PPE, net | G30: ='03_HISTORICALS'!G27 | H30: ='03_HISTORICALS'!H27 | I30: ='03_HISTORICALS'!I27 | J30: =I30+J42+J15 | K30: =J30+K42+K15 | L30: =K30+L42+L15 | M30: =L30+M42+M15 | N30: =M30+N42+N15
B31: Equity | G31: ='03_HISTORICALS'!G28 | H31: ='03_HISTORICALS'!H28 | I31: ='03_HISTORICALS'!I28 | J31: =I31+J18 | K31: =J31+K18 | L31: =K31+L18 | M31: =L31+M18 | N31: =M31+N18
B32: Net debt | G32: ='03_HISTORICALS'!G29 | H32: ='03_HISTORICALS'!H29 | I32: =I25-I24 | J32: =J25-J24 | K32: =K25-K24 | L32: =L25-L24 | M32: =M25-M24 | N32: =N25-N24
B34: CASH FLOW
B36: EBIT | J36: =J16 | K36: =K16 | L36: =L16 | M36: =M16 | N36: =N16
B37: Tax on EBIT | J37: =J17 | K37: =K17 | L37: =L17 | M37: =M17 | N37: =N17
B38: NOPAT | J38: =J36+J37 | K38: =K36+K37 | L38: =L36+L37 | M38: =M36+M37 | N38: =N36+N37
B39: + D&A | J39: =-J15 | K39: =-K15 | L39: =-L15 | M39: =-M15 | N39: =-N15
B40: - ΔNWC | J40: =-(J29-I29) | K40: =-(K29-J29) | L40: =-(L29-K29) | M40: =-(M29-L29) | N40: =-(N29-M29)
B41: CFO | J41: =SUM(J38:J40) | K41: =SUM(K38:K40) | L41: =SUM(L38:L40) | M41: =SUM(M38:M40) | N41: =SUM(N38:N40)
B42: - Capex | J42: =-J10*'04_DRIVERS'!J14 | K42: =-K10*'04_DRIVERS'!K14 | L42: =-L10*'04_DRIVERS'!L14 | M42: =-M10*'04_DRIVERS'!M14 | N42: =-N10*'04_DRIVERS'!N14
B43: FCF | J43: =J41+J42 | K43: =K41+K42 | L43: =L41+L42 | M43: =M41+M42 | N43: =N41+N42
B44: CFF (simplified pre-IPO) | J44: =0 | K44: =0 | L44: =0 | M44: =0 | N44: =0
B45: Net change in cash | J45: =SUM(J41:J44) | K45: =SUM(K41:K44) | L45: =SUM(L41:L44) | M45: =SUM(M41:M44) | N45: =SUM(N41:N44)
B46: Cash (closing) | J46: =I24+J45 | K46: =J24+K45 | L46: =K24+L45 | M46: =L24+M45 | N46: =M24+N45
B50: EXPORT ANCHORS (DO NOT EDIT)
B52: LTM Revenue (FY2025A) | F52: ='05_FORECAST'!I10
B53: NTM Revenue (FY2026E) | F53: ='05_FORECAST'!J10
B54: LTM EBITDA (FY2025A) | F54: ='05_FORECAST'!I14
B55: NTM EBITDA (FY2026E) | F55: ='05_FORECAST'!J14
B56: Net debt pre-IPO (FY2025A) | F56: ='05_FORECAST'!I32

Sheet 06_VALUATION_COMPS
B2: TRADING COMPS (INPUTS + CALCS)
B6: PEER MULTIPLES (INPUTS)
B8: Peer | C8: EV/NTM EBITDA (x) | D8: Notes
B9: Peer 1 | C9: 11 | D9: Nordic branded consumer
B10: Peer 2 | C10: 12.5 | D10: Global brand
B11: Peer 3 | C11: 10 | D11: Lower growth
B12: Peer 4 | C12: 13 | D12: Premium multiple
B13: Peer 5 | C13: 9.5 | D13: Cyclical discount
B16: MULTIPLE STATS + SELECTION
B18: 25th percentile (x) | C18: =PERCENTILE.INC(C9:C13;0,25)
B19: Median (x) | C19: =MEDIAN($C$9:$C$13)
B20: 75th percentile (x) | C20: =PERCENTILE.INC(C9:C13;0,75)
B21: Selected multiple (x) (input) | C21: 12
B24: COMPS VALUATION OUTPUT (EV)
B26: EV Low (DKKm) | C26: =C18*NTM_EBITDA
B27: EV Base (DKKm) | C27: =MULT_SEL*NTM_EBITDA
B28: EV High (DKKm) | C28: =C20*NTM_EBITDA

Sheet 07_VALUATION_DCF
B2: DCF (OPTIONAL) - ENABLE VIA CONTROL
B4: This is a simplified DCF module. If CTRL_VAL_METHOD=1, outputs are blanked.
B6: UNLEVERED FCF (FROM FORECAST)
G8: FY2023A | H8: FY2024A | I8: FY2025A | J8: FY2026E | K8: FY2027E | L8: FY2028E | M8: FY2029E | N8: FY2030E
B10: EBIT (DKKm) | J10: ='05_FORECAST'!J16 | K10: ='05_FORECAST'!K16 | L10: ='05_FORECAST'!L16 | M10: ='05_FORECAST'!M16 | N10: ='05_FORECAST'!N16
B11: Tax on EBIT (DKKm) | J11: ='05_FORECAST'!J17 | K11: ='05_FORECAST'!K17 | L11: ='05_FORECAST'!L17 | M11: ='05_FORECAST'!M17 | N11: ='05_FORECAST'!N17
B12: NOPAT (DKKm) | J12: =J10+J11 | K12: =K10+K11 | L12: =L10+L11 | M12: =M10+M11 | N12: =N10+N11
B13: + D&A (DKKm) | J13: =-'05_FORECAST'!J15 | K13: =-'05_FORECAST'!K15 | L13: =-'05_FORECAST'!L15 | M13: =-'05_FORECAST'!M15 | N13: =-'05_FORECAST'!N15
B14: - Capex (DKKm) | J14: ='05_FORECAST'!J42 | K14: ='05_FORECAST'!K42 | L14: ='05_FORECAST'!L42 | M14: ='05_FORECAST'!M42 | N14: ='05_FORECAST'!N42
B15: - ΔNWC (DKKm) | J15: ='05_FORECAST'!J40 | K15: ='05_FORECAST'!K40 | L15: ='05_FORECAST'!L40 | M15: ='05_FORECAST'!M40 | N15: ='05_FORECAST'!N40
B16: FCF (DKKm) | J16: =SUM(J12:J15) | K16: =SUM(K12:K15) | L16: =SUM(L12:L15) | M16: =SUM(M12:M15) | N16: =SUM(N12:N15)
B19: PV + TERMINAL VALUE
B21: Discount factor | I21: =1/(1+WACC)^1 | J21: =1/(1+WACC)^1 | K21: =1/(1+WACC)^2 | L21: =1/(1+WACC)^3 | M21: =1/(1+WACC)^4 | N21: =1/(1+WACC)^5
B22: PV of FCF | I22: =I16*I21 | J22: =J16*J21 | K22: =K16*K21 | L22: =L16*L21 | M22: =M16*M21 | N22: =N16*N21
B24: PV of explicit period (DKKm) | C24: =IF(CTRL_VAL_METHOD=2;SUM(J22:N22);"")
B25: Terminal value (DKKm) | C25: =IF(CTRL_VAL_METHOD=2;IF(TERM_METHOD=1;(N16*(1+TERM_G))/(WACC-TERM_G);EXIT_MULT*'05_FORECAST'!N14);"")
B26: PV of terminal value (DKKm) | C26: =IF(CTRL_VAL_METHOD=2;C25*N21;"")
B27: DCF EV (DKKm) | C27: =IF(CTRL_VAL_METHOD=2;C24+C26;"")

Sheet 08_VALUATION_TRIANGULATION
B2: VALUATION TRIANGULATION (LOW / BASE / HIGH)
B6: METHOD OUTPUTS (EV)
C8: Low | D8: Base | E8: High
B9: Comps EV (DKKm) | C9: =EV_COMPS_LOW | D9: =EV_COMPS_BASE | E9: =EV_COMPS_HIGH
B10: DCF EV (DKKm) (blank if disabled) | C10: =IF(CTRL_VAL_METHOD=2;EV_DCF_BASE*0,9;"") | D10: =IF(CTRL_VAL_METHOD=2;EV_DCF_BASE;"") | E10: =IF(CTRL_VAL_METHOD=2;EV_DCF_BASE*1,1;"")
B12: WEIGHTS + TRIANGULATED EV
B14: Comps weight | C14: =IF(CTRL_VAL_METHOD=2;W_COMPS;1)
B15: DCF weight | C15: =IF(CTRL_VAL_METHOD=2;W_DCF;0)
B17: Triangulated EV Low (DKKm) | C17: =$C$14*C9+$C$15*C10
B18: Triangulated EV Base (DKKm) | C18: =$C$14*D9+$C$15*D10
B19: Triangulated EV High (DKKm) | C19: =$C$14*E9+$C$15*E10
B22: EQUITY VALUE + IMPLIED PRICE (POST-IPO)
B24: Net debt post (DKKm) | C24: =NETDEBT_POST
B25: Post shares (basic, m) | C25: =POST_SHARES
B26: Equity value Low (DKKm) | C26: =EV_TRI_LOW-NETDEBT_POST
B27: Equity value Base (DKKm) | C27: =EV_TRI_BASE-NETDEBT_POST
B28: Equity value High (DKKm) | C28: =EV_TRI_HIGH-NETDEBT_POST
B29: Implied price Low (DKK/share) | C29: =EQ_LOW/POST_SHARES
B30: Implied price Base (DKK/share) | C30: =EQ_BASE/POST_SHARES
B31: Implied price High (DKK/share) | C31: =EQ_HIGH/POST_SHARES

Sheet 09_OFFER_STRUCTURE
B2: OFFER STRUCTURE (PRIMARY / SECONDARY / GREENSHEOE / FEES)
B6: INPUTS (LINKED FROM CONTROL)
B8: Selected price (DKK/share) | C8: =IPO_PX_SEL
B9: Gross proceeds target at base price (DKKm) | C9: =GROSS_PROCEEDS_BASE
B10: Primary % | C10: =PRIMARY_PCT
B11: Secondary % | C11: =SECONDARY_PCT
B12: Greenshoe on/off | C12: =CTRL_GS_ON
B13: Greenshoe % | C13: =GS_PCT
B14: Fee % | C14: =FEE_PCT
B15: Other costs (DKKm) | C15: =OTHER_COSTS
B18: SHARES & PROCEEDS (CALCS)
B19: Offer shares at base price (m shares) | C19: =GROSS_PROCEEDS_BASE/IPO_PX_BASE
B20: Primary shares (m) | C20: =C19*PRIMARY_PCT
B21: Secondary shares (m) | C21: =C19*SECONDARY_PCT
B22: Greenshoe shares (m) | C22: =IF(CTRL_GS_ON=1;C19*GS_PCT;0)
B23: Total shares sold (m) | C23: =SUM(C20:C22)
B24: Primary proceeds (gross, DKKm) | C24: =C20*IPO_PX_SEL
B25: Secondary proceeds (gross, DKKm) | C25: =C21*IPO_PX_SEL
B26: Greenshoe proceeds (gross, DKKm) | C26: =C22*IPO_PX_SEL
B27: Total gross proceeds (DKKm) | C27: =SUM(C24:C26)
B28: Underwriting fee (DKKm) | C28: =C27*FEE_PCT
B29: Other costs (DKKm) | C29: =OTHER_COSTS
B30: Total costs (DKKm) | C30: =C28+C29
B31: Fee allocation to primary (DKKm) | C31: =IF(CTRL_FEE_ALLOC=1;C30; C30*(C24/C27))
B32: Other cost allocation to primary (DKKm) | C32: =IF(CTRL_FEE_ALLOC=1;C29; C29*(C24/C27))
B33: Net primary proceeds to company (DKKm) | C33: =C24-C31-C32
B36: OUTPUT ANCHORS (DO NOT EDIT)
B38: Primary shares (m) | C38: =C20
B39: Total shares sold to public (m) | C39: =C23
B40: Net primary proceeds (DKKm) | C40: =C33
B41: Total costs (DKKm) | C41: =C30

Sheet 10_CAP_TABLE
B2: CAP TABLE & DILUTION (PRE / POST)
B6: PRE-IPO OWNERSHIP (INPUTS)
B8: Pre-IPO total shares (m) | C8: 100
B9: Options / ESOP (m, fully diluted add-on) | C9: 5
B11: Holder | C11: Pre % | D11: Pre shares (m) | E11: Secondary sold (m) | F11: Post shares (m) | G11: Post %
B12: Owner A | C12: 0.4 | D12: =$C$8*C12 | E12: =IF(CTRL_SEC_ALLOC=1;(SECONDARY_SHARES+GS_SHARES)*C12;0) | F12: =D12-E12 | G12: =F12/POST_SHARES
B13: Owner B | C13: 0.25 | D13: =$C$8*C13 | E13: =IF(CTRL_SEC_ALLOC=1;(SECONDARY_SHARES+GS_SHARES)*C13;0) | F13: =D13-E13 | G13: =F13/POST_SHARES
B14: Owner C | C14: 0.2 | D14: =$C$8*C14 | E14: =IF(CTRL_SEC_ALLOC=1;(SECONDARY_SHARES+GS_SHARES)*C14;0) | F14: =D14-E14 | G14: =F14/POST_SHARES
B15: Owner D | C15: 0.1 | D15: =$C$8*C15 | E15: =IF(CTRL_SEC_ALLOC=1;(SECONDARY_SHARES+GS_SHARES)*C15;0) | F15: =D15-E15 | G15: =F15/POST_SHARES
B16: Other | C16: 0.05 | D16: =$C$8*C16 | E16: =IF(CTRL_SEC_ALLOC=1;(SECONDARY_SHARES+GS_SHARES)*C16;0) | F16: =D16-E16 | G16: =F16/POST_SHARES
B17: Public (free float) | F17: =SHARES_SOLD_PUBLIC | G17: =FREE_FLOAT_PCT
B20: POST-IPO SHARE COUNT (CALCS)
B22: New primary shares issued (m) | C22: =NEW_PRIMARY_SHARES
B23: Post-IPO total shares (basic, m) | C23: =PRE_SHARES+NEW_PRIMARY_SHARES
B24: Post-IPO shares (fully diluted, m) | C24: =C23+OPT_SHARES
B25: Free float (shares sold / post basic) | C25: =SHARES_SOLD_PUBLIC/POST_SHARES
B26: Primary dilution (1 - pre/post) | C26: =1-(PRE_SHARES/POST_SHARES)

Sheet 11_PRO_FORMA_BS
B2: PRO FORMA BALANCE SHEET (POST-IPO)
B6: OPENING POSITION (PRE-IPO) - FY2025A
B8: Cash (DKKm) | C8: ='03_HISTORICALS'!I22
B9: Debt (DKKm) | C9: ='03_HISTORICALS'!I23
B10: Equity (DKKm) | C10: ='03_HISTORICALS'!I28
B13: TRANSACTION ADJUSTMENTS
B15: Net proceeds to company (DKKm) | C15: =NET_PROCEEDS_CO
B16: Debt paydown (DKKm) | C16: =DEBT_PAYDOWN
B17: Growth investment (DKKm) | C17: =GROWTH_INVEST
B20: POST-IPO POSITION (SIMPLIFIED)
B22: Cash post (DKKm) | C22: =C8+C15-C16-C17
B23: Debt post (DKKm) | C23: =C9-C16
B24: Equity post (DKKm) | C24: =C10+C15
B25: Net debt post (DKKm) | C25: =C23-C22
B28: LEVERAGE (HEADLINE)
B30: Net debt / NTM EBITDA (x) | C30: =IFERROR(NETDEBT_POST/NTM_EBITDA;"")

Sheet 12_USE_OF_PROCEEDS
B2: USE OF PROCEEDS (ALLOCATIONS)
B6: NET PROCEEDS + ALLOCATION (LINKED)
B8: Net proceeds to company (DKKm) | C8: =NET_PROCEEDS_CO
B9: Debt paydown % | C9: =UOP_DEBT_PCT
B10: Cash retained % | C10: =UOP_CASH_PCT
B11: Growth investment % | C11: =UOP_GROWTH_PCT
B12: Allocation check | C12: =IF(ABS(C9+C10+C11-1)<0,0001;"PASS";"FAIL")
B15: ALLOCATED AMOUNTS (DKKm)
B17: Debt paydown (DKKm) | C17: =C8*C9
B18: Cash retained (DKKm) | C18: =C8*C10
B19: Growth investment (DKKm) | C19: =C8*C11

Sheet 13_METRICS_AND_KPIS
B2: METRICS & KPIS (LTM / NTM / OFFER MULTIPLES)
B6: HEADLINE FINANCIALS
B8: LTM Revenue (DKKm) | C8: =LTM_REV
B9: NTM Revenue (DKKm) | C9: =NTM_REV
B10: LTM EBITDA (DKKm) | C10: =LTM_EBITDA
B11: NTM EBITDA (DKKm) | C11: =NTM_EBITDA
B12: NTM EBITDA margin | C12: =IFERROR(C11/C9;"")
B15: AT SELECTED OFFER PRICE
B17: Selected offer price (DKK/share) | C17: =IPO_PX_SEL
B18: Post shares (basic, m) | C18: =POST_SHARES
B19: Market cap (DKKm) | C19: =C17*C18
B20: Net debt post (DKKm) | C20: =NETDEBT_POST
B21: Enterprise value (DKKm) | C21: =C19+C20
B22: EV / NTM EBITDA (x) | C22: =IFERROR(C21/C11;"")
B23: EV / NTM Revenue (x) | C23: =IFERROR(C21/C9;"")

Sheet 14_SENSITIVITIES
B2: SENSITIVITIES (2-MIN REVIEW PACK)
B6: 1) MULTIPLE vs GROWTH ADJ - IMPLIED PRICE (DKK/share)
B8: EV/NTM EBITDA multiple | F8: -0.02 | G8: 0 | H8: 0.02 | I8: 0.04 | J8: 0.06 | K8: 0.08
B9: 8 | F9: =((8)*(NTM_REV*(1+-0,02)*('13_METRICS_AND_KPIS'!$C$12)) - NETDEBT_POST)/POST_SHARES | G9: =((8)*(NTM_REV*(1+0,0)*('13_METRICS_AND_KPIS'!$C$12)) - NETDEBT_POST)/POST_SHARES | H9: =((8)*(NTM_REV*(1+0,02)*('13_METRICS_AND_KPIS'!$C$12)) - NETDEBT_POST)/POST_SHARES | I9: =((8)*(NTM_REV*(1+0,04)*('13_METRICS_AND_KPIS'!$C$12)) - NETDEBT_POST)/POST_SHARES | J9: =((8)*(NTM_REV*(1+0,06)*('13_METRICS_AND_KPIS'!$C$12)) - NETDEBT_POST)/POST_SHARES | K9: =((8)*(NTM_REV*(1+0,08)*('13_METRICS_AND_KPIS'!$C$12)) - NETDEBT_POST)/POST_SHARES
B10: 10 | F10: =((10)*(NTM_REV*(1+-0,02)*('13_METRICS_AND_KPIS'!$C$12)) - NETDEBT_POST)/POST_SHARES | G10: =((10)*(NTM_REV*(1+0,0)*('13_METRICS_AND_KPIS'!$C$12)) - NETDEBT_POST)/POST_SHARES | H10: =((10)*(NTM_REV*(1+0,02)*('13_METRICS_AND_KPIS'!$C$12)) - NETDEBT_POST)/POST_SHARES | I10: =((10)*(NTM_REV*(1+0,04)*('13_METRICS_AND_KPIS'!$C$12)) - NETDEBT_POST)/POST_SHARES | J10: =((10)*(NTM_REV*(1+0,06)*('13_METRICS_AND_KPIS'!$C$12)) - NETDEBT_POST)/POST_SHARES | K10: =((10)*(NTM_REV*(1+0,08)*('13_METRICS_AND_KPIS'!$C$12)) - NETDEBT_POST)/POST_SHARES
B11: 12 | F11: =((12)*(NTM_REV*(1+-0,02)*('13_METRICS_AND_KPIS'!$C$12)) - NETDEBT_POST)/POST_SHARES | G11: =((12)*(NTM_REV*(1+0,0)*('13_METRICS_AND_KPIS'!$C$12)) - NETDEBT_POST)/POST_SHARES | H11: =((12)*(NTM_REV*(1+0,02)*('13_METRICS_AND_KPIS'!$C$12)) - NETDEBT_POST)/POST_SHARES | I11: =((12)*(NTM_REV*(1+0,04)*('13_METRICS_AND_KPIS'!$C$12)) - NETDEBT_POST)/POST_SHARES | J11: =((12)*(NTM_REV*(1+0,06)*('13_METRICS_AND_KPIS'!$C$12)) - NETDEBT_POST)/POST_SHARES | K11: =((12)*(NTM_REV*(1+0,08)*('13_METRICS_AND_KPIS'!$C$12)) - NETDEBT_POST)/POST_SHARES
B12: 14 | F12: =((14)*(NTM_REV*(1+-0,02)*('13_METRICS_AND_KPIS'!$C$12)) - NETDEBT_POST)/POST_SHARES | G12: =((14)*(NTM_REV*(1+0,0)*('13_METRICS_AND_KPIS'!$C$12)) - NETDEBT_POST)/POST_SHARES | H12: =((14)*(NTM_REV*(1+0,02)*('13_METRICS_AND_KPIS'!$C$12)) - NETDEBT_POST)/POST_SHARES | I12: =((14)*(NTM_REV*(1+0,04)*('13_METRICS_AND_KPIS'!$C$12)) - NETDEBT_POST)/POST_SHARES | J12: =((14)*(NTM_REV*(1+0,06)*('13_METRICS_AND_KPIS'!$C$12)) - NETDEBT_POST)/POST_SHARES | K12: =((14)*(NTM_REV*(1+0,08)*('13_METRICS_AND_KPIS'!$C$12)) - NETDEBT_POST)/POST_SHARES
B13: 16 | F13: =((16)*(NTM_REV*(1+-0,02)*('13_METRICS_AND_KPIS'!$C$12)) - NETDEBT_POST)/POST_SHARES | G13: =((16)*(NTM_REV*(1+0,0)*('13_METRICS_AND_KPIS'!$C$12)) - NETDEBT_POST)/POST_SHARES | H13: =((16)*(NTM_REV*(1+0,02)*('13_METRICS_AND_KPIS'!$C$12)) - NETDEBT_POST)/POST_SHARES | I13: =((16)*(NTM_REV*(1+0,04)*('13_METRICS_AND_KPIS'!$C$12)) - NETDEBT_POST)/POST_SHARES | J13: =((16)*(NTM_REV*(1+0,06)*('13_METRICS_AND_KPIS'!$C$12)) - NETDEBT_POST)/POST_SHARES | K13: =((16)*(NTM_REV*(1+0,08)*('13_METRICS_AND_KPIS'!$C$12)) - NETDEBT_POST)/POST_SHARES
B15: 2) PRICE CASE vs FREE FLOAT & DILUTION
B17: Free float % (post) | C17: =FREE_FLOAT_PCT
B18: Primary dilution % | C18: =PRIMARY_DILUTION
B19: Implied price range (Low/Base/High) | C19: =PX_IMP_LOW | D19: =PX_IMP_BASE | E19: =PX_IMP_HIGH
B22: 3) USE OF PROCEEDS vs NET DEBT (BASE)
B24: Net debt post (DKKm) | C24: =NETDEBT_POST
B25: Debt paydown (DKKm) | C25: =DEBT_PAYDOWN

Sheet 80_IPO_LEARN_MAP
B2: IPO Model Learning Layer | 80_IPO_LEARN_MAP (Explainability Map)
B4: Purpose: Top KPIs used in ECM discussions. Each row ties back to specific cells or named ranges in the base model, with pitfalls and sanity checks.
B8: KPI (Top 30) | C8: Where it appears (tab + cell / name) | D8: Definition | E8: Primary drivers (specific) | F8: Directional intuition | G8: Common pitfalls | H8: Sanity checks | I8: If asked by CFO/board, say this | J8: Link
B9: Implied price range (Low/Base/High) | C9: 14_SENSITIVITIES!C19:E19 | PX_IMP_LOW / PX_IMP_BASE / PX_IMP_HIGH | D9: Model implied equity price per share across valuation range points (used for discussion, not final pricing). | E9: • 06_VALUATION_COMPS!C23 MULTIPLE_SEL • 07_VALUATION_DCF inputs: 01_CONTROL!C47 WACC, 01_CONTROL!C48 TERM_G (if DCF used) • 01_CONTROL!C40 W_COMPS and 01_CONTROL!C41 W_DCF (triangulation) • 13_METRICS_AND_KPIS!C20 NETDEBT_POST • 10_CAP_TABLE!C23 POST_SHARES | F9: Higher multiple or higher EBITDA/FCF lifts range. Higher net debt reduces equity price. | G9: • Mixing LTM vs NTM basis between comps and issuer • Using a single outlier peer multiple without explaining why • Not updating net debt definition after use of proceeds | H9: • Range should bracket selected offer price (01_CONTROL!C56) unless explicitly positioning above/below • Equity value at each point must be positive (EV >= net debt) • Price steps should be consistent with multiple/DCF sensitivity direction | I9: These are model-implied prices from comps and optional DCF, combined by a transparent weighting. We will still set a final offer price based on demand, market conditions and our targeting of float and proceeds within this range. | J9: =HYPERLINK("#'14_SENSITIVITIES'!C19","Go")
B10: Selected offer price (current case) | C10: 01_CONTROL!C56 | IPO_PX_SEL | D10: Single offer price used across dashboard and outputs for the current run (used for the draft term sheet view). | E10: • 01_CONTROL price case selector (Low/Base/High) • 01_CONTROL!C24:C26 PRICE_LOW/BASE/HIGH (range inputs) • 14_SENSITIVITIES implied range • Market feedback (outside model) for discount and demand • Free float and dilution constraints (10_CAP_TABLE) | F10: Raising offer price increases market cap and proceeds, but can strain demand and require a larger discount argument. | G10: • Selecting price inconsistent with range narrative • Forgetting to update downstream summary decks when price is changed • Confusing 'implied price' with 'offer price' | H10: • Offer price should be defensible vs peer distribution and DCF outputs (if used) • Check proceeds and float remain within agreed constraints • Sanity: Market cap at offer price = price x post shares | I10: This is the working offer price for the current case. It is chosen inside the implied valuation range, with an explicit discount and float target to support marketability and execution. | J10: =HYPERLINK("#'01_CONTROL'!C56","Go")
B11: Market cap at offer price (DKKm) | C11: 13_METRICS_AND_KPIS!C19 | MKT_CAP | D11: Equity value at offer price based on post deal shares outstanding (DKKm). | E11: • 01_CONTROL!C56 IPO_PX_SEL • 10_CAP_TABLE!C23 POST_SHARES • Offer structure impacts POST_SHARES via primary issuance • Any share split / share count adjustments • Share count definitions (basic vs diluted) if present | F11: Market cap rises linearly with price and with post shares. More primary issuance increases post shares and market cap for a given price. | G11: • Using pre shares instead of post shares • Mixing shares in shares vs millions in price or market cap • Not aligning share count with cap table ownership | H11: • Market cap change should equal price change x post shares • Market cap should reconcile to equity value bridge when using implied EV and net debt • Post shares should equal pre shares + new primary shares | I11: Market cap is simply the offer price times post deal shares. We use it for positioning versus peers, index eligibility and stakeholder communication. | J11: =HYPERLINK("#'13_METRICS_AND_KPIS'!C19","Go")
B12: Enterprise value at offer price (DKKm) | C12: 13_METRICS_AND_KPIS!C21 | EV_OFFER | D12: EV used for valuation multiples: market cap plus net debt (per definition). | E12: • 13_METRICS_AND_KPIS!C19 MKT_CAP • 13_METRICS_AND_KPIS!C20 NETDEBT_POST (definition controlled) • 11_PRO_FORMA_BS cash and debt post (use of proceeds) • Net debt definition toggles (if any) • Any pension, lease or minority adjustments (if included) | F12: Higher net debt increases EV for a given price. Debt paydown reduces EV only if equity price held constant; if EV held constant, equity rises when net debt falls. | G12: • Sign error in net debt (cash vs debt) • Inconsistent definition across comps and issuer • Treating secondary proceeds as company cash | H12: • EV = market cap + net debt should reconcile exactly • EV multiples should move logically with EBITDA/revenue changes • Net debt post must reconcile to pro forma balance sheet | I12: Enterprise value bridges equity and capital structure. We use EV to compare across peers regardless of leverage, so the net debt definition must be consistent and clearly stated. | J12: =HYPERLINK("#'13_METRICS_AND_KPIS'!C21","Go")
B13: Gross proceeds (total) (DKKm) | C13: 09_OFFER_STRUCTURE!C27 | GROSS_TOTAL | D13: Total cash paid by investors for shares sold (primary + secondary + greenshoe). | E13: • 01_CONTROL!C56 offer price • 09_OFFER_STRUCTURE sizing (primary/secondary/greenshoe shares) • 01_CONTROL!C27 gross proceeds target • 01_CONTROL!C28:C30 primary/secondary/greenshoe mix • Any rounding rules on share counts | F13: Increasing price or sold shares increases gross proceeds. Shifting from secondary to primary does not change total gross if total sold is constant. | G13: • Mixing gross proceeds with net proceeds to company • Forgetting greenshoe proceeds in total sold • Using target proceeds without checking implied sold shares | H13: • Gross proceeds total should equal price x total shares sold incl greenshoe • Gross primary proceeds should reconcile to cash to company before fees • Secondary gross proceeds should not flow to pro forma cash | I13: Gross proceeds reflect total investor spend. Only the primary portion creates cash for the company. We separate these cleanly when discussing funding versus shareholder sell down. | J13: =HYPERLINK("#'09_OFFER_STRUCTURE'!C27","Go")
B14: Net proceeds to company (DKKm) | C14: 09_OFFER_STRUCTURE!C33 | NET_PROCEEDS_CO | D14: Cash the company receives after underwriting fee allocation and other transaction costs. | E14: • 09_OFFER_STRUCTURE gross primary proceeds (C24) • Underwriting fee % (01_CONTROL!C31 FEE_PCT) • Fee allocation to primary vs secondary (09_OFFER_STRUCTURE!C31:C32) • Other costs (09_OFFER_STRUCTURE!C29) • Use of proceeds allocation (11_PRO_FORMA_BS) | F14: Higher fee % and costs reduce net proceeds. More primary shares increases net proceeds if price constant. | G14: • Applying fees on total when only primary should be charged (or vice versa) • Sign errors on fees and costs • Double counting costs on both primary and secondary | H14: • Net proceeds must be <= gross primary proceeds • Fee amounts should equal fee % x relevant gross proceeds base • Pro forma cash increase should match net proceeds minus allocations | I14: Net proceeds are what the company actually receives. This is the figure that matters for funding the strategy and for balance sheet impact; it is not the same as gross raise. | J14: =HYPERLINK("#'09_OFFER_STRUCTURE'!C33","Go")
B15: Primary shares issued (m) | C15: 09_OFFER_STRUCTURE!C38 | NEW_PRIMARY_SHARES | D15: New shares issued by the company in the IPO (drives dilution and company cash). | E15: • 01_CONTROL!C27 gross proceeds target • 01_CONTROL!C28 primary % • Offer price selection • Any minimum float constraint (free float target) • Rounding of shares sold | F15: More primary increases dilution and net proceeds. Holding gross constant, increasing price reduces shares required. | G15: • Confusing primary shares with total shares sold • Changing primary % without checking cash to company vs stated use of proceeds • Not updating cap table roll forward | H15: • Post shares = pre shares + primary shares issued • Dilution should increase with primary issuance • Net proceeds should increase with primary issuance | I15: Primary shares are the capital raise for the company. They drive cash and dilution. We size them to fund use of proceeds while keeping dilution and float within acceptable bounds. | J15: =HYPERLINK("#'09_OFFER_STRUCTURE'!C38","Go")
B16: Secondary shares sold (m) | C16: 09_OFFER_STRUCTURE!C21 | SECONDARY_SHARES | D16: Existing shareholder sell down in the IPO (creates float without raising company cash). | E16: • 01_CONTROL!C29 secondary % • Total shares sold sizing (09_OFFER_STRUCTURE!C23) • Any lock up constraints (outside model) • Float target and ownership objectives • Overhang considerations (outside model) | F16: More secondary increases float and reduces selling shareholder stake but does not increase company cash. | G16: • Treating secondary proceeds as company cash • Forgetting secondary affects ownership table and control • Not reconciling to pre existing holder shares | H16: • Secondary cash should not appear in pro forma balance sheet • Ownership after transaction should reconcile to pre shares minus sold shares • Float % should increase with secondary sold | I16: Secondary is a liquidity and ownership tool, not a funding tool. It helps meet float and aftermarket liquidity targets while keeping primary dilution controlled. | J16: =HYPERLINK("#'09_OFFER_STRUCTURE'!C21","Go")
B17: Total shares sold (base) (m) | C17: 09_OFFER_STRUCTURE!C23 | TOTAL_SOLD_SHARES | D17: Total shares offered to the public excluding any greenshoe, as a base deal size. | E17: • Gross proceeds target and offer price • Primary vs secondary mix (01_CONTROL!C28:C29) • Float target (10_CAP_TABLE free float) • Minimum deal size constraints (market practice) • Rounding | F17: More sold shares increase float and gross proceeds at a given price. | G17: • Comparing total sold across deals without normalising for float and market cap • Not including greenshoe when quoting total sold in meetings • Using different share units (m vs shares) | H17: • Gross proceeds base should equal price x total sold shares (ex greenshoe) • Total sold should reconcile to primary + secondary • Public float shares post should be at least total sold (if shares are new+existing) | I17: Total shares sold sets the base deal size. Greenshoe is an optional add-on. We communicate base and with-greenshoe clearly to avoid confusion. | J17: =HYPERLINK("#'09_OFFER_STRUCTURE'!C23","Go")
B18: Greenshoe shares (m) | C18: 09_OFFER_STRUCTURE!C22 | GS_SHARES | D18: Additional shares sold if overallotment is exercised (supports stabilisation and demand management). | E18: • 01_CONTROL!C30 greenshoe % • Total sold shares base (09_OFFER_STRUCTURE!C23) • Investor demand and allocation strategy (outside model) • Free float and ownership targets • Regulatory / prospectus limits (outside model) | F18: Greenshoe increases float and gross proceeds slightly. It can be structured as primary or secondary depending on the base model setup. | G18: • Forgetting to include greenshoe when quoting total sold or float • Assuming greenshoe increases company cash when it is secondary • Not reflecting greenshoe in ownership table | H18: • Total sold incl greenshoe = base sold x (1 + GS%) • Float % should increase when greenshoe is on • Check fee base includes greenshoe if applicable | I18: Greenshoe is mainly an execution tool. It helps the syndicate manage allocations and stabilise trading. Economically it modestly increases float and proceeds, and we disclose the effect explicitly. | J18: =HYPERLINK("#'09_OFFER_STRUCTURE'!C22","Go")
B19: Underwriting fee (DKKm) and fee % of gross | C19: 09_OFFER_STRUCTURE!C28 | 01_CONTROL!C31 FEE_PCT | D19: Fees paid to underwriters. Fee % applied to a defined proceeds base and allocated between primary and secondary. | E19: • 01_CONTROL!C31 fee % • Fee base definition (primary only vs total, per model logic) • 09_OFFER_STRUCTURE fee allocation logic (C31:C32) • Other costs (C29) • Total sold shares incl greenshoe (if fee base includes GS) | F19: Higher fee % reduces net proceeds to company. Fee allocation changes net proceeds vs selling shareholder proceeds. | G19: • Applying fee on wrong base • Sign errors or double counting fees • Not disclosing whether fees are applied to secondary proceeds | H19: • Fee amount should equal fee% x defined base • Net proceeds should change one-for-one with fees • Fees should not affect EV, only cash received and use of proceeds | I19: Fees are a transaction cost. We are transparent about the fee base and allocation. The key economic outcome is net proceeds to the company and balance sheet impact. | J19: =HYPERLINK("#'09_OFFER_STRUCTURE'!C28","Go")
B20: Primary vs secondary split (%, cash to company vs sellers) | C20: 01_CONTROL!C28:C29 (mix) | 09_OFFER_STRUCTURE outputs | D20: Deal structure split: how much is capital raise versus shareholder sell down. | E20: • 01_CONTROL!C28 primary % • 01_CONTROL!C29 secondary % • Gross proceeds target (01_CONTROL!C27) • Fee allocation (09_OFFER_STRUCTURE C31:C32) • Investor demand / float constraints (outside model) | F20: More primary increases company cash and dilution. More secondary increases float and reduces overhang but does not fund the company. | G20: • Talking about total raise without stating primary portion • Inconsistent use of 'raise' vs 'sell down' • Not aligning use of proceeds narrative to primary cash | H20: • Primary % + secondary % should equal 100% for base sizing • Net proceeds to company should move with primary % • Float % should move with secondary as well as primary | I20: The split is a deliberate trade-off. Primary supports the strategy and balance sheet; secondary supports liquidity and ownership objectives. We size both to meet float and dilution constraints. | J20: =HYPERLINK("#'01_CONTROL'!C28","Go")
B21: Pre IPO shares outstanding (m) | C21: 10_CAP_TABLE!C21 | PRE_SHARES | D21: Shares outstanding before the IPO (used for ownership and dilution base). | E21: • Cap table input / pre shareholders data (10_CAP_TABLE section) • Any option pools or convertibles (if included) • Share split adjustments • Definition of basic shares • Any pre-IPO issuance assumptions | F21: Higher pre shares reduce dilution percentage for a given primary issuance (all else equal). | G21: • Using fully diluted when model assumes basic (or vice versa) • Not reflecting pre-IPO option pool top-up • Inconsistent share counts across tabs | H21: • Pre shares should reconcile to cap table sum of holders • Pre shares should match historical share count in financials (if included) • Ownership % should sum to 100% pre IPO | I21: These are the shares outstanding before the transaction. They anchor ownership and dilution calculations. We keep the definition consistent and disclose whether it is basic or fully diluted. | J21: =HYPERLINK("#'10_CAP_TABLE'!C21","Go")
B22: Post IPO shares outstanding (m) | C22: 10_CAP_TABLE!C23 | POST_SHARES | D22: Total shares outstanding after primary issuance (basis for market cap and ownership). | E22: • Pre shares (10_CAP_TABLE!C21) • Primary shares issued (09_OFFER_STRUCTURE!C38) • Any new option pool or conversion adjustments (if included) • Rounding / share issuance constraints • Greenshoe effect if model treats as primary | F22: More primary issuance increases post shares. Secondary sales do not change post shares. | G22: • Adding secondary sold into post shares (wrong) • Mixing pre/post shares in market cap and ownership metrics • Not reflecting greenshoe treatment correctly | H22: • Post shares should equal pre shares + primary shares (plus any other new shares) • Market cap uses post shares, not total sold • Ownership post should sum to 100% | I22: Post shares are the equity base after the IPO. They drive market cap and ownership. Only primary issuance changes the total outstanding shares. | J22: =HYPERLINK("#'10_CAP_TABLE'!C23","Go")
B23: Primary dilution % (existing holders) | C23: 10_CAP_TABLE!C18 | PRIMARY_DILUTION | D23: Percentage dilution experienced by existing holders due to new primary shares issued. | E23: • Pre shares (10_CAP_TABLE!C21) • Primary shares issued (09_OFFER_STRUCTURE!C38) • Any other new shares (options, convertibles) • Offer price does not directly affect dilution (share count driven) • Rounding | F23: More primary shares increases dilution. Higher price can reduce required shares for the same raise, lowering dilution. | G23: • Calling sell-down 'dilution' (it is ownership reduction, not dilution) • Using sold shares instead of new shares in dilution formula • Not distinguishing dilution from change in voting control | H23: • Dilution should be approximately primary shares / post shares • If primary shares = 0, dilution should be 0 • Ownership of each existing holder should fall proportionally when only primary issued | I23: Dilution is purely share-count driven. It is the cost of raising capital. We manage it by balancing price, primary size and float requirements. | J23: =HYPERLINK("#'10_CAP_TABLE'!C18","Go")
B24: Free float % post IPO | C24: 10_CAP_TABLE!C17 | FREE_FLOAT_PCT | D24: Public float as a percentage of post shares, including shares sold (and greenshoe if exercised). | E24: • Total sold shares and greenshoe (09_OFFER_STRUCTURE) • Post shares (10_CAP_TABLE!C23) • Primary vs secondary mix (01_CONTROL) • Any cornerstone / locked shares (if included) • Regulatory float minimums (outside model) | F24: More shares sold increases float. More primary issuance can increase float and dilution simultaneously. | G24: • Calculating float off pre shares (wrong) • Excluding greenshoe when it is expected to be exercised • Forgetting locked-up/free float restrictions | H24: • Float % should be within the targeted range (commonly 20-40% depending on market and size) • Total float shares should reconcile to shares sold to public • Ownership table: Free float holder should match float shares | I24: Free float is the liquidity promise to the market. We target a float that supports trading and index eligibility without creating unnecessary dilution or loss of control. | J24: =HYPERLINK("#'10_CAP_TABLE'!C17","Go")
B25: Ownership table (top holders + free float) | C25: 10_CAP_TABLE ownership block (rows 27-37) | 00_DASHBOARD ownership summary | D25: Post IPO ownership percentages for key holders and the public float. | E25: • Pre holder shares inputs • Primary issuance effect (dilution) • Secondary shares sold by specific holders (if allocated) • Greenshoe treatment • Rounding | F25: More secondary sold by a holder reduces their stake; more primary issuance reduces everyone proportionally. | G25: • Not specifying which holders are selling secondary • Using percentage ownership based on wrong share count basis • Rounding causing totals not to sum to 100% | H25: • Total ownership should sum to 100% post • Top holders should reconcile to pre shares minus sold shares • Free float holder should match float % calculation | I25: This table explains who owns what after the IPO. It is the basis for governance, control discussions and investor messaging around alignment. | J25: =HYPERLINK("#'10_CAP_TABLE'!B27","Go")
B26: Pro forma cash post (DKKm) | C26: 11_PRO_FORMA_BS!C22 | CASH_POST | D26: Cash balance after receiving net primary proceeds and applying use of proceeds. | E26: • Net proceeds to company (09_OFFER_STRUCTURE!C33) • Use of proceeds allocation (11_PRO_FORMA_BS inputs) • Transaction costs treatment (expense vs capitalised) • Debt paydown decision • Any existing cash adjustments | F26: More net proceeds increases cash unless allocated to pay down debt or other uses. | G26: • Adding secondary proceeds to company cash • Double counting debt paydown (reduce debt and cash twice) • Ignoring transaction costs in cash bridge | H26: • Cash post should reconcile to: cash pre + net proceeds - cash uses • Cash post should not be negative unless overdraft assumed • Net debt post should reconcile to debt and cash post | I26: Cash post shows the balance sheet impact of the IPO. It must reconcile directly to net primary proceeds and the stated use of proceeds. | J26: =HYPERLINK("#'11_PRO_FORMA_BS'!C22","Go")
B27: Pro forma debt post (DKKm) | C27: 11_PRO_FORMA_BS!C23 | DEBT_POST | D27: Debt balance after applying any debt paydown from proceeds. | E27: • Debt pre (11_PRO_FORMA_BS inputs) • Debt paydown allocation (11_PRO_FORMA_BS) • Any refinancing assumptions (if included) • Transaction fees capitalised to debt (if included) • Timing assumptions | F27: Debt decreases with paydown. If no paydown, debt remains flat. | G27: • Paying down more debt than outstanding • Assuming secondary proceeds can be used for paydown • Inconsistent debt definition across leverage and net debt | H27: • Debt post must be >= 0 and <= debt pre • Debt paydown must be <= net proceeds allocated to paydown • Net debt post should reconcile | I27: Debt post is a mechanical outcome of the use of proceeds. It drives credit story and leverage metrics and must match the pro forma bridge. | J27: =HYPERLINK("#'11_PRO_FORMA_BS'!C23","Go")
B28: Net debt post (DKKm) | C28: 13_METRICS_AND_KPIS!C20 | NETDEBT_POST | D28: Net debt used in the EV bridge and leverage, calculated from pro forma debt and cash (per definition). | E28: • Debt post (11_PRO_FORMA_BS) • Cash post (11_PRO_FORMA_BS) • Definition controls: include/exclude cash equivalents, leases etc (if any) • Use of proceeds • Any adjustments (pension/leases) | F28: More cash reduces net debt; more debt increases net debt. Including cash equivalents reduces net debt further. | G28: • Sign errors (cash added instead of subtracted) • Inconsistent definition between EV bridge and leverage • Not updating after changing use of proceeds | H28: • Net debt should equal debt post - cash post (+/- adjustments) exactly • Net debt should move in line with paydown and cash changes • Definition should be consistent in comps and narrative | I28: Net debt is the key bridge between EV and equity. We define it explicitly and keep it consistent across valuation, leverage and investor materials. | J28: =HYPERLINK("#'13_METRICS_AND_KPIS'!C20","Go")
B29: Net leverage post (x) | C29: 13_METRICS_AND_KPIS!C24 | LEVERAGE_POST | D29: Net debt divided by EBITDA (per basis), showing post transaction leverage. | E29: • Net debt post (13_METRICS_AND_KPIS!C20) • EBITDA metric (LTM or NTM, per model) • Debt paydown allocation • Scenario drivers affecting EBITDA (04_DRIVERS) • Any addbacks or normalisation | F29: Lower net debt or higher EBITDA reduces leverage. Leverage improves with debt paydown funded by IPO proceeds. | G29: • Dividing by the wrong EBITDA basis (LTM vs NTM) • Not adjusting EBITDA for one offs while adjusting peers • Inconsistent net debt definition | H29: • Leverage should improve when debt is paid down (if EBITDA constant) • Leverage should be in a plausible range for the sector and rating objectives • Reconcile EBITDA basis to comps basis | I29: Post IPO leverage is a core part of the equity story and credit perception. It is driven by net proceeds allocation and must be consistent with the chosen EBITDA basis. | J29: =HYPERLINK("#'13_METRICS_AND_KPIS'!C24","Go")
B30: Use of proceeds: debt paydown (DKKm) | C30: 11_PRO_FORMA_BS!C17 | DEBT_PAYDOWN | D30: Portion of net primary proceeds allocated to pay down debt. | E30: • Net proceeds to company • Use of proceeds assumption input • Debt outstanding pre • Strategic rationale (balance sheet vs growth) • Constraints: minimum cash buffer | F30: More paydown reduces net debt and leverage but reduces cash available for growth uses. | G30: • Allocating more than net proceeds available • Not aligning use of proceeds narrative to the allocation • Treating paydown as affecting EV rather than net debt/equity bridge | H30: • Debt paydown <= debt pre and <= net proceeds • Cash post should reflect the allocation • Leverage should move consistently | I30: Debt paydown is a choice: use proceeds to de risk the balance sheet and improve leverage. We size it so the company retains sufficient cash for operations and growth investments. | J30: =HYPERLINK("#'11_PRO_FORMA_BS'!C17","Go")
B31: Selected comps multiple (EV/EBITDA or EV/Rev) | C31: 06_VALUATION_COMPS!C23 | MULTIPLE_SEL | D31: Chosen valuation multiple used to translate issuer metric into implied EV via comps. | E31: • Peer group selection in comps table (06_VALUATION_COMPS) • Metric mapping (EBITDA vs revenue) • Normalisation adjustments (one offs, IFRS differences) • Growth and margin positioning versus peers • Market conditions (outside model) | F31: Higher selected multiple increases implied EV and implied price range. | G31: • Selecting a multiple outside peer distribution without justification • Inconsistent metric basis (LTM vs NTM) across peers and issuer • Not documenting normalisation adjustments | H31: • Selected multiple should sit within peer distribution and be explained • Implied EV should reconcile to multiple x metric • Check for currency and unit consistency | I31: The selected multiple is defensible if it reflects where the issuer sits versus peers on growth, margins and quality, and if normalisations are documented. We show distribution and rationale transparently. | J31: =HYPERLINK("#'06_VALUATION_COMPS'!C23","Go")
B32: Key valuation multiple at offer price (EV/EBITDA) | C32: 13_METRICS_AND_KPIS!C22 (EV/LTM EBITDA) | Dashboard tile | D32: Offer valuation multiple implied by the selected offer price and EV bridge. | E32: • EV at offer price • EBITDA metric (basis) • Net debt definition and paydown • Scenario drivers affecting EBITDA • Any normalisations | F32: Higher EV or lower EBITDA increases the multiple. Improving EBITDA reduces multiple at fixed EV. | G32: • Using inconsistent EBITDA basis versus comps • Comparing unadjusted issuer EBITDA to adjusted peer EBITDA • Not disclosing whether multiple is LTM or NTM | H32: • Offer multiple should be consistent with comps distribution at selected price • Direction: raising price increases EV and the multiple (all else equal) • Check EBITDA is not zero/negative when using EV/EBITDA | I32: This is the multiple implied by the offer price. It is the anchor for pricing defensibility versus peers, so we always state the EBITDA basis and any adjustments. | J32: =HYPERLINK("#'13_METRICS_AND_KPIS'!C22","Go")
B33: Key valuation multiple at offer price (EV/Revenue) | C33: 13_METRICS_AND_KPIS!C23 (EV/LTM Rev) | Dashboard tile | D33: Offer EV to revenue multiple implied by the selected offer price. | E33: • EV at offer price • Revenue metric (basis) • Net debt definition • Scenario drivers affecting revenue • Any normalisations | F33: Higher EV or lower revenue increases the multiple. | G33: • Mixing IFRS revenue definitions across peers and issuer • Currency mismatch or units mismatch (DKKm vs EURm) • Using period inconsistent with peers (LTM vs NTM) | H33: • Offer EV/Rev should be within peer range for similar growth and margin profile • Reconcile revenue basis to financial module outputs • Check scaling: EV and revenue must be in same currency and units | I33: We use EV/Revenue when EBITDA is volatile or negative. The multiple must be benchmarked to peers with similar growth and margin trajectory and the basis must be consistent. | J33: =HYPERLINK("#'13_METRICS_AND_KPIS'!C23","Go")
B34: DCF implied enterprise value (if enabled) | C34: 07_VALUATION_DCF output block (EV) | W_DCF weighting used in triangulation | D34: DCF based enterprise value from discounted cash flows and terminal value (optional cross check). | E34: • 01_CONTROL!C47 WACC • 01_CONTROL!C48 terminal growth • Forecast free cash flows (05_FORECAST) • Terminal method and timing (mid year or year end) • Net debt bridge | F34: Lower WACC increases PV and EV. Higher terminal growth increases terminal value and EV. | G34: • Using g >= WACC causing infinite terminal value • Wrong timing (year end vs mid year) across PV • Mixing nominal and real rates | H34: • TV formula must have WACC > g with a buffer • Terminal value should be the majority but not unrealistic share of EV • DCF implied EV should be directionally consistent with comps | I34: DCF is a cross check, not the pricing driver. We use it to validate that the offer range is consistent with the issuer's cash generation under reasonable discount rates and terminal assumptions. | J34: =HYPERLINK("#'07_VALUATION_DCF'!C30","Go")
B35: Triangulated EV range (Low/Base/High) (DKKm) | C35: 00_DASHBOARD!C14:E14 | EV_TRI_LOW / EV_TRI_BASE / EV_TRI_HIGH | D35: Combined EV range from comps and optional DCF using explicit weights. | E35: • Comps implied EV range • DCF implied EV range (if used) • 01_CONTROL triangulation weights (W_COMPS, W_DCF) • Net debt post (equity bridge) • Peer distribution / DCF assumptions | F35: Higher comps multiple or stronger DCF increases EV range. Changing weights shifts range toward the dominating method. | G35: • Changing weights without explaining which method dominates • Inconsistent metric basis between comps and DCF • Not updating narrative when weights change | H35: • Weights must sum to 100% • Triangulated EV should sit between method EVs when weights are convex • Range should be consistent with implied price range | I35: The triangulated range is the model's combined view. The defensibility comes from showing both methods and a clear rationale for the weights rather than hiding the inputs. | J35: =HYPERLINK("#'00_DASHBOARD'!C14","Go")
B36: Sensitivity: implied price vs multiple (comps) | C36: 14_SENSITIVITIES matrix area | multiple sensitivity table | D36: How implied price changes as the selected multiple changes (holding metric constant). | E36: • Peer distribution and selected multiple • Issuer metric (EBITDA or revenue) • Net debt and post shares • Triangulation weights (if sensitivity is on comps only) • Scenario impacts on metric | F36: Higher multiple increases implied EV and implied price linearly. | G36: • Non linearity from mixing units (m vs k) or rounding issues • Using the wrong metric in sensitivity table • Not locking references causing sensitivity table to break | H36: • Price change per +0.1x multiple should be stable and directionally positive • Check that the table references the correct issuer metric • Ensure the sensitivity table uses absolute references where needed | I36: This table is for explaining what drives the range. It shows the linear relationship between the multiple and implied price and helps prioritise which assumptions matter most. | J36: =HYPERLINK("#'14_SENSITIVITIES'!B19","Go")
B37: Sensitivity: DCF value vs WACC and terminal g | C37: 07_VALUATION_DCF sensitivity block (if present) | WACC and TERM_G inputs | D37: How the DCF implied value responds to discount rate and terminal assumptions. | E37: • WACC (01_CONTROL!C47) • Terminal growth (01_CONTROL!C48) • Forecast FCF • Terminal method (Gordon growth) • Timing and PV convention | F37: Higher WACC decreases value; higher terminal g increases value (non linear). | G37: • Using g too close to WACC • Mixing nominal WACC with real g • Not explaining why WACC moved (risk, rates, beta) | H37: • Ensure WACC - g stays safely positive • Terminal value share should remain plausible • DCF sensitivity should be monotonic in both dimensions | I37: This sensitivity is an explanation tool. It frames the valuation uncertainty and shows that the DCF result is highly sensitive to discount rates and terminal assumptions. | J37: =HYPERLINK("#'07_VALUATION_DCF'!B12","Go")
B38: Pricing narrative constraints: float, dilution, proceeds, leverage | C38: 00_DASHBOARD summary list + 10_CAP_TABLE + 09_OFFER_STRUCTURE + 13_METRICS | D38: Key constraints that often drive the feasible pricing range beyond pure valuation: float, dilution, net proceeds and leverage. | E38: • Free float % (10_CAP_TABLE!C17) • Primary dilution % (10_CAP_TABLE!C18) • Net proceeds to company (09_OFFER_STRUCTURE!C33) • Leverage post (13_METRICS_AND_KPIS!C24) • Selected offer price (01_CONTROL!C56) | F38: Higher price can improve proceeds and reduce share count based dilution, but can hurt marketability if valuation becomes too rich. Structure changes can improve float without increasing dilution. | G38: • Optimising price without checking float and dilution • Assuming market will accept any implied valuation without discount • Using secondary to 'raise' money for the company | H38: • Check free float meets minimum target and ownership sums to 100% • Check dilution and net proceeds are consistent with board expectations • Check pro forma leverage improves as promised in the equity story | I38: In practice, the range is defined by what is marketable and acceptable to stakeholders. We align price, structure and use of proceeds so that float, dilution, proceeds and leverage all tell a coherent story. | J38: =HYPERLINK("#'00_DASHBOARD'!B15","Go")

Sheet 81_IPO_LEARN_FORMULAS
B2: IPO Model Learning Layer | 81_IPO_LEARN_FORMULAS (Formula Walkthrough)
B4: Purpose: The 35 most important IPO model formulas, tied to exact model cells. Use these to explain outputs, debug issues and build confidence under time pressure.
B8: # | C8: Formula (concept) | D8: Model ref | E8: Exact model formula | F8: Plain-language explanation | G8: Why it matters in ECM | H8: Typical mistake | I8: Mini-example
B9: 1 | C9: Offer price selection via price case | D9: 01_CONTROL!C56 | E9: =CHOOSE(CTRL_PX_CASE;IPO_PX_LOW;IPO_PX_BASE;IPO_PX_HIGH) | F9: Chooses the offer price used by the entire model based on the selected Low/Base/High case. | G9: This is how the model switches between range points without rewriting formulas. | H9: Hardcoding a price elsewhere and forgetting the CHOOSE logic, causing inconsistent outputs. | I9: Example: Low=90, Base=100, High=110; case=2 -> OfferPrice=100.
B10: 2 | C10: Market cap at offer price | D10: 13_METRICS_AND_KPIS!C19 | E10: =C17*C18 | F10: Calculates equity value at offer price using post deal shares outstanding. | G10: Market cap is used for positioning, float discussion and EV bridge. | H10: Using pre shares or wrong units (shares vs millions) leading to 10× errors. | I10: Example: 100 DKK/share × 50m shares = 5,000 DKKm.
B11: 3 | C11: Net debt post | D11: 13_METRICS_AND_KPIS!C20 | E11: =NETDEBT_POST | F11: Computes net debt after the transaction based on pro forma debt and cash. | G11: Net debt is the bridge between EV and equity and drives leverage. | H11: Sign errors (adding cash) or changing definition without updating comps and narrative. | I11: Example: Debt 1,200 − Cash 200 = NetDebt 1,000.
B12: 4 | C12: Enterprise value at offer | D12: 13_METRICS_AND_KPIS!C21 | E12: =C19+C20 | F12: Builds enterprise value by adding net debt to market cap. | G12: EV is what you benchmark to peers for EV-based multiples (EV/EBITDA, EV/Revenue). | H12: Using gross debt instead of net debt, or mixing currency/units. | I12: Example: MarketCap 5,000 + NetDebt 1,000 = EV 6,000.
B13: 5 | C13: EV/EBITDA at offer (basis per model) | D13: 13_METRICS_AND_KPIS!C22 | E13: =IFERROR(C21/C11;"") | F13: Computes the valuation multiple implied by the offer price. | G13: This is the core pricing defensibility metric in ECM conversations. | H13: Using LTM for issuer and NTM for peers (or vice versa) without stating it. | I13: Example: EV 6,000 ÷ EBITDA 600 = 10.0×.
B14: 6 | C14: EV/Revenue at offer (basis per model) | D14: 13_METRICS_AND_KPIS!C23 | E14: =IFERROR(C21/C9;"") | F14: Computes EV/Revenue implied by the offer price. | G14: Used when EBITDA is volatile/low and as a cross-check versus high-growth peers. | H14: Currency mismatch between EV and revenue leading to wrong multiples. | I14: Example: EV 6,000 ÷ Rev 1,500 = 4.0×.
B15: 7 | C15: Gross primary proceeds | D15: 09_OFFER_STRUCTURE!C24 | E15: =C20*IPO_PX_SEL | F15: Cash investors pay for newly issued shares (before fees/costs). | G15: This is the funding amount that can flow to the company (before deductions). | H15: Confusing primary proceeds with total gross proceeds or net proceeds. | I15: Example: 100 × 10m = 1,000 DKKm.
B16: 8 | C16: Gross secondary proceeds | D16: 09_OFFER_STRUCTURE!C25 | E16: =C21*IPO_PX_SEL | F16: Cash investors pay for existing shares sold by shareholders (before fees). | G16: Important for sell-down decisions and ownership outcomes, not for company cash. | H16: Accidentally sending secondary proceeds into pro forma cash. | I16: Example: 100 × 5m = 500 DKKm.
B17: 9 | C17: Greenshoe shares | D17: 09_OFFER_STRUCTURE!C22 | E17: =IF(CTRL_GS_ON=1;C19*GS_PCT;0) | F17: Calculates additional shares available for overallotment (greenshoe). | G17: Greenshoe affects total sold, ownership and sometimes fee base. | H17: Quoting total sold without stating whether it includes greenshoe. | I17: Example: TotalSold 15m × 15% = 2.25m shares.
B18: 10 | C18: Total shares sold incl greenshoe | D18: 09_OFFER_STRUCTURE!C23 | E18: =SUM(C20:C22) | F18: Total shares sold to the public including greenshoe if exercised. | G18: Used for float and gross proceeds disclosures (base vs with greenshoe). | H18: Mixing base and with-greenshoe totals in communications. | I18: Example: 15m + 2.25m = 17.25m.
B19: 11 | C19: Gross greenshoe proceeds | D19: 09_OFFER_STRUCTURE!C26 | E19: =C22*IPO_PX_SEL | F19: Investor cash for greenshoe shares (if exercised). | G19: Helps quantify incremental proceeds and ownership impact. | H19: Assuming greenshoe always increases company cash (depends on primary/secondary). | I19: Example: 100 × 2.25m = 225 DKKm.
B20: 12 | C20: Gross proceeds total | D20: 09_OFFER_STRUCTURE!C27 | E20: =SUM(C24:C26) | F20: Total investor cash for all shares sold (primary + secondary + greenshoe). | G20: Top-line deal size quoted publicly; must be consistent with disclosures. | H20: Leaving out greenshoe or double counting it. | I20: Example: 1,000 + 500 + 225 = 1,725 DKKm.
B21: 13 | C21: Underwriting fee amount | D21: 09_OFFER_STRUCTURE!C28 | E21: =C27*FEE_PCT | F21: Calculates underwriting fee based on the model’s fee base and fee %. | G21: Direct driver of net proceeds and transaction economics. | H21: Applying fee % to the wrong base (total vs primary only). | I21: Example: 3.0% × 1,725 = 51.8 DKKm.
B22: 14 | C22: Total costs deducted from gross proceeds | D22: 09_OFFER_STRUCTURE!C30 | E22: =C28+C29 | F22: Adds underwriting fee and other costs into a single cost line. | G22: Useful for quick reconciliation: gross vs net. | H22: Sign mistakes turning costs into additions. | I22: Example: 51.8 + 15.0 = 66.8 DKKm.
B23: 15 | C23: Fee allocation to primary | D23: 09_OFFER_STRUCTURE!C31 | E23: =IF(CTRL_FEE_ALLOC=1;C30; C30*(C24/C27)) | F23: Allocates the underwriting fee to the primary component (drives company net proceeds). | G23: Fee allocation determines company cash vs selling shareholder economics. | H23: Allocating all fees to primary when fee base includes secondary (or vice versa). | I23: Example: Fee 60; GrossPrimary share 60% -> 36 allocated to primary.
B24: 16 | C24: Fee allocation to secondary | D24: 09_OFFER_STRUCTURE!C32 | E24: =IF(CTRL_FEE_ALLOC=1;C29; C29*(C24/C27)) | F24: Allocates the underwriting fee to the secondary component (reduces seller proceeds). | G24: Needed to explain seller economics and headline vs net. | H24: Mixing seller net proceeds with company net proceeds. | I24: Example: Fee 60; GrossSecondary share 40% -> 24 allocated to secondary.
B25: 17 | C25: Net proceeds to company | D25: 09_OFFER_STRUCTURE!C33 | E25: =C24-C31-C32 | F25: Company cash received after fees and costs applied to the primary raise. | G25: Feeds directly into pro forma cash and use of proceeds. | H25: Deducting fees twice or forgetting other costs. | I25: Example: GrossPrimary 1,000 − FeePrimary 36 − OtherCosts 15 = 949.
B26: 18 | C26: Net proceeds to selling shareholders | D26: 09_OFFER_STRUCTURE!C34 | F26: Net cash to selling shareholders after allocated fees (secondary component). | G26: Explains sell-down trade-offs and shareholder economics. | H26: Including other costs that are company-paid, not seller-paid (depends on agreement). | I26: Example: GrossSecondary 500 − FeeSecondary 24 = 476.
B27: 19 | C27: Primary shares issued (output anchor) | D27: 09_OFFER_STRUCTURE!C38 | E27: =C20 | F27: Outputs the final primary share count used everywhere else. | G27: Primary shares drive dilution, post shares and company cash. | H27: Hardcoding a share count and breaking reconciliation with proceeds target. | I27: Example: If target gross primary is 1,000 at 100 price -> 10m shares.
B28: 20 | C28: Shares sold to public (output anchor) | D28: 09_OFFER_STRUCTURE!C39 | E28: =C23 | F28: Outputs total public sold shares used for float and ownership calculations. | G28: Key for free float %, allocations and disclosure tables. | H28: Mixing base sold shares and sold incl greenshoe. | I28: Example: Base sold 15m, GS 2.25m -> public sold 17.25m.
B29: 21 | C29: Post shares roll-forward | D29: 10_CAP_TABLE!C23 | E29: =PRE_SHARES+NEW_PRIMARY_SHARES | F29: Rolls forward shares outstanding after the IPO. | G29: Critical for market cap, dilution and ownership. | H29: Adding secondary sold into post shares (wrong). | I29: Example: Pre 80m + Primary 10m = Post 90m.
B30: 22 | C30: Primary dilution % | D30: 10_CAP_TABLE!C18 | F30: Computes dilution from new issuance for existing holders. | G30: Dilution is often the board’s key constraint when sizing the raise. | H30: Calling secondary sell-down ‘dilution’ or using sold shares instead of new shares. | I30: Example: Primary 10m ÷ Post 90m = 11.1% dilution.
B31: 23 | C31: Free float % | D31: 10_CAP_TABLE!C17 | F31: Public float as % of post shares (incl greenshoe as modelled). | G31: Float drives liquidity, index inclusion and investor acceptance. | H31: Calculating float on pre shares or ignoring greenshoe. | I31: Example: Float 18m ÷ Post 90m = 20.0%.
B32: 24 | C32: Pro forma cash increase | D32: 11_PRO_FORMA_BS!C21 | F32: Computes the net change in cash from the transaction and allocations. | G32: This connects deal economics to the balance sheet impact. | H32: Double counting paydown or not subtracting costs from cash. | I32: Example: Net proceeds 949 − Paydown 400 = +549 cash.
B33: 25 | C33: Pro forma cash post | D33: 11_PRO_FORMA_BS!C22 | E33: =C8+C15-C16-C17 | F33: Final pro forma cash balance after transaction. | G33: Used to compute net debt and support leverage story. | H33: Adding secondary proceeds or ignoring costs. | I33: Example: CashPre 200 + 549 = 749.
B34: 26 | C34: Pro forma debt post | D34: 11_PRO_FORMA_BS!C23 | E34: =C9-C16 | F34: Final pro forma debt after paydown funded by net proceeds. | G34: Directly drives net debt and leverage outcomes. | H34: Paying down more debt than outstanding or using seller proceeds to pay down. | I34: Example: DebtPre 1,200 − Paydown 400 = 800.
B35: 27 | C35: Comps implied EV (range point) | D35: 06_VALUATION_COMPS!C27 | E35: =MULT_SEL*NTM_EBITDA | F35: Translates issuer metric into implied enterprise value from comps (one range point). | G35: This is the core comps engine behind the range. | H35: Wrong metric mapping (EBITDA vs revenue) or LTM/NTM mismatch. | I35: Example: 10.0× × 600 EBITDA = EV 6,000.
B36: 28 | C36: Triangulated EV (base) | D36: 08_VALUATION_TRIANGULATION!C18 | E36: =$C$14*D9+$C$15*D10 | F36: Combines valuation methods into a single EV using explicit weights. | G36: This makes the model explainable; changes in weights have predictable impact. | H36: Weights not summing to 100% or changing weights without updating narrative. | I36: Example: 70% comps (6,000) + 30% DCF (6,500) = 6,150.
B37: 29 | C37: Equity value from EV bridge (base) | D37: 08_VALUATION_TRIANGULATION!C27 | E37: =EV_TRI_BASE-NETDEBT_POST | F37: Converts EV into equity value by subtracting net debt. | G37: Shows how capital structure affects equity value at a given EV. | H37: Using gross debt instead of net debt or wrong sign on cash. | I37: Example: EV 6,150 − NetDebt 1,000 = Equity 5,150.
B38: 30 | C38: Implied equity price (base) | D38: 08_VALUATION_TRIANGULATION!C30 | E38: =EQ_BASE/POST_SHARES | F38: Converts equity value into per-share implied price. | G38: This is the most intuitive output to discuss range vs offer price. | H38: Dividing by pre shares or using wrong units (m vs shares). | I38: Example: Equity 5,150 ÷ 90m = 57.2 per share.
B39: 31 | C39: DCF terminal value (Gordon growth) | D39: 07_VALUATION_DCF!C25 | E39: =IF(CTRL_VAL_METHOD=2;IF(TERM_METHOD=1;(N16*(1+TERM_G))/(WACC-TERM_G);EXIT_MULT*'05_FORECAST'!N14);"") | F39: Computes terminal value at the end of the explicit forecast period. | G39: Terminal value is typically the largest driver of DCF; needs careful assumptions. | H39: Setting g too high or using g ≥ WACC. | I39: Example: FCF 120, WACC 9%, g 3% -> 120/(0.09−0.03)=2,000.
B40: 32 | C40: PV of terminal value | D40: 07_VALUATION_DCF!C26 | E40: =IF(CTRL_VAL_METHOD=2;C25*N21;"") | F40: Discounts terminal value back to present value. | G40: Small WACC changes can move valuation significantly through PV(TV). | H40: Using wrong exponent (year count) or inconsistent mid-year convention. | I40: Example: TV 2,000 ÷ 1.09^5 = 1,299.
B41: 33 | C41: DCF enterprise value | D41: 07_VALUATION_DCF!C30 | F41: Adds present values of free cash flows and terminal value to get EV from DCF. | G41: Provides an intrinsic cross check versus comps. | H41: Forgetting working capital/capex in FCF or double counting PV(TV). | I41: Example: PV FCF sum 400 + PV TV 1,299 = 1,699 EV.
B42: 34 | C42: Scenario pick logic (drivers) | D42: 04_DRIVERS!I8 | E42: =CHOOSE(CTRL_SCEN;$C8;$D8;$E8) | F42: Selects scenario-specific driver values used by forecast and valuation modules. | G42: Allows fast switching between scenarios without manual rewiring. | H42: Overwriting selected drivers instead of editing the scenario columns, breaking comparability. | I42: Example: Scenario=3 -> picks Upside driver column.
B43: 35 | C43: Core checks pattern (example) | D43: 90_CHECKS!C12 | E43: =IF(ABS('11_PRO_FORMA_BS'!$C$22-('11_PRO_FORMA_BS'!$C$8+'11_PRO_FORMA_BS'!$C$15-'11_PRO_FORMA_BS'!$C$16-'11_PRO_FORMA_BS'!$C$17))<0,1;"PASS";"FAIL") | F43: Standardised check logic used to flag model issues clearly. | G43: Protects against silent errors before sharing with senior bankers or clients. | H43: Using checks that don’t reference the true source cell or that can be bypassed. | I43: Example: If weights sum to 1 -> PASS else FAIL.

Sheet 82_IPO_LEARN_INTERPRETATION
B2: IPO Model Learning Layer | 82_IPO_LEARN_INTERPRETATION (Interpretation Scripts)
B4: Purpose: How to interpret dashboard tiles and how to talk about them in meetings. Scripts are practical and model-traceable.
B7: A) Dashboard tiles (10–14) | Interpretation + follow-ups
B8: Tile / metric | C8: Dashboard cell(s) | D8: How to interpret (1–2 lines) | E8: What it signals | F8: What could make it misleading | G8: Follow-up question | H8: Link
B9: Offer price range (Low/Base/High) | C9: 00_DASHBOARD!C9:E9 | D9: These are the working price points used to compute all other outputs. Offer price is not ‘true value’, it is the executed clearing price. | E9: How much valuation headroom exists and whether pricing is conservative vs implied value. | F9: Confusing implied value range with the offer range, or mixing currencies/units. | G9: What discount to peers is implied at each point and why is it appropriate? | H9: =HYPERLINK("#'81_IPO_LEARN_FORMULAS'!B9","Go")
B10: Market cap (Low/Base/High) | C10: 00_DASHBOARD!C10:E10 | D10: Equity value implied by each price point using post-IPO shares. Use for positioning and index eligibility. | E10: Scale and comparability versus peers; can support or undermine multiple defensibility. | F10: Using pre-shares or diluted shares inconsistently; unit mix (shares vs m). | G10: Are we positioning as a mid-cap/large-cap and what peer set is relevant at this size? | H10: =HYPERLINK("#'81_IPO_LEARN_FORMULAS'!B10","Go")
B11: Enterprise value (Low/Base/High) | C11: 00_DASHBOARD!C11:E11 | D11: EV adds net debt to market cap. Use for EV-based multiples and comps triangulation. | E11: Whether price points imply a reasonable EV relative to peers on the same definition basis. | F11: Net debt definition mismatch (cash treatment, leases, pensions) or wrong sign. | G11: Which net debt definition are we using in comps and does it match the prospectus definition? | H11: =HYPERLINK("#'81_IPO_LEARN_FORMULAS'!B12","Go")
B12: Total shares sold (incl greenshoe) | C12: 00_DASHBOARD!C12:E12 | D12: Publicly offered shares including greenshoe. Drives float and deal size disclosures. | E12: Liquidity and aftermarket support. Too small can hurt trading; too large can imply heavy sell-down. | F12: Not stating whether greenshoe is included; confusion between sold shares and post shares. | G12: Who is selling the secondary and what is the lock-up / overhang profile? | H12: =HYPERLINK("#'80_IPO_LEARN_MAP'!B18","Go")
B13: Gross proceeds (DKKm) | C13: 00_DASHBOARD!C13:E13 | D13: Total investor cash for sold shares. Useful headline, but not what the company receives. | E13: Deal size and investor demand requirements; guides syndicate strategy. | F13: Mixing gross with net proceeds or assuming secondary is company cash. | G13: How much of gross is primary versus secondary and what is the net to company? | H13: =HYPERLINK("#'81_IPO_LEARN_FORMULAS'!B20","Go")
B14: Net proceeds to company (DKKm) | C14: 00_DASHBOARD!C14:E14 | D14: Company cash after fees and costs allocated to primary. Feeds use of proceeds and pro forma BS. | E14: Funding capacity for strategy and balance sheet actions; anchors proceeds narrative. | F14: Wrong fee base or fee allocation; forgetting other costs; secondary leakage into company cash. | G14: Do net proceeds fully cover the stated uses, and what is the cash buffer post-deal? | H14: =HYPERLINK("#'81_IPO_LEARN_FORMULAS'!B25","Go")
B15: Primary dilution (%) | C15: 00_DASHBOARD!C15:E15 | D15: Dilution from new shares only. Indicates how much existing holders are diluted by the raise. | E15: Stakeholder acceptability and governance impact; often a board constraint. | F15: Calling sell-down dilution; using sold shares rather than new shares in the formula. | G15: Which holders are sensitive to dilution and what is their minimum ownership threshold? | H15: =HYPERLINK("#'81_IPO_LEARN_FORMULAS'!B28","Go")
B16: Free float (%) | C16: 00_DASHBOARD!C16:E16 | D16: Public float as % of post shares. Key for liquidity, investor acceptance and index rules. | E16: Marketability and aftermarket liquidity. Too low can fail; too high can indicate excess supply. | F16: Excluding greenshoe when expected; ignoring locked-up shares; using pre shares as denominator. | G16: What is the minimum acceptable float for this market/sector and why? | H16: =HYPERLINK("#'81_IPO_LEARN_FORMULAS'!B29","Go")
B17: Pro forma net debt (DKKm) | C17: 00_DASHBOARD!C17:E17 | D17: Net debt after receiving proceeds and applying use of proceeds. Drives EV bridge and leverage. | E17: How much balance sheet de-risking the IPO delivers; supports equity story. | F17: Cash and debt double counting, or definition mismatch vs comps/leverage. | G17: How much of proceeds are used for paydown versus growth, and what is the rationale? | H17: =HYPERLINK("#'81_IPO_LEARN_FORMULAS'!B11","Go")
B18: EV/EBITDA at offer | C18: 00_DASHBOARD!C18:E18 | D18: Implied valuation multiple at each price point. Compare to peer distribution on the same basis. | E18: Pricing defensibility versus comps and investor appetite. | F18: LTM/NTM mismatch, one-off EBITDA not normalised, or peer metric inconsistency. | G18: Where does this multiple sit vs peer quartiles and what justifies the premium/discount? | H18: =HYPERLINK("#'80_IPO_LEARN_MAP'!B33","Go")
B19: EV/Revenue at offer | C19: 00_DASHBOARD!C19:E19 | D19: Revenue-based multiple cross check, especially useful when EBITDA is volatile or negative. | E19: Growth multiple framing and consistency for high growth stories. | F19: Revenue definition differences and currency/unit mismatches across peers. | G19: Is revenue the right anchor, and how does margin trajectory affect valuation framing? | H19: =HYPERLINK("#'80_IPO_LEARN_MAP'!B34","Go")
B20: NTM EBITDA (DKKm) | C20: 00_DASHBOARD!C20 | D20: Forward EBITDA used for valuation and leverage framing (depending on model basis). | E20: Whether the story is about growth, margin expansion, or quality. Drives implied multiples. | F20: One-offs, run-rate adjustments, or scenario selection not communicated clearly. | G20: What are the key bridge items from LTM to NTM EBITDA (volume, price, margin)? | H20: =HYPERLINK("#'83_IPO_LEARN_SCENARIOS'!B10","Go")
B23: B) ECM meeting-ready scripts (common IPO questions)
B24: # | C24: Question | D24: Script (2–3 sentences) | E24: Model refs (cells / KPIs)
B25: 1 | C25: Pricing defensibility | D25: We price within the model-implied range built from comps and an optional DCF cross-check, with explicit weights. At the selected offer price, the implied EV/EBITDA and EV/Revenue sit within the peer distribution once we normalise for one-offs and ensure the same LTM/NTM basis. | E25: 00_DASHBOARD rows 18–19; 06_VALUATION_COMPS; 08_TRIANGULATION
B26: 2 | C26: Discount logic | D26: The discount reflects execution risk and the need to clear an order book with enough aftermarket support. We show the implied multiples at each price point and choose the one that balances valuation with float, proceeds and leverage outcomes. | E26: 00_DASHBOARD rows 9, 18–19; 10_CAP_TABLE float/dilution
B27: 3 | C27: Free float adequacy | D27: Float is a liquidity promise. Below the target range, trading can be illiquid and index eligibility can be harder, which can reduce demand. We size sold shares and greenshoe to meet float targets without forcing unnecessary primary dilution. | E27: 00_DASHBOARD row 16; 09_OFFER_STRUCTURE; 10_CAP_TABLE
B28: 4 | C28: Proceeds rationale | D28: Net proceeds to the company are what fund the strategy. We reconcile gross-to-net transparently and tie net proceeds to explicit uses of proceeds such as debt paydown and growth investment, then show the pro forma balance sheet impact. | E28: 00_DASHBOARD row 14; 11_PRO_FORMA_BS bridge
B29: 5 | C29: Dilution acceptability | D29: Dilution is share-count driven and is the cost of raising capital. We can reduce dilution by increasing price, shifting toward secondary, or reducing the raise, but each has trade-offs on float and funding. We keep dilution within tolerance while still delivering net proceeds. | E29: 00_DASHBOARD row 15; 09_OFFER_STRUCTURE; 10_CAP_TABLE
B30: 6 | C30: Greenshoe role | D30: Greenshoe is primarily an execution tool. It supports stabilisation and allocation management and economically it modestly increases float and headline proceeds. We show base and with-greenshoe numbers separately to keep ownership and disclosures clean. | E30: 09_OFFER_STRUCTURE greenshoe; 00_DASHBOARD row 12
B31: 7 | C31: Use of proceeds narrative | D31: Use of proceeds must match the story. If de-risking is the goal, more proceeds go to debt paydown and leverage improves. If growth is the goal, proceeds increase cash and investment capacity. The pro forma bridge makes this auditable. | E31: 11_PRO_FORMA_BS; 13_METRICS leverage
B32: 8 | C32: Comps selection defense | D32: Peers are selected on business model, growth and margin profile, and trading liquidity. We document accounting differences and normalise metrics so comparisons are like-for-like. The selected multiple is anchored in the peer distribution, not a single outlier. | E32: 06_VALUATION_COMPS peer set; multiple selection
B33: 9 | C33: DCF role and limitations | D33: DCF is a cross-check, not the primary pricing anchor. It is sensitive to WACC and terminal growth, so we use conservative inputs and show sensitivities. The goal is to validate the range is not inconsistent with cash generation. | E33: 07_VALUATION_DCF; 01_CONTROL WACC/TERM_G
B34: 10 | C34: Range movers | D34: The range is mostly driven by three levers: selected multiple, issuer metric (EBITDA or revenue) and the net debt bridge. Secondary levers include triangulation weights and fee/cost assumptions. Sensitivities show this explicitly. | E34: 06 comps; 08 triangulation; 14 sensitivities
B35: 11 | C35: What could break first in downside | D35: In a downside, one constraint usually binds first: float, net proceeds coverage of uses, or leverage improvement. If price falls while raise is held constant, share count and dilution can worsen. We monitor which KPI fails and re-optimise structure. | E35: 00_DASHBOARD constraints; 90_CHECKS
B36: 12 | C36: Board-ready summary | D36: At the selected price, the company raises net proceeds of X, delivers pro forma net leverage of Y, and provides a free float of Z% while keeping primary dilution within tolerance. The implied multiples are consistent with peers on a like-for-like basis and the range is supported by transparent weights. | E36: 00_DASHBOARD key rows; 80 KPI map

Sheet 83_IPO_LEARN_SCENARIOS
B2: IPO Model Learning Layer | 83_IPO_LEARN_SCENARIOS (Scenario Narratives)
B4: Purpose: Compare Base/Upside/Downside using the existing scenario toggle (CTRL_SCEN). This sheet uses an Excel Data Table so scenarios can be compared side-by-side without manual rewiring.
B7: A) Scenario comparison table (assumptions + outputs)
B9: Scenario | C9: Rev growth % (FY+1) | D9: Gross margin % | E9: Opex % of rev | F9: Offer price | G9: Implied price (Tri) | H9: Market cap @ offer | I9: EV @ offer | J9: Net proceeds (company) | K9: Free float % | L9: Primary dilution % | M9: Net debt post | N9: Net leverage (ND/EBITDA)
C10: ='04_DRIVERS'!$J$8 | D10: ='04_DRIVERS'!$J$9 | E10: ='04_DRIVERS'!$J$10 | F10: ='01_CONTROL'!$C$56 | G10: ='08_VALUATION_TRIANGULATION'!$C$30 | H10: ='13_METRICS_AND_KPIS'!$C$19 | I10: ='13_METRICS_AND_KPIS'!$C$21 | J10: ='09_OFFER_STRUCTURE'!$C$33 | K10: ='10_CAP_TABLE'!$C$17 | L10: ='10_CAP_TABLE'!$C$18 | M10: ='13_METRICS_AND_KPIS'!$C$20 | N10: ='13_METRICS_AND_KPIS'!$C$24
A11: Base | B11: 1 | C11: =TABLE(,'01_CONTROL'!$C$14) | D11: =TABLE(,'01_CONTROL'!$C$14) | E11: =TABLE(,'01_CONTROL'!$C$14) | F11: =TABLE(,'01_CONTROL'!$C$14) | G11: =TABLE(,'01_CONTROL'!$C$14) | H11: =TABLE(,'01_CONTROL'!$C$14) | I11: =TABLE(,'01_CONTROL'!$C$14) | J11: =TABLE(,'01_CONTROL'!$C$14) | ... N11: =TABLE(,'01_CONTROL'!$C$14)
A12: Upside | B12: 2 | C12: =TABLE(,'01_CONTROL'!$C$14) | D12: =TABLE(,'01_CONTROL'!$C$14) | E12: =TABLE(,'01_CONTROL'!$C$14) | F12: =TABLE(,'01_CONTROL'!$C$14) | G12: =TABLE(,'01_CONTROL'!$C$14) | H12: =TABLE(,'01_CONTROL'!$C$14) | I12: =TABLE(,'01_CONTROL'!$C$14) | J12: =TABLE(,'01_CONTROL'!$C$14) | ... N12: =TABLE(,'01_CONTROL'!$C$14)
A13: Downside | B13: 3 | C13: =TABLE(,'01_CONTROL'!$C$14) | D13: =TABLE(,'01_CONTROL'!$C$14) | E13: =TABLE(,'01_CONTROL'!$C$14) | F13: =TABLE(,'01_CONTROL'!$C$14) | G13: =TABLE(,'01_CONTROL'!$C$14) | H13: =TABLE(,'01_CONTROL'!$C$14) | I13: =TABLE(,'01_CONTROL'!$C$14) | J13: =TABLE(,'01_CONTROL'!$C$14) | ... N13: =TABLE(,'01_CONTROL'!$C$14)
B15: Notes
B16: The table above is an Excel Data Table driven by CTRL_SCEN (01_CONTROL!C14). Excel will compute Base/Upside/Downside outputs side-by-side. If values appear blank, open the file in Excel and allow calculation.
B19: B) Aggressiveness flags (Conservative / Neutral / Aggressive)
B20: Learning thresholds (edit if needed): Growth > 8% = Aggressive; Margin > 45% = Aggressive; Opex < 20% = Aggressive (cost-cut); Multiple above comps high = Aggressive.
B21: Scenario | C21: Growth flag | D21: Margin flag | E21: Opex flag | F21: Multiple flag (selected)
B22: Base | C22: =IF(C11>0.08,"Aggressive",IF(C11<0.03,"Conservative","Neutral")) | D22: =IF(D11>0.45,"Aggressive",IF(D11<0.30,"Conservative","Neutral")) | E22: =IF(E11<0.20,"Aggressive",IF(E11>0.30,"Conservative","Neutral")) | F22: =IF(MULT_SEL>06_VALUATION_COMPS!$C$22,"Aggressive",IF(MULT_SEL<06_VALUATION_COMPS!$C$20,"Conservative","Neutral"))
B23: Upside | C23: =IF(C12>0.08,"Aggressive",IF(C12<0.03,"Conservative","Neutral")) | D23: =IF(D12>0.45,"Aggressive",IF(D12<0.30,"Conservative","Neutral")) | E23: =IF(E12<0.20,"Aggressive",IF(E12>0.30,"Conservative","Neutral")) | F23: =IF(MULT_SEL>06_VALUATION_COMPS!$C$22,"Aggressive",IF(MULT_SEL<06_VALUATION_COMPS!$C$20,"Conservative","Neutral"))
B24: Downside | C24: =IF(C13>0.08,"Aggressive",IF(C13<0.03,"Conservative","Neutral")) | D24: =IF(D13>0.45,"Aggressive",IF(D13<0.30,"Conservative","Neutral")) | E24: =IF(E13<0.20,"Aggressive",IF(E13>0.30,"Conservative","Neutral")) | F24: =IF(MULT_SEL>06_VALUATION_COMPS!$C$22,"Aggressive",IF(MULT_SEL<06_VALUATION_COMPS!$C$20,"Conservative","Neutral"))
B26: C) Narrative prompts
B27: What must be true for High price (use together with 00_DASHBOARD Low/Base/High):
B28: 1) At the High price, implied EV/EBITDA and EV/Revenue remain within the peer distribution after normalisation (see 06_VALUATION_COMPS and 13_METRICS_AND_KPIS). 2) Under Downside fundamentals (CTRL_SCEN=3), the Low price still works on critical constraints (float, proceeds coverage, leverage) without breaking checks (see 90_CHECKS). 3) Book quality supports the chosen discount and aftermarket support plan, with greenshoe sized for stabilisation.
B31: What breaks first in Downside (use 90_CHECKS + this table):
B32: Look for the first KPI to cross a practical threshold: free float too low for liquidity, dilution too high vs board tolerance, or net leverage not improving enough to support the equity story. Confirm with 90_CHECKS, then adjust structure (primary/secondary mix, greenshoe, use of proceeds).
B34: Which 3 assumptions drive 80% of the range:
B35: Typically: (i) the selected comps multiple (MULT_SEL in 06_VALUATION_COMPS), (ii) the issuer metric used by that multiple (NTM_EBITDA or NTM_REV), and (iii) the net debt bridge (NET_DEBT_POST). Secondary levers: triangulation weights, WACC and terminal growth (if DCF is enabled).

Sheet 84_IPO_LEARN_DRILLS
B2: IPO Model Learning Layer | 84_IPO_LEARN_DRILLS (Exercises + Scoring)
B4: Purpose: Hands-on drills. Before starting a drill, CAPTURE BASELINE by copy-pasting the 'Current' column into the 'Baseline (values)' column as values. Then make changes only in allowed inputs.
B6: BASELINE SNAPSHOT (CAPTURE BEFORE EACH DRILL)
B8: Metric | C8: Baseline (values) | D8: Current (live) | E8: Delta | F8: Notes
B9: Selected price | C9: =IPO_PX_SEL | D9: =IPO_PX_SEL | E9: =D9-C9 | F9: Use CTRL_PX_CASE in 01_CONTROL.
B10: Gross proceeds target (DKKm) | C10: =CTRL_GROSS_PROCEEDS | D10: =CTRL_GROSS_PROCEEDS | E10: =D10-C10 | F10: Sizing input for offer shares.
B11: Net proceeds to company (DKKm) | C11: =NET_PROCEEDS_CO | D11: =NET_PROCEEDS_CO | E11: =D11-C11 | F11: Primary gross less allocated costs.
B12: Free float % | C12: =FREE_FLOAT_PCT | D12: =FREE_FLOAT_PCT | E12: =D12-C12 | F12: Shares sold to public divided by post shares.
B13: Primary dilution % | C13: =PRIMARY_DILUTION | D13: =PRIMARY_DILUTION | E13: =D13-C13 | F13: New primary shares divided by post shares.
B14: Post shares (m) | C14: =POST_SHARES | D14: =POST_SHARES | E14: =D14-C14 | F14: Pre shares plus new primary shares.
B15: Net debt post (DKKm) | C15: =NETDEBT_POST | D15: =NETDEBT_POST | E15: =D15-C15 | F15: Debt minus cash post transaction.
B16: Net leverage post (x) | C16: =LEVERAGE_POST | D16: =LEVERAGE_POST | E16: =D16-C16 | F16: Net debt post divided by NTM EBITDA.
B17: Selected multiple (x) | C17: =MULTIPLE_SEL | D17: =MULTIPLE_SEL | E17: =D17-C17 | F17: Comps multiple selected.
B18: Triang implied price (base) | C18: ='08_VALUATION_TRIANGULATION'!C30 | D18: ='08_VALUATION_TRIANGULATION'!C30 | E18: =D18-C18 | F18: Implied price base from triangulation.
B19: Extra baseline: Shares sold public (m) | C19: =SHARES_SOLD_PUBLIC | D19: =SHARES_SOLD_PUBLIC | E19: =D19-C19 | F19: Used in Drill 6 greenshoe impact.
B20: Extra baseline: Market Cap at offer (DKKm) | C20: =MKT_CAP | D20: =MKT_CAP | E20: =D20-C20 | F20: Used in Drill 5.
B21: DAILY DRILL MODE
B23: Today's drill # | C23: =RANDBETWEEN(1,12) | D23: (Press F9 to re-roll)
B25: Score tracker (manual entry)
B27: Date | C27: Drill # | D27: Attempt # | E27: Result (PASS/FAIL) | F27: Notes
B40: DRILL LIBRARY (12) - CHANGE ONLY ALLOWED INPUTS
B41: Target Market Cap (DKKm) for Drill 5 | C41: =MKT_CAP | E41: Edit this target as needed.
B42: # | C42: Objective | D42: Allowed inputs (specific cells/blocks) | E42: Forbidden inputs | F42: PASS/FAIL check (formula) | G42: Driver logic (why it works) | H42: Link
B43: 1 | C43: Increase free float by +5pp without increasing primary dilution | D43: 01_CONTROL!C28:C29 (Primary %, Secondary %), 01_CONTROL!C30 (Greenshoe %) and C33 (Fee allocation toggle) | E43: 01_CONTROL!C27 (Gross proceeds), 03_HISTORICALS, 05_FORECAST, grey calc cells | F43: =IF(AND(FREE_FLOAT_PCT>=$C$12+0.05, PRIMARY_DILUTION<=$C$13+0.0001),"PASS","FAIL") | G43: Increase secondary mix or greenshoe to lift float while keeping primary issuance (and therefore dilution) flat. | H43: =HYPERLINK("#'80_IPO_LEARN_MAP'!B9","Go")
B44: 2 | C44: Raise net proceeds by +10% without changing offer price | D44: 01_CONTROL!C31:C32 (Fee %, Other costs), 01_CONTROL!C33 (Fee allocation), 01_CONTROL!C28:C29 (mix) | E44: 01_CONTROL!C56 (Selected price) must remain equal to baseline, do not change gross proceeds | F44: =IF(AND(NET_PROCEEDS_CO>=$C$11*1.10, IPO_PX_SEL=$C$9, CTRL_GROSS_PROCEEDS=$C$10),"PASS","FAIL") | G44: Increase net by reducing fee/cost drag or increasing primary share, while holding the offer price constant. | H44: =HYPERLINK("#'80_IPO_LEARN_MAP'!B9","Go")
B45: 3 | C45: Reduce dilution by 3pp while keeping gross raise constant | D45: 01_CONTROL!C28:C29 (mix), 01_CONTROL!C30 (Greenshoe %) and C33 (allocation) | E45: Do not change 01_CONTROL!C27 (Gross proceeds) | F45: =IF(AND(PRIMARY_DILUTION<=$C$13-0.03, CTRL_GROSS_PROCEEDS=$C$10),"PASS","FAIL") | G45: Issue fewer new shares (lower primary %) while keeping total sell down sized to the same gross raise. | H45: =HYPERLINK("#'80_IPO_LEARN_MAP'!B9","Go")
B46: 4 | C46: Keep EV constant while changing net debt definition and explain why equity value moves | D46: 86_IPO_SPECIAL_MODULE!C18 (NET_DEBT_DEF toggle) and related inputs in the simulator | E46: Do not change price, gross proceeds, or selected multiple | F46: =IF(AND(ABS(SIM_EV_A-SIM_EV_B)<0.01, ABS(SIM_EQ_A-SIM_EQ_B)>0.01),"PASS","FAIL") | G46: EV can be held constant in the simulator while net debt definition shifts, which moves the EV to equity bridge and therefore equity value. | H46: =HYPERLINK("#'80_IPO_LEARN_MAP'!B9","Go")
B47: 5 | C47: Achieve a target Market Cap while keeping free float in 20% to 35% | D47: 01_CONTROL!C24:C56 (Price case / selected price), 01_CONTROL!C28:C29 (mix) | E47: Do not hardcode outputs or edit grey cells | F47: =IF(AND(MKT_CAP>=DRILL_TARGET_MKT_CAP, FREE_FLOAT_PCT>=0.20, FREE_FLOAT_PCT<=0.35),"PASS","FAIL") | G47: Market cap is price times post shares. Manage the tradeoff between price, primary issuance, and float thresholds. | H47: =HYPERLINK("#'80_IPO_LEARN_MAP'!B9","Go")
B48: 6 | C48: Show how greenshoe affects ownership and why it is used (quantify impact) | D48: 01_CONTROL!C30 (Greenshoe %) and 01_CONTROL!C28:C29 (mix) | E48: Do not change gross proceeds | F48: =IF(AND('01_CONTROL'!$C$30>0, SHARES_SOLD_PUBLIC>=$C$19+0.0001, FREE_FLOAT_PCT>$C$12+0.0001),"PASS","FAIL") | G48: Greenshoe increases distribution and float without changing primary proceeds narrative materially; it supports stabilisation and demand management. | H48: =HYPERLINK("#'80_IPO_LEARN_MAP'!B9","Go")
B49: 7 | C49: Defend a higher multiple selection using comps normalisation (without changing peer data) | D49: 06_VALUATION_COMPS!C23 (Selected multiple), 06_VALUATION_COMPS!C11:C17 (normalisation toggles if present) | E49: Do not edit peer financial data table; do not change FX or base metrics | F49: =IF(AND(MULTIPLE_SEL>=$C$17+1.0, MULTIPLE_SEL<='06_VALUATION_COMPS'!$C$20+0.5),"PASS","FAIL") | G49: A higher multiple must still be defensible versus the peer distribution after normalisation and basis alignment. | H49: =HYPERLINK("#'80_IPO_LEARN_MAP'!B9","Go")
B50: 8 | C50: Build a downside pricing case and show which KPI becomes unacceptable first | D50: 01_CONTROL!C15 (Scenario = Downside), 01_CONTROL!C17 (Price case = Low), then adjust only mix and fees if needed | E50: Do not edit forecast mechanics directly | F50: =IF(AND('01_CONTROL'!$C$15=1, '01_CONTROL'!$C$17=1, OR(FREE_FLOAT_PCT<0.20, LEVERAGE_POST>3.5, NET_PROCEEDS_CO<$C$11)),"PASS","FAIL") | G50: Downside combines weaker NTM EBITDA with lower price. Track float, leverage and proceeds as the first breakers for marketability and board acceptability. | H50: =HYPERLINK("#'80_IPO_LEARN_MAP'!B9","Go")
B51: 9 | C51: Change use of proceeds to reduce net leverage by 0.5x without changing gross raise | D51: 01_CONTROL!C38:C40 (Use of proceeds allocation %), 01_CONTROL!C37 (Debt paydown bucket size if present) | E51: Do not change gross proceeds target or price | F51: =IF(AND(LEVERAGE_POST<=$C$16-0.5, CTRL_GROSS_PROCEEDS=$C$10),"PASS","FAIL") | G51: Reallocate proceeds toward debt paydown to lower net debt and leverage, keeping the raise constant. | H51: =HYPERLINK("#'80_IPO_LEARN_MAP'!B9","Go")
B52: 10 | C52: Switch triangulation weight (comps vs DCF) and explain what assumptions dominate | D52: 01_CONTROL!C45:C46 (Comps and DCF weights), 01_CONTROL!C46 must keep sum to 1 | E52: Do not change peer set or forecast; only weights and DCF key assumptions | F52: =IF(AND(ABS(('01_CONTROL'!$C$45+'01_CONTROL'!$C$46)-1)<0.0001, ABS('08_VALUATION_TRIANGULATION'!$C$30-$C$18)>0.01),"PASS","FAIL") | G52: Changing weights shifts which method dominates implied price. DCF sensitivity is driven by WACC and terminal assumptions; comps sensitivity is driven by peer multiple and metric. | H52: =HYPERLINK("#'80_IPO_LEARN_MAP'!B9","Go")
B53: 11 | C53: Identify and fix a definition mismatch (net debt or shares) using definition controls | D53: 86_IPO_SPECIAL_MODULE!C18:C19 (definition toggles) to reconcile bridge flags | E53: Do not edit calculation cells in 11_PRO_FORMA_BS or 13_METRICS | F53: =IF(DEF_STATUS="RESOLVED","PASS","FAIL") | G53: Definition mismatches typically show up as EV bridge inconsistencies. Fix by aligning cash and debt items included in net debt with the definition used in valuation. | H53: =HYPERLINK("#'80_IPO_LEARN_MAP'!B9","Go")
B54: 12 | C54: Build a 6 bullet pricing range narrative referencing model outputs | D54: 84_IPO_LEARN_DRILLS!B60:B65 (enter 6 bullets) | E54: Do not use generic text; each bullet must reference at least one model KPI | F54: =IF(COUNTA(84_IPO_LEARN_DRILLS!B60:B65)=6,"PASS","FAIL") | G54: A defensible narrative ties valuation support (range), float and dilution tradeoffs, proceeds use and balance sheet, and key risks that move the range. | H54: =HYPERLINK("#'80_IPO_LEARN_MAP'!B9","Go")
B59: DRILL 12 - PRICING RANGE NARRATIVE (FILL 6 BULLETS)
B61: Bullet 1
B62: Bullet 2
B63: Bullet 3
B64: Bullet 4
B65: Bullet 5
B66: Bullet 6
B70: B) Daily drill mode (random drill + score tracker)
B71: Use this to train 10 minutes/day. Press F9 (recalc) to re-roll ACTIVE_DRILL if using RANDOM mode.
B73: ACTIVE_DRILL (1–12) | C73: =RANDBETWEEN(1,12) | E73: Go to drill | F73: =HYPERLINK("#B"&CHOOSE($C$73,43,44,45,46,47,48,49,50,51,52,53,54),"Jump")
B74: Active drill title | C74: =INDEX($C$43:$C$54,$C$73)
B75: Active drill status | C75: =INDEX($F$43:$F$54,$C$73)
B77: Daily log (fill one row per attempt)
B78: Date | C78: Drill # | D78: Result (PASS/FAIL) | E78: Notes
B110: Attempts | C110: =COUNTA(C79:C108) | E110: Pass rate | F110: =IF(C110=0,"",C111/C110)
B111: Passes | C111: =COUNTIF(D79:D108,"PASS")

Sheet 85_IPO_LEARN_MISTAKES
B2: IPO Model Learning Layer | 85_IPO_LEARN_MISTAKES (Mistake Library + Training Mode)
B4: Purpose: A practical library of common IPO-model mistakes and how to catch/fix them. Optional TRAINING_MODE provides simulated issues + an answer key (safe, no core calculation changes).
B7: A) Mistake library (25) | grouped by category
B8: Category | C8: Mistake | D8: What it breaks (KPI / check) | E8: How to spot (sanity check) | F8: Fix (where) | G8: Link
B9: Share mechanics | C9: Using pre-shares instead of post-shares for market cap | D9: Market cap, EV, multiples; 80 KPI: Market Cap | E9: Market cap should equal offer price * post shares (check 13_METRICS) | F9: Use POST_SHARES (10_CAP_TABLE) not pre shares | G9: =HYPERLINK("#'80_IPO_LEARN_MAP'!B14","KPI map")
B10: Share mechanics | C10: Greenshoe included in float but not in sold shares (or vice versa) | D10: Free float %, total sold, ownership | E10: Compare 09_OFFER_STRUCTURE greenshoe shares to cap table free float shares | F10: Align inclusion: confirm whether float includes greenshoe and document in dashboard cue | G10: =HYPERLINK("#'80_IPO_LEARN_MAP'!B14","KPI map")
B11: Share mechanics | C11: Secondary shares treated as dilution | D11: Dilution metric overstated; board optics | E11: Dilution should move only with PRIMARY_SHARES, not with secondary | F11: Use dilution formula based on new shares / post shares (10_CAP_TABLE) | G11: =HYPERLINK("#'80_IPO_LEARN_MAP'!B14","KPI map")
B12: Share mechanics | C12: Total shares sold != primary + secondary (+ greenshoe) | D12: Gross proceeds, float, disclosures; 90_CHECKS offer shares tie | E12: Check 90_CHECKS ‘Offer shares tie’ PASS/FAIL | F12: Trace inputs in 01_CONTROL (secondary %, greenshoe %) and 09_OFFER_STRUCTURE | G12: =HYPERLINK("#'80_IPO_LEARN_MAP'!B14","KPI map")
B13: Share mechanics | C13: Free float denominator wrong (pre vs post) | D13: Free float % misreported | E13: Float % should be free float shares / post shares | F13: Use POST_SHARES in denominator (10_CAP_TABLE) | G13: =HYPERLINK("#'80_IPO_LEARN_MAP'!B14","KPI map")
B14: Proceeds & fees | C14: Gross proceeds confused with company cash | D14: Use of proceeds narrative wrong; pro forma cash wrong | E14: Company cash should equal NET_PROCEEDS_CO, not gross | F14: Use 09_OFFER_STRUCTURE net proceeds line; link 11_PRO_FORMA_BS to it | G14: =HYPERLINK("#'90_CHECKS'!B6","Checks")
B15: Proceeds & fees | C15: Fees applied to net proceeds instead of gross (or wrong base) | D15: Net proceeds wrong; 90_CHECKS fees check | E15: Recompute: fee % * gross proceeds (unless otherwise defined) | F15: 01_CONTROL underwriting fee % and 09 gross-to-net bridge | G15: =HYPERLINK("#'90_CHECKS'!B6","Checks")
B16: Proceeds & fees | C16: Other transaction costs sign wrong (negative) | D16: Net proceeds inflated; 90_CHECKS fees check | E16: 90_CHECKS ‘Fees / costs non-negative’ should fail if negative | F16: 01_CONTROL other costs must be >=0; confirm units (DKKm) | G16: =HYPERLINK("#'90_CHECKS'!B6","Checks")
B17: Proceeds & fees | C17: Primary/secondary allocation inconsistent across tabs | D17: Company cash and ownership inconsistent | E17: Tie 09 primary/secondary to 10 cap table and 11 pro forma | F17: Use 01_CONTROL secondary % as single source of truth | G17: =HYPERLINK("#'90_CHECKS'!B6","Checks")
B18: Definitions | C18: Net debt sign convention inconsistent (cash minus debt vs debt minus cash) | D18: EV bridge wrong; multiples wrong | E18: EV should increase when net debt increases (positive debt) | F18: Confirm NET_DEBT_POST definition used in 13_METRICS | G18: =HYPERLINK("#'90_CHECKS'!B6","Checks")
B19: Definitions | C19: Net debt definition differs between comps and model (leases/pensions) | D19: Comps triangulation misleading | E19: Same metric basis required: LTM/NTM, leases included? | F19: Document definition in 86 module and adjust definition toggles if present | G19: =HYPERLINK("#'90_CHECKS'!B6","Checks")
B20: Definitions | C20: LTM vs NTM mismatched across peers and issuer | D20: Multiple selection invalid | E20: Peer multiples should match issuer metric period | F20: Ensure NTM EBITDA used with NTM peer multiple; document in comps notes | G20: =HYPERLINK("#'90_CHECKS'!B6","Checks")
B21: Valuation (comps) | C21: Wrong metric mapping (Revenue vs EBITDA) used for implied EV | D21: Implied price wrong; football field wrong | E21: Implied EV should equal multiple * selected metric (cell trace) | F21: Check 06_VALUATION_COMPS implied EV formula and metric cell references | G21: =HYPERLINK("#'81_IPO_LEARN_FORMULAS'!B33","Formulas")
B22: Valuation (comps) | C22: Currency mismatch (peer metrics vs issuer metrics) | D22: Implied EV wrong by FX factor | E22: Spot if implied EV is off by ~7.45 or similar FX multiple | F22: Confirm all values in same currency and unit; add FX conversion if needed | G22: =HYPERLINK("#'81_IPO_LEARN_FORMULAS'!B33","Formulas")
B23: Valuation (comps) | C23: Using mean when distribution skewed (outliers) | D23: Range too aggressive | E23: Compare median vs mean; check peer dispersion | F23: Prefer median / trimmed mean and document outliers; keep range defendable | G23: =HYPERLINK("#'81_IPO_LEARN_FORMULAS'!B33","Formulas")
B24: DCF | C24: WACC / terminal growth inconsistent (g >= WACC) | D24: Terminal value blows up; range unrealistic | E24: Sanity: WACC must be > g, typically by several pp | F24: 01_CONTROL WACC and TERM_G; enforce checks in DCF module | G24: =HYPERLINK("#'81_IPO_LEARN_FORMULAS'!B33","Formulas")
B25: DCF | C25: Mid-year convention mismatch (half-year shift not applied) | D25: DCF EV overstated/understated | E25: Compare PV factor logic vs timing of cash flows | F25: Align PV timing; document whether mid-year is used | G25: =HYPERLINK("#'81_IPO_LEARN_FORMULAS'!B33","Formulas")
B26: DCF | C26: Terminal value calculated on wrong year cash flow | D26: DCF EV wrong | E26: Terminal base should be final forecast year FCF | F26: Trace terminal value cell to last-year FCF | G26: =HYPERLINK("#'81_IPO_LEARN_FORMULAS'!B33","Formulas")
B27: Presentation | C27: Range narrative uses inconsistent ‘Low/Base/High’ vs ‘Downside/Base/Upside’ | D27: Confuses readers and clients | E27: If asked, clarify price-range vs fundamentals scenario | F27: Keep two axes explicit: Price (Low/Base/High) and Fundamentals (Down/Base/Up) | G27: =HYPERLINK("#'90_CHECKS'!B6","Checks")
B28: Presentation | C28: Dashboard tiles not traceable (no references) | D28: Model not auditable | E28: Each tile must tie to a calc block cell | F28: Use the MAP tab hyperlinks; avoid hardcodes on dashboard | G28: =HYPERLINK("#'90_CHECKS'!B6","Checks")
B29: Model hygiene | C29: Hardcoded numbers inside calc blocks | D29: Breaks updates; audit risk | E29: Use Find: constants; sanity with 90_CHECKS | F29: Replace with links to input cells or named ranges; document | G29: =HYPERLINK("#'90_CHECKS'!B6","Checks")
B30: Model hygiene | C30: Circular references introduced by learning layer or links | D30: Model unstable | E30: Excel warns; outputs change unexpectedly | F30: Keep learning tabs isolated; never reference back into core calcs except read-only | G30: =HYPERLINK("#'90_CHECKS'!B6","Checks")
B31: Model hygiene | C31: Named range points to wrong sheet/cell after edits | D31: Outputs break silently | E31: 90_CHECKS ‘Dashboard tiles not blank’ may fail | F31: Keep named ranges stable; run Name Manager audit | G31: =HYPERLINK("#'90_CHECKS'!B6","Checks")
B32: Sanity checks | C32: EV/Revenue and EV/EBITDA move opposite direction vs price | D32: Sign error or net debt issue | E32: If price rises, Market Cap and EV should rise (all else equal) | F32: Check EV bridge sign; net debt definition; 13_METRICS formulas | G32: =HYPERLINK("#'90_CHECKS'!B6","Checks")
B33: Sanity checks | C33: Net proceeds exceed gross proceeds | D33: Fee sign or base error | E33: Net <= gross always (unless rebate, unusual) | F33: Check underwriting fee %, other costs and sign conventions | G33: =HYPERLINK("#'90_CHECKS'!B6","Checks")
B36: B) TRAINING_MODE (safe) | simulated issues + answer key
B37: TRAINING_MODE | C37: OFF | D37: (Set to ON to work through the 5 issues below. This does NOT alter core calcs automatically.)
B39: Issue | C39: How to reproduce (allowed inputs only) | D39: Expected check to flag | E39: Answer key (fix)
B40: Invalid scenario selector | C40: Set 01_CONTROL!C14 to 4 (anything not 1–3). | D40: 90_CHECKS ‘Scenario toggle valid’ should FAIL. | E40: Set 01_CONTROL!C14 back to 1 (Base), 2 (Upside) or 3 (Downside).
B41: Use of proceeds not 100% | C41: Change one of: 01_CONTROL!C37:C39 so they do NOT sum to 1.00 (e.g., set Growth investment to 0.25). | D41: 90_CHECKS ‘Use of proceeds sums to 100%’ should FAIL. | E41: Rebalance 01_CONTROL!C37:C39 to sum to 1.00 and match narrative.
B42: Negative fees/costs | C42: Set 01_CONTROL!C31 to -0.01 or 01_CONTROL!C32 to -10. | D42: 90_CHECKS ‘Fees / costs non-negative’ should FAIL. | E42: Set underwriting fee % and other costs back to non-negative values; confirm units.
B43: Definition mismatch (EV bridge) | C43: Temporarily flip net debt sign by entering negative cash/debt inputs if exposed (or document mismatch as simulated). | D43: 90_CHECKS may not catch automatically. Use 13_METRICS EV bridge sanity (price up -> EV up). | E43: Ensure NET_DEBT_POST definition uses Debt - Cash consistently and matches comps definition.
B44: Broken link placeholder / blank tile | C44: Clear a dashboard input cell that feeds a tile (only if model is a copy). | D44: 90_CHECKS ‘Dashboard tiles not blank’ should FAIL. | E44: Restore link or re-enter the input; use 80_MAP to trace the tile to its source.

Sheet 86_IPO_SPECIAL_MODULE
B2: IPO Model Learning Layer | 86_IPO_SPECIAL_MODULE (IPO Specific Learning)
B4: Purpose: IPO specific mini modules. Use this tab to understand dilution and ownership tradeoffs, pro forma balance sheet mechanics, and how to defend the valuation range in meetings.
B6: 1) DILUTION AND OWNERSHIP SIMULATOR (PRACTICAL)
B8: Input | C8: Value | D8: Source
B9: Offer price (DKK/share) | C9: =IPO_PX_SEL | D9: 01_CONTROL / 09_OFFER_STRUCTURE
B10: Gross proceeds target (DKKm) | C10: ='01_CONTROL'!$C$27 | D10: 01_CONTROL
B11: Primary % | C11: ='01_CONTROL'!$C$28 | D11: 01_CONTROL
B12: Secondary % | C12: ='01_CONTROL'!$C$29 | D12: 01_CONTROL
B13: Greenshoe % of base sold | C13: ='01_CONTROL'!$C$30 | D13: 01_CONTROL
B15: Outputs (computed from base model)
B17: Output | C17: Value | D17: Interpretation cue | E17: Link
B18: Total shares sold incl greenshoe (m) | C18: =SHARES_SOLD_PUBLIC*(1+'01_CONTROL'!$C$30) | D18: Greenshoe increases sold shares and float; primary dilution is driven by new primary shares only. | E18: =HYPERLINK("#'09_OFFER_STRUCTURE'!B18","Go")
B19: Primary shares issued (m) | C19: =NEW_PRIMARY_SHARES | D19: Drives cash to company and dilution. | E19: =HYPERLINK("#'09_OFFER_STRUCTURE'!B16","Go")
B20: Secondary shares sold (m) | C20: =SHARES_SOLD_PUBLIC-NEW_PRIMARY_SHARES | D20: Drives float without raising cash for company. | E20: =HYPERLINK("#'09_OFFER_STRUCTURE'!B17","Go")
B21: Free float % post | C21: =FREE_FLOAT_PCT | D21: Key marketability metric (liquidity). | E21: =HYPERLINK("#'10_CAP_TABLE'!B17","Go")
B22: Primary dilution % | C22: =PRIMARY_DILUTION | D22: Board sensitive metric; new issuance effect on existing holders. | E22: =HYPERLINK("#'10_CAP_TABLE'!B18","Go")
B23: Gross proceeds total (DKKm) | C23: =GROSS_TOTAL | D23: Total cash paid by investors (primary + secondary). | E23: =HYPERLINK("#'09_OFFER_STRUCTURE'!B25","Go")
B24: Net proceeds to company (DKKm) | C24: =NET_PROCEEDS_CO | D24: Cash the company receives after allocated transaction costs. | E24: =HYPERLINK("#'09_OFFER_STRUCTURE'!B30","Go")
B26: What to say (tradeoffs)
B28: More primary increases cash to company but increases dilution. More secondary increases float without adding cash, but is a sell-down by existing holders. Greenshoe supports demand management and stabilisation and can modestly increase float.
B32: 2) PRO FORMA BALANCE SHEET EXPLAINER
B34: Step | C34: Cell / formula | D34: Why it matters
B35: Net proceeds to company | C35: =NET_PROCEEDS_CO | D35: This is the cash increase on the pro forma balance sheet.
B36: Debt paydown (DKKm) | C36: =DEBT_PAYDOWN | D36: If proceeds are used for debt paydown, net debt drops and leverage improves.
B37: Cash post (DKKm) | C37: ='11_PRO_FORMA_BS'!C22 | D37: Cash after applying net proceeds and allocations.
B38: Debt post (DKKm) | C38: ='11_PRO_FORMA_BS'!C23 | D38: Debt after paydown.
B39: Net debt post (DKKm) | C39: =NETDEBT_POST | D39: Feeds EV bridge and leverage; definition must be consistent.
B40: Net leverage post (x) | C40: =LEVERAGE_POST | D40: Key credit and equity story metric post IPO.
B42: Sanity checks
B43: Net proceeds to company must be <= gross primary proceeds. Debt paydown must be <= debt. Cash post should not go negative. Leverage should move in the direction implied by the allocation and net debt definition.
B47: 3) VALUATION RANGE DEFENSE PACK (ONE PAGE)
B49: Topic | C49: Meeting ready points
B50: Peer selection rationale | C50: Peers match business model, growth and margin, listing venue and liquidity. Exclude outliers with different accounting or capital structure.
B51: Multiple selection | C51: Selected multiple is within peer distribution and supported by relative growth and profitability. Show P25, median and P75 in comps tab.
B52: Normalisation notes | C52: Document adjustments (one offs, leases, IFRS differences). Ensure LTM or NTM basis is consistent across issuer and peers.
B53: What moves the range | C53: NTM EBITDA and selected multiple drive most of the range. EV to equity bridge makes net debt definition and paydown key for price per share.
B54: Top 3 proof points | C54: 1) Peer distribution, 2) Triangulation cross check, 3) Post deal balance sheet and leverage consistency with use of proceeds.
B57: DEFINITION CONTROLS SIMULATOR (FOR DRILLS)
B59: Input / Output | C59: Value | D59: Notes
B60: Cash equivalents adjustment (DKKm) | C60: 50 | D60: Used when toggles are ON.
B61: Valuation net debt includes cash equivalents (ON/OFF) | C61: OFF | D61: Toggle drives Net debt B and Equity B.
B62: Leverage net debt includes cash equivalents (ON/OFF) | C62: OFF | D62: Used for mismatch status only.
B63: EV target (A) (DKKm) | C63: =EV_OFFER | D63: Hold EV constant for drill 4.
B64: EV target (B) (DKKm) | C64: =EV_OFFER | D64: Same EV target; equity changes via net debt.
B65: Net debt A (base) (DKKm) | C65: =NETDEBT_POST | D65: Base model net debt.
B66: Net debt B (incl cash eq) (DKKm) | C66: =NETDEBT_POST-IF(C60=0,0,IF(C61="ON",C60,0)) | D66: Net debt decreases when cash eq included.
B67: Equity value A (DKKm) | C67: =C63-C65 | D67: EV - net debt.
B68: Equity value B (DKKm) | C68: =C64-C66 | D68: EV - net debt (with def).
B69: Definition status (for Drill 11) | C69: =IF(C61=C62,"RESOLVED","MISMATCH") | D69: Align the two toggles to resolve.

Sheet 90_CHECKS
B2: CHECKS HUB (MUST PASS)
B6: Check | C6: Status | D6: Severity | E6: Fix pointer
B7: Scenario toggle valid | C7: =IF(OR(CTRL_SCEN=1;CTRL_SCEN=2;CTRL_SCEN=3);"PASS";"FAIL") | D7: 1 | E7: 01_CONTROL
B8: Use of proceeds sums to 100% | C8: ='01_CONTROL'!$C$57 | D8: 1 | E8: 01_CONTROL
B9: Cap table ties (pre + new = post) | C9: =IF(ABS(POST_SHARES-(PRE_SHARES+NEW_PRIMARY_SHARES))<0,0001;"PASS";"FAIL") | D9: 1 | E9: 10_CAP_TABLE / 09_OFFER_STRUCTURE
B10: Offer shares tie (primary+secondary+GS=total sold) | C10: =IF(ABS(TOTAL_SOLD_SHARES-(NEW_PRIMARY_SHARES+SECONDARY_SHARES+GS_SHARES))<0,0001;"PASS";"FAIL") | D10: 2 | E10: 09_OFFER_STRUCTURE
B11: Fees and costs non-negative | C11: =IF(AND(TXN_COSTS>=0;NET_PROCEEDS_CO>=0);"PASS";"FAIL") | D11: 2 | E11: 09_OFFER_STRUCTURE
B12: Pro forma cash bridge ties | C12: =IF(ABS('11_PRO_FORMA_BS'!$C$22-('11_PRO_FORMA_BS'!$C$8+'11_PRO_FORMA_BS'!$C$15-'11_PRO_FORMA_BS'!$C$16-'11_PRO_FORMA_BS'!$C$17))<0,1;"PASS";"FAIL") | D12: 1 | E12: 11_PRO_FORMA_BS
B13: Dashboard trace sanity (no blanks in key tiles) | C13: =IF(COUNTA('00_DASHBOARD'!$B$8:$E$14)=0;"FAIL";"PASS") | D13: 3 | E13: 00_DASHBOARD
B14: OVERALL
B16: Overall status | C16: =IF(COUNTIF(C7:C13;"FAIL")>0;"FAIL";"PASS")

Sheet 99_APPENDIX_DATA
B2: APPENDIX (OPTIONAL) - NARRATIVE CELLS, DATA SCRATCH
B6: DASHBOARD NARRATIVE (LINKED)
B8: Bullet 1 | C8: ="Valuation range implies equity value of " & TEXT(EQ_BASE;"#,##0") & " DKKm (Base), with EV/NTM EBITDA at offer price of " & TEXT(EV_EBITDA_OFFER;"0.0x") & "."
B9: Bullet 2 | C9: ="Free float post-IPO is " & TEXT(FREE_FLOAT_PCT;"0.0%") & " of basic shares; primary dilution is " & TEXT(PRIMARY_DILUTION;"0.0%") & "."
B10: Bullet 3 | C10: ="Net primary proceeds to company are " & TEXT(NET_PROCEEDS_CO;"#,##0") & " DKKm; allocated " & TEXT(UOP_DEBT_PCT;"0%") & " to debt paydown and " & TEXT(UOP_GROWTH_PCT;"0%") & " to growth investment."
B11: Bullet 4 | C11: ="Post-IPO net debt is " & TEXT(NETDEBT_POST;"#,##0") & " DKKm, implying leverage of " & TEXT('11_PRO_FORMA_BS'!$C$30;"0.0x") & " (Net debt/NTM EBITDA)."
B12: Bullet 5 | C12: =IF(CHECKS_OVERALL="PASS";"Checks are green. Model is internally consistent.";"One or more checks failed. Review 90_CHECKS for fix pointers.")
